Workbook

Sheet 医院
A1: 数据名 | B1: 计量单位 | C1: 填报部门 | D1: Y2021 | E1: Y2020 | F1: Y2019 | G1: 指标说明 | H1: 计算公式
A2: 下转患者人次数 | B2: 人次 | C2: 医务科 | D2: 10291 | E2: 10118 | F2: 9839 | G2: 参考三级中医、三级公立国考手册,原指标名为:下转患者人次数（门急诊、住院） | H2: 门急诊下转患者人次数+住院下转患者人次数。
A3: 出院患者手术占比 | B3: % | C3: 统计室 | D3: 30.063321 | E3: 28.092117 | F3: 28.147768 | G3: 详见三级公立、二级公立国考手册。举例：30%请填写30（不带百分号），而非写成30%，或0.3。下同 | H3: 出院患者手术台次数/同期出院患者总人次数*100
A4: 出院患者微创手术占比 | B4: % | C4: 统计室 | D4: 20.651888 | E4: 19.676328 | F4: 17.502871 | G4: 详见三级公立、二级公立国考手册 | H4: 出院患者微创手术台次数/同期出院患者手术台次数*100
A5: 出院患者四级手术比例 | B5: % | C5: 统计室 | D5: 21.873519 | E5: 18.784758 | F5: 17.427235 | G5: 详见三级公立国考手册 | H5: 出院患者四级手术台次数/同期出院患者手术台次数*100
A6: 出院患者疑难危重病例比例 | B6: % | C6: 统计室 | D6: 94.43 | E6: 91.95 | F6: 89.52 | G6: 即CD型病例占比 | H6: (疑难病例数+危重病例数)/出院人数*100
A7: 特需医疗服务量占比 | B7: % | C7: 医务科 | D7: 1.2 | E7: 0.8 | F7: 0.25 | G7: 参考三级公立国考手册，特需医疗服务占比的构成要素。 | H7: 特需医疗服务量/同期全部医疗服务量*100
A8: 特需医疗服务收入占比 | B8: % | C8: 医务科 | D8: 0.11 | E8: 0.0351 | F8: 0.0424 | G8: 参考三级公立国考手册，特需医疗服务占比的构成要素 | H8: 特需医疗服务收入/同期全部医疗服务收入*100
A9: 手术患者并发症发生率 | B9: % | C9: 质控科 | D9: 0.0036493713 | E9: 0.0054100228 | F9: 0.0052552841 | G9: 详见国考手册 | H9: 手术患者并发症发生例数/同期出院的手术患者人数*100
A10: I类切口手术部位感染率 | B10: % | C10: 院感科 | D10: 0.05 | E10: 0.05 | F10: 0.09 | G10: 详见三级中医、三级公立国考手册 | H10: I类切口手术部位感染人次数/同期I类切口手术台次数*100
A11: 大型医用设备检查阳性率 | B11: % | C11: 医务科 | D11: 94.22 | E11: 93.10 | F11: 85.13 | G11: 详见三级中医、三级公立国考手册 | H11: 大型医用设备检查阳性数/同期大型医用设备检查人次数*100
A12: 国家室间质量评价临床检验项目参加率 | B12: % | C12: 医务科 | D12: 92.65 | E12: 96.28 | F12: 81.25 | G12: 参考三级中医、三级公立国考手册，为“通过国家室间质量评价的临床检验项目数”指标的构成要素 | H12: 参加国家临床检验中心组织的室间质评的检验项目数/同期实验室已开展且同时国家临床检验中心已组织的室间质评检验项目总数*100
A13: 国家室间质量评价临床检验项目合格率 | B13: % | C13: 医务科 | D13: 99.11 | E13: 97.10 | F13: 96.79 | G13: 参考三级中医、三级公立国考手册，为“通过国家室间质量评价的临床检验项目数”指标的构成要素 | H13: 参加国家临床检验中心组织室间质评成绩合格的检验项目数/同期参加国家临床检验中心组织的室间质评检验项目总数*100
A14: 低风险组病例死亡率 | B14: % | C14: 质控科 | D14: 0 | E14: 0 | F14: 0 | G14: 详见三级公立、二级公立国考手册 | H14: 低风险组死亡例数/低风险组病例数*100
A15: 优质护理服务病房覆盖率 | B15: % | C15: 护理部 | D15: 100 | E15: 100 | F15: 100 | G15: 参考三级中医、三级公立国考手册，病房总数（即病区数） | H15: 全院已经开展优质护理服务的病房总数/全院病房总数*100
A16: 医院感染发生率 | B16: % | C16: 院感科 | D16: 0.91 | E16: 1 | F16: 1.19 | G16: 等级评审标准细则
A17: 点评处方占处方总数的比例 | B17: % | C17: 药学部 | D17: 3.09 | E17: 3.03 | F17: 0.43 | G17: 详见三级中医、三级公立国考手册 | H17: 点评处方数/处方总数*100
A18: 抗菌药物使用强度DDDs | B18: DDD | C18: 药学部 | D18: 37.96 | E18: 38.91 | F18: 39.57 | G18: 详见国考手册 | H18: 住院患者抗菌药物消耗量（累计DDD数）/同期收治患者人天数*100
A19: 门诊患者基本药物处方占比 | B19: % | C19: 药学部 | D19: 70.49 | E19: 61.55 | F19: 58.71 | G19: 详见三级中医、三级公立国考手册 | H19: 门诊使用基本药物人次数/同期门诊诊疗总人次数*100
A20: 住院患者基本药物使用率 | B20: % | C20: 药学部 | D20: 95.58 | E20: 94.31 | F20: 91.2 | G20: 详见三级中医、三级公立国考手册 | H20: 出院患者使用基本药物总人次数/同期出院总人次数*100
A21: 基本药物采购品种数占比 | B21: % | C21: 药学部 | D21: 46.43 | E21: 41.41 | F21: 40.02 | G21: 详见三级中医、三级公立国考手册 | H21: 医院采购基本药物品种数/医院同期采购药物品种总数*100
A22: 国家组织药品集中采购中标药品金额占比 | B22: % | C22: 药学部 | D22: 87.09 | E22: 48.46 | F22: 0 | G22: 详见三级中医、三级公立国考手册 | H22: 中标药品用量/同种药品用量*100
A23: 重点监控高值医用耗材收入占比 | B23: % | C23: 设备科 | D23: 35.8021 | E23: 35.8758 | F23: 39.7873 | G23: 详见国考手册 | H23: 重点监控高值医用耗材收入/同期卫生材料收入*100
A24: 门诊患者平均预约诊疗率 | B24: % | C24: 门诊部 | D24: 100 | E24: 98.74 | F24: 89.59 | G24: 详见三级中医、三级公立国考手册 | H24: 预约诊疗人次数/总诊疗人次数*100
A25: 门诊患者预约后平均等待时间 | B25: 分钟 | C25: 门诊部 | D25: 19.52 | E25: 23.56 | F25: 24.53 | G25: 26.52 | H25: ∑{进入诊室诊疗的时钟时间-到达分诊台或通过信息系统（自助机、APP等）报到的时钟时间}/预约诊疗人次数
A26: 电子病历应用功能水平分级 | B26: 级别 | C26: 信息科 | D26: 4 | E26: 4 | F26: 3 | G26: 详见国考手册
A27: 平均住院日 | B27: 天 | C27: 统计室 | D27: 7.59 | E27: 7.91 | F27: 8.3 | G27: 详见二级公立国考手册 | H27: 出院患者占用总床日数/同期出院患者人数
A28: CMI值 | C28: 质控科 | D28: 1.29 | E28: 1.31 | F28: 1.24 | G28: 病例组合指数
A29: DRGs组数 | B29: 组 | C29: 质控科 | D29: 752 | E29: 745 | F29: 746 | G29: 诊断相关分组组数
A30: 每百张病床药师人数 | B30: 人 | C30: 人事科 | D30: 3.18 | E30: 3.31 | F30: 2.48 | G30: 详见三级中医、三级公立国考手册 | H30: 医院药师（包括药剂师和临床药师）总人数/医院实际开放床位数*100
A31: 核定床位数 | B31: 张 | C31: 统计室 | D31: 2500 | E31: 2500 | F31: 2500 | G31: 等级评审标准细则
A32: 实际开放床位数 | B32: 张 | C32: 统计室 | D32: 2800 | E32: 2570 | F32: 2818 | G32: 等级评审标准细则
A33: 开放床位使用率 | B33: % | C33: 统计室 | D33: 96.21 | E33: 96.23 | F33: 102.3 | G33: 等级评审标准细则 | H33: 实际占用的总床日数/同期实际开放的总床日数*100
A34: 卫生技术人员数与开放床位数比 | C34: 人事科 | D34: =2806/D32 -> 1.0021429 | E34: =2806/E32 -> 1.0918288 | F34: =2806/F32 -> 0.99574166 | G34: 等级评审标准细则，原计量单位为比值（1:X），现改为小数 | H34: 医院卫生技术人员数/同期全院实际开放床位数
A35: 医师人数与开放床位数比 | C35: 人事科 | D35: =D60/D32 -> 0.27214286 | E35: =E60/E32 -> 0.28171206 | F35: =F60/F32 -> 0.24733854 | G35: 等级评审标准细则，原计量单位为比值（1:X），现改为小数 | H35: 医院执业（助理）医师总数/同期全院实际开放床位数
A36: 护士人数与开放床位数比 | C36: 人事科 | D36: =D61/D32 -> 0.62178571 | E36: =E61/E32 -> 0.67782101 | F36: =F61/F32 -> 0.61107168 | G36: 等级评审标准细则，原计量单位为比值（1:X），现改为小数 | H36: 医院注册护士总数/同期全院实际开放床位数
A37: 人均医疗服务收入 | B37: 万元 | C37: 财务科 | D37: 16.29 | E37: 14.73 | F37: 16.19 | G37: 按科室人员数人均医疗服务收入
A38: 人均有效收入 | B38: 万元 | C38: 财务科 | D38: 32.71 | E38: 29.78 | F38: 30.71 | G38: 按科室人员数人均有效收入
A39: 床均医疗服务收入 | B39: 万元 | C39: 财务科 | D39: 21.37 | E39: 19.03 | F39: 19.68 | G39: 按开放床位数床均医疗服务收入
A40: 床均有效收入 | B40: 万元 | C40: 财务科 | D40: 42.93 | E40: 38.47 | F40: 37.32 | G40: 按开放床位数床均有效收入
A41: 每名执业医师日均住院工作负担 | B41: 床日 | C41: 财务科 | D41: 3.4397045 | E41: 3.6174979 | F41: 4.1360154 | G41: 详见三级中医、三级公立国考手册 | H41: 全年实际占用总床日数/医院平均执业(助理)医师人数/365
A42: 医疗服务收入占医疗收入比例 | B42: % | C42: 财务科 | D42: 31.87 | E42: 31.51 | F42: 32.55 | G42: 参考国考手册，原指标名为：医疗服务收入（不含药品、耗材、检查检验收入）占医疗收入比例 | H42: 医疗服务收入/医疗收入*100
A43: 医疗收入 | B43: 万元 | C43: 财务科 | D43: 182616.81 | E43: 163923.73 | F43: 170388.46 | H43: 门诊收入+住院收入
A44: 医疗服务收入 | B44: 万元 | C44: 财务科 | D44: 58203.18 | E44: 51648.94 | F44: 55455.67
A45: 有效收入 | B45: 万元 | C45: 财务科 | D45: 116885.33 | E45: 104411.37 | F45: 105169.11 | H45: 医疗服务收入+检查检验收入
A46: 万元收入能耗占比 | B46: 吨标煤/万元 | C46: 后勤管理科 | D46: 0.0189 | E46: 0.0246 | F46: 0.0229 | G46: 详见国考手册 | H46: 年总能耗/年总收入*10000
A47: 资产负债率 | B47: % | C47: 财务科 | D47: 25.55 | E47: 23.39 | F47: 22.43 | G47: 详见国考手册 | H47: 负债合计/资产合计*100
A48: 收支结余率 | B48: % | D48: 0.45 | E48: 0.62 | F48: 1.57
A49: 医疗收入增幅 | B49: % | C49: 财务科 | D49: 11.4 | E49: -3.79 | F49: 12.97 | G49: 详见国考手册 | H49: （本年度医疗收入－上一年度医疗收入）/上一年度医疗收入*100
A50: 门诊次均费用增幅 | B50: % | C50: 财务科 | D50: -3.69 | E50: 0.56 | F50: 6.18 | G50: 详见国考手册 | H50: （本年度门诊患者次均医药费用－上一年度门诊患者次均医药费用）/上一年度门诊患者次均医药费用*100
A51: 住院次均费用增幅 | B51: % | C51: 财务科 | D51: 2.31 | E51: 1.64 | F51: 4.37 | G51: 详见国考手册 | H51: （本年度出院患者次均医药费用－上一年度出院患者次均医药费用）/上一年度出院患者次均医药费用*100
A52: 门诊次均药品费用增幅 | B52: % | C52: 财务科 | D52: 1.02 | E52: -0.8 | F52: 11.05 | G52: 详见国考手册 | H52: （本年度门诊患者次均药品费用－上一年度门诊患者次均药品费用）/上一年度门诊患者次均药品费用*100
A53: 住院次均药品费用增幅 | B53: % | C53: 财务科 | D53: -0.94 | E53: -11.51 | F53: 5.17 | G53: 详见国考手册 | H53: （本年度出院患者次均药品费用－上一年度出院患者次均药品费用）/上一年度出院患者次均药品费用*100
A54: 麻醉医师占比 | B54: % | C54: 人事科 | D54: 5.38 | E54: 5.25 | F54: 5.16 | G54: 详见国考手册 | H54: 医院注册的麻醉在岗医师数/全院同期医师总数*100
A55: 儿科医师占比 | B55: % | C55: 人事科 | D55: 5.38 | E55: 5.52 | F55: 5.74 | G55: 详见国考手册 | H55: 医院注册的儿科在岗医师数/全院同期医师总数*100
A56: 重症医师占比 | B56: % | C56: 人事科 | D56: 3.81 | E56: 4.01 | F56: 3.87 | G56: 详见国考手册 | H56: 医院注册的重症在岗医师数/全院同期医师总数*100
A57: 病理医师占比 | B57: % | C57: 人事科 | D57: 1.71 | E57: 1.66 | F57: 1.43 | G57: 详见国考手册 | H57: 医院注册的病理在岗医师数/全院同期医师总数*100
A58: 中医医师占比 | B58: % | C58: 人事科 | D58: 4.46 | E58: 3.73 | F58: 3.87 | G58: 详见三级公立、二级公立国考手册 | H58: 医院注册的中医在岗医师数/全院同期医师总数*100
A59: 医护比 | C59: 人事科 | D59: 0.44 | E59: 0.42 | F59: 0.4 | G59: 参考国考手册，原计量单位为比值（1:X），现改为小数 | H59: 医院注册医师总数/全院同期注册护士总数
A60: 医师人数 | B60: 人 | C60: 人事科 | D60: 762 | E60: 724 | F60: 697 | G60: 详见国考手册中，医护比定义
A61: 护士人数 | B61: 人 | C61: 人事科 | D61: 1741 | E61: 1742 | F61: 1722 | G61: 详见国考手册中，医护比定义
A62: 医院感染管理专职人员数与开放床位数比 | C62: 人事科 | D62: =6/D32 -> 0.0021428571 | E62: =6/E32 -> 0.0023346304 | F62: =4/F32 -> 0.0014194464 | G62: 等级评审标准细则，原计量单位为比值（1:X），现改为小数 | H62: 医院感染管理专职人员数/同期全院实际开放床位数
A63: 卫生技术人员副高及以上职称占比 | B63: % | C63: 人事科 | D63: 14.54 | E63: 14.89 | F63: 14.24 | G63: 参考三级公立、二级公立国考手册，原指标名为：卫生技术人员职称结构 | H63: 医院具有高级职称的医务人员数/全院同期医务人员总数*100
A64: 医院接受其他医院进修并返回原医院独立工作人数占比 | B64: % | C64: 科教科 | D64: 21.09 | E64: 16.96 | F64: 10.98 | G64: 参考三级中医、三级公立国考手册，原指标名为：医院接受其他医院（尤其是对口支援医院、医联体内医院）进修并返回原医院独立工作人数占比。考核年度内医院接受其他医院（尤其是对口支援医院、医联体内医院）人员进修培训且返回原单位总人数占同期招收进修总人数的比例
A65: 医院住院医师首次参加医师资格考试通过率 | B65: % | C65: 科教科 | D65: 69.35 | E65: 52.63 | F65: 80.33 | G65: 详见三级中医、三级公立国考手册 | H65: 本年度首次参加医师资格考试并通过的住院医师人数/同期首次参加医师资格考试的住院医师总人数*100
A66: 医院在医学人才培养方面的经费投入占比 | B66: % | C66: 科教科 | D66: 1.21 | E66: 1.09 | F66: 0.92 | G66: 参考三级中医、三级公立国考手册，医院承担培养医学人才的工作成效的构成元素 | H66: （院校医学教学经费投入+毕业后医学教育经费投入+继续医学教育经费投入）/医院当年总费用*100
A67: 临床带教教师和指导医师接受教育教学培训占比 | B67: % | C67: 科教科 | D67: 29.2 | E67: 42.21 | F67: 28.08 | G67: 参考三级中医、三级公立国考手册，医院承担培养医学人才的工作成效的构成元素 | H67: 临床带教教师和指导医师接受省级及以上教育教学培训且取得培训合格证书的人数/临床带教教师和指导医师人数*100
A68: 医院医学教育专职管理人员数与医院教育培训学员数之比 | C68: 科教科 | D68: 0.008 | E68: 0.01 | F68: 0.008 | G68: 参考三级中医、三级公立国考手册，医院承担培养医学人才的工作成效的构成元素。原计量单位为比值（1:X），现改为小数 | H68: （本年度院校医学教育专职管理人员数+毕业后医学教育专职管理人员数+继续医学教育专职管理人员数）/同期医院教育培训学员数
A69: 发表教学文章数与卫生技术人员数之比 | C69: 科教科 | D69: 0.001199 | E69: 0.001622 | F69: 0.001654 | G69: 参考三级中医、三级公立国考手册，医院承担培养医学人才的工作成效的构成元素。原计量单位为比值（1:X），现改为小数 | H69: 本年度发表的教学文章数/同期卫生技术人员总数
A70: 省部级及以上教育教学课题数与卫生技术人员数之比 | C70: 科教科 | D70: 0 | E70: 0.000406 | F70: 0.000413 | G70: 参考三级中医、三级公立国考手册，医院承担培养医学人才的工作成效的构成元素。本指标为延伸指标。原计量单位为比值（1:X），现改为小数 | H70: 本年度获得的省部级及以上教育教学课题数/同期卫生技术人员总数
A71: 国家级继续医学教育项目数与卫生技术人员数之比 | C71: 科教科 | D71: 0.003 | E71: 0.002 | F71: 0.003 | G71: 参考三级中医、三级公立国考手册，医院承担培养医学人才的工作成效的构成元素。本指标为延伸指标。原计量单位为比值（1:X），现改为小数 | H71: 本年度举办的国家级继续医学教育项目数/同期卫生技术人员总数
A72: 每百名卫生技术人员科研项目经费 | B72: 元 | C72: 科教科 | D72: 918263.97 | E72: 427465.53 | F72: 16122.365 | G72: 详见三级中医、三级公立国考手册 | H72: 本年度科研项目立项经费总金额/同期卫生技术人员总数*100
A73: 每百名卫生技术人员科研成果转化金额 | B73: 元 | C73: 科教科 | D73: 167370.39 | E73: 136625.18 | F73: 114612.19 | G73: 详见三级公立国考手册 | H73: 本年度科技成果转化总金额/同期医院卫生技术人员总数*100
A74: 医师人均国家自然科学基金项目数量 | B74: 项 | C74: 科教科 | D74: 0 | E74: 0 | F74: 0 | G74: 说明：本年度成功立项的项目数量。要求本科室为主研单位
A75: 医师人均SCI文章数量 | B75: 篇 | C75: 科教科 | D75: 0.077 | E75: 0.062 | F75: 0.026 | G75: 说明：本年度成功发表的论文，要求第一作者或通讯作者为本院员工
A76: SCI平均影响因子 | B76: 分 | C76: 科教科 | D76: 0.366 | E76: 0.165 | F76: 0.06 | G76: 说明：本年度成功发表的论文，要求第一作者或通讯作者为本院员工
A77: 博士研究生导师占比 | B77: % | C77: 科教科 | D77: 0.13 | E77: 0.14 | F77: 0.14 | H77: 博士研究生导师人数/同期医师总数*100
A78: 硕士研究生导师占比 | B78: % | C78: 科教科 | D78: 5.91 | E78: 5.8 | F78: 1 | H78: 硕士研究生导师人数/同期医师总数*100
A79: 外省住院患者占比 | B79: % | C79: 统计室 | D79: 3.7470318 | E79: 4.0743282 | F79: 5.0538584 | H79: 外省住院患者人数/同期出院患者人次数*100
A80: 非医嘱离院率 | B80: % | C80: 统计室 | D80: 1.8640177 | E80: 2.7980525 | F80: 2.7953004 | H80: 非医嘱离院人次/同期出院患者总人次*100

Sheet 大心血管科
A1: 数据名 | B1: 计量单位 | C1: 填报部门 | D1: Y2021 | E1: Y2020 | F1: Y2019 | G1: 指标说明 | H1: 计算公式
A2: 出院患者手术占比 | B2: % | C2: 统计室 | D2: 23.190294 | E2: 21.178184 | F2: 17.842007 | G2: 详见三级公立、二级公立国考手册。举例：30%请填写30（不带百分号），而非写成30%，或0.3。下同 | H2: 出院患者手术台次数/同期出院患者总人次数*100
A3: 出院患者微创手术占比 | B3: % | C3: 统计室 | D3: 0.3511236 | E3: 0.64488392 | F3: 0.14251781 | G3: 详见三级公立、二级公立国考手册 | H3: 出院患者微创手术台次数/同期出院患者手术台次数*100
A4: 出院患者四级手术比例 | B4: % | C4: 统计室 | D4: 12.113764 | E4: 10.83405 | F4: 10.831354 | G4: 详见三级公立国考手册 | H4: 出院患者四级手术台次数/同期出院患者手术台次数*100
A5: 出院患者疑难危重病例比例 | B5: % | C5: 统计室 | D5: 99.63 | E5: 99.695 | F5: 98.625 | G5: 即CD型病例占比 | H5: (疑难病例数+危重病例数)/出院人数*100
A6: 手术患者并发症发生率 | B6: % | C6: 质控科 | D6: 0 | E6: 0 | F6: 0 | G6: 详见国考手册 | H6: 手术患者并发症发生例数/同期出院的手术患者人数*100
A7: I类切口手术部位感染率 | B7: % | C7: 质控科 | D7: 0.03 | E7: 0 | F7: 0.04 | G7: 详见三级中医、三级公立国考手册 | H7: I类切口手术部位感染人次数/同期I类切口手术台次数*100
A8: 大型医用设备检查阳性率 | B8: % | C8: 医务科 | G8: 详见三级中医、三级公立国考手册 | H8: 大型医用设备检查阳性数/同期大型医用设备检查人次数*100
A9: 低风险组病例死亡率 | B9: % | C9: 质控科 | D9: 0 | E9: 0 | F9: 0 | G9: 详见三级公立、二级公立国考手册 | H9: 低风险组死亡例数/低风险组病例数*100
A10: 医院感染发生率 | B10: % | C10: 院感科 | D10: 0.37 | E10: 0.55 | F10: 0.7 | G10: 等级评审标准细则
A11: 抗菌药物使用强度DDDs | B11: DDD | C11: 药学部 | D11: 39.832876 | E11: 40.162805 | F11: 35.158241 | G11: 详见国考手册 | H11: 住院患者抗菌药物消耗量（累计DDD数）/同期收治患者人天数*100
A12: 门诊患者基本药物处方占比 | B12: % | C12: 药学部 | D12: 93.115 | E12: 90.49 | F12: 74.075 | G12: 详见三级中医、三级公立国考手册 | H12: 门诊使用基本药物人次数/同期门诊诊疗总人次数*100
A13: 住院患者基本药物使用率 | B13: % | C13: 药学部 | D13: 99.1 | E13: 99.325 | F13: 96.275 | G13: 详见三级中医、三级公立国考手册 | H13: 出院患者使用基本药物总人次数/同期出院总人次数*100
A14: 重点监控高值医用耗材收入占比 | B14: % | C14: 设备科 | D14: =0.1058*100 -> 10.58 | E14: =33130822/(110206952+20678422)*100 -> 25.312853 | F14: =(23470061+4478610)/(128922725+20353525)*100 -> 18.722785 | G14: 详见国考手册 | H14: 重点监控高值医用耗材收入/同期卫生材料收入*100
A15: 平均住院日 | B15: 天 | C15: 统计室 | D15: 8.33 | E15: 8.235 | F15: 8.06 | G15: 详见二级公立国考手册 | H15: 出院患者占用总床日数/同期出院患者人数
A16: CMI值 | C16: 质控科 | G16: 病例组合指数
A17: DRGs组数 | B17: 组 | C17: 质控科 | G17: 诊断相关分组组数
A18: 核定床位数 | B18: 张 | C18: 统计室 | D18: 206 | E18: 206 | F18: 206 | G18: 等级评审标准细则
A19: 实际开放床位数 | B19: 张 | C19: 统计室 | D19: 220 | E19: 196 | F19: 238 | G19: 等级评审标准细则
A20: 开放床位使用率 | B20: % | C20: 统计室 | D20: 102.33 | E20: 88.415 | F20: 95.9 | G20: 等级评审标准细则 | H20: 实际占用的总床日数/同期实际开放的总床日数*100
A21: 医师人数与开放床位数比 | C21: 人事科 | D21: =D43/D19 -> 0.2 | E21: =E43/E19 -> 0.20408163 | F21: =F43/F19 -> 0.15966387 | G21: 等级评审标准细则，原计量单位为比值（1:X），现改为小数 | H21: 医院执业（助理）医师总数/同期全院实际开放床位数
A22: 护士人数与开放床位数比 | C22: 人事科 | D22: =D44/D19 -> 0.48181818 | E22: =E44/E19 -> 0.53061224 | F22: =F44/F19 -> 0.44117647 | G22: 等级评审标准细则，原计量单位为比值（1:X），现改为小数 | H22: 医院注册护士总数/同期全院实际开放床位数
A23: 人均医疗服务收入 | B23: 万元 | C23: 财务科 | D23: 25.570819 | E23: 21.989401 | F23: 22.94347 | G23: 按科室人员数人均医疗服务收入
A24: 人均有效收入 | B24: 万元 | C24: 财务科 | D24: 51.782776 | E24: 46.304564 | F24: 47.216788 | G24: 按科室人员数人均有效收入
A25: 床均医疗服务收入 | B25: 万元 | C25: 财务科 | D25: 19.891496 | E25: 16.060124 | F25: 15.038577 | G25: 按开放床位数床均医疗服务收入
A26: 床均有效收入 | B26: 万元 | C26: 财务科 | D26: 40.281731 | E26: 33.818884 | F26: 30.948819 | G26: 按开放床位数床均有效收入
A27: 每名执业医师日均住院工作负担 | B27: 床日 | C27: 财务科 | D27: 4.8405978 | E27: 4.9060959 | F27: 5.9886806 | G27: 详见三级中医、三级公立国考手册 | H27: 全年实际占用总床日数/医院平均执业(助理)医师人数/365
A28: 医疗服务收入占医疗收入比例 | B28: % | C28: 财务科 | D28: 27.979896 | E28: 25.497914 | F28: 23.070673 | G28: 参考国考手册，原指标名为：医疗服务收入（不含药品、耗材、检查检验收入）占医疗收入比例 | H28: 医疗服务收入/医疗收入*100
A29: 医疗收入 | B29: 万元 | C29: 财务科 | D29: 15079.345 | E29: 13884.641 | F29: 15513.987 | H29: 门诊收入+住院收入
A30: 医疗服务收入 | B30: 万元 | C30: 财务科 | D30: 4219.1851 | E30: 3540.2936 | F30: 3579.1813
A31: 有效收入 | B31: 万元 | C31: 财务科 | D31: 8544.158 | E31: 7455.0347 | F31: 7365.8189 | H31: 医疗服务收入+检查检验收入
A32: 医疗直接成本 | B32: 万元 | D32: 11031.86 | E32: 10317.21 | F32: 11857.84
A33: 收支结余率 | B33: % | D33: -2.32 | E33: -2 | F33: -0.7
A34: 万元收入能耗占比 | B34: 吨标煤/万元 | C34: 后勤管理科 | G34: 详见国考手册 | H34: 年总能耗/年总收入*10000
A35: 门诊收入占医疗收入比例 | B35: % | C35: 财务科 | D35: 9.5830879 | E35: 8.5848501 | F35: 8.4682459 | G35: 详见三级公立国考手册 | H35: 门诊收入/医疗收入*100
A36: 住院收入占医疗收入比例 | B36: % | C36: 财务科 | D36: 90.416912 | E36: 91.41515 | F36: 91.531754 | G36: 详见三级公立国考手册 | H36: 住院收入/医疗收入*100
A37: 医疗收入增幅 | B37: % | C37: 财务科 | D37: 8.6045048 | E37: -10.502436 | F37: 0.22085775 | G37: 详见国考手册 | H37: （本年度医疗收入－上一年度医疗收入）/上一年度医疗收入*100
A38: 门诊次均费用增幅 | B38: % | C38: 财务科 | D38: -1.8092926 | E38: -7.1418152 | F38: 4.2073907 | G38: 详见国考手册 | H38: （本年度门诊患者次均医药费用－上一年度门诊患者次均医药费用）/上一年度门诊患者次均医药费用*100
A39: 住院次均费用增幅 | B39: % | C39: 财务科 | D39: -3.9421621 | E39: -15.060851 | F39: -9.2614934 | G39: 详见国考手册 | H39: （本年度出院患者次均医药费用－上一年度出院患者次均医药费用）/上一年度出院患者次均医药费用*100
A40: 门诊次均药品费用增幅 | B40: % | C40: 财务科 | D40: -1.1297645 | E40: -17.143776 | F40: 8.3875733 | G40: 详见国考手册 | H40: （本年度门诊患者次均药品费用－上一年度门诊患者次均药品费用）/上一年度门诊患者次均药品费用*100
A41: 住院次均药品费用增幅 | B41: % | C41: 财务科 | D41: -2.0127877 | E41: -43.453103 | F41: -20.485375 | G41: 详见国考手册 | H41: （本年度出院患者次均药品费用－上一年度出院患者次均药品费用）/上一年度出院患者次均药品费用*100
A42: 医护比 | C42: 人事科 | D42: 0.42 | E42: 0.38 | F42: 0.36 | G42: 参考国考手册，原计量单位为比值（1:X），现改为小数 | H42: 医院注册医师总数/全院同期注册护士总数
A43: 医师人数 | B43: 人 | C43: 人事科 | D43: 44 | E43: 40 | F43: 38 | G43: 详见国考手册中，医护比定义
A44: 护士人数 | B44: 人 | C44: 人事科 | D44: 106 | E44: 104 | F44: 105 | G44: 详见国考手册中，医护比定义
A45: 医师高级职称占比 | B45: % | C45: 人事科 | D45: 27.27 | E45: 32.5 | F45: 34.21 | H45: (正高职称医师人数+副高职称医师人数)/医师人数*100
A46: 医师博士占比 | B46: % | C46: 人事科 | D46: 4.55 | E46: 5 | F46: 7.89 | H46: 博士医师人数/医师人数*100
A47: 医师硕士占比 | B47: % | C47: 人事科 | D47: 88.64 | E47: 85 | F47: 81.58 | H47: 硕士医师人数/医师人数*100
A48: 发表教学文章数与卫生技术人员数之比 | C48: 科教科 | D48: 0.007 | E48: 0 | F48: 0 | G48: 参考三级中医、三级公立国考手册，医院承担培养医学人才的工作成效的构成元素。原计量单位为比值（1:X），现改为小数 | H48: 本年度发表的教学文章数/同期卫生技术人员总数
A49: 省部级及以上教育教学课题数与卫生技术人员数之比 | C49: 科教科 | D49: 0 | E49: 0 | F49: 0 | G49: 参考三级中医、三级公立国考手册，医院承担培养医学人才的工作成效的构成元素。本指标为延伸指标。原计量单位为比值（1:X），现改为小数 | H49: 本年度获得的省部级及以上教育教学课题数/同期卫生技术人员总数
A50: 国家级继续医学教育项目数与卫生技术人员数之比 | C50: 科教科 | D50: 0 | E50: 0 | F50: 0 | G50: 参考三级中医、三级公立国考手册，医院承担培养医学人才的工作成效的构成元素。本指标为延伸指标。原计量单位为比值（1:X），现改为小数 | H50: 本年度举办的国家级继续医学教育项目数/同期卫生技术人员总数
A51: 每百名卫生技术人员科研项目经费 | B51: 元 | C51: 科教科 | D51: 3159420.9 | E51: 2001710.5 | F51: 363589.68 | G51: 详见三级中医、三级公立国考手册 | H51: 本年度科研项目立项经费总金额/同期卫生技术人员总数*100
A52: 每百名卫生技术人员科研成果转化金额 | B52: 元 | C52: 科教科 | D52: 0 | E52: 0 | F52: 0 | G52: 详见三级公立国考手册 | H52: 本年度科技成果转化总金额/同期医院卫生技术人员总数*100
A53: 医师人均国家自然科学基金项目数量 | B53: 项 | C53: 科教科 | D53: 0 | E53: 0 | F53: 0 | G53: 说明：本年度成功立项的项目数量。要求本科室为主研单位
A54: 医师人均SCI文章数量 | B54: 篇 | C54: 科教科 | D54: 0.028 | E54: 0.029 | F54: 0 | G54: 说明：本年度成功发表的论文，要求第一作者或通讯作者为本院员工
A55: SCI平均影响因子 | B55: 分 | C55: 科教科 | D55: 0.411 | E55: 0.046 | F55: 0 | G55: 说明：本年度成功发表的论文，要求第一作者或通讯作者为本院员工
A56: 博士研究生导师占比 | B56: % | C56: 科教科 | D56: 0 | E56: 0 | F56: 0 | H56: 博士研究生导师人数/同期医师总数*100
A57: 硕士研究生导师占比 | B57: % | C57: 科教科 | D57: 11.11 | E57: 11.76 | F57: 2.94 | H57: 硕士研究生导师人数/同期医师总数*100
A58: 外省住院患者占比 | B58: % | C58: 统计室 | D58: 3.2062154 | E58: 3.4162542 | F58: 4.0404647 | H58: 外省住院患者人数/同期出院患者人次数*100
A59: 非医嘱离院率 | B59: % | C59: 统计室 | D59: 4.9507369 | E59: 5.6086679 | F59: 5.9586371 | H59: 非医嘱离院人次/同期出院患者总人次*100
A60: 是否为教育部或科技部重点学科或重点实验室 | B60: 分 | C60: 科教科 | D60: 0 | E60: 0 | F60: 0 | G60: 是填1,否填0
A61: 是否为国家卫健委临床重点专科 | B61: 分 | C61: 科教科 | D61: 0 | E61: 0 | F61: 0 | G61: 是填1,否填0
A62: 是否为国家中医药局重点专科 | B62: 分 | C62: 科教科 | D62: 0 | E62: 0 | F62: 0 | G62: 是填1,否填0
A63: 是否为省教育厅或科技厅重点学科或重点实验室 | B63: 分 | C63: 科教科 | D63: 0 | E63: 0 | F63: 0 | G63: 是填1,否填0
A64: 是否为省卫健委重点专科 | B64: 分 | C64: 科教科 | D64: 1 | E64: 1 | F64: 1 | G64: 是填1,否填0
A65: 是否为省中医药局重点专科 | B65: 分 | C65: 科教科 | D65: 0 | E65: 0 | F65: 0 | G65: 是填1,否填0
A66: 是否为地市级教育局或科技局重点学科或重点实验室 | B66: 分 | C66: 科教科 | D66: 0 | E66: 0 | F66: 0 | G66: 是填1,否填0
A67: 是否为地市级卫健委重点专科 | B67: 分 | C67: 科教科 | D67: 1 | E67: 1 | F67: 1 | G67: 是填1,否填0
A68: 是否为地市级中医药局重点专科 | B68: 分 | C68: 科教科 | D68: 0 | E68: 0 | F68: 0 | G68: 是填1,否填0
A69: 是否为县级教育局或科技局重点学科或重点实验室 | B69: 分 | C69: 科教科 | D69: 0 | E69: 0 | F69: 0 | G69: 是填1,否填0
A70: 是否为县级卫健委重点专科 | B70: 分 | C70: 科教科 | D70: 0 | E70: 0 | F70: 0 | G70: 是填1,否填0
A71: 是否为县级中医药局重点专科 | B71: 分 | C71: 科教科 | D71: 0 | E71: 0 | F71: 0 | G71: 是填1,否填0
A72: 第一顺位疾病名称 | C72: 信息科 | D72: =[1]大心血管科!$O$4 -> 心绞痛 | E72: =[1]大心血管科!$I$4 -> 心绞痛 | F72: =[1]大心血管科!$C$4 -> 心绞痛
A73: 第一顺位疾病编码 | C73: 信息科 | D73: =[1]大心血管科!$N$4 -> I20 | E73: =[1]大心血管科!$H$4 -> I20 | F73: =[1]大心血管科!$B$4 -> I20
A74: 第一顺位疾病占比 | B74: % | C74: 信息科 | D74: =[1]大心血管科!$Q$4 -> 20.560215 | E74: =[1]大心血管科!$K$4 -> 19.129564 | F74: =[1]大心血管科!$E$4 -> 18.655704
A75: 第二顺位疾病名称 | C75: 信息科 | D75: =[1]大心血管科!$O$5 -> 冠状动脉粥样硬化性心脏病 | E75: =[1]大心血管科!$I$5 -> 冠状动脉粥样硬化性心脏病 | F75: =[1]大心血管科!$C$5 -> 冠状动脉粥样硬化性心脏病
A76: 第二顺位疾病编码 | C76: 信息科 | D76: =[1]大心血管科!$N$5 -> I25.1 | E76: =[1]大心血管科!$H$5 -> I25.1 | F76: =[1]大心血管科!$B$5 -> I25.1
A77: 第二顺位疾病占比 | B77: % | C77: 信息科 | D77: =[1]大心血管科!$Q$5 -> 13.907662 | E77: =[1]大心血管科!$K$5 -> 13.193117 | F77: =[1]大心血管科!$E$5 -> 13.510765
A78: 第三顺位疾病名称 | C78: 信息科 | D78: =[1]大心血管科!$O$6 -> 急性心肌梗死 | E78: =[1]大心血管科!$I$6 -> 急性心肌梗死 | F78: =[1]大心血管科!$C$6 -> 急性心肌梗死
A79: 第三顺位疾病编码 | C79: 信息科 | D79: =[1]大心血管科!$N$6 -> I21 | E79: =[1]大心血管科!$H$6 -> I21 | F79: =[1]大心血管科!$B$6 -> I21
A80: 第三顺位疾病占比 | B80: % | C80: 信息科 | D80: =[1]大心血管科!$Q$6 -> 10.162039 | E80: =[1]大心血管科!$K$6 -> 11.344806 | F80: =[1]大心血管科!$E$6 -> 10.58654
A81: 第四顺位疾病名称 | C81: 信息科 | D81: =[1]大心血管科!$O$7 -> 瓣膜心内膜炎 | E81: =[1]大心血管科!$I$7 -> 脑梗死 | F81: =[1]大心血管科!$C$7 -> 脑梗死
A82: 第四顺位疾病编码 | C82: 信息科 | D82: =[1]大心血管科!$N$7 -> I38 | E82: =[1]大心血管科!$H$7 -> I63 | F82: =[1]大心血管科!$B$7 -> I63
A83: 第四顺位疾病占比 | B83: % | C83: 信息科 | D83: =[1]大心血管科!$Q$7 -> 4.2748962 | E83: =[1]大心血管科!$K$7 -> 4.1427661 | F83: =[1]大心血管科!$E$7 -> 5.2975081
A84: 第五顺位疾病名称 | C84: 信息科 | D84: =[1]大心血管科!$O$8 -> 脑梗死 | E84: =[1]大心血管科!$I$8 -> 心力衰竭 | F84: =[1]大心血管科!$C$8 -> 特发性(原发性)高血压
A85: 第五顺位疾病编码 | C85: 信息科 | D85: =[1]大心血管科!$N$8 -> I63 | E85: =[1]大心血管科!$H$8 -> I50 | F85: =[1]大心血管科!$B$8 -> I10
A86: 第五顺位疾病占比 | B86: % | C86: 信息科 | D86: =[1]大心血管科!$Q$8 -> 3.4850582 | E86: =[1]大心血管科!$K$8 -> 3.4234726 | F86: =[1]大心血管科!$E$8 -> 4.1447703
A87: 第一顺位手术名称 | C87: 信息科 | D87: =[2]大心血管科!$O$4 -> 药物洗脱冠状动脉支架置入 | E87: =[2]大心血管科!$I$4 -> 药物洗脱冠状动脉支架植入术 | F87: =[2]大心血管科!$C$4 -> 药物洗脱冠状动脉支架植入术
A88: 第一顺位手术编码 | C88: 信息科 | D88: =[2]大心血管科!$N$4 -> 36.07 | E88: =[2]大心血管科!$H$4 -> 36.07 | F88: =[2]大心血管科!$B$4 -> 36.07
A89: 第一顺位手术占比 | B89: % | C89: 信息科 | D89: =[2]大心血管科!$Q$4 -> 14.96 | E89: =[2]大心血管科!$K$4 -> 76.870163 | F89: =[2]大心血管科!$E$4 -> 76.104513
A90: 第二顺位手术名称 | C90: 信息科 | D90: =[2]大心血管科!$O$5 -> 冠状动脉药物涂层支架置入术 | E90: =[2]大心血管科!$I$5 -> 心脏病损腔内消融术 | F90: =[2]大心血管科!$C$5 -> 心脏病损腔内消融术
A91: 第二顺位手术编码 | C91: 信息科 | D91: =[2]大心血管科!$N$5 -> 36.06 | E91: =[2]大心血管科!$H$5 -> 37.34 | F91: =[2]大心血管科!$B$5 -> 37.34
A92: 第二顺位手术占比 | B92: % | C92: 信息科 | D92: =[2]大心血管科!$Q$5 -> 1.7 | E92: =[2]大心血管科!$K$5 -> 5.9329321 | F92: =[2]大心血管科!$E$5 -> 7.695962
A93: 第三顺位手术名称 | C93: 信息科 | D93: =[2]大心血管科!$O$6 -> 经导管心脏射频消融术 | E93: =[2]大心血管科!$I$6 -> 胸主动脉移植物的血管腔内植入术 | F93: =[2]大心血管科!$C$6 -> 胸主动脉支架植入术
A94: 第三顺位手术编码 | C94: 信息科 | D94: =[2]大心血管科!$N$6 -> 37.34 | E94: =[2]大心血管科!$H$6 -> 39.73 | F94: =[2]大心血管科!$B$6 -> 39.73
A95: 第三顺位手术占比 | B95: % | C95: 信息科 | D95: =[2]大心血管科!$Q$6 -> 1.66 | E95: =[2]大心血管科!$K$6 -> 2.7085125 | F95: =[2]大心血管科!$E$6 -> 2.5178147
A96: 第四顺位手术名称 | C96: 信息科 | D96: =[2]大心血管科!$O$7 -> 二尖瓣机械瓣膜置换术 | E96: =[2]大心血管科!$I$7 -> 二尖瓣机械瓣膜置换术 | F96: =[2]大心血管科!$C$7 -> 二尖瓣机械瓣膜置换术
A97: 第四顺位手术编码 | C97: 信息科 | D97: =[2]大心血管科!$N$7 -> 35.24 | E97: =[2]大心血管科!$H$7 -> 35.24 | F97: =[2]大心血管科!$B$7 -> 35.24
A98: 第四顺位手术占比 | B98: % | C98: 信息科 | D98: =[2]大心血管科!$Q$7 -> 0.72 | E98: =[2]大心血管科!$K$7 -> 1.805675 | F98: =[2]大心血管科!$E$7 -> 1.7577197
A99: 第五顺位手术名称 | C99: 信息科 | D99: =[2]大心血管科!$O$8 -> 胸主动脉覆膜支架腔内隔绝术 | E99: =[2]大心血管科!$I$8 -> 下腔静脉滤器植入术 | F99: =[2]大心血管科!$C$8 -> 冠状动脉血管腔内成形术(PTCA)
A100: 第五顺位手术编码 | C100: 信息科 | D100: =[2]大心血管科!$N$8 -> 39.73 | E100: =[2]大心血管科!$H$8 -> 38.70 | F100: =[2]大心血管科!$B$8 -> 00.66
...

Sheet 心血管内科
A1: 数据名 | B1: 计量单位 | C1: 填报部门 | D1: Y2021 | E1: Y2020 | F1: Y2019 | G1: 指标说明 | H1: 计算公式
A2: 出院患者手术占比 | B2: % | C2: 统计室 | D2: 21.647609 | E2: 19.818164 | F2: 16.767933 | G2: 详见三级公立、二级公立国考手册。举例：30%请填写30（不带百分号），而非写成30%，或0.3。下同 | H2: 出院患者手术台次数/同期出院患者总人次数*100
A3: 出院患者微创手术占比 | B3: % | C3: 统计室 | D3: 0.12004802 | E3: 0.048804295 | F3: 0.10816658 | G3: 详见三级公立、二级公立国考手册 | H3: 出院患者微创手术台次数/同期出院患者手术台次数*100
A4: 出院患者四级手术比例 | B4: % | C4: 统计室 | D4: 1.5206082 | E4: 0.9272816 | F4: 1.2439156 | G4: 详见三级公立国考手册 | H4: 出院患者四级手术台次数/同期出院患者手术台次数*100
A5: 出院患者疑难危重病例比例 | B5: % | C5: 统计室 | D5: 99.4 | E5: 99.39 | F5: 98.29 | G5: 即CD型病例占比 | H5: (疑难病例数+危重病例数)/出院人数*100
A6: 手术患者并发症发生率 | B6: % | C6: 质控科 | D6: 0 | E6: 0 | F6: 0 | G6: 详见国考手册 | H6: 手术患者并发症发生例数/同期出院的手术患者人数*100
A7: I类切口手术部位感染率 | B7: % | C7: 质控科 | D7: 0 | E7: 0 | F7: 0.04 | G7: 详见三级中医、三级公立国考手册 | H7: I类切口手术部位感染人次数/同期I类切口手术台次数*100
A8: 大型医用设备检查阳性率 | B8: % | C8: 医务科 | G8: 详见三级中医、三级公立国考手册 | H8: 大型医用设备检查阳性数/同期大型医用设备检查人次数*100
A9: 低风险组病例死亡率 | B9: % | C9: 质控科 | D9: 0 | E9: 0 | F9: 0 | G9: 详见三级公立、二级公立国考手册 | H9: 低风险组死亡例数/低风险组病例数*100
A10: 医院感染发生率 | B10: % | C10: 院感科 | D10: 0.34 | E10: 0.44 | F10: 0.66 | G10: 等级评审标准细则
A11: 抗菌药物使用强度DDDs | B11: DDD | C11: 药学部 | D11: 18.210171 | E11: 17.582223 | F11: 16.975232 | G11: 详见国考手册 | H11: 住院患者抗菌药物消耗量（累计DDD数）/同期收治患者人天数*100
A12: 门诊患者基本药物处方占比 | B12: % | C12: 药学部 | D12: 95.78 | E12: 89.86 | F12: 72.1 | G12: 详见三级中医、三级公立国考手册 | H12: 门诊使用基本药物人次数/同期门诊诊疗总人次数*100
A13: 住院患者基本药物使用率 | B13: % | C13: 药学部 | D13: 99.46 | E13: 99.29 | F13: 96.79 | G13: 详见三级中医、三级公立国考手册 | H13: 出院患者使用基本药物总人次数/同期出院总人次数*100
A14: 重点监控高值医用耗材收入占比 | B14: % | C14: 设备科 | D14: =(7764647+1000339)/118547152*100 -> 7.3936707 | E14: =32920822/110206952*100 -> 29.87182 | F14: =23470061/128922725*100 -> 18.204751 | G14: 详见国考手册 | H14: 重点监控高值医用耗材收入/同期卫生材料收入*100
A15: 平均住院日 | B15: 天 | C15: 统计室 | D15: 6.16 | E15: 6.4 | F15: 6.92 | G15: 详见二级公立国考手册 | H15: 出院患者占用总床日数/同期出院患者人数
A16: CMI值 | C16: 质控科 | D16: 1.57 | E16: 1.49 | F16: 1.43 | G16: 病例组合指数
A17: DRGs组数 | B17: 组 | C17: 质控科 | D17: 279 | E17: 251 | F17: 267 | G17: 诊断相关分组组数
A18: 核定床位数 | B18: 张 | C18: 统计室 | D18: 190 | E18: 190 | F18: 190 | G18: 等级评审标准细则
A19: 实际开放床位数 | B19: 张 | C19: 统计室 | D19: 203 | E19: 180 | F19: 220 | G19: 等级评审标准细则
A20: 开放床位使用率 | B20: % | C20: 统计室 | D20: 100.06 | E20: 88.85 | F20: 95.57 | G20: 等级评审标准细则 | H20: 实际占用的总床日数/同期实际开放的总床日数*100
A21: 医师人数与开放床位数比 | C21: 人事科 | D21: =D43/D19 -> 0.1773399 | E21: =E43/E19 -> 0.18888889 | F21: =F43/F19 -> 0.15454545 | G21: 等级评审标准细则，原计量单位为比值（1:X），现改为小数 | H21: 医院执业（助理）医师总数/同期全院实际开放床位数
A22: 护士人数与开放床位数比 | C22: 人事科 | D22: =D44/D19 -> 0.52216749 | E22: =E44/E19 -> 0.57777778 | F22: =F44/F19 -> 0.47727273 | G22: 等级评审标准细则，原计量单位为比值（1:X），现改为小数 | H22: 医院注册护士总数/同期全院实际开放床位数
A23: 人均医疗服务收入 | B23: 万元 | C23: 财务科 | D23: 23.810493 | E23: 19.38115 | F23: 21.21953 | G23: 按科室人员数人均医疗服务收入
A24: 人均有效收入 | B24: 万元 | C24: 财务科 | D24: 50.321795 | E24: 42.692755 | F24: 45.31541 | G24: 按科室人员数人均有效收入
A25: 床均医疗服务收入 | B25: 万元 | C25: 财务科 | D25: 18.518189 | E25: 14.873373 | F25: 14.082051 | G25: 按开放床位数床均医疗服务收入
A26: 床均有效收入 | B26: 万元 | C26: 财务科 | D26: 39.136885 | E26: 32.763035 | F26: 30.072954 | G26: 按开放床位数床均有效收入
A27: 每名执业医师日均住院工作负担 | B27: 床日 | C27: 财务科 | D27: 5.4318874 | E27: 5.3265109 | F27: 6.1838034 | G27: 详见三级中医、三级公立国考手册 | H27: 全年实际占用总床日数/医院平均执业(助理)医师人数/365
A28: 医疗服务收入占医疗收入比例 | B28: % | C28: 财务科 | D28: 28.995036 | E28: 25.908957 | F28: 23.142359 | G28: 参考国考手册，原指标名为：医疗服务收入（不含药品、耗材、检查检验收入）占医疗收入比例 | H28: 医疗服务收入/医疗收入*100
A29: 医疗收入 | B29: 万元 | C29: 财务科 | D29: 12482.119 | E29: 11669.552 | F29: 13386.929 | H29: 门诊收入+住院收入
A30: 医疗服务收入 | B30: 万元 | C30: 财务科 | D30: 3619.1949 | E30: 3023.4593 | F30: 3098.0513
A31: 有效收入 | B31: 万元 | C31: 财务科 | D31: 7648.9129 | E31: 6660.0699 | F31: 6616.0499 | H31: 医疗服务收入+检查检验收入
A32: 医疗直接成本 | B32: 万元 | D32: 9349.11 | E32: 8863.6 | F32: 10579.01
A33: 收支结余率 | B33: % | D33: -6.87 | E33: -6.94 | F33: -5.48
A34: 万元收入能耗占比 | B34: 吨标煤/万元 | C34: 后勤管理科 | G34: 详见国考手册 | H34: 年总能耗/年总收入*10000
A35: 门诊收入占医疗收入比例 | B35: % | C35: 财务科 | D35: 10.850673 | E35: 9.5636458 | F35: 9.4331297 | G35: 详见三级公立国考手册 | H35: 门诊收入/医疗收入*100
A36: 住院收入占医疗收入比例 | B36: % | C36: 财务科 | D36: 89.149327 | E36: 90.436354 | F36: 90.56687 | G36: 详见三级公立国考手册 | H36: 住院收入/医疗收入*100
A37: 医疗收入增幅 | B37: % | C37: 财务科 | D37: 6.9631344 | E37: -12.82876 | F37: -0.38687462 | G37: 详见国考手册 | H37: （本年度医疗收入－上一年度医疗收入）/上一年度医疗收入*100
A38: 门诊次均费用增幅 | B38: % | C38: 财务科 | D38: -2.1723017 | E38: -9.3341584 | F38: 3.5656335 | G38: 详见国考手册 | H38: （本年度门诊患者次均医药费用－上一年度门诊患者次均医药费用）/上一年度门诊患者次均医药费用*100
A39: 住院次均费用增幅 | B39: % | C39: 财务科 | D39: -6.0050248 | E39: -6.6986242 | F39: -6.437672 | G39: 详见国考手册 | H39: （本年度出院患者次均医药费用－上一年度出院患者次均医药费用）/上一年度出院患者次均医药费用*100
A40: 门诊次均药品费用增幅 | B40: % | C40: 财务科 | D40: -3.1239045 | E40: -17.851685 | F40: 7.5957336 | G40: 详见国考手册 | H40: （本年度门诊患者次均药品费用－上一年度门诊患者次均药品费用）/上一年度门诊患者次均药品费用*100
A41: 住院次均药品费用增幅 | B41: % | C41: 财务科 | D41: -3.1767865 | E41: -37.114499 | F41: -17.096259 | G41: 详见国考手册 | H41: （本年度出院患者次均药品费用－上一年度出院患者次均药品费用）/上一年度出院患者次均药品费用*100
A42: 医护比 | C42: 人事科 | D42: 0.34 | E42: 0.33 | F42: 0.32 | G42: 参考国考手册，原计量单位为比值（1:X），现改为小数 | H42: 医院注册医师总数/全院同期注册护士总数
A43: 医师人数 | B43: 人 | C43: 人事科 | D43: 36 | E43: 34 | F43: 34 | G43: 详见国考手册中，医护比定义
A44: 护士人数 | B44: 人 | C44: 人事科 | D44: 106 | E44: 104 | F44: 105 | G44: 详见国考手册中，医护比定义
A45: 医师高级职称占比 | B45: % | C45: 人事科 | D45: 22.22 | E45: 29.41 | F45: 32.35 | H45: (正高职称医师人数+副高职称医师人数)/医师人数*100
A46: 医师博士占比 | B46: % | C46: 人事科 | D46: 2.78 | E46: 5.88 | F46: 8.82 | H46: 博士医师人数/医师人数*100
A47: 医师硕士占比 | B47: % | C47: 人事科 | D47: 91.67 | E47: 85.29 | F47: 82.35 | H47: 硕士医师人数/医师人数*100
A48: 发表教学文章数与卫生技术人员数之比 | C48: 科教科 | D48: 0.007 | E48: 0 | F48: 0 | G48: 参考三级中医、三级公立国考手册，医院承担培养医学人才的工作成效的构成元素。原计量单位为比值（1:X），现改为小数 | H48: 本年度发表的教学文章数/同期卫生技术人员总数
A49: 省部级及以上教育教学课题数与卫生技术人员数之比 | C49: 科教科 | D49: 0 | E49: 0 | F49: 0 | G49: 参考三级中医、三级公立国考手册，医院承担培养医学人才的工作成效的构成元素。本指标为延伸指标。原计量单位为比值（1:X），现改为小数 | H49: 本年度获得的省部级及以上教育教学课题数/同期卫生技术人员总数
A50: 国家级继续医学教育项目数与卫生技术人员数之比 | C50: 科教科 | D50: 0 | E50: 0 | F50: 0 | G50: 参考三级中医、三级公立国考手册，医院承担培养医学人才的工作成效的构成元素。本指标为延伸指标。原计量单位为比值（1:X），现改为小数 | H50: 本年度举办的国家级继续医学教育项目数/同期卫生技术人员总数
A51: 每百名卫生技术人员科研项目经费 | B51: 元 | C51: 科教科 | D51: 3159420.9 | E51: 2001710.5 | F51: 363589.68 | G51: 详见三级中医、三级公立国考手册 | H51: 本年度科研项目立项经费总金额/同期卫生技术人员总数*100
A52: 每百名卫生技术人员科研成果转化金额 | B52: 元 | C52: 科教科 | D52: 0 | E52: 0 | F52: 0 | G52: 详见三级公立国考手册 | H52: 本年度科技成果转化总金额/同期医院卫生技术人员总数*100
A53: 医师人均国家自然科学基金项目数量 | B53: 项 | C53: 科教科 | D53: 0 | E53: 0 | F53: 0 | G53: 说明：本年度成功立项的项目数量。要求本科室为主研单位
A54: 医师人均SCI文章数量 | B54: 篇 | C54: 科教科 | D54: 0.028 | E54: 0.029 | F54: 0 | G54: 说明：本年度成功发表的论文，要求第一作者或通讯作者为本院员工
A55: SCI平均影响因子 | B55: 分 | C55: 科教科 | D55: 0.411 | E55: 0.046 | F55: 0 | G55: 说明：本年度成功发表的论文，要求第一作者或通讯作者为本院员工
A56: 博士研究生导师占比 | B56: % | C56: 科教科 | D56: 0 | E56: 0 | F56: 0 | H56: 博士研究生导师人数/同期医师总数*100
A57: 硕士研究生导师占比 | B57: % | C57: 科教科 | D57: 11.11 | E57: 11.76 | F57: 2.94 | H57: 硕士研究生导师人数/同期医师总数*100
A58: 外省住院患者占比 | B58: % | C58: 统计室 | D58: 2.8846154 | E58: 2.7952413 | F58: 3.4116686 | H58: 外省住院患者人数/同期出院患者人次数*100
A59: 非医嘱离院率 | B59: % | C59: 统计室 | D59: 5.2581428 | E59: 5.9290067 | F59: 6.3752607 | H59: 非医嘱离院人次/同期出院患者总人次*100
A60: 是否为教育部或科技部重点学科或重点实验室 | B60: 分 | C60: 科教科 | D60: 0 | E60: 0 | F60: 0 | G60: 是填1,否填0
A61: 是否为国家卫健委临床重点专科 | B61: 分 | C61: 科教科 | D61: 0 | E61: 0 | F61: 0 | G61: 是填1,否填0
A62: 是否为国家中医药局重点专科 | B62: 分 | C62: 科教科 | D62: 0 | E62: 0 | F62: 0 | G62: 是填1,否填0
A63: 是否为省教育厅或科技厅重点学科或重点实验室 | B63: 分 | C63: 科教科 | D63: 0 | E63: 0 | F63: 0 | G63: 是填1,否填0
A64: 是否为省卫健委重点专科 | B64: 分 | C64: 科教科 | D64: 1 | E64: 1 | F64: 1 | G64: 是填1,否填0
A65: 是否为省中医药局重点专科 | B65: 分 | C65: 科教科 | D65: 0 | E65: 0 | F65: 0 | G65: 是填1,否填0
A66: 是否为地市级教育局或科技局重点学科或重点实验室 | B66: 分 | C66: 科教科 | D66: 0 | E66: 0 | F66: 0 | G66: 是填1,否填0
A67: 是否为地市级卫健委重点专科 | B67: 分 | C67: 科教科 | D67: 1 | E67: 1 | F67: 1 | G67: 是填1,否填0
A68: 是否为地市级中医药局重点专科 | B68: 分 | C68: 科教科 | D68: 0 | E68: 0 | F68: 0 | G68: 是填1,否填0
A69: 是否为县级教育局或科技局重点学科或重点实验室 | B69: 分 | C69: 科教科 | D69: 0 | E69: 0 | F69: 0 | G69: 是填1,否填0
A70: 是否为县级卫健委重点专科 | B70: 分 | C70: 科教科 | D70: 0 | E70: 0 | F70: 0 | G70: 是填1,否填0
A71: 是否为县级中医药局重点专科 | B71: 分 | C71: 科教科 | D71: 0 | E71: 0 | F71: 0 | G71: 是填1,否填0
A72: 第一顺位疾病名称 | C72: 信息科 | D72: 0 | E72: 0 | F72: 0
A73: 第一顺位疾病编码 | C73: 信息科 | D73: 0 | E73: 0 | F73: 0
A74: 第一顺位疾病占比 | B74: % | C74: 信息科 | D74: =[1]心血管内科!$Q$4 -> 21.872834 | E74: =[1]心血管内科!$K$4 -> 20.321114 | F74: =[1]心血管内科!$E$4 -> 19.960098
A75: 第二顺位疾病名称 | C75: 信息科 | D75: =[1]心血管内科!$O$5 -> 冠状动脉粥样硬化性心脏病 | E75: =[1]心血管内科!$I$5 -> 冠状动脉粥样硬化性心脏病 | F75: =[1]心血管内科!$C$5 -> 冠状动脉粥样硬化性心脏病
A76: 第二顺位疾病编码 | C76: 信息科 | D76: =[1]心血管内科!$N$5 -> I25.1 | E76: =[1]心血管内科!$H$5 -> I25.1 | F76: =[1]心血管内科!$B$5 -> I25.1
A77: 第二顺位疾病占比 | B77: % | C77: 信息科 | D77: =[1]心血管内科!$Q$5 -> 14.310464 | E77: =[1]心血管内科!$K$5 -> 14.014895 | F77: =[1]心血管内科!$E$5 -> 14.156162
A78: 第三顺位疾病名称 | C78: 信息科 | D78: =[1]心血管内科!$O$6 -> 急性心肌梗死 | E78: =[1]心血管内科!$I$6 -> 急性心肌梗死 | F78: =[1]心血管内科!$C$6 -> 急性心肌梗死
A79: 第三顺位疾病编码 | C79: 信息科 | D79: =[1]心血管内科!$N$6 -> I21 | E79: =[1]心血管内科!$H$6 -> I21 | F79: =[1]心血管内科!$B$6 -> I21
A80: 第三顺位疾病占比 | B80: % | C80: 信息科 | D80: =[1]心血管内科!$Q$6 -> 10.810811 | E80: =[1]心血管内科!$K$6 -> 12.051456 | F80: =[1]心血管内科!$E$6 -> 11.326743
A81: 第四顺位疾病名称 | C81: 信息科 | D81: =[1]心血管内科!$O$7 -> 瓣膜心内膜炎 | E81: =[1]心血管内科!$I$7 -> 脑梗死 | F81: =[1]心血管内科!$C$7 -> 脑梗死
A82: 第四顺位疾病编码 | C82: 信息科 | D82: =[1]心血管内科!$N$7 -> I38 | E82: =[1]心血管内科!$H$7 -> I63 | F82: =[1]心血管内科!$B$7 -> I63
A83: 第四顺位疾病占比 | B83: % | C83: 信息科 | D83: =[1]心血管内科!$Q$7 -> 3.967429 | E83: =[1]心血管内科!$K$7 -> 4.4008125 | F83: =[1]心血管内科!$E$7 -> 5.667906
A84: 第五顺位疾病名称 | C84: 信息科 | D84: =[1]心血管内科!$O$8 -> 脑梗死 | E84: =[1]心血管内科!$I$8 -> 心力衰竭 | F84: =[1]心血管内科!$C$8 -> 特发性(原发性)高血压
A85: 第五顺位疾病编码 | C85: 信息科 | D85: =[1]心血管内科!$N$8 -> I63 | E85: =[1]心血管内科!$H$8 -> I50 | F85: =[1]心血管内科!$B$8 -> I10
A86: 第五顺位疾病占比 | B86: % | C86: 信息科 | D86: =[1]心血管内科!$Q$8 -> 3.7075537 | E86: =[1]心血管内科!$K$8 -> 3.6367153 | F86: =[1]心血管内科!$E$8 -> 4.4345697
A87: 第一顺位手术名称 | C87: 信息科 | D87: =[2]心血管内科!$O$4 -> 药物洗脱冠状动脉支架置入 | E87: =[2]心血管内科!$I$4 -> 药物洗脱冠状动脉支架植入术 | F87: =[2]心血管内科!$C$4 -> 药物洗脱冠状动脉支架植入术
A88: 第一顺位手术编码 | C88: 信息科 | D88: =[2]心血管内科!$N$4 -> 36.07 | E88: =[2]心血管内科!$H$4 -> 36.07 | F88: =[2]心血管内科!$B$4 -> 36.07
A89: 第一顺位手术占比 | B89: % | C89: 信息科 | D89: =[2]心血管内科!$Q$4 -> 73.509404 | E89: =[2]心血管内科!$K$4 -> 87.262079 | F89: =[2]心血管内科!$E$4 -> 86.641428
A90: 第二顺位手术名称 | C90: 信息科 | D90: =[2]心血管内科!$O$5 -> 冠状动脉药物涂层支架置入术 | E90: =[2]心血管内科!$I$5 -> 心脏病损腔内消融术 | F90: =[2]心血管内科!$C$5 -> 心脏病损腔内消融术
A91: 第二顺位手术编码 | C91: 信息科 | D91: =[2]心血管内科!$N$5 -> 36.06 | E91: =[2]心血管内科!$H$5 -> 37.34 | F91: =[2]心血管内科!$B$5 -> 37.34
A92: 第二顺位手术占比 | B92: % | C92: 信息科 | D92: =[2]心血管内科!$Q$5 -> 8.3633453 | E92: =[2]心血管内科!$K$5 -> 6.7349927 | F92: =[2]心血管内科!$E$5 -> 8.7614927
A93: 第三顺位手术名称 | C93: 信息科 | D93: =[2]心血管内科!$O$6 -> 经导管心脏射频消融术 | E93: =[2]心血管内科!$I$6 -> 下腔静脉滤器植入术 | F93: =[2]心血管内科!$C$6 -> 冠状动脉血管腔内成形术(PTCA)
A94: 第三顺位手术编码 | C94: 信息科 | D94: =[2]心血管内科!$N$6 -> 37.34 | E94: =[2]心血管内科!$H$6 -> 38.70 | F94: =[2]心血管内科!$B$6 -> 00.66
A95: 第三顺位手术占比 | B95: % | C95: 信息科 | D95: =[2]心血管内科!$Q$6 -> 8.1632653 | E95: =[2]心血管内科!$K$6 -> 1.3665203 | F95: =[2]心血管内科!$E$6 -> 1.5143321
A96: 第四顺位手术名称 | C96: 信息科 | D96: =[2]心血管内科!$O$7 -> 下腔静脉滤器置入术 | E96: =[2]心血管内科!$I$7 -> 冠状动脉血管腔内成形术(PTCA) | F96: =[2]心血管内科!$C$7 -> 心房间隔缺损封堵术(闭合法)
A97: 第四顺位手术编码 | C97: 信息科 | D97: =[2]心血管内科!$N$7 -> 38.7x | E97: =[2]心血管内科!$H$7 -> 00.66 | F97: =[2]心血管内科!$B$7 -> 35.52
A98: 第四顺位手术占比 | B98: % | C98: 信息科 | D98: =[2]心血管内科!$Q$7 -> 2.2008804 | E98: =[2]心血管内科!$K$7 -> 1.1713031 | F98: =[2]心血管内科!$E$7 -> 0.48674959
A99: 第五顺位手术名称 | C99: 信息科 | D99: =[2]心血管内科!$O$8 -> 经皮冠状动脉腔内血管成形术[PTCA] | E99: =[2]心血管内科!$I$8 -> 下腔静脉植入物去除术 | F99: =[2]心血管内科!$C$8 -> 胸主动脉血管腔内成形术
A100: 第五顺位手术编码 | C100: 信息科 | D100: =[2]心血管内科!$N$8 -> 00.66 | E100: =[2]心血管内科!$H$8 -> 39.49 | F100: =[2]心血管内科!$B$8 -> 39.50
...

Sheet 心脏外科
A1: 数据名 | B1: 计量单位 | C1: 填报部门 | D1: Y2021 | E1: Y2020 | F1: Y2019 | G1: 指标说明 | H1: 计算公式
A2: 出院患者手术占比 | B2: % | C2: 统计室 | D2: 47.354138 | E2: 43.012422 | F2: 33.203632 | G2: 详见三级公立、二级公立国考手册。举例：30%请填写30（不带百分号），而非写成30%，或0.3。下同 | H2: 出院患者手术台次数/同期出院患者总人次数*100
A3: 出院患者微创手术占比 | B3: % | C3: 统计室 | D3: 2.0057307 | E3: 5.0541516 | F3: 0.390625 | G3: 详见三级公立、二级公立国考手册 | H3: 出院患者微创手术台次数/同期出院患者手术台次数*100
A4: 出院患者四级手术比例 | B4: % | C4: 统计室 | D4: 87.965616 | E4: 84.115523 | F4: 80.078125 | G4: 详见三级公立国考手册 | H4: 出院患者四级手术台次数/同期出院患者手术台次数*100
A5: 出院患者疑难危重病例比例 | B5: % | C5: 统计室 | D5: 99.86 | E5: 100 | F5: 98.96 | G5: 即CD型病例占比 | H5: (疑难病例数+危重病例数)/出院人数*100
A6: 手术患者并发症发生率 | B6: % | C6: 质控科 | D6: 0 | E6: 0 | F6: 0 | G6: 详见国考手册 | H6: 手术患者并发症发生例数/同期出院的手术患者人数*100
A7: I类切口手术部位感染率 | B7: % | C7: 质控科 | D7: 0.26 | E7: 0 | F7: 0 | G7: 详见三级中医、三级公立国考手册 | H7: I类切口手术部位感染人次数/同期I类切口手术台次数*100
A8: 大型医用设备检查阳性率 | B8: % | C8: 医务科 | G8: 详见三级中医、三级公立国考手册 | H8: 大型医用设备检查阳性数/同期大型医用设备检查人次数*100
A9: 低风险组病例死亡率 | B9: % | C9: 质控科 | D9: 0 | E9: 0 | F9: 0 | G9: 详见三级公立、二级公立国考手册 | H9: 低风险组死亡例数/低风险组病例数*100
A10: 医院感染发生率 | B10: % | C10: 院感科 | D10: 0.93 | E10: 2.21 | F10: 1.28 | G10: 等级评审标准细则
A11: 抗菌药物使用强度DDDs | B11: DDD | C11: 药学部 | D11: 61.455581 | E11: 62.743386 | F11: 53.34125 | G11: 详见国考手册 | H11: 住院患者抗菌药物消耗量（累计DDD数）/同期收治患者人天数*100
A12: 门诊患者基本药物处方占比 | B12: % | C12: 药学部 | D12: 90.45 | E12: 91.12 | F12: 76.05 | G12: 详见三级中医、三级公立国考手册 | H12: 门诊使用基本药物人次数/同期门诊诊疗总人次数*100
A13: 住院患者基本药物使用率 | B13: % | C13: 药学部 | D13: 98.74 | E13: 99.36 | F13: 95.76 | G13: 详见三级中医、三级公立国考手册 | H13: 出院患者使用基本药物总人次数/同期出院总人次数*100
A14: 重点监控高值医用耗材收入占比 | B14: % | C14: 设备科 | D14: =(5416100+771120)/22790299*100 -> 27.148481 | E14: =5640850/20678422*100 -> 27.278919 | F14: =4478610/20353525*100 -> 22.0041 | G14: 详见国考手册 | H14: 重点监控高值医用耗材收入/同期卫生材料收入*100
A15: 平均住院日 | B15: 天 | C15: 统计室 | D15: 10.5 | E15: 10.07 | F15: 9.2 | G15: 详见二级公立国考手册 | H15: 出院患者占用总床日数/同期出院患者人数
A16: CMI值 | C16: 质控科 | D16: 4.43 | E16: 4.11 | F16: 3.25 | G16: 病例组合指数
A17: DRGs组数 | B17: 组 | C17: 质控科 | D17: 80 | E17: 73 | F17: 84 | G17: 诊断相关分组组数
A18: 核定床位数 | B18: 张 | C18: 统计室 | D18: 16 | E18: 16 | F18: 16 | G18: 等级评审标准细则
A19: 实际开放床位数 | B19: 张 | C19: 统计室 | D19: 17 | E19: 16 | F19: 18 | G19: 等级评审标准细则
A20: 开放床位使用率 | B20: % | C20: 统计室 | D20: 104.6 | E20: 87.98 | F20: 96.23 | G20: 等级评审标准细则 | H20: 实际占用的总床日数/同期实际开放的总床日数*100
A21: 医师人数与开放床位数比 | C21: 人事科 | D21: =D43/D19 -> 0.41176471 | E21: =E43/E19 -> 0.375 | F21: =F43/F19 -> 0.22222222 | G21: 等级评审标准细则，原计量单位为比值（1:X），现改为小数 | H21: 医院执业（助理）医师总数/同期全院实际开放床位数
A22: 护士人数与开放床位数比 | C22: 人事科 | D22: =D44/D19 -> 1.2352941 | E22: =E44/E19 -> 1.0625 | F22: =F44/F19 -> 0.94444444 | G22: 等级评审标准细则，原计量单位为比值（1:X），现改为小数 | H22: 医院注册护士总数/同期全院实际开放床位数
A23: 人均医疗服务收入 | B23: 万元 | C23: 财务科 | D23: 46.153092 | E23: 103.36686 | F23: 48.112997 | G23: 按科室人员数人均医疗服务收入
A24: 人均有效收入 | B24: 万元 | C24: 财务科 | D24: 68.865008 | E24: 158.99298 | F24: 74.976901 | G24: 按科室人员数人均有效收入
A25: 床均医疗服务收入 | B25: 万元 | C25: 财务科 | D25: 35.992213 | E25: 30.118549 | F25: 26.729443 | G25: 按开放床位数床均医疗服务收入
A26: 床均有效收入 | B26: 万元 | C26: 财务科 | D26: 53.703966 | E26: 46.326626 | F26: 41.653834 | G26: 按开放床位数床均有效收入
A27: 每名执业医师日均住院工作负担 | B27: 床日 | C27: 财务科 | D27: 2.4911937 | E27: 2.5237443 | F27: 4.330137 | G27: 详见三级中医、三级公立国考手册 | H27: 全年实际占用总床日数/医院平均执业(助理)医师人数/365
A28: 医疗服务收入占医疗收入比例 | B28: % | C28: 财务科 | D28: 23.101193 | E28: 23.332449 | F28: 22.619509 | G28: 参考国考手册，原指标名为：医疗服务收入（不含药品、耗材、检查检验收入）占医疗收入比例 | H28: 医疗服务收入/医疗收入*100
A29: 医疗收入 | B29: 万元 | C29: 财务科 | D29: 2597.226 | E29: 2215.0881 | F29: 2127.0576 | H29: 门诊收入+住院收入
A30: 医疗服务收入 | B30: 万元 | C30: 财务科 | D30: 599.99019 | E30: 516.8343 | F30: 481.12997
A31: 有效收入 | B31: 万元 | C31: 财务科 | D31: 895.24511 | E31: 794.96489 | F31: 749.76901 | H31: 医疗服务收入+检查检验收入
A32: 医疗直接成本 | B32: 万元 | D32: 1682.75 | E32: 1453.6 | F32: 1278.83
A33: 收支结余率 | B33: % | D33: 26.3 | E33: 24.07 | F33: 22.3
A34: 万元收入能耗占比 | B34: 吨标煤/万元 | C34: 后勤管理科 | G34: 详见国考手册 | H34: 年总能耗/年总收入*10000
A35: 门诊收入占医疗收入比例 | B35: % | C35: 财务科 | D35: 3.4911444 | E35: 3.4283475 | F35: 2.3956174 | G35: 详见三级公立国考手册 | H35: 门诊收入/医疗收入*100
A36: 住院收入占医疗收入比例 | B36: % | C36: 财务科 | D36: 96.508856 | E36: 96.571653 | F36: 97.604383 | G36: 详见三级公立国考手册 | H36: 住院收入/医疗收入*100
A37: 医疗收入增幅 | B37: % | C37: 财务科 | D37: 17.251591 | E37: 4.1386036 | F37: 4.2226989 | G37: 详见国考手册 | H37: （本年度医疗收入－上一年度医疗收入）/上一年度医疗收入*100
A38: 门诊次均费用增幅 | B38: % | C38: 财务科 | D38: 2.2728365 | E38: 48.359273 | F38: 15.967105 | G38: 详见国考手册 | H38: （本年度门诊患者次均医药费用－上一年度门诊患者次均医药费用）/上一年度门诊患者次均医药费用*100
A39: 住院次均费用增幅 | B39: % | C39: 财务科 | D39: 6.1698802 | E39: 28.929786 | F39: -6.6898599 | G39: 详见国考手册 | H39: （本年度出院患者次均医药费用－上一年度出院患者次均医药费用）/上一年度出院患者次均医药费用*100
A40: 门诊次均药品费用增幅 | B40: % | C40: 财务科 | D40: 65.422451 | E40: 37.34942 | F40: 48.422107 | G40: 详见国考手册 | H40: （本年度门诊患者次均药品费用－上一年度门诊患者次均药品费用）/上一年度门诊患者次均药品费用*100
A41: 住院次均药品费用增幅 | B41: % | C41: 财务科 | D41: 4.4620095 | E41: -18.654581 | F41: -23.614237 | G41: 详见国考手册 | H41: （本年度出院患者次均药品费用－上一年度出院患者次均药品费用）/上一年度出院患者次均药品费用*100
A42: 医护比 | C42: 人事科 | D42: 0.33 | E42: 0.35 | F42: 0.24 | G42: 参考国考手册，原计量单位为比值（1:X），现改为小数 | H42: 医院注册医师总数/全院同期注册护士总数
A43: 医师人数 | B43: 人 | C43: 人事科 | D43: 7 | E43: 6 | F43: 4 | G43: 详见国考手册中，医护比定义
A44: 护士人数 | B44: 人 | C44: 人事科 | D44: 21 | E44: 17 | F44: 17 | G44: 详见国考手册中，医护比定义
A45: 医师高级职称占比 | B45: % | C45: 人事科 | D45: 42.86 | E45: 50 | F45: 50 | H45: (正高职称医师人数+副高职称医师人数)/医师人数*100
A46: 医师博士占比 | B46: % | C46: 人事科 | D46: 0 | E46: 0 | F46: 0 | H46: 博士医师人数/医师人数*100
A47: 医师硕士占比 | B47: % | C47: 人事科 | D47: 85.71 | E47: 83.33 | F47: 75 | H47: 硕士医师人数/医师人数*100
A48: 发表教学文章数与卫生技术人员数之比 | C48: 科教科 | D48: 0 | E48: 0 | F48: 0 | G48: 参考三级中医、三级公立国考手册，医院承担培养医学人才的工作成效的构成元素。原计量单位为比值（1:X），现改为小数 | H48: 本年度发表的教学文章数/同期卫生技术人员总数
A49: 省部级及以上教育教学课题数与卫生技术人员数之比 | C49: 科教科 | D49: 0 | E49: 0 | F49: 0 | G49: 参考三级中医、三级公立国考手册，医院承担培养医学人才的工作成效的构成元素。本指标为延伸指标。原计量单位为比值（1:X），现改为小数 | H49: 本年度获得的省部级及以上教育教学课题数/同期卫生技术人员总数
A50: 国家级继续医学教育项目数与卫生技术人员数之比 | C50: 科教科 | D50: 0 | E50: 0 | F50: 0 | G50: 参考三级中医、三级公立国考手册，医院承担培养医学人才的工作成效的构成元素。本指标为延伸指标。原计量单位为比值（1:X），现改为小数 | H50: 本年度举办的国家级继续医学教育项目数/同期卫生技术人员总数
A51: 每百名卫生技术人员科研项目经费 | B51: 元 | C51: 科教科 | D51: 0 | E51: 0 | F51: 0 | G51: 详见三级中医、三级公立国考手册 | H51: 本年度科研项目立项经费总金额/同期卫生技术人员总数*100
A52: 每百名卫生技术人员科研成果转化金额 | B52: 元 | C52: 科教科 | D52: 0 | E52: 0 | F52: 0 | G52: 详见三级公立国考手册 | H52: 本年度科技成果转化总金额/同期医院卫生技术人员总数*100
A53: 医师人均国家自然科学基金项目数量 | B53: 项 | C53: 科教科 | D53: 0 | E53: 0 | F53: 0 | G53: 说明：本年度成功立项的项目数量。要求本科室为主研单位
A54: 医师人均SCI文章数量 | B54: 篇 | C54: 科教科 | D54: 0 | E54: 0 | F54: 0 | G54: 说明：本年度成功发表的论文，要求第一作者或通讯作者为本院员工
A55: SCI平均影响因子 | B55: 分 | C55: 科教科 | D55: 0 | E55: 0 | F55: 0 | G55: 说明：本年度成功发表的论文，要求第一作者或通讯作者为本院员工
A56: 博士研究生导师占比 | B56: % | C56: 科教科 | D56: 0 | E56: 0 | F56: 0 | H56: 博士研究生导师人数/同期医师总数*100
A57: 硕士研究生导师占比 | B57: % | C57: 科教科 | D57: 0 | E57: 0 | F57: 0 | H57: 硕士研究生导师人数/同期医师总数*100
A58: 外省住院患者占比 | B58: % | C58: 统计室 | D58: 3.5278155 | E58: 4.0372671 | F58: 4.6692607 | H58: 外省住院患者人数/同期出院患者人次数*100
A59: 非医嘱离院率 | B59: % | C59: 统计室 | D59: 0.13568521 | E59: 0.46583851 | F59: 0 | H59: 非医嘱离院人次/同期出院患者总人次*100
A60: 是否为教育部或科技部重点学科或重点实验室 | B60: 分 | C60: 科教科 | D60: 0 | E60: 0 | F60: 0 | G60: 是填1,否填0
A61: 是否为国家卫健委临床重点专科 | B61: 分 | C61: 科教科 | D61: 0 | E61: 0 | F61: 0 | G61: 是填1,否填0
A62: 是否为国家中医药局重点专科 | B62: 分 | C62: 科教科 | D62: 0 | E62: 0 | F62: 0 | G62: 是填1,否填0
A63: 是否为省教育厅或科技厅重点学科或重点实验室 | B63: 分 | C63: 科教科 | D63: 0 | E63: 0 | F63: 0 | G63: 是填1,否填0
A64: 是否为省卫健委重点专科 | B64: 分 | C64: 科教科 | D64: 0 | E64: 0 | F64: 0 | G64: 是填1,否填0
A65: 是否为省中医药局重点专科 | B65: 分 | C65: 科教科 | D65: 0 | E65: 0 | F65: 0 | G65: 是填1,否填0
A66: 是否为地市级教育局或科技局重点学科或重点实验室 | B66: 分 | C66: 科教科 | D66: 0 | E66: 0 | F66: 0 | G66: 是填1,否填0
A67: 是否为地市级卫健委重点专科 | B67: 分 | C67: 科教科 | D67: 0 | E67: 0 | F67: 0 | G67: 是填1,否填0
A68: 是否为地市级中医药局重点专科 | B68: 分 | C68: 科教科 | D68: 0 | E68: 0 | F68: 0 | G68: 是填1,否填0
A69: 是否为县级教育局或科技局重点学科或重点实验室 | B69: 分 | C69: 科教科 | D69: 0 | E69: 0 | F69: 0 | G69: 是填1,否填0
A70: 是否为县级卫健委重点专科 | B70: 分 | C70: 科教科 | D70: 0 | E70: 0 | F70: 0 | G70: 是填1,否填0
A71: 是否为县级中医药局重点专科 | B71: 分 | C71: 科教科 | D71: 0 | E71: 0 | F71: 0 | G71: 是填1,否填0
A72: 第一顺位疾病名称 | C72: 信息科 | D72: =[1]心脏外科!$O$4 -> 主动脉瘤和主动脉夹层 | E72: =[1]心脏外科!$I$4 -> 主动脉瘤和主动脉夹层 | F72: =[1]心脏外科!$C$4 -> 主动脉瘤和主动脉夹层
A73: 第一顺位疾病编码 | C73: 信息科 | D73: =[1]心脏外科!$N$4 -> I71 | E73: =[1]心脏外科!$H$4 -> I71. | F73: =[1]心脏外科!$B$4 -> I71
A74: 第一顺位疾病占比 | B74: % | C74: 信息科 | D74: =[1]心脏外科!$Q$4 -> 25.101764 | E74: =[1]心脏外科!$K$4 -> 33.850932 | F74: =[1]心脏外科!$E$4 -> 29.442283
A75: 第二顺位疾病名称 | C75: 信息科 | D75: =[1]心脏外科!$O$5 -> 循环系统的操作后疾患，不可归类在他处者 | E75: =[1]心脏外科!$I$5 -> 心脏外科手术后的其他功能性障碍 | F75: =[1]心脏外科!$C$5 -> 心脏外科手术后的其他功能性障碍
A76: 第二顺位疾病编码 | C76: 信息科 | D76: =[1]心脏外科!$N$5 -> I97 | E76: =[1]心脏外科!$H$5 -> I97.1 | F76: =[1]心脏外科!$B$5 -> I97.1
A77: 第二顺位疾病占比 | B77: % | C77: 信息科 | D77: =[1]心脏外科!$Q$5 -> 12.75441 | E77: =[1]心脏外科!$K$5 -> 16.459627 | F77: =[1]心脏外科!$E$5 -> 26.718547
A78: 第三顺位疾病名称 | C78: 信息科 | D78: =[1]心脏外科!$O$6 -> 风湿性联合瓣膜病 | E78: =[1]心脏外科!$I$6 -> 风湿性联合瓣膜病 | F78: =[1]心脏外科!$C$6 -> 风湿性联合瓣膜病
A79: 第三顺位疾病编码 | C79: 信息科 | D79: =[1]心脏外科!$N$6 -> I08 | E79: =[1]心脏外科!$H$6 -> I08 | F79: =[1]心脏外科!$B$6 -> I08
A80: 第三顺位疾病占比 | B80: % | C80: 信息科 | D80: =[1]心脏外科!$Q$6 -> 10.854817 | E80: =[1]心脏外科!$K$6 -> 10.403727 | F80: =[1]心脏外科!$E$6 -> 8.690013
A81: 第四顺位疾病名称 | C81: 信息科 | D81: =[1]心脏外科!$O$7 -> 瓣膜的心内膜炎 | E81: =[1]心脏外科!$I$7 -> 瓣膜的心内膜炎 | F81: =[1]心脏外科!$C$7 -> 房、室间隔缺损
A82: 第四顺位疾病编码 | C82: 信息科 | D82: =[1]心脏外科!$N$7 -> I38.x | E82: =[1]心脏外科!$H$7 -> I38.x | F82: =[1]心脏外科!$B$7 -> Q21
A83: 第四顺位疾病占比 | B83: % | C83: 信息科 | D83: =[1]心脏外科!$Q$7 -> 9.0909091 | E83: =[1]心脏外科!$K$7 -> 5.4347826 | F83: =[1]心脏外科!$E$7 -> 5.7068742
A84: 第五顺位疾病名称 | C84: 信息科 | D84: =[1]心脏外科!$O$8 -> 冠状动脉硬化性心脏病 | E84: =[1]心脏外科!$I$8 -> 房、室间隔缺损 | F84: =[1]心脏外科!$C$8 -> 冠状动脉硬化性心脏病
A85: 第五顺位疾病编码 | C85: 信息科 | D85: =[1]心脏外科!$N$8 -> I25 | E85: =[1]心脏外科!$H$8 -> Q21 | F85: =[1]心脏外科!$B$8 -> I25.1
A86: 第五顺位疾病占比 | B86: % | C86: 信息科 | D86: =[1]心脏外科!$Q$8 -> 7.734057 | E86: =[1]心脏外科!$K$8 -> 4.0372671 | F86: =[1]心脏外科!$E$8 -> 4.2801556
A87: 第一顺位手术名称 | C87: 信息科 | D87: =[2]心脏外科!$O$4 -> 二尖瓣机械瓣膜置换术 | E87: =[2]心脏外科!$I$4 -> 胸主动脉移植物的血管腔内植入术 | F87: =[2]心脏外科!$C$4 -> 胸主动脉移植物的血管腔内植入术
A88: 第一顺位手术编码 | C88: 信息科 | D88: =[2]心脏外科!$N$4 -> 35.24 | E88: =[2]心脏外科!$H$4 -> 39.73 | F88: =[2]心脏外科!$B$4 -> 39.73
A89: 第一顺位手术占比 | B89: % | C89: 信息科 | D89: =[2]心脏外科!$Q$4 -> 25.501433 | E89: =[2]心脏外科!$K$4 -> 22.743682 | F89: =[2]心脏外科!$E$4 -> 20.703125
A90: 第二顺位手术名称 | C90: 信息科 | D90: =[2]心脏外科!$O$5 -> 胸主动脉覆膜支架腔内隔绝术 | E90: =[2]心脏外科!$I$5 -> 二尖瓣机械瓣膜置换术 | F90: =[2]心脏外科!$C$5 -> 二尖瓣机械瓣膜置换术
A91: 第二顺位手术编码 | C91: 信息科 | D91: =[2]心脏外科!$N$5 -> 39.73 | E91: =[2]心脏外科!$H$5 -> 35.24 | F91: =[2]心脏外科!$B$5 -> 35.24
A92: 第二顺位手术占比 | B92: % | C92: 信息科 | D92: =[2]心脏外科!$Q$5 -> 18.338109 | E92: =[2]心脏外科!$K$5 -> 15.162455 | F92: =[2]心脏外科!$E$5 -> 14.453125
A93: 第三顺位手术名称 | C93: 信息科 | D93: =[2]心脏外科!$O$6 -> 腹主动脉覆膜支架腔内隔绝术 | E93: =[2]心脏外科!$I$6 -> 腹主动脉瘤腔内修补术 | F93: =[2]心脏外科!$C$6 -> 主动脉瓣机械瓣膜置换术
A94: 第三顺位手术编码 | C94: 信息科 | D94: =[2]心脏外科!$N$6 -> 39.71 | E94: =[2]心脏外科!$H$6 -> 39.71 | F94: =[2]心脏外科!$B$6 -> 35.22
A95: 第三顺位手术占比 | B95: % | C95: 信息科 | D95: =[2]心脏外科!$Q$6 -> 9.7421203 | E95: =[2]心脏外科!$K$6 -> 8.6642599 | F95: =[2]心脏外科!$E$6 -> 7.8125
A96: 第四顺位手术名称 | C96: 信息科 | D96: =[2]心脏外科!$O$7 -> 主动脉瓣机械瓣膜置换术 | E96: =[2]心脏外科!$I$7 -> 主动脉瓣机械瓣膜置换术 | F96: =[2]心脏外科!$C$7 -> 腹主动脉瘤腔内修补术
A97: 第四顺位手术编码 | C97: 信息科 | D97: =[2]心脏外科!$N$7 -> 35.22 | E97: =[2]心脏外科!$H$7 -> 35.22 | F97: =[2]心脏外科!$B$7 -> 39.71
A98: 第四顺位手术占比 | B98: % | C98: 信息科 | D98: =[2]心脏外科!$Q$7 -> 5.730659 | E98: =[2]心脏外科!$K$7 -> 6.1371841 | F98: =[2]心脏外科!$E$7 -> 6.640625
A99: 第五顺位手术名称 | C99: 信息科 | D99: =[2]心脏外科!$O$8 -> 经胸房间隔缺损闭式封堵术 | E99: =[2]心脏外科!$I$8 -> 二尖瓣成形术，不伴置换，直视法 | F99: =[2]心脏外科!$C$8 -> 动脉血管腔内成形术
A100: 第五顺位手术编码 | C100: 信息科 | D100: =[2]心脏外科!$N$8 -> 35.51 | E100: =[2]心脏外科!$H$8 -> 35.12 | F100: =[2]心脏外科!$B$8 -> 39.50
...

Sheet 大骨科
A1: 数据名 | B1: 计量单位 | C1: 填报部门 | D1: Y2021 | E1: Y2020 | F1: Y2019 | G1: 指标说明 | H1: 计算公式
A2: 出院患者手术占比 | B2: % | C2: 统计室 | D2: 76.167845 | E2: 65.829617 | F2: 65.526631 | G2: 详见三级公立、二级公立国考手册。举例：30%请填写30（不带百分号），而非写成30%，或0.3。下同 | H2: 出院患者手术台次数/同期出院患者总人次数*100
A3: 出院患者微创手术占比 | B3: % | C3: 统计室 | D3: 10.348501 | E3: 7.5579323 | F3: 7.5964096 | G3: 详见三级公立、二级公立国考手册 | H3: 出院患者微创手术台次数/同期出院患者手术台次数*100
A4: 出院患者四级手术比例 | B4: % | C4: 统计室 | D4: 33.389134 | E4: 31.247772 | F4: 31.100399 | G4: 详见三级公立国考手册 | H4: 出院患者四级手术台次数/同期出院患者手术台次数*100
A5: 出院患者疑难危重病例比例 | B5: % | C5: 统计室 | D5: 95.196667 | E5: 85.523333 | F5: 79.603333 | G5: 即CD型病例占比 | H5: (疑难病例数+危重病例数)/出院人数*100
A6: 手术患者并发症发生率 | B6: % | C6: 质控科 | D6: 0 | E6: 0 | F6: 0 | G6: 详见国考手册 | H6: 手术患者并发症发生例数/同期出院的手术患者人数*100
A7: I类切口手术部位感染率 | B7: % | C7: 质控科 | D7: 0.21 | E7: 0.27 | F7: 0.23 | G7: 详见三级中医、三级公立国考手册 | H7: I类切口手术部位感染人次数/同期I类切口手术台次数*100
A8: 大型医用设备检查阳性率 | B8: % | C8: 医务科 | G8: 详见三级中医、三级公立国考手册 | H8: 大型医用设备检查阳性数/同期大型医用设备检查人次数*100
A9: 低风险组病例死亡率 | B9: % | C9: 质控科 | D9: 0 | E9: 0 | F9: 0 | G9: 详见三级公立、二级公立国考手册 | H9: 低风险组死亡例数/低风险组病例数*100
A10: 医院感染发生率 | B10: % | C10: 院感科 | D10: 1.03 | E10: 1.01 | F10: 0.8 | G10: 等级评审标准细则
A11: 抗菌药物使用强度DDDs | B11: DDD | C11: 药学部 | D11: 45.186613 | E11: 48.461146 | F11: 45.132843 | G11: 详见国考手册 | H11: 住院患者抗菌药物消耗量（累计DDD数）/同期收治患者人天数*100
A12: 门诊患者基本药物处方占比 | B12: % | C12: 药学部 | D12: 79.2 | E12: 71.096667 | F12: 67.34 | G12: 详见三级中医、三级公立国考手册 | H12: 门诊使用基本药物人次数/同期门诊诊疗总人次数*100
A13: 住院患者基本药物使用率 | B13: % | C13: 药学部 | D13: 97.863333 | E13: 96.55 | F13: 95.336667 | G13: 详见三级中医、三级公立国考手册 | H13: 出院患者使用基本药物总人次数/同期出院总人次数*100
A14: 重点监控高值医用耗材收入占比 | B14: % | C14: 设备科 | D14: =(34041302.4+5049693)/(61030488+52314296+34657840)*100 -> 26.412366 | E14: =40248949/(59638630+52373450+30035598)*100 -> 28.334817 | F14: =(22522726+5321361+5301602)/(67539684+56858658+33233253)*100 -> 21.027313 | G14: 详见国考手册 | H14: 重点监控高值医用耗材收入/同期卫生材料收入*100
A15: 平均住院日 | B15: 天 | C15: 统计室 | D15: 9.5 | E15: 9.6433333 | F15: 10.486667 | G15: 详见二级公立国考手册 | H15: 出院患者占用总床日数/同期出院患者人数
A16: CMI值 | C16: 质控科 | G16: 病例组合指数
A17: DRGs组数 | B17: 组 | C17: 质控科 | G17: 诊断相关分组组数
A18: 核定床位数 | B18: 张 | C18: 统计室 | D18: 214 | E18: 214 | F18: 214 | G18: 等级评审标准细则
A19: 实际开放床位数 | B19: 张 | C19: 统计室 | D19: 249 | E19: 214 | F19: 275 | G19: 等级评审标准细则
A20: 开放床位使用率 | B20: % | C20: 统计室 | D20: 94.276667 | E20: 89.743333 | F20: 96.3 | G20: 等级评审标准细则 | H20: 实际占用的总床日数/同期实际开放的总床日数*100
A21: 医师人数与开放床位数比 | C21: 人事科 | D21: =D43/D19 -> 0.13253012 | E21: =E43/E19 -> 0.14953271 | F21: =F43/F19 -> 0.11636364 | G21: 等级评审标准细则，原计量单位为比值（1:X），现改为小数 | H21: 医院执业（助理）医师总数/同期全院实际开放床位数
A22: 护士人数与开放床位数比 | C22: 人事科 | D22: =D44/D19 -> 0.43373494 | E22: =E44/E19 -> 0.55607477 | F22: =F44/F19 -> 0.44 | G22: 等级评审标准细则，原计量单位为比值（1:X），现改为小数 | H22: 医院注册护士总数/同期全院实际开放床位数
A23: 人均医疗服务收入 | B23: 万元 | C23: 财务科 | D23: 35.704502 | E23: 32.307204 | F23: 33.120738 | G23: 按科室人员数人均医疗服务收入
A24: 人均有效收入 | B24: 万元 | C24: 财务科 | D24: 60.182548 | E24: 56.493334 | F24: 56.63798 | G24: 按科室人员数人均有效收入
A25: 床均医疗服务收入 | B25: 万元 | C25: 财务科 | D25: 23.152525 | E25: 20.200095 | F25: 19.631565 | G25: 按开放床位数床均医疗服务收入
A26: 床均有效收入 | B26: 万元 | C26: 财务科 | D26: 39.025274 | E26: 35.322485 | F26: 33.570875 | G26: 按开放床位数床均有效收入
A27: 每名执业医师日均住院工作负担 | B27: 床日 | C27: 财务科 | D27: 6.8298049 | E27: 7.0974315 | F27: 8.2855308 | G27: 详见三级中医、三级公立国考手册 | H27: 全年实际占用总床日数/医院平均执业(助理)医师人数/365
A28: 医疗服务收入占医疗收入比例 | B28: % | C28: 财务科 | D28: 33.605564 | E28: 33.20553 | F28: 32.881393 | G28: 参考国考手册，原指标名为：医疗服务收入（不含药品、耗材、检查检验收入）占医疗收入比例 | H28: 医疗服务收入/医疗收入*100
A29: 医疗收入 | B29: 万元 | C29: 财务科 | D29: 16361.854 | E29: 15177.965 | F29: 16418.649 | H29: 门诊收入+住院收入
A30: 医疗服务收入 | B30: 万元 | C30: 财务科 | D30: 5498.4933 | E30: 5039.9238 | F30: 5398.6803
A31: 有效收入 | B31: 万元 | C31: 财务科 | D31: 9268.1124 | E31: 8812.9601 | F31: 9231.9907 | H31: 医疗服务收入+检查检验收入
A32: 医疗直接成本 | B32: 万元 | D32: 11799.24 | E32: 9924.36 | F32: 11373.22
A33: 收支结余率 | B33: % | D33: 3.26 | E33: 7.14 | F33: 2.18
A34: 万元收入能耗占比 | B34: 吨标煤/万元 | C34: 后勤管理科 | G34: 详见国考手册 | H34: 年总能耗/年总收入*10000
A35: 门诊收入占医疗收入比例 | B35: % | C35: 财务科 | D35: 8.7814786 | E35: 7.7745092 | F35: 7.0768024 | G35: 详见三级公立国考手册 | H35: 门诊收入/医疗收入*100
A36: 住院收入占医疗收入比例 | B36: % | C36: 财务科 | D36: 91.218521 | E36: 92.225491 | F36: 92.923198 | G36: 详见三级公立国考手册 | H36: 住院收入/医疗收入*100
A37: 医疗收入增幅 | B37: % | C37: 财务科 | D37: 7.800047 | E37: -7.556549 | F37: 12.625806 | G37: 详见国考手册 | H37: （本年度医疗收入－上一年度医疗收入）/上一年度医疗收入*100
A38: 门诊次均费用增幅 | B38: % | C38: 财务科 | D38: 2.7962866 | E38: 2.347993 | F38: -66.956926 | G38: 详见国考手册 | H38: （本年度门诊患者次均医药费用－上一年度门诊患者次均医药费用）/上一年度门诊患者次均医药费用*100
A39: 住院次均费用增幅 | B39: % | C39: 财务科 | D39: 6.6463008 | E39: -2.066098 | F39: 19.28938 | G39: 详见国考手册 | H39: （本年度出院患者次均医药费用－上一年度出院患者次均医药费用）/上一年度出院患者次均医药费用*100
A40: 门诊次均药品费用增幅 | B40: % | C40: 财务科 | D40: 5.2522104 | E40: -3.733806 | F40: -63.011532 | G40: 详见国考手册 | H40: （本年度门诊患者次均药品费用－上一年度门诊患者次均药品费用）/上一年度门诊患者次均药品费用*100
A41: 住院次均药品费用增幅 | B41: % | C41: 财务科 | D41: -3.7327155 | E41: -19.478424 | F41: 2.3681169 | G41: 详见国考手册 | H41: （本年度出院患者次均药品费用－上一年度出院患者次均药品费用）/上一年度出院患者次均药品费用*100
A42: 医护比 | C42: 人事科 | D42: 0.31 | E42: 0.27 | F42: 0.26 | G42: 参考国考手册，原计量单位为比值（1:X），现改为小数 | H42: 医院注册医师总数/全院同期注册护士总数
A43: 医师人数 | B43: 人 | C43: 人事科 | D43: 33 | E43: 32 | F43: 32 | G43: 详见国考手册中，医护比定义
A44: 护士人数 | B44: 人 | C44: 人事科 | D44: 108 | E44: 119 | F44: 121 | G44: 详见国考手册中，医护比定义
A45: 医师高级职称占比 | B45: % | C45: 人事科 | D45: 48.48 | E45: 46.88 | F45: 46.88 | H45: (正高职称医师人数+副高职称医师人数)/医师人数*100
A46: 医师博士占比 | B46: % | C46: 人事科 | D46: 12.12 | E46: 12.5 | F46: 9.38 | H46: 博士医师人数/医师人数*100
A47: 医师硕士占比 | B47: % | C47: 人事科 | D47: 63.64 | E47: 59.38 | F47: 62.5 | H47: 硕士医师人数/医师人数*100
A48: 发表教学文章数与卫生技术人员数之比 | C48: 科教科 | D48: 0 | E48: 0 | F48: 0 | G48: 参考三级中医、三级公立国考手册，医院承担培养医学人才的工作成效的构成元素。原计量单位为比值（1:X），现改为小数 | H48: 本年度发表的教学文章数/同期卫生技术人员总数
A49: 省部级及以上教育教学课题数与卫生技术人员数之比 | C49: 科教科 | D49: 0 | E49: 0 | F49: 0 | G49: 参考三级中医、三级公立国考手册，医院承担培养医学人才的工作成效的构成元素。本指标为延伸指标。原计量单位为比值（1:X），现改为小数 | H49: 本年度获得的省部级及以上教育教学课题数/同期卫生技术人员总数
A50: 国家级继续医学教育项目数与卫生技术人员数之比 | C50: 科教科 | D50: 0.007092 | E50: 0.006623 | F50: 0.006536 | G50: 参考三级中医、三级公立国考手册，医院承担培养医学人才的工作成效的构成元素。本指标为延伸指标。原计量单位为比值（1:X），现改为小数 | H50: 本年度举办的国家级继续医学教育项目数/同期卫生技术人员总数
A51: 每百名卫生技术人员科研项目经费 | B51: 元 | C51: 科教科 | D51: 282511.59 | E51: 135298.01 | F51: 389056.21 | G51: 详见三级中医、三级公立国考手册 | H51: 本年度科研项目立项经费总金额/同期卫生技术人员总数*100
A52: 每百名卫生技术人员科研成果转化金额 | B52: 元 | C52: 科教科 | D52: 0 | E52: 0 | F52: 0 | G52: 详见三级公立国考手册 | H52: 本年度科技成果转化总金额/同期医院卫生技术人员总数*100
A53: 医师人均国家自然科学基金项目数量 | B53: 项 | C53: 科教科 | D53: 0 | E53: 0 | F53: 0 | G53: 说明：本年度成功立项的项目数量。要求本科室为主研单位
A54: 医师人均SCI文章数量 | B54: 篇 | C54: 科教科 | D54: 0.1 | E54: 0.184 | F54: 0.079 | G54: 说明：本年度成功发表的论文，要求第一作者或通讯作者为本院员工
A55: SCI平均影响因子 | B55: 分 | C55: 科教科 | D55: 0.315 | E55: 0.468 | F55: 0.169 | G55: 说明：本年度成功发表的论文，要求第一作者或通讯作者为本院员工
A56: 博士研究生导师占比 | B56: % | C56: 科教科 | D56: 0 | E56: 0 | F56: 0 | H56: 博士研究生导师人数/同期医师总数*100
A57: 硕士研究生导师占比 | B57: % | C57: 科教科 | D57: 18.18 | E57: 15.66 | F57: 6.25 | H57: 硕士研究生导师人数/同期医师总数*100
A58: 外省住院患者占比 | B58: % | C58: 统计室 | D58: 7.8630526 | E58: 7.4458418 | F58: 8.9621848 | H58: 外省住院患者人数/同期出院患者人次数*100
A59: 非医嘱离院率 | B59: % | C59: 统计室 | D59: 0.10432364 | E59: 0.058671673 | F59: 0.63173946 | H59: 非医嘱离院人次/同期出院患者总人次*100
A60: 是否为教育部或科技部重点学科或重点实验室 | B60: 分 | C60: 科教科 | D60: 0 | E60: 0 | F60: 0 | G60: 是填1,否填0
A61: 是否为国家卫健委临床重点专科 | B61: 分 | C61: 科教科 | D61: 0 | E61: 0 | F61: 0 | G61: 是填1,否填0
A62: 是否为国家中医药局重点专科 | B62: 分 | C62: 科教科 | D62: 0 | E62: 0 | F62: 0 | G62: 是填1,否填0
A63: 是否为省教育厅或科技厅重点学科或重点实验室 | B63: 分 | C63: 科教科 | D63: 0 | E63: 0 | F63: 0 | G63: 是填1,否填0
A64: 是否为省卫健委重点专科 | B64: 分 | C64: 科教科 | D64: 0 | E64: 0 | F64: 0 | G64: 是填1,否填0
A65: 是否为省中医药局重点专科 | B65: 分 | C65: 科教科 | D65: 0 | E65: 0 | F65: 0 | G65: 是填1,否填0
A66: 是否为地市级教育局或科技局重点学科或重点实验室 | B66: 分 | C66: 科教科 | D66: 0 | E66: 0 | F66: 0 | G66: 是填1,否填0
A67: 是否为地市级卫健委重点专科 | B67: 分 | C67: 科教科 | D67: 1 | E67: 1 | F67: 1 | G67: 是填1,否填0
A68: 是否为地市级中医药局重点专科 | B68: 分 | C68: 科教科 | D68: 0 | E68: 0 | F68: 0 | G68: 是填1,否填0
A69: 是否为县级教育局或科技局重点学科或重点实验室 | B69: 分 | C69: 科教科 | D69: 0 | E69: 0 | F69: 0 | G69: 是填1,否填0
A70: 是否为县级卫健委重点专科 | B70: 分 | C70: 科教科 | D70: 0 | E70: 0 | F70: 0 | G70: 是填1,否填0
A71: 是否为县级中医药局重点专科 | B71: 分 | C71: 科教科 | D71: 0 | E71: 0 | F71: 0 | G71: 是填1,否填0
A72: 第一顺位疾病名称 | C72: 信息科 | D72: =[1]大骨科!$O$4 -> 取除骨折或关节内外固定 | E72: =[1]大骨科!$I$4 -> 腰椎间盘疾患 | F72: =[1]大骨科!$C$4 -> 腰椎间盘疾患
A73: 第一顺位疾病编码 | C73: 信息科 | D73: =[1]大骨科!$N$4 -> Z47 | E73: =[1]大骨科!$H$4 -> M51- | F73: =[1]大骨科!$B$4 -> M51-
A74: 第一顺位疾病占比 | B74: % | C74: 信息科 | D74: =[1]大骨科!$Q$4 -> 10.015069 | E74: =[1]大骨科!$K$4 -> 10.596104 | F74: =[1]大骨科!$E$4 -> 13.876484
A75: 第二顺位疾病名称 | C75: 信息科 | D75: =[1]大骨科!$O$5 -> 腰椎间盘疾患 | E75: =[1]大骨科!$I$5 -> 取除骨折或关节内外固定 | F75: =[1]大骨科!$C$5 -> 取除骨折内固定装置
A76: 第二顺位疾病编码 | C76: 信息科 | D76: =[1]大骨科!$N$5 -> M51.- | E76: =[1]大骨科!$H$5 -> Z47 | F76: =[1]大骨科!$B$5 -> Z47.0
A77: 第二顺位疾病占比 | B77: % | C77: 信息科 | D77: =[1]大骨科!$Q$5 -> 10.003477 | E77: =[1]大骨科!$K$5 -> 8.2022999 | F77: =[1]大骨科!$E$5 -> 7.853175
A78: 第三顺位疾病名称 | C78: 信息科 | D78: =[1]大骨科!$O$6 -> 股骨骨折 | E78: =[1]大骨科!$I$6 -> 股骨骨折 | F78: =[1]大骨科!$C$6 -> 股骨骨折
A79: 第三顺位疾病编码 | C79: 信息科 | D79: =[1]大骨科!$N$6 -> S72 | E79: =[1]大骨科!$H$6 -> S72 | F79: =[1]大骨科!$B$6 -> S72
A80: 第三顺位疾病占比 | B80: % | C80: 信息科 | D80: =[1]大骨科!$Q$6 -> 5.5407442 | E80: =[1]大骨科!$K$6 -> 4.3534382 | F80: =[1]大骨科!$E$6 -> 5.7727916
A81: 第四顺位疾病名称 | C81: 信息科 | D81: =[1]大骨科!$O$7 -> 小腿骨骨折 | E81: =[1]大骨科!$I$7 -> 肱骨骨折 | F81: =[1]大骨科!$C$7 -> 骨质疏松伴有病理性骨折
A82: 第四顺位疾病编码 | C82: 信息科 | D82: =[1]大骨科!$N$7 -> S82 | E82: =[1]大骨科!$H$7 -> S42 | F82: =[1]大骨科!$B$7 -> M80
A83: 第四顺位疾病占比 | B83: % | C83: 信息科 | D83: =[1]大骨科!$Q$7 -> 4.1149878 | E83: =[1]大骨科!$K$7 -> 3.9192678 | F83: =[1]大骨科!$E$7 -> 4.5528809
A84: 第五顺位疾病名称 | C84: 信息科 | D84: =[1]大骨科!$O$8 -> 骨质疏松伴有病理性骨折 | E84: =[1]大骨科!$I$8 -> 骨质疏松伴有病理性骨折 | F84: =[1]大骨科!$C$8 -> 小腿骨骨折
A85: 第五顺位疾病编码 | C85: 信息科 | D85: =[1]大骨科!$N$8 -> M80 | E85: =[1]大骨科!$H$8 -> M80 | F85: =[1]大骨科!$B$8 -> S82
A86: 第五顺位疾病占比 | B86: % | C86: 信息科 | D86: =[1]大骨科!$Q$8 -> 4.0338472 | E86: =[1]大骨科!$K$8 -> 3.8488618 | F86: =[1]大骨科!$E$8 -> 4.2152271
A87: 第一顺位手术名称 | C87: 信息科 | D87: =[2]大骨科!$O$4 -> 骨折切开复位内固定术 | E87: =[2]大骨科!$I$4 -> 骨折切开复位内固定术 | F87: =[2]大骨科!$C$4 -> 骨折切开复位内固定术
A88: 第一顺位手术编码 | C88: 信息科 | D88: =[2]大骨科!$N$4 -> 79.3 | E88: =[2]大骨科!$H$4 -> 79.3 | F88: =[2]大骨科!$B$4 -> 79.3
A89: 第一顺位手术占比 | B89: % | C89: 信息科 | D89: =[2]大骨科!$Q$4 -> 18.764267 | E89: =[2]大骨科!$K$4 -> 19.982175 | F89: =[2]大骨科!$E$4 -> 21.210106
A90: 第二顺位手术名称 | C90: 信息科 | D90: =[2]大骨科!$O$5 -> 骨内固定装置去除术 | E90: =[2]大骨科!$I$5 -> 骨内固定装置去除术 | F90: =[2]大骨科!$C$5 -> 骨内固定装置去除术
A91: 第二顺位手术编码 | C91: 信息科 | D91: =[2]大骨科!$N$5 -> 78.6 | E91: =[2]大骨科!$H$5 -> 78.6 | F91: =[2]大骨科!$B$5 -> 78.6
A92: 第二顺位手术占比 | B92: % | C92: 信息科 | D92: =[2]大骨科!$Q$5 -> 13.422615 | E92: =[2]大骨科!$K$5 -> 12.976827 | F92: =[2]大骨科!$E$5 -> 24.456163
A93: 第三顺位手术名称 | C93: 信息科 | D93: =[2]大骨科!$O$6 -> 腰椎间盘切除术(椎间盘髓核切除术)，后路法 | E93: =[2]大骨科!$I$6 -> 腰椎间盘切除术(椎间盘髓核切除术)，后路法 | F93: =[2]大骨科!$C$6 -> 腰椎间盘切除术(椎间盘髓核切除术)，后路法
A94: 第三顺位手术编码 | C94: 信息科 | D94: =[2]大骨科!$N$6 -> 80.5 | E94: =[2]大骨科!$H$6 -> 80.5 | F94: =[2]大骨科!$B$6 -> 80.5
A95: 第三顺位手术占比 | B95: % | C95: 信息科 | D95: =[2]大骨科!$Q$6 -> 10.561558 | E95: =[2]大骨科!$K$6 -> 11.319073 | F95: =[2]大骨科!$E$6 -> 48.619958
A96: 第四顺位手术名称 | C96: 信息科 | D96: =[2]大骨科!$O$7 -> 髋膝关节置换术，单侧，骨病型 | E96: =[2]大骨科!$I$7 -> 髋膝关节置换术，单侧，骨病型 | F96: =[2]大骨科!$C$7 -> 髋膝关节置换术，单侧，骨病型
A97: 第四顺位手术编码 | C97: 信息科 | D97: =[2]大骨科!$N$7 -> 81.5 | E97: =[2]大骨科!$H$7 -> 81.5 | F97: =[2]大骨科!$B$7 -> 81.5
A98: 第四顺位手术占比 | B98: % | C98: 信息科 | D98: =[2]大骨科!$Q$7 -> 8.4918582 | E98: =[2]大骨科!$K$7 -> 9.3226381 | F98: =[2]大骨科!$E$7 -> 35.245379
A99: 第五顺位手术名称 | C99: 信息科 | D99: =[2]大骨科!$O$8 -> 腰胸椎骨成形术(PVP) | E99: =[2]大骨科!$I$8 -> 腰胸椎骨成形术(PVP) | F99: =[2]大骨科!$C$8 -> 腰胸椎骨成形术(PVP)
A100: 第五顺位手术编码 | C100: 信息科 | D100: =[2]大骨科!$N$8 -> 81.6 | E100: =[2]大骨科!$H$8 -> 81.6 | F100: =[2]大骨科!$B$8 -> 81.6
...

Sheet 脊柱外科
A1: 数据名 | B1: 计量单位 | C1: 填报部门 | D1: Y2021 | E1: Y2020 | F1: Y2019 | G1: 指标说明 | H1: 计算公式
A2: 出院患者手术占比 | B2: % | C2: 统计室 | D2: 57.256236 | E2: 44.429018 | F2: 45.683802 | G2: 详见三级公立、二级公立国考手册。举例：30%请填写30（不带百分号），而非写成30%，或0.3。下同 | H2: 出院患者手术台次数/同期出院患者总人次数*100
A3: 出院患者微创手术占比 | B3: % | C3: 统计室 | D3: 8.3168317 | E3: 5.546875 | F3: 4.8124558 | G3: 详见三级公立、二级公立国考手册 | H3: 出院患者微创手术台次数/同期出院患者手术台次数*100
A4: 出院患者四级手术比例 | B4: % | C4: 统计室 | D4: 89.50495 | E4: 89.140625 | F4: 85.704176 | G4: 详见三级公立国考手册 | H4: 出院患者四级手术台次数/同期出院患者手术台次数*100
A5: 出院患者疑难危重病例比例 | B5: % | C5: 统计室 | D5: 95.88 | E5: 97.71 | F5: 89.3 | G5: 即CD型病例占比 | H5: (疑难病例数+危重病例数)/出院人数*100
A6: 手术患者并发症发生率 | B6: % | C6: 质控科 | D6: 0 | E6: 0 | F6: 0 | G6: 详见国考手册 | H6: 手术患者并发症发生例数/同期出院的手术患者人数*100
A7: I类切口手术部位感染率 | B7: % | C7: 质控科 | D7: 0.32 | E7: 0.37 | F7: 0.2 | G7: 详见三级中医、三级公立国考手册 | H7: I类切口手术部位感染人次数/同期I类切口手术台次数*100
A8: 大型医用设备检查阳性率 | B8: % | C8: 医务科 | G8: 详见三级中医、三级公立国考手册 | H8: 大型医用设备检查阳性数/同期大型医用设备检查人次数*100
A9: 低风险组病例死亡率 | B9: % | C9: 质控科 | D9: 0 | E9: 0 | F9: 0 | G9: 详见三级公立、二级公立国考手册 | H9: 低风险组死亡例数/低风险组病例数*100
A10: 医院感染发生率 | B10: % | C10: 院感科 | D10: 1.63 | E10: 1.63 | F10: 0.9 | G10: 等级评审标准细则
A11: 抗菌药物使用强度DDDs | B11: DDD | C11: 药学部 | D11: 35.718693 | E11: 38.509554 | F11: 33.14572 | G11: 详见国考手册 | H11: 住院患者抗菌药物消耗量（累计DDD数）/同期收治患者人天数*100
A12: 门诊患者基本药物处方占比 | B12: % | C12: 药学部 | D12: 83.22 | E12: 80.97 | F12: 72.79 | G12: 详见三级中医、三级公立国考手册 | H12: 门诊使用基本药物人次数/同期门诊诊疗总人次数*100
A13: 住院患者基本药物使用率 | B13: % | C13: 药学部 | D13: 97.55 | E13: 96.96 | F13: 94.87 | G13: 详见三级中医、三级公立国考手册 | H13: 出院患者使用基本药物总人次数/同期出院总人次数*100
A14: 重点监控高值医用耗材收入占比 | B14: % | C14: 设备科 | D14: =(15295843.6+2398085)/61030488*100 -> 28.99195 | E14: =20544757/59638630*100 -> 34.448741 | F14: =22522726/67539684*100 -> 33.347396 | G14: 详见国考手册 | H14: 重点监控高值医用耗材收入/同期卫生材料收入*100
A15: 平均住院日 | B15: 天 | C15: 统计室 | D15: 10.38 | E15: 10.23 | F15: 10.57 | G15: 详见二级公立国考手册 | H15: 出院患者占用总床日数/同期出院患者人数
A16: CMI值 | C16: 质控科 | D16: 2.15 | E16: 1.84 | F16: 1.88 | G16: 病例组合指数
A17: DRGs组数 | B17: 组 | C17: 质控科 | D17: 85 | E17: 94 | F17: 91 | G17: 诊断相关分组组数
A18: 核定床位数 | B18: 张 | C18: 统计室 | D18: 80 | E18: 80 | F18: 80 | G18: 等级评审标准细则
A19: 实际开放床位数 | B19: 张 | C19: 统计室 | D19: 97 | E19: 80 | F19: 110 | G19: 等级评审标准细则
A20: 开放床位使用率 | B20: % | C20: 统计室 | D20: 83.94 | E20: 82.61 | F20: 81.92 | G20: 等级评审标准细则 | H20: 实际占用的总床日数/同期实际开放的总床日数*100
A21: 医师人数与开放床位数比 | C21: 人事科 | D21: =D43/D19 -> 0.092783505 | E21: =E43/E19 -> 0.1125 | F21: =F43/F19 -> 0.072727273 | G21: 等级评审标准细则，原计量单位为比值（1:X），现改为小数 | H21: 医院执业（助理）医师总数/同期全院实际开放床位数
A22: 护士人数与开放床位数比 | C22: 人事科 | D22: =D44/D19 -> 0.3814433 | E22: =E44/E19 -> 0.5625 | F22: =F44/F19 -> 0.40909091 | G22: 等级评审标准细则，原计量单位为比值（1:X），现改为小数 | H22: 医院注册护士总数/同期全院实际开放床位数
A23: 人均医疗服务收入 | B23: 万元 | C23: 财务科 | D23: 40.349086 | E23: 34.834736 | F23: 37.713232 | G23: 按科室人员数人均医疗服务收入
A24: 人均有效收入 | B24: 万元 | C24: 财务科 | D24: 69.927297 | E24: 65.061471 | F24: 66.822795 | G24: 按科室人员数人均有效收入
A25: 床均医疗服务收入 | B25: 万元 | C25: 财务科 | D25: 23.394613 | E25: 20.015855 | F25: 19.542311 | G25: 按开放床位数床均医疗服务收入
A26: 床均有效收入 | B26: 万元 | C26: 财务科 | D26: 40.544215 | E26: 37.383977 | F26: 34.626357 | G26: 按开放床位数床均有效收入
A27: 每名执业医师日均住院工作负担 | B27: 床日 | C27: 财务科 | D27: 8.525723 | E27: 8.9704718 | F27: 11.264384 | G27: 详见三级中医、三级公立国考手册 | H27: 全年实际占用总床日数/医院平均执业(助理)医师人数/365
A28: 医疗服务收入占医疗收入比例 | B28: % | C28: 财务科 | D28: 31.826415 | E28: 30.652236 | F28: 30.630897 | G28: 参考国考手册，原指标名为：医疗服务收入（不含药品、耗材、检查检验收入）占医疗收入比例 | H28: 医疗服务收入/医疗收入*100
A29: 医疗收入 | B29: 万元 | C29: 财务科 | D29: 6719.2664 | E29: 6364.1206 | F29: 7017.9278 | H29: 门诊收入+住院收入
A30: 医疗服务收入 | B30: 万元 | C30: 财务科 | D30: 2138.5016 | E30: 1950.7452 | F30: 2149.6542
A31: 有效收入 | B31: 万元 | C31: 财务科 | D31: 3706.1467 | E31: 3643.4424 | F31: 3808.8993 | H31: 医疗服务收入+检查检验收入
A32: 医疗直接成本 | B32: 万元 | D32: 4511.2 | E32: 4025.45 | F32: 4499.61
A33: 收支结余率 | B33: % | D33: 13.83 | E33: 13.38 | F33: 11.48
A34: 万元收入能耗占比 | B34: 吨标煤/万元 | C34: 后勤管理科 | G34: 详见国考手册 | H34: 年总能耗/年总收入*10000
A35: 门诊收入占医疗收入比例 | B35: % | C35: 财务科 | D35: 9.0991142 | E35: 8.3279932 | F35: 7.2850811 | G35: 详见三级公立国考手册 | H35: 门诊收入/医疗收入*100
A36: 住院收入占医疗收入比例 | B36: % | C36: 财务科 | D36: 90.900886 | E36: 91.672007 | F36: 92.714919 | G36: 详见三级公立国考手册 | H36: 住院收入/医疗收入*100
A37: 医疗收入增幅 | B37: % | C37: 财务科 | D37: 5.5804384 | E37: -9.3162437 | F37: 36.829274 | G37: 详见国考手册 | H37: （本年度医疗收入－上一年度医疗收入）/上一年度医疗收入*100
A38: 门诊次均费用增幅 | B38: % | C38: 财务科 | D38: 5.8087673 | E38: -1.6785888 | F38: -59.507961 | G38: 详见国考手册 | H38: （本年度门诊患者次均医药费用－上一年度门诊患者次均医药费用）/上一年度门诊患者次均医药费用*100
A39: 住院次均费用增幅 | B39: % | C39: 财务科 | D39: 11.76881 | E39: -3.1372301 | F39: 42.223666 | G39: 详见国考手册 | H39: （本年度出院患者次均医药费用－上一年度出院患者次均医药费用）/上一年度出院患者次均医药费用*100
A40: 门诊次均药品费用增幅 | B40: % | C40: 财务科 | D40: 16.336403 | E40: -6.9633366 | F40: -55.237157 | G40: 详见国考手册 | H40: （本年度门诊患者次均药品费用－上一年度门诊患者次均药品费用）/上一年度门诊患者次均药品费用*100
A41: 住院次均药品费用增幅 | B41: % | C41: 财务科 | D41: -10.492529 | E41: -18.749155 | F41: 5.8153529 | G41: 详见国考手册 | H41: （本年度出院患者次均药品费用－上一年度出院患者次均药品费用）/上一年度出院患者次均药品费用*100
A42: 医护比 | C42: 人事科 | D42: 0.24 | E42: 0.2 | F42: 0.18 | G42: 参考国考手册，原计量单位为比值（1:X），现改为小数 | H42: 医院注册医师总数/全院同期注册护士总数
A43: 医师人数 | B43: 人 | C43: 人事科 | D43: 9 | E43: 9 | F43: 8 | G43: 详见国考手册中，医护比定义
A44: 护士人数 | B44: 人 | C44: 人事科 | D44: 37 | E44: 45 | F44: 45 | G44: 详见国考手册中，医护比定义
A45: 医师高级职称占比 | B45: % | C45: 人事科 | D45: 55.56 | E45: 55.56 | F45: 62.5 | H45: (正高职称医师人数+副高职称医师人数)/医师人数*100
A46: 医师博士占比 | B46: % | C46: 人事科 | D46: 22.22 | E46: 22.22 | F46: 25 | H46: 博士医师人数/医师人数*100
A47: 医师硕士占比 | B47: % | C47: 人事科 | D47: 55.56 | E47: 55.56 | F47: 50 | H47: 硕士医师人数/医师人数*100
A48: 发表教学文章数与卫生技术人员数之比 | C48: 科教科 | D48: 0 | E48: 0 | F48: 0 | G48: 参考三级中医、三级公立国考手册，医院承担培养医学人才的工作成效的构成元素。原计量单位为比值（1:X），现改为小数 | H48: 本年度发表的教学文章数/同期卫生技术人员总数
A49: 省部级及以上教育教学课题数与卫生技术人员数之比 | C49: 科教科 | D49: 0 | E49: 0 | F49: 0 | G49: 参考三级中医、三级公立国考手册，医院承担培养医学人才的工作成效的构成元素。本指标为延伸指标。原计量单位为比值（1:X），现改为小数 | H49: 本年度获得的省部级及以上教育教学课题数/同期卫生技术人员总数
A50: 国家级继续医学教育项目数与卫生技术人员数之比 | C50: 科教科 | D50: 0 | E50: 0 | F50: 0 | G50: 参考三级中医、三级公立国考手册，医院承担培养医学人才的工作成效的构成元素。本指标为延伸指标。原计量单位为比值（1:X），现改为小数 | H50: 本年度举办的国家级继续医学教育项目数/同期卫生技术人员总数
A51: 每百名卫生技术人员科研项目经费 | B51: 元 | C51: 科教科 | D51: 565217.39 | E51: 0 | F51: 0 | G51: 详见三级中医、三级公立国考手册 | H51: 本年度科研项目立项经费总金额/同期卫生技术人员总数*100
A52: 每百名卫生技术人员科研成果转化金额 | B52: 元 | C52: 科教科 | D52: 0 | E52: 0 | F52: 0 | G52: 详见三级公立国考手册 | H52: 本年度科技成果转化总金额/同期医院卫生技术人员总数*100
A53: 医师人均国家自然科学基金项目数量 | B53: 项 | C53: 科教科 | D53: 0 | E53: 0 | F53: 0 | G53: 说明：本年度成功立项的项目数量。要求本科室为主研单位
A54: 医师人均SCI文章数量 | B54: 篇 | C54: 科教科 | D54: 0.333 | E54: 0.667 | F54: 0.25 | G54: 说明：本年度成功发表的论文，要求第一作者或通讯作者为本院员工
A55: SCI平均影响因子 | B55: 分 | C55: 科教科 | D55: 0.811 | E55: 1.725 | F55: 0.63 | G55: 说明：本年度成功发表的论文，要求第一作者或通讯作者为本院员工
A56: 博士研究生导师占比 | B56: % | C56: 科教科 | D56: 0 | E56: 0 | F56: 0 | H56: 博士研究生导师人数/同期医师总数*100
A57: 硕士研究生导师占比 | B57: % | C57: 科教科 | D57: 33.33 | E57: 33.33 | F57: 12.5 | H57: 硕士研究生导师人数/同期医师总数*100
A58: 外省住院患者占比 | B58: % | C58: 统计室 | D58: 6.462585 | E58: 6.3866713 | F58: 8.276754 | H58: 外省住院患者人数/同期出院患者人次数*100
A59: 非医嘱离院率 | B59: % | C59: 统计室 | D59: 0.22675737 | E59: 0 | F59: 0.19398642 | H59: 非医嘱离院人次/同期出院患者总人次*100
A60: 是否为教育部或科技部重点学科或重点实验室 | B60: 分 | C60: 科教科 | D60: 0 | E60: 0 | F60: 0 | G60: 是填1,否填0
A61: 是否为国家卫健委临床重点专科 | B61: 分 | C61: 科教科 | D61: 0 | E61: 0 | F61: 0 | G61: 是填1,否填0
A62: 是否为国家中医药局重点专科 | B62: 分 | C62: 科教科 | D62: 0 | E62: 0 | F62: 0 | G62: 是填1,否填0
A63: 是否为省教育厅或科技厅重点学科或重点实验室 | B63: 分 | C63: 科教科 | D63: 0 | E63: 0 | F63: 0 | G63: 是填1,否填0
A64: 是否为省卫健委重点专科 | B64: 分 | C64: 科教科 | D64: 0 | E64: 0 | F64: 0 | G64: 是填1,否填0
A65: 是否为省中医药局重点专科 | B65: 分 | C65: 科教科 | D65: 0 | E65: 0 | F65: 0 | G65: 是填1,否填0
A66: 是否为地市级教育局或科技局重点学科或重点实验室 | B66: 分 | C66: 科教科 | D66: 0 | E66: 0 | F66: 0 | G66: 是填1,否填0
A67: 是否为地市级卫健委重点专科 | B67: 分 | C67: 科教科 | D67: 1 | E67: 1 | F67: 1 | G67: 是填1,否填0
A68: 是否为地市级中医药局重点专科 | B68: 分 | C68: 科教科 | D68: 0 | E68: 0 | F68: 0 | G68: 是填1,否填0
A69: 是否为县级教育局或科技局重点学科或重点实验室 | B69: 分 | C69: 科教科 | D69: 0 | E69: 0 | F69: 0 | G69: 是填1,否填0
A70: 是否为县级卫健委重点专科 | B70: 分 | C70: 科教科 | D70: 0 | E70: 0 | F70: 0 | G70: 是填1,否填0
A71: 是否为县级中医药局重点专科 | B71: 分 | C71: 科教科 | D71: 0 | E71: 0 | F71: 0 | G71: 是填1,否填0
A72: 第一顺位疾病名称 | C72: 信息科 | D72: =[1]脊柱外科!$O$4 -> 腰椎间盘疾患 | E72: =[1]脊柱外科!$I$4 -> 腰椎间盘疾患 | F72: =[1]脊柱外科!$C$4 -> 腰椎间盘疾患
A73: 第一顺位疾病编码 | C73: 信息科 | D73: =[1]脊柱外科!$N$4 -> M51.- | E73: =[1]脊柱外科!$H$4 -> M51.- | F73: =[1]脊柱外科!$B$4 -> M51.-
A74: 第一顺位疾病占比 | B74: % | C74: 信息科 | D74: =[1]脊柱外科!$Q$4 -> 32.577475 | E74: =[1]脊柱外科!$K$4 -> 31.169733 | F74: =[1]脊柱外科!$E$4 -> 41.028128
A75: 第二顺位疾病名称 | C75: 信息科 | D75: =[1]脊柱外科!$O$5 -> 骨质疏松伴有病理性骨折 | E75: =[1]脊柱外科!$I$5 -> 骨质疏松伴有病理性骨折 | F75: =[1]脊柱外科!$C$5 -> 骨质疏松伴有病理性骨折
A76: 第二顺位疾病编码 | C76: 信息科 | D76: =[1]脊柱外科!$N$5 -> M80 | E76: =[1]脊柱外科!$H$5 -> M80 | F76: =[1]脊柱外科!$B$5 -> M80
A77: 第二顺位疾病占比 | B77: % | C77: 信息科 | D77: =[1]脊柱外科!$Q$5 -> 12.773998 | E77: =[1]脊柱外科!$K$5 -> 11.489066 | F77: =[1]脊柱外科!$E$5 -> 13.223408
A78: 第三顺位疾病名称 | C78: 信息科 | D78: =[1]脊柱外科!$O$6 -> 腰椎骨折 | E78: =[1]脊柱外科!$I$6 -> 脊椎滑脱 | F78: =[1]脊柱外科!$C$6 -> 脊椎关节强硬
A79: 第三顺位疾病编码 | C79: 信息科 | D79: =[1]脊柱外科!$N$6 -> S32.0 | E79: =[1]脊柱外科!$H$6 -> M43.0 | F79: =[1]脊柱外科!$B$6 -> M47.-
A80: 第三顺位疾病占比 | B80: % | C80: 信息科 | D80: =[1]脊柱外科!$Q$6 -> 7.2562358 | E80: =[1]脊柱外科!$K$6 -> 9.4064561 | F80: =[1]脊柱外科!$E$6 -> 9.8609764
A81: 第四顺位疾病名称 | C81: 信息科 | D81: =[1]脊柱外科!$O$7 -> 脊椎关节强硬 | E81: =[1]脊柱外科!$I$7 -> 脊椎关节强硬 | F81: =[1]脊柱外科!$C$7 -> 腰椎骨折
A82: 第四顺位疾病编码 | C82: 信息科 | D82: =[1]脊柱外科!$N$7 -> M47.- | E82: =[1]脊柱外科!$H$7 -> M47.- | F82: =[1]脊柱外科!$B$7 -> S32.0
A83: 第四顺位疾病占比 | B83: % | C83: 信息科 | D83: =[1]脊柱外科!$Q$7 -> 6.9538927 | E83: =[1]脊柱外科!$K$7 -> 7.9486289 | F83: =[1]脊柱外科!$E$7 -> 4.138377
A84: 第五顺位疾病名称 | C84: 信息科 | D84: =[1]脊柱外科!$O$8 -> 脊椎滑脱 | E84: =[1]脊柱外科!$I$8 -> 腰椎骨折 | F84: =[1]脊柱外科!$C$8 -> 脊椎滑脱
A85: 第五顺位疾病编码 | C85: 信息科 | D85: =[1]脊柱外科!$N$8 -> M43.0 | E85: =[1]脊柱外科!$H$8 -> S32.0 | F85: =[1]脊柱外科!$B$8 -> M43.0
A86: 第五顺位疾病占比 | B86: % | C86: 信息科 | D86: =[1]脊柱外科!$Q$8 -> 6.840514 | E86: =[1]脊柱外科!$K$8 -> 4.4429018 | F86: =[1]脊柱外科!$E$8 -> 3.6534109
A87: 第一顺位手术名称 | C87: 信息科 | D87: =[2]脊柱外科!$O$4 -> 腰椎间盘切除术(椎间盘髓核切除术)，后路法 | E87: =[2]脊柱外科!$I$4 -> 腰椎间盘切除术(椎间盘髓核切除术)，后路法 | F87: =[2]脊柱外科!$C$4 -> 腰椎间盘切除术(椎间盘髓核切除术)，后路法
A88: 第一顺位手术编码 | C88: 信息科 | D88: =[2]脊柱外科!$N$4 -> 80.5 | E88: =[2]脊柱外科!$H$4 -> 80.5 | F88: =[2]脊柱外科!$B$4 -> 80.5
A89: 第一顺位手术占比 | B89: % | C89: 信息科 | D89: =[2]脊柱外科!$Q$4 -> 45.742574 | E89: =[2]脊柱外科!$K$4 -> 49.609375 | F89: =[2]脊柱外科!$E$4 -> 48.478415
A90: 第二顺位手术名称 | C90: 信息科 | D90: =[2]脊柱外科!$O$5 -> 腰胸椎骨成形术(PVP) | E90: =[2]脊柱外科!$I$5 -> 腰胸椎骨成形术(PVP) | F90: =[2]脊柱外科!$C$5 -> 腰胸椎骨成形术(PVP)
A91: 第二顺位手术编码 | C91: 信息科 | D91: =[2]脊柱外科!$N$5 -> 81.6 | E91: =[2]脊柱外科!$H$5 -> 81.6 | F91: =[2]脊柱外科!$B$5 -> 81.6
A92: 第二顺位手术占比 | B92: % | C92: 信息科 | D92: =[2]脊柱外科!$Q$5 -> 25.214521 | E92: =[2]脊柱外科!$K$5 -> 21.953125 | F92: =[2]脊柱外科!$E$5 -> 16.418967
A93: 第三顺位手术名称 | C93: 信息科 | D93: =[2]脊柱外科!$O$6 -> 脊椎骨折复位术 | E93: =[2]脊柱外科!$I$6 -> 脊椎骨折复位术 | F93: =[2]脊柱外科!$C$6 -> 脊椎骨折复位术
A94: 第三顺位手术编码 | C94: 信息科 | D94: =[2]脊柱外科!$N$6 -> 03.53 | E94: =[2]脊柱外科!$H$6 -> 03.53 | F94: =[2]脊柱外科!$B$6 -> 03.53
A95: 第三顺位手术占比 | B95: % | C95: 信息科 | D95: =[2]脊柱外科!$Q$6 -> 8.8448845 | E95: =[2]脊柱外科!$K$6 -> 9.6875 | F95: =[2]脊柱外科!$E$6 -> 14.08351
A96: 第四顺位手术名称 | C96: 信息科 | D96: =[2]脊柱外科!$O$7 -> 脊柱内固定装置去除术 | E96: =[2]脊柱外科!$I$7 -> 脊柱内固定装置去除术 | F96: =[2]脊柱外科!$C$7 -> 脊柱韧带松解术
A97: 第四顺位手术编码 | C97: 信息科 | D97: =[2]脊柱外科!$N$7 -> 78.6 | E97: =[2]脊柱外科!$H$7 -> 78.6 | F97: =[2]脊柱外科!$B$7 -> 80.4
A98: 第四顺位手术占比 | B98: % | C98: 信息科 | D98: =[2]脊柱外科!$Q$7 -> 7.1947195 | E98: =[2]脊柱外科!$K$7 -> 6.40625 | F98: =[2]脊柱外科!$E$7 -> 6.7232838
A99: 第五顺位手术名称 | C99: 信息科 | D99: =[2]脊柱外科!$O$8 -> 腰颈椎脱位切开复位内固定术 | E99: =[2]脊柱外科!$I$8 -> 颈椎单开门式椎板成形术，后路法 | F99: =[2]脊柱外科!$C$8 -> 脊柱内固定装置去除术
A100: 第五顺位手术编码 | C100: 信息科 | D100: =[2]脊柱外科!$N$8 -> 79.8 | E100: =[2]脊柱外科!$H$8 -> 03.09 | F100: =[2]脊柱外科!$B$8 -> 78.6
...

Sheet 创伤骨科
A1: 数据名 | B1: 计量单位 | C1: 填报部门 | D1: Y2021 | E1: Y2020 | F1: Y2019 | G1: 指标说明 | H1: 计算公式
A2: 出院患者手术占比 | B2: % | C2: 统计室 | D2: 84.929757 | E2: 76.529822 | F2: 76.154618 | G2: 详见三级公立、二级公立国考手册。举例：30%请填写30（不带百分号），而非写成30%，或0.3。下同 | H2: 出院患者手术台次数/同期出院患者总人次数*100
A3: 出院患者微创手术占比 | B3: % | C3: 统计室 | D3: 1.4736842 | E3: 0.60728745 | F3: 0.92287409 | G3: 详见三级公立、二级公立国考手册 | H3: 出院患者微创手术台次数/同期出院患者手术台次数*100
A4: 出院患者四级手术比例 | B4: % | C4: 统计室 | D4: 5.2330827 | E4: 1.0458839 | F4: 1.3513514 | G4: 详见三级公立国考手册 | H4: 出院患者四级手术台次数/同期出院患者手术台次数*100
A5: 出院患者疑难危重病例比例 | B5: % | C5: 统计室 | D5: 94.89 | E5: 75.83 | F5: 69.8 | G5: 即CD型病例占比 | H5: (疑难病例数+危重病例数)/出院人数*100
A6: 手术患者并发症发生率 | B6: % | C6: 质控科 | D6: 0 | E6: 0 | F6: 0 | G6: 详见国考手册 | H6: 手术患者并发症发生例数/同期出院的手术患者人数*100
A7: I类切口手术部位感染率 | B7: % | C7: 质控科 | D7: 0.2 | E7: 0.05 | F7: 0.29 | G7: 详见三级中医、三级公立国考手册 | H7: I类切口手术部位感染人次数/同期I类切口手术台次数*100
A8: 大型医用设备检查阳性率 | B8: % | C8: 医务科 | G8: 详见三级中医、三级公立国考手册 | H8: 大型医用设备检查阳性数/同期大型医用设备检查人次数*100
A9: 低风险组病例死亡率 | B9: % | C9: 质控科 | D9: 0 | E9: 0 | F9: 0 | G9: 详见三级公立、二级公立国考手册 | H9: 低风险组死亡例数/低风险组病例数*100
A10: 医院感染发生率 | B10: % | C10: 院感科 | D10: 0.87 | E10: 0.67 | F10: 0.9 | G10: 等级评审标准细则
A11: 抗菌药物使用强度DDDs | B11: DDD | C11: 药学部 | D11: 68.260528 | E11: 70.134053 | F11: 70.25339 | G11: 详见国考手册 | H11: 住院患者抗菌药物消耗量（累计DDD数）/同期收治患者人天数*100
A12: 门诊患者基本药物处方占比 | B12: % | C12: 药学部 | D12: 78.87 | E12: 72.16 | F12: 68.79 | G12: 详见三级中医、三级公立国考手册 | H12: 门诊使用基本药物人次数/同期门诊诊疗总人次数*100
A13: 住院患者基本药物使用率 | B13: % | C13: 药学部 | D13: 98.6 | E13: 96.79 | F13: 95.8 | G13: 详见三级中医、三级公立国考手册 | H13: 出院患者使用基本药物总人次数/同期出院总人次数*100
A14: 重点监控高值医用耗材收入占比 | B14: % | C14: 设备科 | D14: =(10462203+1179040)/52314296*100 -> 22.252508 | E14: =9599104/52373450*100 -> 18.328187 | F14: =5321361/56858658*100 -> 9.3589282 | G14: 详见国考手册 | H14: 重点监控高值医用耗材收入/同期卫生材料收入*100
A15: 平均住院日 | B15: 天 | C15: 统计室 | D15: 10.25 | E15: 9.95 | F15: 11.55 | G15: 详见二级公立国考手册 | H15: 出院患者占用总床日数/同期出院患者人数
A16: CMI值 | C16: 质控科 | D16: 1.58 | E16: 1.4 | F16: 1.49 | G16: 病例组合指数
A17: DRGs组数 | B17: 组 | C17: 质控科 | D17: 133 | E17: 146 | F17: 149 | G17: 诊断相关分组组数
A18: 核定床位数 | B18: 张 | C18: 统计室 | D18: 94 | E18: 94 | F18: 94 | G18: 等级评审标准细则
A19: 实际开放床位数 | B19: 张 | C19: 统计室 | D19: 103 | E19: 94 | F19: 110 | G19: 等级评审标准细则
A20: 开放床位使用率 | B20: % | C20: 统计室 | D20: 105.7 | E20: 100.85 | F20: 111.25 | G20: 等级评审标准细则 | H20: 实际占用的总床日数/同期实际开放的总床日数*100
A21: 医师人数与开放床位数比 | C21: 人事科 | D21: =D43/D19 -> 0.15533981 | E21: =E43/E19 -> 0.18085106 | F21: =F43/F19 -> 0.13636364 | G21: 等级评审标准细则，原计量单位为比值（1:X），现改为小数 | H21: 医院执业（助理）医师总数/同期全院实际开放床位数
A22: 护士人数与开放床位数比 | C22: 人事科 | D22: =D44/D19 -> 0.47572816 | E22: =E44/E19 -> 0.54255319 | F22: =F44/F19 -> 0.45454545 | G22: 等级评审标准细则，原计量单位为比值（1:X），现改为小数 | H22: 医院注册护士总数/同期全院实际开放床位数
A23: 人均医疗服务收入 | B23: 万元 | C23: 财务科 | D23: 31.482536 | E23: 31.30081 | F23: 31.376036 | G23: 按科室人员数人均医疗服务收入
A24: 人均有效收入 | B24: 万元 | C24: 财务科 | D24: 50.790221 | E24: 51.612046 | F24: 49.728532 | G24: 按科室人员数人均有效收入
A25: 床均医疗服务收入 | B25: 万元 | C25: 财务科 | D25: 21.399564 | E25: 19.996646 | F25: 19.966568 | G25: 按开放床位数床均医疗服务收入
A26: 床均有效收入 | B26: 万元 | C26: 财务科 | D26: 34.523541 | E26: 32.972559 | F26: 31.64543 | G26: 按开放床位数床均有效收入
A27: 每名执业医师日均住院工作负担 | B27: 床日 | C27: 财务科 | D27: 6.6077055 | E27: 6.1455278 | F27: 8.1579909 | G27: 详见三级中医、三级公立国考手册 | H27: 全年实际占用总床日数/医院平均执业(助理)医师人数/365
A28: 医疗服务收入占医疗收入比例 | B28: % | C28: 财务科 | D28: 36.978335 | E28: 36.652478 | F28: 36.828963 | G28: 参考国考手册，原指标名为：医疗服务收入（不含药品、耗材、检查检验收入）占医疗收入比例 | H28: 医疗服务收入/医疗收入*100
A29: 医疗收入 | B29: 万元 | C29: 财务科 | D29: 5789.3694 | E29: 5636.3269 | F29: 5963.5741 | H29: 门诊收入+住院收入
A30: 医疗服务收入 | B30: 万元 | C30: 财务科 | D30: 2140.8124 | E30: 2065.8535 | F30: 2196.3225
A31: 有效收入 | B31: 万元 | C31: 财务科 | D31: 3453.735 | E31: 3406.395 | F31: 3480.9973 | H31: 医疗服务收入+检查检验收入
A32: 医疗直接成本 | B32: 万元 | D32: 4583.68 | E32: 3671.92 | F32: 3977.79
A33: 收支结余率 | B33: % | D33: -0.8 | E33: 1.76 | F33: -12.58
A34: 万元收入能耗占比 | B34: 吨标煤/万元 | C34: 后勤管理科 | G34: 详见国考手册 | H34: 年总能耗/年总收入*10000
A35: 门诊收入占医疗收入比例 | B35: % | C35: 财务科 | D35: 6.2751173 | E35: 5.344615 | F35: 4.921211 | G35: 详见三级公立国考手册 | H35: 门诊收入/医疗收入*100
A36: 住院收入占医疗收入比例 | B36: % | C36: 财务科 | D36: 93.724883 | E36: 94.655385 | F36: 95.078789 | G36: 详见三级公立国考手册 | H36: 住院收入/医疗收入*100
A37: 医疗收入增幅 | B37: % | C37: 财务科 | D37: 2.7152888 | E37: -5.487434 | F37: -1.8271884 | G37: 详见国考手册 | H37: （本年度医疗收入－上一年度医疗收入）/上一年度医疗收入*100
A38: 门诊次均费用增幅 | B38: % | C38: 财务科 | D38: 0.14773991 | E38: 6.5845257 | F38: -80.314729 | G38: 详见国考手册 | H38: （本年度门诊患者次均医药费用－上一年度门诊患者次均医药费用）/上一年度门诊患者次均医药费用*100
A39: 住院次均费用增幅 | B39: % | C39: 财务科 | D39: 3.5098375 | E39: -5.0579291 | F39: 1.9116855 | G39: 详见国考手册 | H39: （本年度出院患者次均医药费用－上一年度出院患者次均医药费用）/上一年度出院患者次均医药费用*100
A40: 门诊次均药品费用增幅 | B40: % | C40: 财务科 | D40: 9.01097 | E40: -6.2946889 | F40: -81.656571 | G40: 详见国考手册 | H40: （本年度门诊患者次均药品费用－上一年度门诊患者次均药品费用）/上一年度门诊患者次均药品费用*100
A41: 住院次均药品费用增幅 | B41: % | C41: 财务科 | D41: 5.7336867 | E41: -26.444618 | F41: 14.17774 | G41: 详见国考手册 | H41: （本年度出院患者次均药品费用－上一年度出院患者次均药品费用）/上一年度出院患者次均药品费用*100
A42: 医护比 | C42: 人事科 | D42: 0.33 | E42: 0.33 | F42: 0.3 | G42: 参考国考手册，原计量单位为比值（1:X），现改为小数 | H42: 医院注册医师总数/全院同期注册护士总数
A43: 医师人数 | B43: 人 | C43: 人事科 | D43: 16 | E43: 17 | F43: 15 | G43: 详见国考手册中，医护比定义
A44: 护士人数 | B44: 人 | C44: 人事科 | D44: 49 | E44: 51 | F44: 50 | G44: 详见国考手册中，医护比定义
A45: 医师高级职称占比 | B45: % | C45: 人事科 | D45: 37.5 | E45: 29.41 | F45: 33.33 | H45: (正高职称医师人数+副高职称医师人数)/医师人数*100
A46: 医师博士占比 | B46: % | C46: 人事科 | D46: 6.25 | E46: 11.76 | F46: 6.67 | H46: 博士医师人数/医师人数*100
A47: 医师硕士占比 | B47: % | C47: 人事科 | D47: 75 | E47: 64.71 | F47: 73.33 | H47: 硕士医师人数/医师人数*100
A48: 发表教学文章数与卫生技术人员数之比 | C48: 科教科 | D48: 0 | E48: 0 | F48: 0 | G48: 参考三级中医、三级公立国考手册，医院承担培养医学人才的工作成效的构成元素。原计量单位为比值（1:X），现改为小数 | H48: 本年度发表的教学文章数/同期卫生技术人员总数
A49: 省部级及以上教育教学课题数与卫生技术人员数之比 | C49: 科教科 | D49: 0 | E49: 0 | F49: 0 | G49: 参考三级中医、三级公立国考手册，医院承担培养医学人才的工作成效的构成元素。本指标为延伸指标。原计量单位为比值（1:X），现改为小数 | H49: 本年度获得的省部级及以上教育教学课题数/同期卫生技术人员总数
A50: 国家级继续医学教育项目数与卫生技术人员数之比 | C50: 科教科 | D50: 0.015385 | E50: 0 | F50: 0 | G50: 参考三级中医、三级公立国考手册，医院承担培养医学人才的工作成效的构成元素。本指标为延伸指标。原计量单位为比值（1:X），现改为小数 | H50: 本年度举办的国家级继续医学教育项目数/同期卫生技术人员总数
A51: 每百名卫生技术人员科研项目经费 | B51: 元 | C51: 科教科 | D51: 169038.43 | E51: 0 | F51: 0 | G51: 详见三级中医、三级公立国考手册 | H51: 本年度科研项目立项经费总金额/同期卫生技术人员总数*100
A52: 每百名卫生技术人员科研成果转化金额 | B52: 元 | C52: 科教科 | D52: 0 | E52: 0 | F52: 0 | G52: 详见三级公立国考手册 | H52: 本年度科技成果转化总金额/同期医院卫生技术人员总数*100
A53: 医师人均国家自然科学基金项目数量 | B53: 项 | C53: 科教科 | D53: 0 | E53: 0 | F53: 0 | G53: 说明：本年度成功立项的项目数量。要求本科室为主研单位
A54: 医师人均SCI文章数量 | B54: 篇 | C54: 科教科 | D54: 0 | E54: 0.059 | F54: 0 | G54: 说明：本年度成功发表的论文，要求第一作者或通讯作者为本院员工
A55: SCI平均影响因子 | B55: 分 | C55: 科教科 | D55: 0 | E55: 0.134 | F55: 0 | G55: 说明：本年度成功发表的论文，要求第一作者或通讯作者为本院员工
A56: 博士研究生导师占比 | B56: % | C56: 科教科 | D56: 0 | E56: 0 | F56: 0 | H56: 博士研究生导师人数/同期医师总数*100
A57: 硕士研究生导师占比 | B57: % | C57: 科教科 | D57: 6.25 | E57: 5.88 | F57: 0 | H57: 硕士研究生导师人数/同期医师总数*100
A58: 外省住院患者占比 | B58: % | C58: 统计室 | D58: 10.45 | E58: 9.79 | F58: 12.1 | H58: 外省住院患者人数/同期出院患者人次数*100
A59: 非医嘱离院率 | B59: % | C59: 统计室 | D59: 0.076628352 | E59: 0.12909889 | F59: 0.95381526 | H59: 非医嘱离院人次/同期出院患者总人次*100
A60: 是否为教育部或科技部重点学科或重点实验室 | B60: 分 | C60: 科教科 | D60: 0 | E60: 0 | F60: 0 | G60: 是填1,否填0
A61: 是否为国家卫健委临床重点专科 | B61: 分 | C61: 科教科 | D61: 0 | E61: 0 | F61: 0 | G61: 是填1,否填0
A62: 是否为国家中医药局重点专科 | B62: 分 | C62: 科教科 | D62: 0 | E62: 0 | F62: 0 | G62: 是填1,否填0
A63: 是否为省教育厅或科技厅重点学科或重点实验室 | B63: 分 | C63: 科教科 | D63: 0 | E63: 0 | F63: 0 | G63: 是填1,否填0
A64: 是否为省卫健委重点专科 | B64: 分 | C64: 科教科 | D64: 0 | E64: 0 | F64: 0 | G64: 是填1,否填0
A65: 是否为省中医药局重点专科 | B65: 分 | C65: 科教科 | D65: 0 | E65: 0 | F65: 0 | G65: 是填1,否填0
A66: 是否为地市级教育局或科技局重点学科或重点实验室 | B66: 分 | C66: 科教科 | D66: 0 | E66: 0 | F66: 0 | G66: 是填1,否填0
A67: 是否为地市级卫健委重点专科 | B67: 分 | C67: 科教科 | D67: 1 | E67: 1 | F67: 1 | G67: 是填1,否填0
A68: 是否为地市级中医药局重点专科 | B68: 分 | C68: 科教科 | D68: 0 | E68: 0 | F68: 0 | G68: 是填1,否填0
A69: 是否为县级教育局或科技局重点学科或重点实验室 | B69: 分 | C69: 科教科 | D69: 0 | E69: 0 | F69: 0 | G69: 是填1,否填0
A70: 是否为县级卫健委重点专科 | B70: 分 | C70: 科教科 | D70: 0 | E70: 0 | F70: 0 | G70: 是填1,否填0
A71: 是否为县级中医药局重点专科 | B71: 分 | C71: 科教科 | D71: 0 | E71: 0 | F71: 0 | G71: 是填1,否填0
A72: 第一顺位疾病名称 | C72: 信息科 | D72: =[1]创伤骨科!$O$4 -> 取除骨折或关节内外固定 | E72: =[1]创伤骨科!$I$4 -> 取除骨折或关节内外固定 | F72: =[1]创伤骨科!$C$4 -> 取除骨折或关节内外固定
A73: 第一顺位疾病编码 | C73: 信息科 | D73: =[1]创伤骨科!$N$4 -> Z47 | E73: =[1]创伤骨科!$H$4 -> Z47 | F73: =[1]创伤骨科!$B$4 -> Z47
A74: 第一顺位疾病占比 | B74: % | C74: 信息科 | D74: =[1]创伤骨科!$Q$4 -> 16.091954 | E74: =[1]创伤骨科!$K$4 -> 14.510715 | F74: =[1]创伤骨科!$E$4 -> 13.679719
A75: 第二顺位疾病名称 | C75: 信息科 | D75: =[1]创伤骨科!$O$5 -> 小腿骨骨折 | E75: =[1]创伤骨科!$I$5 -> 小腿骨骨折 | F75: =[1]创伤骨科!$C$5 -> 小腿骨骨折
A76: 第二顺位疾病编码 | C76: 信息科 | D76: =[1]创伤骨科!$N$5 -> S82 | E76: =[1]创伤骨科!$H$5 -> S82 | F76: =[1]创伤骨科!$B$5 -> S82
A77: 第二顺位疾病占比 | B77: % | C77: 信息科 | D77: =[1]创伤骨科!$Q$5 -> 8.6079183 | E77: =[1]创伤骨科!$K$5 -> 8.2106894 | F77: =[1]创伤骨科!$E$5 -> 9.3624498
A78: 第三顺位疾病名称 | C78: 信息科 | D78: =[1]创伤骨科!$O$6 -> 股骨骨折 | E78: =[1]创伤骨科!$I$6 -> 股骨骨折 | F78: =[1]创伤骨科!$C$6 -> 股骨骨折
A79: 第三顺位疾病编码 | C79: 信息科 | D79: =[1]创伤骨科!$N$6 -> S72 | E79: =[1]创伤骨科!$H$6 -> S72 | F79: =[1]创伤骨科!$B$6 -> S72
A80: 第三顺位疾病占比 | B80: % | C80: 信息科 | D80: =[1]创伤骨科!$Q$6 -> 6.9220945 | E80: =[1]创伤骨科!$K$6 -> 8.1074103 | F80: =[1]创伤骨科!$E$6 -> 8.6094378
A81: 第四顺位疾病名称 | C81: 信息科 | D81: =[1]创伤骨科!$O$7 -> 前臂骨折 | E81: =[1]创伤骨科!$I$7 -> 肱骨骨折 | F81: =[1]创伤骨科!$C$7 -> 肱骨骨折
A82: 第四顺位疾病编码 | C82: 信息科 | D82: =[1]创伤骨科!$N$7 -> S52 | E82: =[1]创伤骨科!$H$7 -> S42.2-4 | F82: =[1]创伤骨科!$B$7 -> S42.2-4
A83: 第四顺位疾病占比 | B83: % | C83: 信息科 | D83: =[1]创伤骨科!$Q$7 -> 5.7471264 | E83: =[1]创伤骨科!$K$7 -> 5.3188743 | F83: =[1]创伤骨科!$E$7 -> 4.9698795
A84: 第五顺位疾病名称 | C84: 信息科 | D84: =[1]创伤骨科!$O$8 -> 肩和上臂骨折 | E84: =[1]创伤骨科!$I$8 -> 尺桡骨骨折 | F84: =[1]创伤骨科!$C$8 -> 尺桡骨骨折
A85: 第五顺位疾病编码 | C85: 信息科 | D85: =[1]创伤骨科!$N$8 -> S42.2-4 肱骨骨折 | E85: =[1]创伤骨科!$H$8 -> S52 | F85: =[1]创伤骨科!$B$8 -> S52
A86: 第五顺位疾病占比 | B86: % | C86: 信息科 | D86: =[1]创伤骨科!$Q$8 -> 4.8786718 | E86: =[1]创伤骨科!$K$8 -> 5.1639556 | F86: =[1]创伤骨科!$E$8 -> 4.5933735
A87: 第一顺位手术名称 | C87: 信息科 | D87: =[2]创伤骨科!$O$4 -> 骨折切开复位内固定术 | E87: =[2]创伤骨科!$I$4 -> 骨折切开复位内固定术 | F87: =[2]创伤骨科!$C$4 -> 骨折切开复位内固定术
A88: 第一顺位手术编码 | C88: 信息科 | D88: =[2]创伤骨科!$N$4 -> 79.3 | E88: =[2]创伤骨科!$H$4 -> 79.3 | F88: =[2]创伤骨科!$B$4 -> 79.3
A89: 第一顺位手术占比 | B89: % | C89: 信息科 | D89: =[2]创伤骨科!$Q$4 -> 36.481203 | E89: =[2]创伤骨科!$K$4 -> 37.280702 | F89: =[2]创伤骨科!$E$4 -> 41.430455
A90: 第二顺位手术名称 | C90: 信息科 | D90: =[2]创伤骨科!$O$5 -> 骨内固定装置去除术 | E90: =[2]创伤骨科!$I$5 -> 骨内固定装置去除术 | F90: =[2]创伤骨科!$C$5 -> 骨内固定装置去除术
A91: 第二顺位手术编码 | C91: 信息科 | D91: =[2]创伤骨科!$N$5 -> 78.6 | E91: =[2]创伤骨科!$H$5 -> 78.6 | F91: =[2]创伤骨科!$B$5 -> 78.6
A92: 第二顺位手术占比 | B92: % | C92: 信息科 | D92: =[2]创伤骨科!$Q$5 -> 19.518797 | E92: =[2]创伤骨科!$K$5 -> 19.095816 | F92: =[2]创伤骨科!$E$5 -> 18.259723
A93: 第三顺位手术名称 | C93: 信息科 | D93: =[2]创伤骨科!$O$6 -> 骨折闭合性复位内固定术 | E93: =[2]创伤骨科!$I$6 -> 骨折闭合性复位内固定术 | F93: =[2]创伤骨科!$C$6 -> 骨折闭合性复位内固定术
A94: 第三顺位手术编码 | C94: 信息科 | D94: =[2]创伤骨科!$N$6 -> 79.1 | E94: =[2]创伤骨科!$H$6 -> 79.1 | F94: =[2]创伤骨科!$B$6 -> 79.1
A95: 第三顺位手术占比 | B95: % | C95: 信息科 | D95: =[2]创伤骨科!$Q$6 -> 6.0150376 | E95: =[2]创伤骨科!$K$6 -> 6.5789474 | F95: =[2]创伤骨科!$E$6 -> 5.2076467
A96: 第四顺位手术名称 | C96: 信息科 | D96: =[2]创伤骨科!$O$7 -> 伤口、感染或烧伤的切除性清创术 | E96: =[2]创伤骨科!$I$7 -> 手游离皮瓣移植术 | F96: =[2]创伤骨科!$C$7 -> 手游离皮瓣移植术
A97: 第四顺位手术编码 | C97: 信息科 | D97: =[2]创伤骨科!$N$7 -> 86.2 | E97: =[2]创伤骨科!$H$7 -> 86.7 | F97: =[2]创伤骨科!$B$7 -> 86.7
A98: 第四顺位手术占比 | B98: % | C98: 信息科 | D98: =[2]创伤骨科!$Q$7 -> 5.4736842 | E98: =[2]创伤骨科!$K$7 -> 5.7017544 | F98: =[2]创伤骨科!$E$7 -> 4.4825313
A99: 第五顺位手术名称 | C99: 信息科 | D99: =[2]创伤骨科!$O$8 -> 手游离皮瓣移植术 | E99: =[2]创伤骨科!$I$8 -> 手部屈肌腱缝合术，Ⅰ期 | F99: =[2]创伤骨科!$C$8 -> 手部屈肌腱缝合术，Ⅰ期
A100: 第五顺位手术编码 | C100: 信息科 | D100: =[2]创伤骨科!$N$8 -> 86.7 | E100: =[2]创伤骨科!$H$8 -> 82.4 | F100: =[2]创伤骨科!$B$8 -> 82.4
...

Sheet 关节骨病科
A1: 数据名 | B1: 计量单位 | C1: 填报部门 | D1: Y2021 | E1: Y2020 | F1: Y2019 | G1: 指标说明 | H1: 计算公式
A2: 出院患者手术占比 | B2: % | C2: 统计室 | D2: 84.929757 | E2: 76.529822 | F2: 76.154618 | G2: 详见三级公立、二级公立国考手册。举例：30%请填写30（不带百分号），而非写成30%，或0.3。下同 | H2: 出院患者手术台次数/同期出院患者总人次数*100
A3: 出院患者微创手术占比 | B3: % | C3: 统计室 | D3: 1.4736842 | E3: 0.60728745 | F3: 0.92287409 | G3: 详见三级公立、二级公立国考手册 | H3: 出院患者微创手术台次数/同期出院患者手术台次数*100
A4: 出院患者四级手术比例 | B4: % | C4: 统计室 | D4: 5.2330827 | E4: 1.0458839 | F4: 1.3513514 | G4: 详见三级公立国考手册 | H4: 出院患者四级手术台次数/同期出院患者手术台次数*100
A5: 出院患者疑难危重病例比例 | B5: % | C5: 统计室 | D5: 94.89 | E5: 75.83 | F5: 69.8 | G5: 即CD型病例占比 | H5: (疑难病例数+危重病例数)/出院人数*100
A6: 手术患者并发症发生率 | B6: % | C6: 质控科 | D6: 0 | E6: 0 | F6: 0 | G6: 详见国考手册 | H6: 手术患者并发症发生例数/同期出院的手术患者人数*100
A7: I类切口手术部位感染率 | B7: % | C7: 质控科 | D7: 0.2 | E7: 0.05 | F7: 0.29 | G7: 详见三级中医、三级公立国考手册 | H7: I类切口手术部位感染人次数/同期I类切口手术台次数*100
A8: 大型医用设备检查阳性率 | B8: % | C8: 医务科 | G8: 详见三级中医、三级公立国考手册 | H8: 大型医用设备检查阳性数/同期大型医用设备检查人次数*100
A9: 低风险组病例死亡率 | B9: % | C9: 质控科 | D9: 0 | E9: 0 | F9: 0 | G9: 详见三级公立、二级公立国考手册 | H9: 低风险组死亡例数/低风险组病例数*100
A10: 医院感染发生率 | B10: % | C10: 院感科 | D10: 0.87 | E10: 0.67 | F10: 0.9 | G10: 等级评审标准细则
A11: 抗菌药物使用强度DDDs | B11: DDD | C11: 药学部 | D11: 68.260528 | E11: 70.134053 | F11: 70.25339 | G11: 详见国考手册 | H11: 住院患者抗菌药物消耗量（累计DDD数）/同期收治患者人天数*100
A12: 门诊患者基本药物处方占比 | B12: % | C12: 药学部 | D12: 78.87 | E12: 72.16 | F12: 68.79 | G12: 详见三级中医、三级公立国考手册 | H12: 门诊使用基本药物人次数/同期门诊诊疗总人次数*100
A13: 住院患者基本药物使用率 | B13: % | C13: 药学部 | D13: 98.6 | E13: 96.79 | F13: 95.8 | G13: 详见三级中医、三级公立国考手册 | H13: 出院患者使用基本药物总人次数/同期出院总人次数*100
A14: 重点监控高值医用耗材收入占比 | B14: % | C14: 设备科 | D14: =(8283256.5+1472568)/34657840*100 -> 28.148969 | E14: =10105088/30034498*100 -> 33.644937 | F14: =5301602/33233253*100 -> 15.952703 | G14: 详见国考手册 | H14: 重点监控高值医用耗材收入/同期卫生材料收入*100
A15: 平均住院日 | B15: 天 | C15: 统计室 | D15: 10.25 | E15: 9.95 | F15: 11.55 | G15: 详见二级公立国考手册 | H15: 出院患者占用总床日数/同期出院患者人数
A16: CMI值 | C16: 质控科 | D16: 1.58 | E16: 1.4 | F16: 1.49 | G16: 病例组合指数
A17: DRGs组数 | B17: 组 | C17: 质控科 | D17: 133 | E17: 146 | F17: 149 | G17: 诊断相关分组组数
A18: 核定床位数 | B18: 张 | C18: 统计室 | D18: 94 | E18: 94 | F18: 94 | G18: 等级评审标准细则
A19: 实际开放床位数 | B19: 张 | C19: 统计室 | D19: 49 | E19: 40 | F19: 55 | G19: 等级评审标准细则
A20: 开放床位使用率 | B20: % | C20: 统计室 | D20: 105.7 | E20: 100.85 | F20: 111.25 | G20: 等级评审标准细则 | H20: 实际占用的总床日数/同期实际开放的总床日数*100
A21: 医师人数与开放床位数比 | C21: 人事科 | D21: =D43/D19 -> 0.32653061 | E21: =E43/E19 -> 0.425 | F21: =F43/F19 -> 0.27272727 | G21: 等级评审标准细则，原计量单位为比值（1:X），现改为小数 | H21: 医院执业（助理）医师总数/同期全院实际开放床位数
A22: 护士人数与开放床位数比 | C22: 人事科 | D22: =D44/D19 -> 1 | E22: =E44/E19 -> 1.275 | F22: =F44/F19 -> 0.90909091 | G22: 等级评审标准细则，原计量单位为比值（1:X），现改为小数 | H22: 医院注册护士总数/同期全院实际开放床位数
A23: 人均医疗服务收入 | B23: 万元 | C23: 财务科 | D23: 31.482536 | E23: 31.30081 | F23: 31.376036 | G23: 按科室人员数人均医疗服务收入
A24: 人均有效收入 | B24: 万元 | C24: 财务科 | D24: 50.790221 | E24: 51.612046 | F24: 49.728532 | G24: 按科室人员数人均有效收入
A25: 床均医疗服务收入 | B25: 万元 | C25: 财务科 | D25: 21.399564 | E25: 19.996646 | F25: 19.966568 | G25: 按开放床位数床均医疗服务收入
A26: 床均有效收入 | B26: 万元 | C26: 财务科 | D26: 34.523541 | E26: 32.972559 | F26: 31.64543 | G26: 按开放床位数床均有效收入
A27: 每名执业医师日均住院工作负担 | B27: 床日 | C27: 财务科 | D27: 6.6077055 | E27: 6.1455278 | F27: 8.1579909 | G27: 详见三级中医、三级公立国考手册 | H27: 全年实际占用总床日数/医院平均执业(助理)医师人数/365
A28: 医疗服务收入占医疗收入比例 | B28: % | C28: 财务科 | D28: 36.978335 | E28: 36.652478 | F28: 36.828963 | G28: 参考国考手册，原指标名为：医疗服务收入（不含药品、耗材、检查检验收入）占医疗收入比例 | H28: 医疗服务收入/医疗收入*100
A29: 医疗收入 | B29: 万元 | C29: 财务科 | D29: 5789.3694 | E29: 5636.3269 | F29: 5963.5741 | H29: 门诊收入+住院收入
A30: 医疗服务收入 | B30: 万元 | C30: 财务科 | D30: 2140.8124 | E30: 2065.8535 | F30: 2196.3225
A31: 有效收入 | B31: 万元 | C31: 财务科 | D31: 3453.735 | E31: 3406.395 | F31: 3480.9973 | H31: 医疗服务收入+检查检验收入
A32: 医疗直接成本 | B32: 万元 | D32: 2704.35 | E32: 2226.99 | F32: 2895.82
A33: 收支结余率 | B33: % | D33: -11.29 | E33: 4.19 | F33: 8.16
A34: 万元收入能耗占比 | B34: 吨标煤/万元 | C34: 后勤管理科 | G34: 详见国考手册 | H34: 年总能耗/年总收入*10000
A35: 门诊收入占医疗收入比例 | B35: % | C35: 财务科 | D35: 6.2751173 | E35: 5.344615 | F35: 4.921211 | G35: 详见三级公立国考手册 | H35: 门诊收入/医疗收入*100
A36: 住院收入占医疗收入比例 | B36: % | C36: 财务科 | D36: 93.724883 | E36: 94.655385 | F36: 95.078789 | G36: 详见三级公立国考手册 | H36: 住院收入/医疗收入*100
A37: 医疗收入增幅 | B37: % | C37: 财务科 | D37: 2.7152888 | E37: -5.487434 | F37: -1.8271884 | G37: 详见国考手册 | H37: （本年度医疗收入－上一年度医疗收入）/上一年度医疗收入*100
A38: 门诊次均费用增幅 | B38: % | C38: 财务科 | D38: 0.14773991 | E38: 6.5845257 | F38: -80.314729 | G38: 详见国考手册 | H38: （本年度门诊患者次均医药费用－上一年度门诊患者次均医药费用）/上一年度门诊患者次均医药费用*100
A39: 住院次均费用增幅 | B39: % | C39: 财务科 | D39: 3.5098375 | E39: -5.0579291 | F39: 1.9116855 | G39: 详见国考手册 | H39: （本年度出院患者次均医药费用－上一年度出院患者次均医药费用）/上一年度出院患者次均医药费用*100
A40: 门诊次均药品费用增幅 | B40: % | C40: 财务科 | D40: 9.01097 | E40: -6.2946889 | F40: -81.656571 | G40: 详见国考手册 | H40: （本年度门诊患者次均药品费用－上一年度门诊患者次均药品费用）/上一年度门诊患者次均药品费用*100
A41: 住院次均药品费用增幅 | B41: % | C41: 财务科 | D41: 5.7336867 | E41: -26.444618 | F41: 14.17774 | G41: 详见国考手册 | H41: （本年度出院患者次均药品费用－上一年度出院患者次均药品费用）/上一年度出院患者次均药品费用*100
A42: 医护比 | C42: 人事科 | D42: 0.33 | E42: 0.33 | F42: 0.3 | G42: 参考国考手册，原计量单位为比值（1:X），现改为小数 | H42: 医院注册医师总数/全院同期注册护士总数
A43: 医师人数 | B43: 人 | C43: 人事科 | D43: 16 | E43: 17 | F43: 15 | G43: 详见国考手册中，医护比定义
A44: 护士人数 | B44: 人 | C44: 人事科 | D44: 49 | E44: 51 | F44: 50 | G44: 详见国考手册中，医护比定义
A45: 医师高级职称占比 | B45: % | C45: 人事科 | D45: 37.5 | E45: 29.41 | F45: 33.33 | H45: (正高职称医师人数+副高职称医师人数)/医师人数*100
A46: 医师博士占比 | B46: % | C46: 人事科 | D46: 6.25 | E46: 11.76 | F46: 6.67 | H46: 博士医师人数/医师人数*100
A47: 医师硕士占比 | B47: % | C47: 人事科 | D47: 75 | E47: 64.71 | F47: 73.33 | H47: 硕士医师人数/医师人数*100
A48: 发表教学文章数与卫生技术人员数之比 | C48: 科教科 | D48: 0 | E48: 0 | F48: 0 | G48: 参考三级中医、三级公立国考手册，医院承担培养医学人才的工作成效的构成元素。原计量单位为比值（1:X），现改为小数 | H48: 本年度发表的教学文章数/同期卫生技术人员总数
A49: 省部级及以上教育教学课题数与卫生技术人员数之比 | C49: 科教科 | D49: 0 | E49: 0 | F49: 0 | G49: 参考三级中医、三级公立国考手册，医院承担培养医学人才的工作成效的构成元素。本指标为延伸指标。原计量单位为比值（1:X），现改为小数 | H49: 本年度获得的省部级及以上教育教学课题数/同期卫生技术人员总数
A50: 国家级继续医学教育项目数与卫生技术人员数之比 | C50: 科教科 | D50: 0.015385 | E50: 0 | F50: 0 | G50: 参考三级中医、三级公立国考手册，医院承担培养医学人才的工作成效的构成元素。本指标为延伸指标。原计量单位为比值（1:X），现改为小数 | H50: 本年度举办的国家级继续医学教育项目数/同期卫生技术人员总数
A51: 每百名卫生技术人员科研项目经费 | B51: 元 | C51: 科教科 | D51: 169038.43 | E51: 0 | F51: 0 | G51: 详见三级中医、三级公立国考手册 | H51: 本年度科研项目立项经费总金额/同期卫生技术人员总数*100
A52: 每百名卫生技术人员科研成果转化金额 | B52: 元 | C52: 科教科 | D52: 0 | E52: 0 | F52: 0 | G52: 详见三级公立国考手册 | H52: 本年度科技成果转化总金额/同期医院卫生技术人员总数*100
A53: 医师人均国家自然科学基金项目数量 | B53: 项 | C53: 科教科 | D53: 0 | E53: 0 | F53: 0 | G53: 说明：本年度成功立项的项目数量。要求本科室为主研单位
A54: 医师人均SCI文章数量 | B54: 篇 | C54: 科教科 | D54: 0 | E54: 0.059 | F54: 0 | G54: 说明：本年度成功发表的论文，要求第一作者或通讯作者为本院员工
A55: SCI平均影响因子 | B55: 分 | C55: 科教科 | D55: 0 | E55: 0.134 | F55: 0 | G55: 说明：本年度成功发表的论文，要求第一作者或通讯作者为本院员工
A56: 博士研究生导师占比 | B56: % | C56: 科教科 | D56: 0 | E56: 0 | F56: 0 | H56: 博士研究生导师人数/同期医师总数*100
A57: 硕士研究生导师占比 | B57: % | C57: 科教科 | D57: 6.25 | E57: 5.88 | F57: 0 | H57: 硕士研究生导师人数/同期医师总数*100
A58: 外省住院患者占比 | B58: % | C58: 统计室 | D58: 6.6795741 | E58: 6.1651584 | F58: 6.5114068 | H58: 外省住院患者人数/同期出院患者人次数*100
A59: 非医嘱离院率 | B59: % | C59: 统计室 | D59: 0.076628352 | E59: 0.12909889 | F59: 0.95381526 | H59: 非医嘱离院人次/同期出院患者总人次*100
A60: 是否为教育部或科技部重点学科或重点实验室 | B60: 分 | C60: 科教科 | D60: 0 | E60: 0 | F60: 0 | G60: 是填1,否填0
A61: 是否为国家卫健委临床重点专科 | B61: 分 | C61: 科教科 | D61: 0 | E61: 0 | F61: 0 | G61: 是填1,否填0
A62: 是否为国家中医药局重点专科 | B62: 分 | C62: 科教科 | D62: 0 | E62: 0 | F62: 0 | G62: 是填1,否填0
A63: 是否为省教育厅或科技厅重点学科或重点实验室 | B63: 分 | C63: 科教科 | D63: 0 | E63: 0 | F63: 0 | G63: 是填1,否填0
A64: 是否为省卫健委重点专科 | B64: 分 | C64: 科教科 | D64: 0 | E64: 0 | F64: 0 | G64: 是填1,否填0
A65: 是否为省中医药局重点专科 | B65: 分 | C65: 科教科 | D65: 0 | E65: 0 | F65: 0 | G65: 是填1,否填0
A66: 是否为地市级教育局或科技局重点学科或重点实验室 | B66: 分 | C66: 科教科 | D66: 0 | E66: 0 | F66: 0 | G66: 是填1,否填0
A67: 是否为地市级卫健委重点专科 | B67: 分 | C67: 科教科 | D67: 1 | E67: 1 | F67: 1 | G67: 是填1,否填0
A68: 是否为地市级中医药局重点专科 | B68: 分 | C68: 科教科 | D68: 0 | E68: 0 | F68: 0 | G68: 是填1,否填0
A69: 是否为县级教育局或科技局重点学科或重点实验室 | B69: 分 | C69: 科教科 | D69: 0 | E69: 0 | F69: 0 | G69: 是填1,否填0
A70: 是否为县级卫健委重点专科 | B70: 分 | C70: 科教科 | D70: 0 | E70: 0 | F70: 0 | G70: 是填1,否填0
A71: 是否为县级中医药局重点专科 | B71: 分 | C71: 科教科 | D71: 0 | E71: 0 | F71: 0 | G71: 是填1,否填0
A72: 第一顺位疾病名称 | C72: 信息科 | D72: =[1]关节骨病科!$O$4 -> 膝关节病 | E72: =[1]关节骨病科!$I$4 -> 膝关节病 | F72: =[1]关节骨病科!$C$4 -> 膝关节病
A73: 第一顺位疾病编码 | C73: 信息科 | D73: =[1]关节骨病科!$N$4 -> M17 | E73: =[1]关节骨病科!$H$4 -> M17 | F73: =[1]关节骨病科!$B$4 -> M17
A74: 第一顺位疾病占比 | B74: % | C74: 信息科 | D74: =[1]关节骨病科!$Q$4 -> 13.310745 | E74: =[1]关节骨病科!$K$4 -> 15.667421 | F74: =[1]关节骨病科!$E$4 -> 13.830798
A75: 第二顺位疾病名称 | C75: 信息科 | D75: =[1]关节骨病科!$O$5 -> 股骨骨折 | E75: =[1]关节骨病科!$I$5 -> 股骨头坏死 | F75: =[1]关节骨病科!$C$5 -> 股骨头坏死
A76: 第二顺位疾病编码 | C76: 信息科 | D76: =[1]关节骨病科!$N$5 -> S72 | E76: =[1]关节骨病科!$H$5 -> M87.8 | F76: =[1]关节骨病科!$B$5 -> M87.8
A77: 第二顺位疾病占比 | B77: % | C77: 信息科 | D77: =[1]关节骨病科!$Q$5 -> 9.9709584 | E77: =[1]关节骨病科!$K$5 -> 11.199095 | F77: =[1]关节骨病科!$E$5 -> 11.692015
A78: 第三顺位疾病名称 | C78: 信息科 | D78: =[1]关节骨病科!$O$6 -> 膝关节脱位和韧带损伤 | E78: =[1]关节骨病科!$I$6 -> 股骨骨折 | F78: =[1]关节骨病科!$C$6 -> 股骨骨折
A79: 第三顺位疾病编码 | C79: 信息科 | D79: =[1]关节骨病科!$N$6 -> S83 | E79: =[1]关节骨病科!$H$6 -> S72 | F79: =[1]关节骨病科!$B$6 -> S72
A80: 第三顺位疾病占比 | B80: % | C80: 信息科 | D80: =[1]关节骨病科!$Q$6 -> 7.2604066 | E80: =[1]关节骨病科!$K$6 -> 10.124434 | F80: =[1]关节骨病科!$E$6 -> 8.8878327
A81: 第四顺位疾病名称 | C81: 信息科 | D81: =[1]关节骨病科!$O$7 -> 股骨头坏死 | E81: =[1]关节骨病科!$I$7 -> 膝关节脱位和韧带损伤 | F81: =[1]关节骨病科!$C$7 -> 膝关节脱位和韧带损伤
A82: 第四顺位疾病编码 | C82: 信息科 | D82: =[1]关节骨病科!$N$7 -> M87- | E82: =[1]关节骨病科!$H$7 -> S83 | F82: =[1]关节骨病科!$B$7 -> S83
A83: 第四顺位疾病占比 | B83: % | C83: 信息科 | D83: =[1]关节骨病科!$Q$7 -> 7.1151985 | E83: =[1]关节骨病科!$K$7 -> 6.7307692 | F83: =[1]关节骨病科!$E$7 -> 6.6539924
A84: 第五顺位疾病名称 | C84: 信息科 | D84: =[1]关节骨病科!$O$8 -> 取除骨折内固定装置 | E84: =[1]关节骨病科!$I$8 -> 取除骨折内固定装置 | F84: =[1]关节骨病科!$C$8 -> 取除骨折内固定装置
A85: 第五顺位疾病编码 | C85: 信息科 | D85: =[1]关节骨病科!$N$8 -> Z47.0 | E85: =[1]关节骨病科!$H$8 -> Z47.0 | F85: =[1]关节骨病科!$B$8 -> Z47.0
A86: 第五顺位疾病占比 | B86: % | C86: 信息科 | D86: =[1]关节骨病科!$Q$8 -> 5.9051307 | E86: =[1]关节骨病科!$K$8 -> 4.581448 | F86: =[1]关节骨病科!$E$8 -> 6.1311787
A87: 第一顺位手术名称 | C87: 信息科 | D87: =[2]关节骨病科!$O$4 -> 髋膝关节置换术，单侧，骨病型 | E87: =[2]关节骨病科!$I$4 -> 髋膝关节置换术，单侧，骨病型 | F87: =[2]关节骨病科!$C$4 -> 髋膝关节置换术，单侧，骨病型
A88: 第一顺位手术编码 | C88: 信息科 | D88: =[2]关节骨病科!$N$4 -> 81.5 | E88: =[2]关节骨病科!$H$4 -> 81.5 | F88: =[2]关节骨病科!$B$4 -> 81.5
A89: 第一顺位手术占比 | B89: % | C89: 信息科 | D89: =[2]关节骨病科!$Q$4 -> 32.120162 | E89: =[2]关节骨病科!$K$4 -> 38.213763 | F89: =[2]关节骨病科!$E$4 -> 35.245379
A90: 第二顺位手术名称 | C90: 信息科 | D90: =[2]关节骨病科!$O$5 -> 前交叉韧带修补术，伴自体肌腱植入，经关节镜 | E90: =[2]关节骨病科!$I$5 -> 膝外侧半月板修整术，经关节镜 | F90: =[2]关节骨病科!$C$5 -> 骨内固定装置去除术
A91: 第二顺位手术编码 | C91: 信息科 | D91: =[2]关节骨病科!$N$5 -> 81.4 | E91: =[2]关节骨病科!$H$5 -> 80.6 | F91: =[2]关节骨病科!$B$5 -> 78.6
A92: 第二顺位手术占比 | B92: % | C92: 信息科 | D92: =[2]关节骨病科!$Q$5 -> 13.287117 | E92: =[2]关节骨病科!$K$5 -> 9.0043924 | F92: =[2]关节骨病科!$E$5 -> 8.4130019
A93: 第三顺位手术名称 | C93: 信息科 | D93: =[2]关节骨病科!$O$6 -> 骨内固定装置去除术 | E93: =[2]关节骨病科!$I$6 -> 骨内固定装置去除术 | F93: =[2]关节骨病科!$C$6 -> 腘窝囊肿切除术(贝克氏囊肿切除术)
A94: 第三顺位手术编码 | C94: 信息科 | D94: =[2]关节骨病科!$N$6 -> 78.6 | E94: =[2]关节骨病科!$H$6 -> 78.6 | F94: =[2]关节骨病科!$B$6 -> 83.3
A95: 第三顺位手术占比 | B95: % | C95: 信息科 | D95: =[2]关节骨病科!$Q$6 -> 7.1634893 | E95: =[2]关节骨病科!$K$6 -> 5.8565154 | F95: =[2]关节骨病科!$E$6 -> 7.3932441
A96: 第四顺位手术名称 | C96: 信息科 | D96: =[2]关节骨病科!$O$7 -> 腘窝囊肿切除术(贝克氏囊肿切除术) | E96: =[2]关节骨病科!$I$7 -> 腘窝囊肿切除术(贝克氏囊肿切除术) | F96: =[2]关节骨病科!$C$7 -> 膝外侧半月板修整术，经关节镜
A97: 第四顺位手术编码 | C97: 信息科 | D97: =[2]关节骨病科!$N$7 -> 83.3 | E97: =[2]关节骨病科!$H$7 -> 83.3 | F97: =[2]关节骨病科!$B$7 -> 80.6
A98: 第四顺位手术占比 | B98: % | C98: 信息科 | D98: =[2]关节骨病科!$Q$7 -> 6.0080878 | E98: =[2]关节骨病科!$K$7 -> 5.8565154 | F98: =[2]关节骨病科!$E$7 -> 6.9471001
A99: 第五顺位手术名称 | C99: 信息科 | D99: =[2]关节骨病科!$O$8 -> 关节镜膝关节滑膜切除术 | E99: =[2]关节骨病科!$I$8 -> 前交叉韧带修补术，伴自体肌腱植入，经关节镜 | F99: =[2]关节骨病科!$C$8 -> 前交叉韧带修补术，伴自体肌腱植入，经关节镜
A100: 第五顺位手术编码 | C100: 信息科 | D100: =[2]关节骨病科!$N$8 -> 80.7 | E100: =[2]关节骨病科!$H$8 -> 81.4 | F100: =[2]关节骨病科!$B$8 -> 81.4
...

Sheet 妇科
A1: 数据名 | B1: 计量单位 | C1: 填报部门 | D1: Y2021 | E1: Y2020 | F1: Y2019 | G1: 指标说明 | H1: 计算公式
A2: 出院患者手术占比 | B2: % | C2: 统计室 | D2: 71.521246 | E2: 66.066351 | F2: 65.272727 | G2: 详见三级公立、二级公立国考手册。举例：30%请填写30（不带百分号），而非写成30%，或0.3。下同 | H2: 出院患者手术台次数/同期出院患者总人次数*100
A3: 出院患者微创手术占比 | B3: % | C3: 统计室 | D3: 65.170068 | E3: 64.08417 | F3: 64.623955 | G3: 详见三级公立、二级公立国考手册 | H3: 出院患者微创手术台次数/同期出院患者手术台次数*100
A4: 出院患者四级手术比例 | B4: % | C4: 统计室 | D4: 40.589569 | E4: 41.415591 | F4: 37.558032 | G4: 详见三级公立国考手册 | H4: 出院患者四级手术台次数/同期出院患者手术台次数*100
A5: 出院患者疑难危重病例比例 | B5: % | C5: 统计室 | D5: 99.32 | E5: 98.01 | F5: 93.73 | G5: 即CD型病例占比 | H5: (疑难病例数+危重病例数)/出院人数*100
A6: 手术患者并发症发生率 | B6: % | C6: 质控科 | D6: 0 | E6: 0 | F6: 0 | G6: 详见国考手册 | H6: 手术患者并发症发生例数/同期出院的手术患者人数*100
A7: I类切口手术部位感染率 | B7: % | C7: 质控科 | D7: 0 | E7: 0 | F7: 0 | G7: 详见三级中医、三级公立国考手册 | H7: I类切口手术部位感染人次数/同期I类切口手术台次数*100
A8: 大型医用设备检查阳性率 | B8: % | C8: 医务科 | G8: 详见三级中医、三级公立国考手册 | H8: 大型医用设备检查阳性数/同期大型医用设备检查人次数*100
A9: 低风险组病例死亡率 | B9: % | C9: 质控科 | D9: 0 | E9: 0 | F9: 0 | G9: 详见三级公立、二级公立国考手册 | H9: 低风险组死亡例数/低风险组病例数*100
A10: 医院感染发生率 | B10: % | C10: 院感科 | D10: 0.1 | E10: 0.25 | F10: 0.55 | G10: 等级评审标准细则
A11: 抗菌药物使用强度DDDs | B11: DDD | C11: 药学部 | D11: 65.305947 | E11: 67.274962 | F11: 53.561583 | G11: 详见国考手册 | H11: 住院患者抗菌药物消耗量（累计DDD数）/同期收治患者人天数*100
A12: 门诊患者基本药物处方占比 | B12: % | C12: 药学部 | D12: 97.46 | E12: 86.69 | F12: 79.12 | G12: 详见三级中医、三级公立国考手册 | H12: 门诊使用基本药物人次数/同期门诊诊疗总人次数*100
A13: 住院患者基本药物使用率 | B13: % | C13: 药学部 | D13: 92.77 | E13: 92.01 | F13: 95.35 | G13: 详见三级中医、三级公立国考手册 | H13: 出院患者使用基本药物总人次数/同期出院总人次数*100
A14: 重点监控高值医用耗材收入占比 | B14: % | C14: 设备科 | D14: =1080/51499757*100 -> 0.0020970973 | E14: =1512/52054773*100 -> 0.0029046328 | F14: =3528/57189813*100 -> 0.0061689308 | G14: 详见国考手册 | H14: 重点监控高值医用耗材收入/同期卫生材料收入*100
A15: 平均住院日 | B15: 天 | C15: 统计室 | D15: 5.51 | E15: 5.56 | F15: 6.23 | G15: 详见二级公立国考手册 | H15: 出院患者占用总床日数/同期出院患者人数
A16: CMI值 | C16: 质控科 | D16: 1.17 | E16: 1.13 | F16: 1.14 | G16: 病例组合指数
A17: DRGs组数 | B17: 组 | C17: 质控科 | D17: 72 | E17: 69 | F17: 81 | G17: 诊断相关分组组数
A18: 核定床位数 | B18: 张 | C18: 统计室 | D18: 49 | E18: 49 | F18: 49 | G18: 等级评审标准细则
A19: 实际开放床位数 | B19: 张 | C19: 统计室 | D19: 55 | E19: 49 | F19: 60 | G19: 等级评审标准细则
A20: 开放床位使用率 | B20: % | C20: 统计室 | D20: 87.12 | E20: 86.95 | F20: 94.88 | G20: 等级评审标准细则 | H20: 实际占用的总床日数/同期实际开放的总床日数*100
A21: 医师人数与开放床位数比 | C21: 人事科 | D21: =D43/D19 -> 0.34545455 | E21: =E43/E19 -> 0.36734694 | F21: =F43/F19 -> 0.28333333 | G21: 等级评审标准细则，原计量单位为比值（1:X），现改为小数 | H21: 医院执业（助理）医师总数/同期全院实际开放床位数
A22: 护士人数与开放床位数比 | C22: 人事科 | D22: =D44/D19 -> 0.78181818 | E22: =E44/E19 -> 0.91836735 | F22: =F44/F19 -> 0.73333333 | G22: 等级评审标准细则，原计量单位为比值（1:X），现改为小数 | H22: 医院注册护士总数/同期全院实际开放床位数
A23: 人均医疗服务收入 | B23: 万元 | C23: 财务科 | D23: 31.096024 | E23: 34.975719 | F23: 31.497223 | G23: 按科室人员数人均医疗服务收入
A24: 人均有效收入 | B24: 万元 | C24: 财务科 | D24: 66.039754 | E24: 72.704035 | F24: 67.43082 | G24: 按科室人员数人均有效收入
A25: 床均医疗服务收入 | B25: 万元 | C25: 财务科 | D25: 40.4606 | E25: 37.87984 | F25: 37.271714 | G25: 按开放床位数床均医疗服务收入
A26: 床均有效收入 | B26: 万元 | C26: 财务科 | D26: 85.927645 | E26: 78.740832 | F26: 79.793138 | G26: 按开放床位数床均有效收入
A27: 每名执业医师日均住院工作负担 | B27: 床日 | C27: 财务科 | D27: 2.4315789 | E27: 2.6835616 | F27: 3.3485898 | G27: 详见三级中医、三级公立国考手册 | H27: 全年实际占用总床日数/医院平均执业(助理)医师人数/365
A28: 医疗服务收入占医疗收入比例 | B28: % | C28: 财务科 | D28: 40.198723 | E28: 40.954099 | F28: 39.560647 | G28: 参考国考手册，原指标名为：医疗服务收入（不含药品、耗材、检查检验收入）占医疗收入比例 | H28: 医疗服务收入/医疗收入*100
A29: 医疗收入 | B29: 万元 | C29: 财务科 | D29: 5337.5467 | E29: 5124.1347 | F29: 5652.8469 | H29: 门诊收入+住院收入
A30: 医疗服务收入 | B30: 万元 | C30: 财务科 | D30: 2145.6256 | E30: 2098.5432 | F30: 2236.3028
A31: 有效收入 | B31: 万元 | C31: 财务科 | D31: 4556.743 | E31: 4362.2421 | F31: 4787.5883 | H31: 医疗服务收入+检查检验收入
A32: 医疗直接成本 | B32: 万元 | D32: 3083.38 | E32: 2642.69 | F32: 2882.95
A33: 收支结余率 | B33: % | D33: 26 | E33: 26.3 | F33: 19.66
A34: 万元收入能耗占比 | B34: 吨标煤/万元 | C34: 后勤管理科 | G34: 详见国考手册 | H34: 年总能耗/年总收入*10000
A35: 门诊收入占医疗收入比例 | B35: % | C35: 财务科 | D35: 43.923369 | E35: 40.761308 | F35: 43.142719 | G35: 详见三级公立国考手册 | H35: 门诊收入/医疗收入*100
A36: 住院收入占医疗收入比例 | B36: % | C36: 财务科 | D36: 56.076631 | E36: 59.238692 | F36: 56.857281 | G36: 详见三级公立国考手册 | H36: 住院收入/医疗收入*100
A37: 医疗收入增幅 | B37: % | C37: 财务科 | D37: 4.1648412 | E37: -9.3530268 | F37: 19.065351 | G37: 详见国考手册 | H37: （本年度医疗收入－上一年度医疗收入）/上一年度医疗收入*100
A38: 门诊次均费用增幅 | B38: % | C38: 财务科 | D38: -0.49770391 | E38: 2.0812188 | F38: 7.330144 | G38: 详见国考手册 | H38: （本年度门诊患者次均医药费用－上一年度门诊患者次均医药费用）/上一年度门诊患者次均医药费用*100
A39: 住院次均费用增幅 | B39: % | C39: 财务科 | D39: 2.1683849 | E39: -0.66867654 | F39: 4.3485981 | G39: 详见国考手册 | H39: （本年度出院患者次均医药费用－上一年度出院患者次均医药费用）/上一年度出院患者次均医药费用*100
A40: 门诊次均药品费用增幅 | B40: % | C40: 财务科 | D40: 12.019418 | E40: 6.2848418 | F40: 20.843788 | G40: 详见国考手册 | H40: （本年度门诊患者次均药品费用－上一年度门诊患者次均药品费用）/上一年度门诊患者次均药品费用*100
A41: 住院次均药品费用增幅 | B41: % | C41: 财务科 | D41: -9.3291558 | E41: -10.704668 | F41: -0.84718648 | G41: 详见国考手册 | H41: （本年度出院患者次均药品费用－上一年度出院患者次均药品费用）/上一年度出院患者次均药品费用*100
A42: 医护比 | C42: 人事科 | D42: 0.44 | E42: 0.4 | F42: 0.39 | G42: 参考国考手册，原计量单位为比值（1:X），现改为小数 | H42: 医院注册医师总数/全院同期注册护士总数
A43: 医师人数 | B43: 人 | C43: 人事科 | D43: 19 | E43: 18 | F43: 17 | G43: 详见国考手册中，医护比定义
A44: 护士人数 | B44: 人 | C44: 人事科 | D44: 43 | E44: 45 | F44: 44 | G44: 详见国考手册中，医护比定义
A45: 医师高级职称占比 | B45: % | C45: 人事科 | D45: 47.37 | E45: 50 | F45: 52.94 | H45: (正高职称医师人数+副高职称医师人数)/医师人数*100
A46: 医师博士占比 | B46: % | C46: 人事科 | D46: 0 | E46: 0 | F46: 0 | H46: 博士医师人数/医师人数*100
A47: 医师硕士占比 | B47: % | C47: 人事科 | D47: 52.63 | E47: 50 | F47: 47.06 | H47: 硕士医师人数/医师人数*100
A48: 发表教学文章数与卫生技术人员数之比 | C48: 科教科 | D48: 0.016 | E48: 0 | F48: 0 | G48: 参考三级中医、三级公立国考手册，医院承担培养医学人才的工作成效的构成元素。原计量单位为比值（1:X），现改为小数 | H48: 本年度发表的教学文章数/同期卫生技术人员总数
A49: 省部级及以上教育教学课题数与卫生技术人员数之比 | C49: 科教科 | D49: 0 | E49: 0 | F49: 0 | G49: 参考三级中医、三级公立国考手册，医院承担培养医学人才的工作成效的构成元素。本指标为延伸指标。原计量单位为比值（1:X），现改为小数 | H49: 本年度获得的省部级及以上教育教学课题数/同期卫生技术人员总数
A50: 国家级继续医学教育项目数与卫生技术人员数之比 | C50: 科教科 | D50: 0 | E50: 0 | F50: 0 | G50: 参考三级中医、三级公立国考手册，医院承担培养医学人才的工作成效的构成元素。本指标为延伸指标。原计量单位为比值（1:X），现改为小数 | H50: 本年度举办的国家级继续医学教育项目数/同期卫生技术人员总数
A51: 每百名卫生技术人员科研项目经费 | B51: 元 | C51: 科教科 | D51: 2552904.3 | E51: 283287.86 | F51: 131147.54 | G51: 详见三级中医、三级公立国考手册 | H51: 本年度科研项目立项经费总金额/同期卫生技术人员总数*100
A52: 每百名卫生技术人员科研成果转化金额 | B52: 元 | C52: 科教科 | D52: 0 | E52: 0 | F52: 0 | G52: 详见三级公立国考手册 | H52: 本年度科技成果转化总金额/同期医院卫生技术人员总数*100
A53: 医师人均国家自然科学基金项目数量 | B53: 项 | C53: 科教科 | D53: 0 | E53: 0 | F53: 0 | G53: 说明：本年度成功立项的项目数量。要求本科室为主研单位
A54: 医师人均SCI文章数量 | B54: 篇 | C54: 科教科 | D54: 0.053 | E54: 0 | F54: 0 | G54: 说明：本年度成功发表的论文，要求第一作者或通讯作者为本院员工
A55: SCI平均影响因子 | B55: 分 | C55: 科教科 | D55: 0.082 | E55: 0 | F55: 0 | G55: 说明：本年度成功发表的论文，要求第一作者或通讯作者为本院员工
A56: 博士研究生导师占比 | B56: % | C56: 科教科 | D56: 0 | E56: 0 | F56: 0 | H56: 博士研究生导师人数/同期医师总数*100
A57: 硕士研究生导师占比 | B57: % | C57: 科教科 | D57: 10.53 | E57: 11.11 | F57: 5.88 | H57: 硕士研究生导师人数/同期医师总数*100
A58: 外省住院患者占比 | B58: % | C58: 统计室 | D58: 4.768083 | E58: 4.7393365 | F58: 7.3333333 | H58: 外省住院患者人数/同期出院患者人次数*100
A59: 非医嘱离院率 | B59: % | C59: 统计室 | D59: 0.1621797 | E59: 0.5371248 | F59: 1.1818182 | H59: 非医嘱离院人次/同期出院患者总人次*100
A60: 是否为教育部或科技部重点学科或重点实验室 | B60: 分 | C60: 科教科 | D60: 0 | E60: 0 | F60: 0 | G60: 是填1,否填0
A61: 是否为国家卫健委临床重点专科 | B61: 分 | C61: 科教科 | D61: 0 | E61: 0 | F61: 0 | G61: 是填1,否填0
A62: 是否为国家中医药局重点专科 | B62: 分 | C62: 科教科 | D62: 0 | E62: 0 | F62: 0 | G62: 是填1,否填0
A63: 是否为省教育厅或科技厅重点学科或重点实验室 | B63: 分 | C63: 科教科 | D63: 0 | E63: 0 | F63: 0 | G63: 是填1,否填0
A64: 是否为省卫健委重点专科 | B64: 分 | C64: 科教科 | D64: 1 | E64: 1 | F64: 1 | G64: 是填1,否填0
A65: 是否为省中医药局重点专科 | B65: 分 | C65: 科教科 | D65: 0 | E65: 0 | F65: 0 | G65: 是填1,否填0
A66: 是否为地市级教育局或科技局重点学科或重点实验室 | B66: 分 | C66: 科教科 | D66: 0 | E66: 0 | F66: 0 | G66: 是填1,否填0
A67: 是否为地市级卫健委重点专科 | B67: 分 | C67: 科教科 | D67: 1 | E67: 1 | F67: 1 | G67: 是填1,否填0
A68: 是否为地市级中医药局重点专科 | B68: 分 | C68: 科教科 | D68: 0 | E68: 0 | F68: 0 | G68: 是填1,否填0
A69: 是否为县级教育局或科技局重点学科或重点实验室 | B69: 分 | C69: 科教科 | D69: 0 | E69: 0 | F69: 0 | G69: 是填1,否填0
A70: 是否为县级卫健委重点专科 | B70: 分 | C70: 科教科 | D70: 0 | E70: 0 | F70: 0 | G70: 是填1,否填0
A71: 是否为县级中医药局重点专科 | B71: 分 | C71: 科教科 | D71: 0 | E71: 0 | F71: 0 | G71: 是填1,否填0
A72: 第一顺位疾病名称 | C72: 信息科 | D72: =[1]妇科!$O$4 -> 子宫平滑肌瘤 | E72: =[1]妇科!$I$4 -> 子宫平滑肌瘤 | F72: =[1]妇科!$C$4 -> 子宫平滑肌瘤
A73: 第一顺位疾病编码 | C73: 信息科 | D73: =[1]妇科!$N$4 -> D25.- | E73: =[1]妇科!$H$4 -> D25. | F73: =[1]妇科!$B$4 -> D25.-
A74: 第一顺位疾病占比 | B74: % | C74: 信息科 | D74: =[1]妇科!$Q$4 -> 19.00746 | E74: =[1]妇科!$K$4 -> 18.420221 | F74: =[1]妇科!$E$4 -> 16.272727
A75: 第二顺位疾病名称 | C75: 信息科 | D75: =[1]妇科!$O$5 -> 为肿瘤化学治疗疗程 | E75: =[1]妇科!$I$5 -> 为肿瘤化学治疗疗程 | F75: =[1]妇科!$C$5 -> 为肿瘤化学治疗疗程
A76: 第二顺位疾病编码 | C76: 信息科 | D76: =[1]妇科!$N$5 -> Z51.1 | E76: =[1]妇科!$H$5 -> Z51.1 | F76: =[1]妇科!$B$5 -> Z51.1
A77: 第二顺位疾病占比 | B77: % | C77: 信息科 | D77: =[1]妇科!$Q$5 -> 15.601687 | E77: =[1]妇科!$K$5 -> 14.849921 | F77: =[1]妇科!$E$5 -> 13.363636
A78: 第三顺位疾病名称 | C78: 信息科 | D78: =[1]妇科!$O$6 -> 宫颈原位癌 | E78: =[1]妇科!$I$6 -> 输卵管妊娠 | F78: =[1]妇科!$C$6 -> 输卵管妊娠
A79: 第三顺位疾病编码 | C79: 信息科 | D79: =[1]妇科!$N$6 -> D06.- | E79: =[1]妇科!$H$6 -> O00.1 | F79: =[1]妇科!$B$6 -> O00.1
A80: 第三顺位疾病占比 | B80: % | C80: 信息科 | D80: =[1]妇科!$Q$6 -> 8.9523192 | E80: =[1]妇科!$K$6 -> 6.7298578 | F80: =[1]妇科!$E$6 -> 7.9393939
A81: 第四顺位疾病名称 | C81: 信息科 | D81: =[1]妇科!$O$7 -> 卵巢良性肿瘤 | E81: =[1]妇科!$I$7 -> 宫颈外膜原位癌 | F81: =[1]妇科!$C$7 -> 宫颈外膜原位癌
A82: 第四顺位疾病编码 | C82: 信息科 | D82: =[1]妇科!$N$7 -> D27.x | E82: =[1]妇科!$H$7 -> D06.- | F82: =[1]妇科!$B$7 -> D06.-
A83: 第四顺位疾病占比 | B83: % | C83: 信息科 | D83: =[1]妇科!$Q$7 -> 6.9737269 | E83: =[1]妇科!$K$7 -> 7.2037915 | F83: =[1]妇科!$E$7 -> 8.7272727
A84: 第五顺位疾病名称 | C84: 信息科 | D84: =[1]妇科!$O$8 -> 输卵管妊娠 | E84: =[1]妇科!$I$8 -> 卵巢良性肿瘤 | F84: =[1]妇科!$C$8 -> 宫颈发育不良
A85: 第五顺位疾病编码 | C85: 信息科 | D85: =[1]妇科!$N$8 -> O00.1 | E85: =[1]妇科!$H$8 -> D27.x | F85: =[1]妇科!$B$8 -> N87.
A86: 第五顺位疾病占比 | B86: % | C86: 信息科 | D86: =[1]妇科!$Q$8 -> 5.5465456 | E86: =[1]妇科!$K$8 -> 5.4660348 | F86: =[1]妇科!$E$8 -> 6.2121212
A87: 第一顺位手术名称 | C87: 信息科 | D87: =[2]妇科!$O$4 -> 腹腔镜经腹全子宫切除术 | E87: =[2]妇科!$I$4 -> 子宫全切除术，经腹腔镜 | F87: =[2]妇科!$C$4 -> 子宫全切除术，经腹腔镜
A88: 第一顺位手术编码 | C88: 信息科 | D88: =[2]妇科!$N$4 -> 68.41 | E88: =[2]妇科!$H$4 -> 68.41 | F88: =[2]妇科!$B$4 -> 68.41
A89: 第一顺位手术占比 | B89: % | C89: 信息科 | D89: =[2]妇科!$Q$4 -> 27.165533 | E89: =[2]妇科!$K$4 -> 26.25538 | F89: =[2]妇科!$E$4 -> 25.023213
A90: 第二顺位手术名称 | C90: 信息科 | D90: =[2]妇科!$O$5 -> 腹腔镜子宫病损切除术 | E90: =[2]妇科!$I$5 -> 子宫病损切除术，经腹腔镜 | F90: =[2]妇科!$C$5 -> 子宫颈锥形电切除(LeepLLETZ)
A91: 第二顺位手术编码 | C91: 信息科 | D91: =[2]妇科!$N$5 -> 68.29 | E91: =[2]妇科!$H$5 -> 68.29 | F91: =[2]妇科!$B$5 -> 67.32
A92: 第二顺位手术占比 | B92: % | C92: 信息科 | D92: =[2]妇科!$Q$5 -> 14.693878 | E92: =[2]妇科!$K$5 -> 14.44285 | F92: =[2]妇科!$E$5 -> 16.480966
A93: 第三顺位手术名称 | C93: 信息科 | D93: =[2]妇科!$O$6 -> 子宫颈锥形电切术 | E93: =[2]妇科!$I$6 -> 子宫颈锥形电切除(LpLLETZ) | F93: =[2]妇科!$C$6 -> 子宫病损切除术，经腹腔镜
A94: 第三顺位手术编码 | C94: 信息科 | D94: =[2]妇科!$N$6 -> 67.32 | E94: =[2]妇科!$H$6 -> 67.32 | F94: =[2]妇科!$B$6 -> 68.29
A95: 第三顺位手术占比 | B95: % | C95: 信息科 | D95: =[2]妇科!$Q$6 -> 12.018141 | E95: =[2]妇科!$K$6 -> 12.864658 | F95: =[2]妇科!$E$6 -> 12.395543
A96: 第四顺位手术名称 | C96: 信息科 | D96: =[2]妇科!$O$7 -> 腹腔镜卵巢病损切除术 | E96: =[2]妇科!$I$7 -> 输卵管妊娠清除伴输卵管切除术，经腹腔镜 | F96: =[2]妇科!$C$7 -> 输卵管妊娠清除伴输卵管切除术，经腹腔镜
A97: 第四顺位手术编码 | C97: 信息科 | D97: =[2]妇科!$N$7 -> 65.25 | E97: =[2]妇科!$H$7 -> 66.62 | F97: =[2]妇科!$B$7 -> 66.62
A98: 第四顺位手术占比 | B98: % | C98: 信息科 | D98: =[2]妇科!$Q$7 -> 8.6621315 | E98: =[2]妇科!$K$7 -> 7.3648972 | F98: =[2]妇科!$E$7 -> 9.09935
A99: 第五顺位手术名称 | C99: 信息科 | D99: =[2]妇科!$O$8 -> 腹腔镜输卵管切除伴输卵管妊娠去除术 | E99: =[2]妇科!$I$8 -> 卵巢病损切除术，经腹腔镜 | F99: =[2]妇科!$C$8 -> 卵巢病损切除术，经腹腔镜
A100: 第五顺位手术编码 | C100: 信息科 | D100: =[2]妇科!$N$8 -> 66.62 | E100: =[2]妇科!$H$8 -> 65.25 | F100: =[2]妇科!$B$8 -> 65.25
...

Sheet 头颈乳腺外科
A1: 数据名 | B1: 计量单位 | C1: 填报部门 | D1: Y2021 | E1: Y2020 | F1: Y2019 | G1: 指标说明 | H1: 计算公式
A2: 出院患者手术占比 | B2: % | C2: 统计室 | D2: 44.786815 | E2: 35.476443 | F2: 29.81376 | G2: 详见三级公立、二级公立国考手册。举例：30%请填写30（不带百分号），而非写成30%，或0.3。下同 | H2: 出院患者手术台次数/同期出院患者总人次数*100
A3: 出院患者微创手术占比 | B3: % | C3: 统计室 | D3: 7.8 | E3: 0.84872691 | F3: 1.9617966 | G3: 详见三级公立、二级公立国考手册 | H3: 出院患者微创手术台次数/同期出院患者手术台次数*100
A4: 出院患者四级手术比例 | B4: % | C4: 统计室 | D4: 28.4 | E4: 14.827758 | F4: 14.868353 | G4: 详见三级公立国考手册 | H4: 出院患者四级手术台次数/同期出院患者手术台次数*100
A5: 出院患者疑难危重病例比例 | B5: % | C5: 统计室 | D5: 81.6 | E5: 85.05 | F5: 87.56 | G5: 即CD型病例占比 | H5: (疑难病例数+危重病例数)/出院人数*100
A6: 手术患者并发症发生率 | B6: % | C6: 质控科 | D6: 0 | E6: 0 | F6: 0 | G6: 详见国考手册 | H6: 手术患者并发症发生例数/同期出院的手术患者人数*100
A7: I类切口手术部位感染率 | B7: % | C7: 质控科 | D7: 0 | E7: 0.15 | F7: 0.24 | G7: 详见三级中医、三级公立国考手册 | H7: I类切口手术部位感染人次数/同期I类切口手术台次数*100
A8: 大型医用设备检查阳性率 | B8: % | C8: 医务科 | G8: 详见三级中医、三级公立国考手册 | H8: 大型医用设备检查阳性数/同期大型医用设备检查人次数*100
A9: 低风险组病例死亡率 | B9: % | C9: 质控科 | D9: 0 | E9: 0 | F9: 0 | G9: 详见三级公立、二级公立国考手册 | H9: 低风险组死亡例数/低风险组病例数*100
A10: 医院感染发生率 | B10: % | C10: 院感科 | D10: 0.02 | E10: 0.14 | F10: 0.12 | G10: 等级评审标准细则
A11: 抗菌药物使用强度DDDs | B11: DDD | C11: 药学部 | D11: 1.6007262 | E11: 2.8148538 | F11: 3.1358822 | G11: 详见国考手册 | H11: 住院患者抗菌药物消耗量（累计DDD数）/同期收治患者人天数*100
A12: 门诊患者基本药物处方占比 | B12: % | C12: 药学部 | D12: 65.66 | E12: 57.12 | F12: 54.68 | G12: 详见三级中医、三级公立国考手册 | H12: 门诊使用基本药物人次数/同期门诊诊疗总人次数*100
A13: 住院患者基本药物使用率 | B13: % | C13: 药学部 | D13: 98.83 | E13: 94.85 | F13: 83.4 | G13: 详见三级中医、三级公立国考手册 | H13: 出院患者使用基本药物总人次数/同期出院总人次数*100
A14: 重点监控高值医用耗材收入占比 | B14: % | C14: 设备科 | D14: =(302540+48840)/56061415*100 -> 0.6267769 | E14: =236467/49617724*100 -> 0.47657768 | F14: =23400/52577102*100 -> 0.044506067 | G14: 详见国考手册 | H14: 重点监控高值医用耗材收入/同期卫生材料收入*100
A15: 平均住院日 | B15: 天 | C15: 统计室 | D15: 4.67 | E15: 5.46 | F15: 4.96 | G15: 详见二级公立国考手册 | H15: 出院患者占用总床日数/同期出院患者人数
A16: CMI值 | C16: 质控科 | D16: 0.99 | E16: 0.92 | F16: 0.92 | G16: 病例组合指数
A17: DRGs组数 | B17: 组 | C17: 质控科 | D17: 78 | E17: 71 | F17: 91 | G17: 诊断相关分组组数
A18: 核定床位数 | B18: 张 | C18: 统计室 | D18: 85 | E18: 85 | F18: 85 | G18: 等级评审标准细则
A19: 实际开放床位数 | B19: 张 | C19: 统计室 | D19: 82 | E19: 85 | F19: 80 | G19: 等级评审标准细则
A20: 开放床位使用率 | B20: % | C20: 统计室 | D20: 86.33 | E20: 102.94 | F20: 112.15 | G20: 等级评审标准细则 | H20: 实际占用的总床日数/同期实际开放的总床日数*100
A21: 医师人数与开放床位数比 | C21: 人事科 | D21: =D43/D19 -> 0.15853659 | E21: =E43/E19 -> 0.14117647 | F21: =F43/F19 -> 0.15 | G21: 等级评审标准细则，原计量单位为比值（1:X），现改为小数 | H21: 医院执业（助理）医师总数/同期全院实际开放床位数
A22: 护士人数与开放床位数比 | C22: 人事科 | D22: =D44/D19 -> 0.31707317 | E22: =E44/E19 -> 0.47058824 | F22: =F44/F19 -> 0.4875 | G22: 等级评审标准细则，原计量单位为比值（1:X），现改为小数 | H22: 医院注册护士总数/同期全院实际开放床位数
A23: 人均医疗服务收入 | B23: 万元 | C23: 财务科 | D23: 31.202979 | E23: 22.232908 | F23: 22.354122 | G23: 按科室人员数人均医疗服务收入
A24: 人均有效收入 | B24: 万元 | C24: 财务科 | D24: 81.856735 | E24: 58.974829 | F24: 55.852576 | G24: 按科室人员数人均有效收入
A25: 床均医疗服务收入 | B25: 万元 | C25: 财务科 | D25: 17.295301 | E25: 14.895967 | F25: 15.647885 | G25: 按开放床位数床均医疗服务收入
A26: 床均有效收入 | B26: 万元 | C26: 财务科 | D26: 45.37185 | E26: 39.51292 | F26: 39.096803 | G26: 按开放床位数床均有效收入
A27: 每名执业医师日均住院工作负担 | B27: 床日 | C27: 财务科 | D27: 5.5106428 | E27: 7.0611872 | F27: 7.4767123 | G27: 详见三级中医、三级公立国考手册 | H27: 全年实际占用总床日数/医院平均执业(助理)医师人数/365
A28: 医疗服务收入占医疗收入比例 | B28: % | C28: 财务科 | D28: 23.679199 | E28: 23.177579 | F28: 22.855243 | G28: 参考国考手册，原指标名为：医疗服务收入（不含药品、耗材、检查检验收入）占医疗收入比例 | H28: 医疗服务收入/医疗收入*100
A29: 医疗收入 | B29: 万元 | C29: 财务科 | D29: 6061.5946 | E29: 5275.8311 | F29: 5477.2151 | H29: 门诊收入+住院收入
A30: 医疗服务收入 | B30: 万元 | C30: 财务科 | D30: 1435.337 | E30: 1222.8099 | F30: 1251.8308
A31: 有效收入 | B31: 万元 | C31: 财务科 | D31: 3765.4098 | E31: 3243.6156 | F31: 3127.7443 | H31: 医疗服务收入+检查检验收入
A32: 医疗直接成本 | B32: 万元 | D32: 3553.46 | E32: 3258.84 | F32: 3606.82
A33: 收支结余率 | B33: % | D33: 6.14 | E33: 9.3 | F33: 19.77
A34: 万元收入能耗占比 | B34: 吨标煤/万元 | C34: 后勤管理科 | G34: 详见国考手册 | H34: 年总能耗/年总收入*10000
A35: 门诊收入占医疗收入比例 | B35: % | C35: 财务科 | D35: 18.457595 | E35: 16.486996 | F35: 14.246373 | G35: 详见三级公立国考手册 | H35: 门诊收入/医疗收入*100
A36: 住院收入占医疗收入比例 | B36: % | C36: 财务科 | D36: 81.542405 | E36: 83.513004 | F36: 85.753627 | G36: 详见三级公立国考手册 | H36: 住院收入/医疗收入*100
A37: 医疗收入增幅 | B37: % | C37: 财务科 | D37: 14.893644 | E37: -3.6767598 | F37: 24.008013 | G37: 详见国考手册 | H37: （本年度医疗收入－上一年度医疗收入）/上一年度医疗收入*100
A38: 门诊次均费用增幅 | B38: % | C38: 财务科 | D38: 6.5654787 | E38: 18.436958 | F38: 13.419844 | G38: 详见国考手册 | H38: （本年度门诊患者次均医药费用－上一年度门诊患者次均医药费用）/上一年度门诊患者次均医药费用*100
A39: 住院次均费用增幅 | B39: % | C39: 财务科 | D39: 13.495085 | E39: 9.3358433 | F39: 2.359181 | G39: 详见国考手册 | H39: （本年度出院患者次均医药费用－上一年度出院患者次均医药费用）/上一年度出院患者次均医药费用*100
A40: 门诊次均药品费用增幅 | B40: % | C40: 财务科 | D40: 6.369115 | E40: 90.876535 | F40: 14.024844 | G40: 详见国考手册 | H40: （本年度门诊患者次均药品费用－上一年度门诊患者次均药品费用）/上一年度门诊患者次均药品费用*100
A41: 住院次均药品费用增幅 | B41: % | C41: 财务科 | D41: 10.391232 | E41: -7.3570171 | F41: 25.438282 | G41: 详见国考手册 | H41: （本年度出院患者次均药品费用－上一年度出院患者次均药品费用）/上一年度出院患者次均药品费用*100
A42: 医护比 | C42: 人事科 | D42: 0.5 | E42: 0.3 | F42: 0.31 | G42: 参考国考手册，原计量单位为比值（1:X），现改为小数 | H42: 医院注册医师总数/全院同期注册护士总数
A43: 医师人数 | B43: 人 | C43: 人事科 | D43: 13 | E43: 12 | F43: 12 | G43: 详见国考手册中，医护比定义
A44: 护士人数 | B44: 人 | C44: 人事科 | D44: 26 | E44: 40 | F44: 39 | G44: 详见国考手册中，医护比定义
A45: 医师高级职称占比 | B45: % | C45: 人事科 | D45: 53.85 | E45: 58.33 | F45: 50 | H45: (正高职称医师人数+副高职称医师人数)/医师人数*100
A46: 医师博士占比 | B46: % | C46: 人事科 | D46: 7.69 | E46: 8.33 | F46: 0 | H46: 博士医师人数/医师人数*100
A47: 医师硕士占比 | B47: % | C47: 人事科 | D47: 76.92 | E47: 75 | F47: 75 | H47: 硕士医师人数/医师人数*100
A48: 发表教学文章数与卫生技术人员数之比 | C48: 科教科 | D48: 0 | E48: 0 | F48: 0 | G48: 参考三级中医、三级公立国考手册，医院承担培养医学人才的工作成效的构成元素。原计量单位为比值（1:X），现改为小数 | H48: 本年度发表的教学文章数/同期卫生技术人员总数
A49: 省部级及以上教育教学课题数与卫生技术人员数之比 | C49: 科教科 | D49: 0 | E49: 0 | F49: 0 | G49: 参考三级中医、三级公立国考手册，医院承担培养医学人才的工作成效的构成元素。本指标为延伸指标。原计量单位为比值（1:X），现改为小数 | H49: 本年度获得的省部级及以上教育教学课题数/同期卫生技术人员总数
A50: 国家级继续医学教育项目数与卫生技术人员数之比 | C50: 科教科 | D50: 0 | E50: 0 | F50: 0 | G50: 参考三级中医、三级公立国考手册，医院承担培养医学人才的工作成效的构成元素。本指标为延伸指标。原计量单位为比值（1:X），现改为小数 | H50: 本年度举办的国家级继续医学教育项目数/同期卫生技术人员总数
A51: 每百名卫生技术人员科研项目经费 | B51: 元 | C51: 科教科 | D51: 17888273 | E51: 6274706.4 | F51: 1699036.1 | G51: 详见三级中医、三级公立国考手册 | H51: 本年度科研项目立项经费总金额/同期卫生技术人员总数*100
A52: 每百名卫生技术人员科研成果转化金额 | B52: 元 | C52: 科教科 | D52: 0 | E52: 0 | F52: 0 | G52: 详见三级公立国考手册 | H52: 本年度科技成果转化总金额/同期医院卫生技术人员总数*100
A53: 医师人均国家自然科学基金项目数量 | B53: 项 | C53: 科教科 | D53: 0 | E53: 0 | F53: 0 | G53: 说明：本年度成功立项的项目数量。要求本科室为主研单位
A54: 医师人均SCI文章数量 | B54: 篇 | C54: 科教科 | D54: 0 | E54: 0 | F54: 0.083 | G54: 说明：本年度成功发表的论文，要求第一作者或通讯作者为本院员工
A55: SCI平均影响因子 | B55: 分 | C55: 科教科 | D55: 0 | E55: 0 | F55: 0.227 | G55: 说明：本年度成功发表的论文，要求第一作者或通讯作者为本院员工
A56: 博士研究生导师占比 | B56: % | C56: 科教科 | D56: 0 | E56: 0 | F56: 0 | H56: 博士研究生导师人数/同期医师总数*100
A57: 硕士研究生导师占比 | B57: % | C57: 科教科 | D57: 15.38 | E57: 16.67 | F57: 0 | H57: 硕士研究生导师人数/同期医师总数*100
A58: 外省住院患者占比 | B58: % | C58: 统计室 | D58: 2.5797205 | E58: 3.9142756 | F58: 4.3096814 | H58: 外省住院患者人数/同期出院患者人次数*100
A59: 非医嘱离院率 | B59: % | C59: 统计室 | D59: 0.12540308 | E59: 0.088558271 | F59: 0.23087579 | H59: 非医嘱离院人次/同期出院患者总人次*100
A60: 是否为教育部或科技部重点学科或重点实验室 | B60: 分 | C60: 科教科 | D60: 0 | E60: 0 | F60: 0 | G60: 是填1,否填0
A61: 是否为国家卫健委临床重点专科 | B61: 分 | C61: 科教科 | D61: 0 | E61: 0 | F61: 0 | G61: 是填1,否填0
A62: 是否为国家中医药局重点专科 | B62: 分 | C62: 科教科 | D62: 0 | E62: 0 | F62: 0 | G62: 是填1,否填0
A63: 是否为省教育厅或科技厅重点学科或重点实验室 | B63: 分 | C63: 科教科 | D63: 0 | E63: 0 | F63: 0 | G63: 是填1,否填0
A64: 是否为省卫健委重点专科 | B64: 分 | C64: 科教科 | D64: 1 | E64: 1 | F64: 1 | G64: 是填1,否填0
A65: 是否为省中医药局重点专科 | B65: 分 | C65: 科教科 | D65: 0 | E65: 0 | F65: 0 | G65: 是填1,否填0
A66: 是否为地市级教育局或科技局重点学科或重点实验室 | B66: 分 | C66: 科教科 | D66: 0 | E66: 0 | F66: 0 | G66: 是填1,否填0
A67: 是否为地市级卫健委重点专科 | B67: 分 | C67: 科教科 | D67: 1 | E67: 1 | F67: 1 | G67: 是填1,否填0
A68: 是否为地市级中医药局重点专科 | B68: 分 | C68: 科教科 | D68: 0 | E68: 0 | F68: 0 | G68: 是填1,否填0
A69: 是否为县级教育局或科技局重点学科或重点实验室 | B69: 分 | C69: 科教科 | D69: 0 | E69: 0 | F69: 0 | G69: 是填1,否填0
A70: 是否为县级卫健委重点专科 | B70: 分 | C70: 科教科 | D70: 0 | E70: 0 | F70: 0 | G70: 是填1,否填0
A71: 是否为县级中医药局重点专科 | B71: 分 | C71: 科教科 | D71: 0 | E71: 0 | F71: 0 | G71: 是填1,否填0
A72: 第一顺位疾病名称 | C72: 信息科 | D72: =[1]头颈乳腺外科!$O$4 -> 为肿瘤化学治疗疗程 | E72: =[1]头颈乳腺外科!$I$4 -> 为肿瘤化学治疗疗程 | F72: =[1]头颈乳腺外科!$C$4 -> 为肿瘤化学治疗疗程
A73: 第一顺位疾病编码 | C73: 信息科 | D73: =[1]头颈乳腺外科!$N$4 -> Z51.1 | E73: =[1]头颈乳腺外科!$H$4 -> Z51.1 | F73: =[1]头颈乳腺外科!$B$4 -> Z51.1
A74: 第一顺位疾病占比 | B74: % | C74: 信息科 | D74: =[1]头颈乳腺外科!$Q$4 -> 50.931566 | E74: =[1]头颈乳腺外科!$K$4 -> 61.300035 | F74: =[1]头颈乳腺外科!$E$4 -> 34.369709
A75: 第二顺位疾病名称 | C75: 信息科 | D75: =[1]头颈乳腺外科!$O$5 -> 乳房恶性肿瘤 | E75: =[1]头颈乳腺外科!$I$5 -> 抗肿瘤治疗 | F75: =[1]头颈乳腺外科!$C$5 -> 抗肿瘤治疗
A76: 第二顺位疾病编码 | C76: 信息科 | D76: =[1]头颈乳腺外科!$N$5 -> C50 | E76: =[1]头颈乳腺外科!$H$5 -> Z51.8 | F76: =[1]头颈乳腺外科!$B$5 -> Z51.8
A77: 第二顺位疾病占比 | B77: % | C77: 信息科 | D77: =[1]头颈乳腺外科!$Q$5 -> 10.80258 | E77: =[1]头颈乳腺外科!$K$5 -> 18.862912 | F77: =[1]头颈乳腺外科!$E$5 -> 32.23026
A78: 第三顺位疾病名称 | C78: 信息科 | D78: =[1]头颈乳腺外科!$O$6 -> 乳房纤维囊性乳腺病 | E78: =[1]头颈乳腺外科!$I$6 -> 乳房恶性肿瘤 | F78: =[1]头颈乳腺外科!$C$6 -> 乳房恶性肿瘤
A79: 第三顺位疾病编码 | C79: 信息科 | D79: =[1]头颈乳腺外科!$N$6 -> N60.2 | E79: =[1]头颈乳腺外科!$H$6 -> C50 | F79: =[1]头颈乳腺外科!$B$6 -> C50
A80: 第三顺位疾病占比 | B80: % | C80: 信息科 | D80: =[1]头颈乳腺外科!$Q$6 -> 10.4622 | E80: =[1]头颈乳腺外科!$K$6 -> 8.7318456 | F80: =[1]头颈乳腺外科!$E$6 -> 7.2648915
A81: 第四顺位疾病名称 | C81: 信息科 | D81: =[1]头颈乳腺外科!$O$7 -> 抗肿瘤治疗 | E81: =[1]头颈乳腺外科!$I$7 -> 乳房纤维囊性乳腺病 | F81: =[1]头颈乳腺外科!$C$7 -> 乳房纤维囊性乳腺病
A82: 第四顺位疾病编码 | C82: 信息科 | D82: =[1]头颈乳腺外科!$N$7 -> Z51.8 | E82: =[1]头颈乳腺外科!$H$7 -> N60.2 | F82: =[1]头颈乳腺外科!$B$7 -> N60.2
A83: 第四顺位疾病占比 | B83: % | C83: 信息科 | D83: =[1]头颈乳腺外科!$Q$7 -> 7.7570763 | E83: =[1]头颈乳腺外科!$K$7 -> 8.4661707 | F83: =[1]头颈乳腺外科!$E$7 -> 6.0489457
A84: 第五顺位疾病名称 | C84: 信息科 | D84: =[1]头颈乳腺外科!$O$8 -> 乳房良性肿瘤 | E84: =[1]头颈乳腺外科!$I$8 -> 乳房良性肿瘤 | F84: =[1]头颈乳腺外科!$C$8 -> 乳房良性肿瘤
A85: 第五顺位疾病编码 | C85: 信息科 | D85: =[1]头颈乳腺外科!$N$8 -> D24 | E85: =[1]头颈乳腺外科!$H$8 -> D24 | F85: =[1]头颈乳腺外科!$B$8 -> D24
A86: 第五顺位疾病占比 | B86: % | C86: 信息科 | D86: =[1]头颈乳腺外科!$Q$8 -> 6.6821928 | E86: =[1]头颈乳腺外科!$K$8 -> 5.9156925 | F86: =[1]头颈乳腺外科!$E$8 -> 5.3255349
A87: 第一顺位手术名称 | C87: 信息科 | D87: =[2]头颈乳腺外科!$O$4 -> 乳房腺体区段切除术 | E87: =[2]头颈乳腺外科!$I$4 -> 乳腺区段切除术 | F87: =[2]头颈乳腺外科!$C$4 -> 乳腺区段切除术
A88: 第一顺位手术编码 | C88: 信息科 | D88: =[2]头颈乳腺外科!$N$4 -> 85.21 | E88: =[2]头颈乳腺外科!$H$4 -> 85.22 | F88: =[2]头颈乳腺外科!$B$4 -> 85.22
A89: 第一顺位手术占比 | B89: % | C89: 信息科 | D89: =[2]头颈乳腺外科!$Q$4 -> 41.44 | E89: =[2]头颈乳腺外科!$K$4 -> 34.098852 | F89: =[2]头颈乳腺外科!$E$4 -> 35.363965
A90: 第二顺位手术名称 | C90: 信息科 | D90: =[2]头颈乳腺外科!$O$5 -> 单侧甲状腺切除伴甲状腺峡部切除术 | E90: =[2]头颈乳腺外科!$I$5 -> 单侧甲状腺全切除，伴另侧次全(大部份)切除术 | F90: =[2]头颈乳腺外科!$C$5 -> 乳腺病损微创旋切术(麦默通)
A91: 第二顺位手术编码 | C91: 信息科 | D91: =[2]头颈乳腺外科!$N$5 -> 06.2x | E91: =[2]头颈乳腺外科!$H$5 -> 06.2 | F91: =[2]头颈乳腺外科!$B$5 -> 85.21
A92: 第二顺位手术占比 | B92: % | C92: 信息科 | D92: =[2]头颈乳腺外科!$Q$5 -> 18.4 | E92: =[2]头颈乳腺外科!$K$5 -> 11.682476 | F92: =[2]头颈乳腺外科!$E$5 -> 10.428498
A93: 第三顺位手术名称 | C93: 信息科 | D93: =[2]头颈乳腺外科!$O$6 -> 单侧乳腺改良根治术 | E93: =[2]头颈乳腺外科!$I$6 -> 乳腺病损微创旋切术(麦默通) | F93: =[2]头颈乳腺外科!$C$6 -> 乳腺改良根治术，单侧
A94: 第三顺位手术编码 | C94: 信息科 | D94: =[2]头颈乳腺外科!$N$6 -> 85.43 | E94: =[2]头颈乳腺外科!$H$6 -> 85.21 | F94: =[2]头颈乳腺外科!$B$6 -> 85.43
A95: 第三顺位手术占比 | B95: % | C95: 信息科 | D95: =[2]头颈乳腺外科!$Q$6 -> 12.28 | E95: =[2]头颈乳腺外科!$K$6 -> 8.7368947 | F95: =[2]头颈乳腺外科!$E$6 -> 7.3825503
A96: 第四顺位手术名称 | C96: 信息科 | D96: =[2]头颈乳腺外科!$O$7 -> 甲状腺全部切除术 | E96: =[2]头颈乳腺外科!$I$7 -> 乳腺改良根治术，单侧 | F96: =[2]头颈乳腺外科!$C$7 -> 单侧甲状腺全切除，伴另侧次全(大部份)切除术
A97: 第四顺位手术编码 | C97: 信息科 | D97: =[2]头颈乳腺外科!$N$7 -> 06.4x | E97: =[2]头颈乳腺外科!$H$7 -> 85.43 | F97: =[2]头颈乳腺外科!$B$7 -> 06.2
A98: 第四顺位手术占比 | B98: % | C98: 信息科 | D98: =[2]头颈乳腺外科!$Q$7 -> 7.56 | E98: =[2]头颈乳腺外科!$K$7 -> 8.1377933 | F98: =[2]头颈乳腺外科!$E$7 -> 12.700052
A99: 第五顺位手术名称 | C99: 信息科 | D99: =[2]头颈乳腺外科!$O$8 -> 静脉输液港植入术 | E99: =[2]头颈乳腺外科!$I$8 -> 双侧甲状腺全部切除术 | F99: =[2]头颈乳腺外科!$C$8 -> 乳房单纯切除术，单侧
A100: 第五顺位手术编码 | C100: 信息科 | D100: =[2]头颈乳腺外科!$N$8 -> 86.07 | E100: =[2]头颈乳腺外科!$H$8 -> 06.4 | F100: =[2]头颈乳腺外科!$B$8 -> 85.41
...

Sheet 胃肠外科
A1: 数据名 | B1: 计量单位 | C1: 填报部门 | D1: Y2021 | E1: Y2020 | F1: Y2019 | G1: 指标说明 | H1: 计算公式
A2: 出院患者手术占比 | B2: % | C2: 统计室 | D2: 37.416728 | E2: 32.102672 | F2: 32.84949 | G2: 详见三级公立、二级公立国考手册。举例：30%请填写30（不带百分号），而非写成30%，或0.3。下同 | H2: 出院患者手术台次数/同期出院患者总人次数*100
A3: 出院患者微创手术占比 | B3: % | C3: 统计室 | D3: 53.363007 | E3: 54.874042 | F3: 43.92425 | G3: 详见三级公立、二级公立国考手册 | H3: 出院患者微创手术台次数/同期出院患者手术台次数*100
A4: 出院患者四级手术比例 | B4: % | C4: 统计室 | D4: 32.492582 | E4: 34.720701 | F4: 32.456602 | G4: 详见三级公立国考手册 | H4: 出院患者四级手术台次数/同期出院患者手术台次数*100
A5: 出院患者疑难危重病例比例 | B5: % | C5: 统计室 | D5: 95.97 | E5: 95.43 | F5: 92.41 | G5: 即CD型病例占比 | H5: (疑难病例数+危重病例数)/出院人数*100
A6: 手术患者并发症发生率 | B6: % | C6: 质控科 | D6: 0 | E6: 0 | F6: 0 | G6: 详见国考手册 | H6: 手术患者并发症发生例数/同期出院的手术患者人数*100
A7: I类切口手术部位感染率 | B7: % | C7: 质控科 | D7: 0 | E7: 0.2 | F7: 0.52 | G7: 详见三级中医、三级公立国考手册 | H7: I类切口手术部位感染人次数/同期I类切口手术台次数*100
A8: 大型医用设备检查阳性率 | B8: % | C8: 医务科 | G8: 详见三级中医、三级公立国考手册 | H8: 大型医用设备检查阳性数/同期大型医用设备检查人次数*100
A9: 低风险组病例死亡率 | B9: % | C9: 质控科 | D9: 0 | E9: 0 | F9: 0 | G9: 详见三级公立、二级公立国考手册 | H9: 低风险组死亡例数/低风险组病例数*100
A10: 医院感染发生率 | B10: % | C10: 院感科 | D10: 1.09 | E10: 1.16 | F10: 1.66 | G10: 等级评审标准细则
A11: 抗菌药物使用强度DDDs | B11: DDD | C11: 药学部 | D11: 46.052634 | E11: 46.386234 | F11: 40.892234 | G11: 详见国考手册 | H11: 住院患者抗菌药物消耗量（累计DDD数）/同期收治患者人天数*100
A12: 门诊患者基本药物处方占比 | B12: % | C12: 药学部 | D12: 71.5 | E12: 51.61 | F12: 44.6 | G12: 详见三级中医、三级公立国考手册 | H12: 门诊使用基本药物人次数/同期门诊诊疗总人次数*100
A13: 住院患者基本药物使用率 | B13: % | C13: 药学部 | D13: 97.5 | E13: 97.88 | F13: 95.3 | G13: 详见三级中医、三级公立国考手册 | H13: 出院患者使用基本药物总人次数/同期出院总人次数*100
A14: 重点监控高值医用耗材收入占比 | B14: % | C14: 设备科 | D14: =(55900+48840)/60839917*100 -> 0.17215671 | E14: =57900/60915806*100 -> 0.095049223 | F14: 0 | G14: 详见国考手册 | H14: 重点监控高值医用耗材收入/同期卫生材料收入*100
A15: 平均住院日 | B15: 天 | C15: 统计室 | D15: 7.09 | E15: 6.93 | F15: 7.1 | G15: 详见二级公立国考手册 | H15: 出院患者占用总床日数/同期出院患者人数
A16: CMI值 | C16: 质控科 | D16: 1.52 | E16: 1.43 | F16: 1.41 | G16: 病例组合指数
A17: DRGs组数 | B17: 组 | C17: 质控科 | D17: 160 | E17: 153 | F17: 171 | G17: 诊断相关分组组数
A18: 核定床位数 | B18: 张 | C18: 统计室 | D18: 90 | E18: 90 | F18: 90 | G18: 等级评审标准细则
A19: 实际开放床位数 | B19: 张 | C19: 统计室 | D19: 100 | E19: 100 | F19: 100 | G19: 等级评审标准细则
A20: 开放床位使用率 | B20: % | C20: 统计室 | D20: 101.77 | E20: 104.54 | F20: 109.28 | G20: 等级评审标准细则 | H20: 实际占用的总床日数/同期实际开放的总床日数*100
A21: 医师人数与开放床位数比 | C21: 人事科 | D21: =D43/D19 -> 0.18 | E21: =E43/E19 -> 0.18 | F21: =F43/F19 -> 0.18 | G21: 等级评审标准细则，原计量单位为比值（1:X），现改为小数 | H21: 医院执业（助理）医师总数/同期全院实际开放床位数
A22: 护士人数与开放床位数比 | C22: 人事科 | D22: =D44/D19 -> 0.46 | E22: =E44/E19 -> 0.45 | F22: =F44/F19 -> 0.46 | G22: 等级评审标准细则，原计量单位为比值（1:X），现改为小数 | H22: 医院注册护士总数/同期全院实际开放床位数
A23: 人均医疗服务收入 | B23: 万元 | C23: 财务科 | D23: 29.612724 | E23: 27.934196 | F23: 28.56485 | G23: 按科室人员数人均医疗服务收入
A24: 人均有效收入 | B24: 万元 | C24: 财务科 | D24: 59.67313 | E24: 56.512557 | F24: 58.007161 | G24: 按科室人员数人均有效收入
A25: 床均医疗服务收入 | B25: 万元 | C25: 财务科 | D25: 19.544398 | E25: 18.995253 | F25: 18.567153 | G25: 按开放床位数床均医疗服务收入
A26: 床均有效收入 | B26: 万元 | C26: 财务科 | D26: 39.384266 | E26: 38.428539 | F26: 37.704655 | G26: 按开放床位数床均有效收入
A27: 每名执业医师日均住院工作负担 | B27: 床日 | C27: 财务科 | D27: 5.6537291 | E27: 5.8237443 | F27: 6.0712329 | G27: 详见三级中医、三级公立国考手册 | H27: 全年实际占用总床日数/医院平均执业(助理)医师人数/365
A28: 医疗服务收入占医疗收入比例 | B28: % | C28: 财务科 | D28: 28.968177 | E28: 28.645276 | F28: 27.331443 | G28: 参考国考手册，原指标名为：医疗服务收入（不含药品、耗材、检查检验收入）占医疗收入比例 | H28: 医疗服务收入/医疗收入*100
A29: 医疗收入 | B29: 万元 | C29: 财务科 | D29: 6746.8512 | E29: 6631.1991 | F29: 6793.3304 | H29: 门诊收入+住院收入
A30: 医疗服务收入 | B30: 万元 | C30: 财务科 | D30: 1954.4398 | E30: 1899.5253 | F30: 1856.7153
A31: 有效收入 | B31: 万元 | C31: 财务科 | D31: 3938.4266 | E31: 3842.8539 | F31: 3770.4655 | H31: 医疗服务收入+检查检验收入
A32: 医疗直接成本 | B32: 万元 | D32: 4112.92 | E32: 3699.12 | F32: 3814.5
A33: 收支结余率 | B33: % | D33: 16.78 | E33: 15.75 | F33: 11.37
A34: 万元收入能耗占比 | B34: 吨标煤/万元 | C34: 后勤管理科 | G34: 详见国考手册 | H34: 年总能耗/年总收入*10000
A35: 门诊收入占医疗收入比例 | B35: % | C35: 财务科 | D35: 6.738559 | E35: 5.9830235 | F35: 5.6201895 | G35: 详见三级公立国考手册 | H35: 门诊收入/医疗收入*100
A36: 住院收入占医疗收入比例 | B36: % | C36: 财务科 | D36: 93.261441 | E36: 94.016977 | F36: 94.37981 | G36: 详见三级公立国考手册 | H36: 住院收入/医疗收入*100
A37: 医疗收入增幅 | B37: % | C37: 财务科 | D37: 1.7440608 | E37: -2.3866251 | F37: 16.957931 | G37: 详见国考手册 | H37: （本年度医疗收入－上一年度医疗收入）/上一年度医疗收入*100
A38: 门诊次均费用增幅 | B38: % | C38: 财务科 | D38: 10.661835 | E38: 14.5602 | F38: 14.593392 | G38: 详见国考手册 | H38: （本年度门诊患者次均医药费用－上一年度门诊患者次均医药费用）/上一年度门诊患者次均医药费用*100
A39: 住院次均费用增幅 | B39: % | C39: 财务科 | D39: 6.3616861 | E39: -1.0543114 | F39: 8.732032 | G39: 详见国考手册 | H39: （本年度出院患者次均医药费用－上一年度出院患者次均医药费用）/上一年度出院患者次均医药费用*100
A40: 门诊次均药品费用增幅 | B40: % | C40: 财务科 | D40: 36.022247 | E40: 50.335019 | F40: 29.044004 | G40: 详见国考手册 | H40: （本年度门诊患者次均药品费用－上一年度门诊患者次均药品费用）/上一年度门诊患者次均药品费用*100
A41: 住院次均药品费用增幅 | B41: % | C41: 财务科 | D41: 3.1833469 | E41: -7.8214083 | F41: 5.4639114 | G41: 详见国考手册 | H41: （本年度出院患者次均药品费用－上一年度出院患者次均药品费用）/上一年度出院患者次均药品费用*100
A42: 医护比 | C42: 人事科 | D42: 0.39 | E42: 0.4 | F42: 0.39 | G42: 参考国考手册，原计量单位为比值（1:X），现改为小数 | H42: 医院注册医师总数/全院同期注册护士总数
A43: 医师人数 | B43: 人 | C43: 人事科 | D43: 18 | E43: 18 | F43: 18 | G43: 详见国考手册中，医护比定义
A44: 护士人数 | B44: 人 | C44: 人事科 | D44: 46 | E44: 45 | F44: 46 | G44: 详见国考手册中，医护比定义
A45: 医师高级职称占比 | B45: % | C45: 人事科 | D45: 55.56 | E45: 55.56 | F45: 55.56 | H45: (正高职称医师人数+副高职称医师人数)/医师人数*100
A46: 医师博士占比 | B46: % | C46: 人事科 | D46: 11.11 | E46: 11.11 | F46: 11.11 | H46: 博士医师人数/医师人数*100
A47: 医师硕士占比 | B47: % | C47: 人事科 | D47: 72.22 | E47: 72.22 | F47: 72.22 | H47: 硕士医师人数/医师人数*100
A48: 发表教学文章数与卫生技术人员数之比 | C48: 科教科 | D48: 0 | E48: 0 | F48: 0 | G48: 参考三级中医、三级公立国考手册，医院承担培养医学人才的工作成效的构成元素。原计量单位为比值（1:X），现改为小数 | H48: 本年度发表的教学文章数/同期卫生技术人员总数
A49: 省部级及以上教育教学课题数与卫生技术人员数之比 | C49: 科教科 | D49: 0 | E49: 0 | F49: 0 | G49: 参考三级中医、三级公立国考手册，医院承担培养医学人才的工作成效的构成元素。本指标为延伸指标。原计量单位为比值（1:X），现改为小数 | H49: 本年度获得的省部级及以上教育教学课题数/同期卫生技术人员总数
A50: 国家级继续医学教育项目数与卫生技术人员数之比 | C50: 科教科 | D50: 0 | E50: 0 | F50: 0 | G50: 参考三级中医、三级公立国考手册，医院承担培养医学人才的工作成效的构成元素。本指标为延伸指标。原计量单位为比值（1:X），现改为小数 | H50: 本年度举办的国家级继续医学教育项目数/同期卫生技术人员总数
A51: 每百名卫生技术人员科研项目经费 | B51: 元 | C51: 科教科 | D51: 484579.75 | E51: 335409.52 | F51: 345792.14 | G51: 详见三级中医、三级公立国考手册 | H51: 本年度科研项目立项经费总金额/同期卫生技术人员总数*100
A52: 每百名卫生技术人员科研成果转化金额 | B52: 元 | C52: 科教科 | D52: 0 | E52: 0 | F52: 0 | G52: 详见三级公立国考手册 | H52: 本年度科技成果转化总金额/同期医院卫生技术人员总数*100
A53: 医师人均国家自然科学基金项目数量 | B53: 项 | C53: 科教科 | D53: 0 | E53: 0 | F53: 0 | G53: 说明：本年度成功立项的项目数量。要求本科室为主研单位
A54: 医师人均SCI文章数量 | B54: 篇 | C54: 科教科 | D54: 0.056 | E54: 0 | F54: 0.111 | G54: 说明：本年度成功发表的论文，要求第一作者或通讯作者为本院员工
A55: SCI平均影响因子 | B55: 分 | C55: 科教科 | D55: 0.126 | E55: 0 | F55: 0.207 | G55: 说明：本年度成功发表的论文，要求第一作者或通讯作者为本院员工
A56: 博士研究生导师占比 | B56: % | C56: 科教科 | D56: 0 | E56: 0 | F56: 0 | H56: 博士研究生导师人数/同期医师总数*100
A57: 硕士研究生导师占比 | B57: % | C57: 科教科 | D57: 11.11 | E57: 11.11 | F57: 0 | H57: 硕士研究生导师人数/同期医师总数*100
A58: 外省住院患者占比 | B58: % | C58: 统计室 | D58: 4.4781643 | E58: 3.7974684 | F58: 4.0089857 | H58: 外省住院患者人数/同期出院患者人次数*100
A59: 非医嘱离院率 | B59: % | C59: 统计室 | D59: 3.1828275 | E59: 2.7777778 | F59: 2.1254536 | H59: 非医嘱离院人次/同期出院患者总人次*100
A60: 是否为教育部或科技部重点学科或重点实验室 | B60: 分 | C60: 科教科 | D60: 0 | E60: 0 | F60: 0 | G60: 是填1,否填0
A61: 是否为国家卫健委临床重点专科 | B61: 分 | C61: 科教科 | D61: 0 | E61: 0 | F61: 0 | G61: 是填1,否填0
A62: 是否为国家中医药局重点专科 | B62: 分 | C62: 科教科 | D62: 0 | E62: 0 | F62: 0 | G62: 是填1,否填0
A63: 是否为省教育厅或科技厅重点学科或重点实验室 | B63: 分 | C63: 科教科 | D63: 0 | E63: 0 | F63: 0 | G63: 是填1,否填0
A64: 是否为省卫健委重点专科 | B64: 分 | C64: 科教科 | D64: 1 | E64: 1 | F64: 1 | G64: 是填1,否填0
A65: 是否为省中医药局重点专科 | B65: 分 | C65: 科教科 | D65: 0 | E65: 0 | F65: 0 | G65: 是填1,否填0
A66: 是否为地市级教育局或科技局重点学科或重点实验室 | B66: 分 | C66: 科教科 | D66: 0 | E66: 0 | F66: 0 | G66: 是填1,否填0
A67: 是否为地市级卫健委重点专科 | B67: 分 | C67: 科教科 | D67: 1 | E67: 1 | F67: 1 | G67: 是填1,否填0
A68: 是否为地市级中医药局重点专科 | B68: 分 | C68: 科教科 | D68: 0 | E68: 0 | F68: 0 | G68: 是填1,否填0
A69: 是否为县级教育局或科技局重点学科或重点实验室 | B69: 分 | C69: 科教科 | D69: 0 | E69: 0 | F69: 0 | G69: 是填1,否填0
A70: 是否为县级卫健委重点专科 | B70: 分 | C70: 科教科 | D70: 0 | E70: 0 | F70: 0 | G70: 是填1,否填0
A71: 是否为县级中医药局重点专科 | B71: 分 | C71: 科教科 | D71: 0 | E71: 0 | F71: 0 | G71: 是填1,否填0
A72: 第一顺位疾病名称 | C72: 信息科 | D72: =[1]胃肠外科!$O$4 -> 为肿瘤化学治疗疗程 | E72: =[1]胃肠外科!$I$4 -> 为肿瘤化学治疗疗程 | F72: =[1]胃肠外科!$C$4 -> 为肿瘤化学治疗疗程
A73: 第一顺位疾病编码 | C73: 信息科 | D73: =[1]胃肠外科!$N$4 -> Z51.1 | E73: =[1]胃肠外科!$H$4 -> Z51.1 | F73: =[1]胃肠外科!$B$4 -> Z51.1
A74: 第一顺位疾病占比 | B74: % | C74: 信息科 | D74: =[1]胃肠外科!$Q$4 -> 36.621021 | E74: =[1]胃肠外科!$K$4 -> 42.791842 | F74: =[1]胃肠外科!$E$4 -> 43.926041
A75: 第二顺位疾病名称 | C75: 信息科 | D75: =[1]胃肠外科!$O$5 -> 急性阑尾炎 | E75: =[1]胃肠外科!$I$5 -> 急性阑尾炎 | F75: =[1]胃肠外科!$C$5 -> 急性阑尾炎
A76: 第二顺位疾病编码 | C76: 信息科 | D76: =[1]胃肠外科!$N$5 -> K35 | E76: =[1]胃肠外科!$H$5 -> K35 | F76: =[1]胃肠外科!$B$5 -> K35
A77: 第二顺位疾病占比 | B77: % | C77: 信息科 | D77: =[1]胃肠外科!$Q$5 -> 7.1243523 | E77: =[1]胃肠外科!$K$5 -> 7.4542897 | F77: =[1]胃肠外科!$E$5 -> 7.2576464
A78: 第三顺位疾病名称 | C78: 信息科 | D78: =[1]胃肠外科!$O$6 -> 单侧或未特指腹股沟疝，不伴有梗阻或坏疽 | E78: =[1]胃肠外科!$I$6 -> 肠梗阻 | F78: =[1]胃肠外科!$C$6 -> 单侧或未特指腹股沟疝，不伴有梗阻或坏疽
A79: 第三顺位疾病编码 | C79: 信息科 | D79: =[1]胃肠外科!$N$6 -> K40.9 | E79: =[1]胃肠外科!$H$6 -> K56 | F79: =[1]胃肠外科!$B$6 -> K40.9
A80: 第三顺位疾病占比 | B80: % | C80: 信息科 | D80: =[1]胃肠外科!$Q$6 -> 5.3478905 | E80: =[1]胃肠外科!$K$6 -> 5.2390999 | F80: =[1]胃肠外科!$E$6 -> 5.7542768
A81: 第四顺位疾病名称 | C81: 信息科 | D81: =[1]胃肠外科!$O$7 -> 结肠恶性肿瘤 | E81: =[1]胃肠外科!$I$7 -> 单侧或未特指腹股沟疝，不伴有梗阻或坏疽 | F81: =[1]胃肠外科!$C$7 -> 肠梗阻
A82: 第四顺位疾病编码 | C82: 信息科 | D82: =[1]胃肠外科!$N$7 -> C18 | E82: =[1]胃肠外科!$H$7 -> K40.9 | F82: =[1]胃肠外科!$B$7 -> K56
A83: 第四顺位疾病占比 | B83: % | C83: 信息科 | D83: =[1]胃肠外科!$Q$7 -> 5.1628423 | E83: =[1]胃肠外科!$K$7 -> 4.8874824 | F83: =[1]胃肠外科!$E$7 -> 4.371868
A84: 第五顺位疾病名称 | C84: 信息科 | D84: =[1]胃肠外科!$O$8 -> 肠梗阻 | E84: =[1]胃肠外科!$I$8 -> 结肠恶性肿瘤 | F84: =[1]胃肠外科!$C$8 -> 结肠恶性肿瘤
A85: 第五顺位疾病编码 | C85: 信息科 | D85: =[1]胃肠外科!$N$8 -> K56 | E85: =[1]胃肠外科!$H$8 -> C18 | F85: =[1]胃肠外科!$B$8 -> C18
A86: 第五顺位疾病占比 | B86: % | C86: 信息科 | D86: =[1]胃肠外科!$Q$8 -> 4.4966691 | E86: =[1]胃肠外科!$K$8 -> 4.4655415 | F86: =[1]胃肠外科!$E$8 -> 4.3545879
A87: 第一顺位手术名称 | C87: 信息科 | D87: =[2]胃肠外科!$O$4 -> 腹腔镜下阑尾切除术 | E87: =[2]胃肠外科!$I$4 -> 阑尾切除术，经腹腔镜 | F87: =[2]胃肠外科!$C$4 -> 阑尾切除术，经腹腔镜
A88: 第一顺位手术编码 | C88: 信息科 | D88: =[2]胃肠外科!$N$4 -> 47.01 | E88: =[2]胃肠外科!$H$4 -> 47.01 | F88: =[2]胃肠外科!$B$4 -> 47.01
A89: 第一顺位手术占比 | B89: % | C89: 信息科 | D89: =[2]胃肠外科!$Q$4 -> 13.452028 | E89: =[2]胃肠外科!$K$4 -> 13.855422 | F89: =[2]胃肠外科!$E$4 -> 14.045239
A90: 第二顺位手术名称 | C90: 信息科 | D90: =[2]胃肠外科!$O$5 -> 大隐静脉主干激光闭合术 | E90: =[2]胃肠外科!$I$5 -> 腹股沟斜疝补片修补术，单侧 | F90: =[2]胃肠外科!$C$5 -> 腹股沟斜疝补片修补术，单侧
A91: 第二顺位手术编码 | C91: 信息科 | D91: =[2]胃肠外科!$N$5 -> 38.59 | E91: =[2]胃肠外科!$H$5 -> 53.04 | F91: =[2]胃肠外科!$B$5 -> 53.04
A92: 第二顺位手术占比 | B92: % | C92: 信息科 | D92: =[2]胃肠外科!$Q$5 -> 7.6162216 | E92: =[2]胃肠外科!$K$5 -> 7.8313253 | F92: =[2]胃肠外科!$E$5 -> 13.361389
A93: 第三顺位手术名称 | C93: 信息科 | D93: =[2]胃肠外科!$O$6 -> 腹腔镜胃大部切除伴胃空肠吻合术 | E93: =[2]胃肠外科!$I$6 -> 腹股沟斜疝补片修补术，单侧，经腹腔镜 | F93: =[2]胃肠外科!$C$6 -> 乙状结肠直肠切除术伴结肠吻合术，经腹腔镜（腹腔镜下Dixon)
A94: 第三顺位手术编码 | C94: 信息科 | D94: =[2]胃肠外科!$N$6 -> 43.7x | E94: =[2]胃肠外科!$H$6 -> 17.12 | F94: =[2]胃肠外科!$B$6 -> 48.63
A95: 第三顺位手术占比 | B95: % | C95: 信息科 | D95: =[2]胃肠外科!$Q$6 -> 7.0722057 | E95: =[2]胃肠外科!$K$6 -> 6.0240964 | F95: =[2]胃肠外科!$E$6 -> 7.5749605
A96: 第四顺位手术名称 | C96: 信息科 | D96: =[2]胃肠外科!$O$7 -> 单侧腹股沟斜疝无张力修补术 | E96: =[2]胃肠外科!$I$7 -> 乙状结肠直肠切除术伴结肠吻合术，经腹腔镜（腹腔镜下Dixon) | F96: =[2]胃肠外科!$C$7 -> 胃远端切除术，伴胃空肠吻合术(毕Ⅱ式)
A97: 第四顺位手术编码 | C97: 信息科 | D97: =[2]胃肠外科!$N$7 -> 53.04 | E97: =[2]胃肠外科!$H$7 -> 48.63 | F97: =[2]胃肠外科!$B$7 -> 43.70
A98: 第四顺位手术占比 | B98: % | C98: 信息科 | D98: =[2]胃肠外科!$Q$7 -> 6.7260138 | E98: =[2]胃肠外科!$K$7 -> 9.9671413 | F98: =[2]胃肠外科!$E$7 -> 6.4702788
A99: 第五顺位手术名称 | C99: 信息科 | D99: =[2]胃肠外科!$O$8 -> 腹腔镜下直肠前切除术 | E99: =[2]胃肠外科!$I$8 -> 肠粘连松解术 | F99: =[2]胃肠外科!$C$8 -> 十二指肠溃疡修补术
A100: 第五顺位手术编码 | C100: 信息科 | D100: =[2]胃肠外科!$N$8 -> 48.63 | E100: =[2]胃肠外科!$H$8 -> 54.59 | F100: =[2]胃肠外科!$B$8 -> 44.42
...

Sheet 胸外科
A1: 数据名 | B1: 计量单位 | C1: 填报部门 | D1: Y2021 | E1: Y2020 | F1: Y2019 | G1: 指标说明 | H1: 计算公式
A2: 出院患者手术占比 | B2: % | C2: 统计室 | D2: 30 | E2: 20.97561 | F2: 19.842989 | G2: 详见三级公立、二级公立国考手册。举例：30%请填写30（不带百分号），而非写成30%，或0.3。下同 | H2: 出院患者手术台次数/同期出院患者总人次数*100
A3: 出院患者微创手术占比 | B3: % | C3: 统计室 | D3: 85.163776 | E3: 79.198966 | F3: 82.946794 | G3: 详见三级公立、二级公立国考手册 | H3: 出院患者微创手术台次数/同期出院患者手术台次数*100
A4: 出院患者四级手术比例 | B4: % | C4: 统计室 | D4: 85.934489 | E4: 79.97416 | F4: 82.673943 | G4: 详见三级公立国考手册 | H4: 出院患者四级手术台次数/同期出院患者手术台次数*100
A5: 出院患者疑难危重病例比例 | B5: % | C5: 统计室 | D5: 97.11 | E5: 95.58 | F5: 96.7 | G5: 即CD型病例占比 | H5: (疑难病例数+危重病例数)/出院人数*100
A6: 手术患者并发症发生率 | B6: % | C6: 质控科 | D6: 0 | E6: 0 | F6: 0 | G6: 详见国考手册 | H6: 手术患者并发症发生例数/同期出院的手术患者人数*100
A7: I类切口手术部位感染率 | B7: % | C7: 质控科 | D7: 0 | E7: 0 | F7: 0 | G7: 详见三级中医、三级公立国考手册 | H7: I类切口手术部位感染人次数/同期I类切口手术台次数*100
A8: 大型医用设备检查阳性率 | B8: % | C8: 医务科 | G8: 详见三级中医、三级公立国考手册 | H8: 大型医用设备检查阳性数/同期大型医用设备检查人次数*100
A9: 低风险组病例死亡率 | B9: % | C9: 质控科 | D9: 0 | E9: 0 | F9: 0 | G9: 详见三级公立、二级公立国考手册 | H9: 低风险组死亡例数/低风险组病例数*100
A10: 医院感染发生率 | B10: % | C10: 院感科 | D10: 0.38 | E10: 0.51 | F10: 0.78 | G10: 等级评审标准细则
A11: 抗菌药物使用强度DDDs | B11: DDD | C11: 药学部 | D11: 49.760806 | E11: 35.052652 | F11: 33.901218 | G11: 详见国考手册 | H11: 住院患者抗菌药物消耗量（累计DDD数）/同期收治患者人天数*100
A12: 门诊患者基本药物处方占比 | B12: % | C12: 药学部 | D12: 60.58 | E12: 80 | F12: 40.35 | G12: 详见三级中医、三级公立国考手册 | H12: 门诊使用基本药物人次数/同期门诊诊疗总人次数*100
A13: 住院患者基本药物使用率 | B13: % | C13: 药学部 | D13: 92.17 | E13: 93.09 | F13: 87.08 | G13: 详见三级中医、三级公立国考手册 | H13: 出院患者使用基本药物总人次数/同期出院总人次数*100
A14: 重点监控高值医用耗材收入占比 | B14: % | C14: 设备科 | D14: =1/56351599*100 -> 1.7745725e-06 | E14: =1075200/55860751*100 -> 1.9247862 | F14: =1/54607463*100 -> 1.8312515e-06 | G14: 详见国考手册 | H14: 重点监控高值医用耗材收入/同期卫生材料收入*100
A15: 平均住院日 | B15: 天 | C15: 统计室 | D15: 7.44 | E15: 7.9 | F15: 8.3 | G15: 详见二级公立国考手册 | H15: 出院患者占用总床日数/同期出院患者人数
A16: CMI值 | C16: 质控科 | D16: 1.95 | E16: 1.63 | F16: 1.76 | G16: 病例组合指数
A17: DRGs组数 | B17: 组 | C17: 质控科 | D17: 129 | E17: 138 | F17: 140 | G17: 诊断相关分组组数
A18: 核定床位数 | B18: 张 | C18: 统计室 | D18: 75 | E18: 75 | F18: 75 | G18: 等级评审标准细则
A19: 实际开放床位数 | B19: 张 | C19: 统计室 | D19: 77 | E19: 75 | F19: 71 | G19: 等级评审标准细则
A20: 开放床位使用率 | B20: % | C20: 统计室 | D20: 87.38 | E20: 105.75 | F20: 117.48 | G20: 等级评审标准细则 | H20: 实际占用的总床日数/同期实际开放的总床日数*100
A21: 医师人数与开放床位数比 | C21: 人事科 | D21: =D43/D19 -> 0.12987013 | E21: =E43/E19 -> 0.14666667 | F21: =F43/F19 -> 0.15492958 | G21: 等级评审标准细则，原计量单位为比值（1:X），现改为小数 | H21: 医院执业（助理）医师总数/同期全院实际开放床位数
A22: 护士人数与开放床位数比 | C22: 人事科 | D22: =D44/D19 -> 0.31168831 | E22: =E44/E19 -> 0.36 | F22: =F44/F19 -> 0.43661972 | G22: 等级评审标准细则，原计量单位为比值（1:X），现改为小数 | H22: 医院注册护士总数/同期全院实际开放床位数
A23: 人均医疗服务收入 | B23: 万元 | C23: 财务科 | D23: 35.239787 | E23: 32.232985 | F23: 34.08213 | G23: 按科室人员数人均医疗服务收入
A24: 人均有效收入 | B24: 万元 | C24: 财务科 | D24: 70.502028 | E24: 71.701404 | F24: 66.248631 | G24: 按科室人员数人均有效收入
A25: 床均医疗服务收入 | B25: 万元 | C25: 财务科 | D25: 18.926267 | E25: 17.298561 | F25: 18.72117 | G25: 按开放床位数床均医疗服务收入
A26: 床均有效收入 | B26: 万元 | C26: 财务科 | D26: 37.864595 | E26: 38.480181 | F26: 36.390093 | G26: 按开放床位数床均有效收入
A27: 每名执业医师日均住院工作负担 | B27: 床日 | C27: 财务科 | D27: 6.6709589 | E27: 7.0057285 | F27: 7.5825654 | G27: 详见三级中医、三级公立国考手册 | H27: 全年实际占用总床日数/医院平均执业(助理)医师人数/365
A28: 医疗服务收入占医疗收入比例 | B28: % | C28: 财务科 | D28: 23.199972 | E28: 20.732901 | F28: 22.880764 | G28: 参考国考手册，原指标名为：医疗服务收入（不含药品、耗材、检查检验收入）占医疗收入比例 | H28: 医疗服务收入/医疗收入*100
A29: 医疗收入 | B29: 万元 | C29: 财务科 | D29: 6227.7284 | E29: 6063.2442 | F29: 5809.2601 | H29: 门诊收入+住院收入
A30: 医疗服务收入 | B30: 万元 | C30: 财务科 | D30: 1444.8313 | E30: 1257.0864 | F30: 1329.2031
A31: 有效收入 | B31: 万元 | C31: 财务科 | D31: 2890.5831 | E31: 2796.3548 | F31: 2583.6966 | H31: 医疗服务收入+检查检验收入
A32: 医疗直接成本 | B32: 万元 | D32: 3439.25 | E32: 3405.06 | F32: 3345.08
A33: 收支结余率 | B33: % | D33: 19.94 | E33: 22.62 | F33: 25.46
A34: 万元收入能耗占比 | B34: 吨标煤/万元 | C34: 后勤管理科 | G34: 详见国考手册 | H34: 年总能耗/年总收入*10000
A35: 门诊收入占医疗收入比例 | B35: % | C35: 财务科 | D35: 15.369214 | E35: 11.013109 | F35: 2.8855431 | G35: 详见三级公立国考手册 | H35: 门诊收入/医疗收入*100
A36: 住院收入占医疗收入比例 | B36: % | C36: 财务科 | D36: 84.630786 | E36: 88.986891 | F36: 97.114457 | G36: 详见三级公立国考手册 | H36: 住院收入/医疗收入*100
A37: 医疗收入增幅 | B37: % | C37: 财务科 | D37: 2.7128083 | E37: 4.372057 | F37: 26.337406 | G37: 详见国考手册 | H37: （本年度医疗收入－上一年度医疗收入）/上一年度医疗收入*100
A38: 门诊次均费用增幅 | B38: % | C38: 财务科 | D38: 12.1991 | E38: 247.66235 | F38: 2.7969211 | G38: 详见国考手册 | H38: （本年度门诊患者次均医药费用－上一年度门诊患者次均医药费用）/上一年度门诊患者次均医药费用*100
A39: 住院次均费用增幅 | B39: % | C39: 财务科 | D39: 6.274852 | E39: -1.4768585 | F39: 11.995076 | G39: 详见国考手册 | H39: （本年度出院患者次均医药费用－上一年度出院患者次均医药费用）/上一年度出院患者次均医药费用*100
A40: 门诊次均药品费用增幅 | B40: % | C40: 财务科 | D40: 15.16227 | E40: 1653.4715 | F40: -5.6922404 | G40: 详见国考手册 | H40: （本年度门诊患者次均药品费用－上一年度门诊患者次均药品费用）/上一年度门诊患者次均药品费用*100
A41: 住院次均药品费用增幅 | B41: % | C41: 财务科 | D41: -19.151225 | E41: -16.683705 | F41: 25.513255 | G41: 详见国考手册 | H41: （本年度出院患者次均药品费用－上一年度出院患者次均药品费用）/上一年度出院患者次均药品费用*100
A42: 医护比 | C42: 人事科 | D42: 0.42 | E42: 0.41 | F42: 0.35 | G42: 参考国考手册，原计量单位为比值（1:X），现改为小数 | H42: 医院注册医师总数/全院同期注册护士总数
A43: 医师人数 | B43: 人 | C43: 人事科 | D43: 10 | E43: 11 | F43: 11 | G43: 详见国考手册中，医护比定义
A44: 护士人数 | B44: 人 | C44: 人事科 | D44: 24 | E44: 27 | F44: 31 | G44: 详见国考手册中，医护比定义
A45: 医师高级职称占比 | B45: % | C45: 人事科 | D45: 40 | E45: 36.36 | F45: 36.36 | H45: (正高职称医师人数+副高职称医师人数)/医师人数*100
A46: 医师博士占比 | B46: % | C46: 人事科 | D46: 10 | E46: 9.09 | F46: 9.09 | H46: 博士医师人数/医师人数*100
A47: 医师硕士占比 | B47: % | C47: 人事科 | D47: 60 | E47: 63.64 | F47: 63.64 | H47: 硕士医师人数/医师人数*100
A48: 发表教学文章数与卫生技术人员数之比 | C48: 科教科 | D48: 0 | E48: 0 | F48: 0 | G48: 参考三级中医、三级公立国考手册，医院承担培养医学人才的工作成效的构成元素。原计量单位为比值（1:X），现改为小数 | H48: 本年度发表的教学文章数/同期卫生技术人员总数
A49: 省部级及以上教育教学课题数与卫生技术人员数之比 | C49: 科教科 | D49: 0 | E49: 0 | F49: 0 | G49: 参考三级中医、三级公立国考手册，医院承担培养医学人才的工作成效的构成元素。本指标为延伸指标。原计量单位为比值（1:X），现改为小数 | H49: 本年度获得的省部级及以上教育教学课题数/同期卫生技术人员总数
A50: 国家级继续医学教育项目数与卫生技术人员数之比 | C50: 科教科 | D50: 0 | E50: 0 | F50: 0 | G50: 参考三级中医、三级公立国考手册，医院承担培养医学人才的工作成效的构成元素。本指标为延伸指标。原计量单位为比值（1:X），现改为小数 | H50: 本年度举办的国家级继续医学教育项目数/同期卫生技术人员总数
A51: 每百名卫生技术人员科研项目经费 | B51: 元 | C51: 科教科 | D51: 1266379.8 | E51: 0 | F51: 1219339 | G51: 详见三级中医、三级公立国考手册 | H51: 本年度科研项目立项经费总金额/同期卫生技术人员总数*100
A52: 每百名卫生技术人员科研成果转化金额 | B52: 元 | C52: 科教科 | D52: 0 | E52: 0 | F52: 0 | G52: 详见三级公立国考手册 | H52: 本年度科技成果转化总金额/同期医院卫生技术人员总数*100
A53: 医师人均国家自然科学基金项目数量 | B53: 项 | C53: 科教科 | D53: 0 | E53: 0 | F53: 0 | G53: 说明：本年度成功立项的项目数量。要求本科室为主研单位
A54: 医师人均SCI文章数量 | B54: 篇 | C54: 科教科 | D54: 0.3 | E54: 0 | F54: 0 | G54: 说明：本年度成功发表的论文，要求第一作者或通讯作者为本院员工
A55: SCI平均影响因子 | B55: 分 | C55: 科教科 | D55: 1.15 | E55: 0 | F55: 0 | G55: 说明：本年度成功发表的论文，要求第一作者或通讯作者为本院员工
A56: 博士研究生导师占比 | B56: % | C56: 科教科 | D56: 0 | E56: 0 | F56: 0 | H56: 博士研究生导师人数/同期医师总数*100
A57: 硕士研究生导师占比 | B57: % | C57: 科教科 | D57: 0 | E57: 0 | F57: 0 | H57: 硕士研究生导师人数/同期医师总数*100
A58: 外省住院患者占比 | B58: % | C58: 统计室 | D58: 2.4855491 | E58: 2.8455285 | F58: 4.6291283 | H58: 外省住院患者人数/同期出院患者人次数*100
A59: 非医嘱离院率 | B59: % | C59: 统计室 | D59: 0.60693642 | E59: 0.43360434 | F59: 1.5159718 | H59: 非医嘱离院人次/同期出院患者总人次*100
A60: 是否为教育部或科技部重点学科或重点实验室 | B60: 分 | C60: 科教科 | D60: 0 | E60: 0 | F60: 0 | G60: 是填1,否填0
A61: 是否为国家卫健委临床重点专科 | B61: 分 | C61: 科教科 | D61: 0 | E61: 0 | F61: 0 | G61: 是填1,否填0
A62: 是否为国家中医药局重点专科 | B62: 分 | C62: 科教科 | D62: 0 | E62: 0 | F62: 0 | G62: 是填1,否填0
A63: 是否为省教育厅或科技厅重点学科或重点实验室 | B63: 分 | C63: 科教科 | D63: 0 | E63: 0 | F63: 0 | G63: 是填1,否填0
A64: 是否为省卫健委重点专科 | B64: 分 | C64: 科教科 | D64: 1 | E64: 1 | F64: 1 | G64: 是填1,否填0
A65: 是否为省中医药局重点专科 | B65: 分 | C65: 科教科 | D65: 0 | E65: 0 | F65: 0 | G65: 是填1,否填0
A66: 是否为地市级教育局或科技局重点学科或重点实验室 | B66: 分 | C66: 科教科 | D66: 0 | E66: 0 | F66: 0 | G66: 是填1,否填0
A67: 是否为地市级卫健委重点专科 | B67: 分 | C67: 科教科 | D67: 1 | E67: 1 | F67: 1 | G67: 是填1,否填0
A68: 是否为地市级中医药局重点专科 | B68: 分 | C68: 科教科 | D68: 0 | E68: 0 | F68: 0 | G68: 是填1,否填0
A69: 是否为县级教育局或科技局重点学科或重点实验室 | B69: 分 | C69: 科教科 | D69: 0 | E69: 0 | F69: 0 | G69: 是填1,否填0
A70: 是否为县级卫健委重点专科 | B70: 分 | C70: 科教科 | D70: 0 | E70: 0 | F70: 0 | G70: 是填1,否填0
A71: 是否为县级中医药局重点专科 | B71: 分 | C71: 科教科 | D71: 0 | E71: 0 | F71: 0 | G71: 是填1,否填0
A72: 第一顺位疾病名称 | C72: 信息科 | D72: =[1]胸外科!$O$4 -> 为肿瘤化学治疗疗程 | E72: =[1]胸外科!$I$4 -> 为肿瘤化学治疗疗程 | F72: =[1]胸外科!$C$4 -> 为肿瘤化学治疗疗程
A73: 第一顺位疾病编码 | C73: 信息科 | D73: =[1]胸外科!$N$4 -> Z51.1 | E73: =[1]胸外科!$H$4 -> Z51.1 | F73: =[1]胸外科!$B$4 -> Z51.1
A74: 第一顺位疾病占比 | B74: % | C74: 信息科 | D74: =[1]胸外科!$Q$4 -> 27.774566 | E74: =[1]胸外科!$K$4 -> 30.135501 | F74: =[1]胸外科!$E$4 -> 28.586898
A75: 第二顺位疾病名称 | C75: 信息科 | D75: =[1]胸外科!$O$5 -> 肺恶性肿瘤 | E75: =[1]胸外科!$I$5 -> 抗肿瘤治疗 | F75: =[1]胸外科!$C$5 -> 抗肿瘤治疗
A76: 第二顺位疾病编码 | C76: 信息科 | D76: =[1]胸外科!$N$5 -> C34 | E76: =[1]胸外科!$H$5 -> Z51.8 | F76: =[1]胸外科!$B$5 -> Z51.8
A77: 第二顺位疾病占比 | B77: % | C77: 信息科 | D77: =[1]胸外科!$Q$5 -> 18.236994 | E77: =[1]胸外科!$K$5 -> 20.406504 | F77: =[1]胸外科!$E$5 -> 22.008663
A78: 第三顺位疾病名称 | C78: 信息科 | D78: =[1]胸外科!$O$6 -> 抗肿瘤治疗 | E78: =[1]胸外科!$I$6 -> 肺恶性肿瘤 | F78: =[1]胸外科!$C$6 -> 肺恶性肿瘤
A79: 第三顺位疾病编码 | C79: 信息科 | D79: =[1]胸外科!$N$6 -> Z51.8 | E79: =[1]胸外科!$H$6 -> C34 | F79: =[1]胸外科!$B$6 -> C34
A80: 第三顺位疾病占比 | B80: % | C80: 信息科 | D80: =[1]胸外科!$Q$6 -> 12.774566 | E80: =[1]胸外科!$K$6 -> 14.878049 | F80: =[1]胸外科!$E$6 -> 14.266378
A81: 第四顺位疾病名称 | C81: 信息科 | D81: =[1]胸外科!$O$7 -> 肺气肿 | E81: =[1]胸外科!$I$7 -> 食管恶性肿瘤 | F81: =[1]胸外科!$C$7 -> 肺气肿
A82: 第四顺位疾病编码 | C82: 信息科 | D82: =[1]胸外科!$N$7 -> J43 | E82: =[1]胸外科!$H$7 -> C15 | F82: =[1]胸外科!$B$7 -> J43
A83: 第四顺位疾病占比 | B83: % | C83: 信息科 | D83: =[1]胸外科!$Q$7 -> 3.583815 | E83: =[1]胸外科!$K$7 -> 3.1165312 | F83: =[1]胸外科!$E$7 -> 3.275582
A84: 第五顺位疾病名称 | C84: 信息科 | D84: =[1]胸外科!$O$8 -> 其他呼吸性疾患 | E84: =[1]胸外科!$I$8 -> 肺气肿 | F84: =[1]胸外科!$C$8 -> 食管恶性肿瘤
A85: 第五顺位疾病编码 | C85: 信息科 | D85: =[1]胸外科!$N$8 -> J98 | E85: =[1]胸外科!$H$8 -> J43 | F85: =[1]胸外科!$B$8 -> C15
A86: 第五顺位疾病占比 | B86: % | C86: 信息科 | D86: =[1]胸外科!$Q$8 -> 3.4393064 | E86: =[1]胸外科!$K$8 -> 3.1165312 | F86: =[1]胸外科!$E$8 -> 2.7612344
A87: 第一顺位手术名称 | C87: 信息科 | D87: =[2]胸外科!$O$4 -> 胸腔镜下肺楔形切除术 | E87: =[2]胸外科!$I$4 -> 肺叶切除术，经单孔胸腔镜 | F87: =[2]胸外科!$C$4 -> 肺叶切除术，经胸腔镜
A88: 第一顺位手术编码 | C88: 信息科 | D88: =[2]胸外科!$N$4 -> 32.2 | E88: =[2]胸外科!$H$4 -> 32.41 | F88: =[2]胸外科!$B$4 -> 32.41
A89: 第一顺位手术占比 | B89: % | C89: 信息科 | D89: =[2]胸外科!$Q$4 -> 31.117534 | E89: =[2]胸外科!$K$4 -> 27.002584 | F89: =[2]胸外科!$E$4 -> 32.60573
A90: 第二顺位手术名称 | C90: 信息科 | D90: =[2]胸外科!$O$5 -> 胸腔镜下肺叶切除术 | E90: =[2]胸外科!$I$5 -> 肺大泡切除术，经胸腔镜 | F90: =[2]胸外科!$C$5 -> 肺部分切除术（含肺楔形切除术），经胸腔镜
A91: 第二顺位手术编码 | C91: 信息科 | D91: =[2]胸外科!$N$5 -> 32.41 | E91: =[2]胸外科!$H$5 -> 32.20 | F91: =[2]胸外科!$B$5 -> 32.2
A92: 第二顺位手术占比 | B92: % | C92: 信息科 | D92: =[2]胸外科!$Q$5 -> 28.323699 | E92: =[2]胸外科!$K$5 -> 16.020672 | F92: =[2]胸外科!$E$5 -> 27.012278
A93: 第三顺位手术名称 | C93: 信息科 | D93: =[2]胸外科!$O$6 -> 胸腔镜肺叶节段切除术 | E93: =[2]胸外科!$I$6 -> 纵隔病损切除术，经胸腔镜 | F93: =[2]胸外科!$C$6 -> 纵隔病损切除术，经胸腔镜
A94: 第三顺位手术编码 | C94: 信息科 | D94: =[2]胸外科!$N$6 -> 32.3 | E94: =[2]胸外科!$H$6 -> 34.30 | F94: =[2]胸外科!$B$6 -> 34.3
A95: 第三顺位手术占比 | B95: % | C95: 信息科 | D95: =[2]胸外科!$Q$6 -> 6.4547206 | E95: =[2]胸外科!$K$6 -> 6.0723514 | F95: =[2]胸外科!$E$6 -> 4.638472
A96: 第四顺位手术名称 | C96: 信息科 | D96: =[2]胸外科!$O$7 -> 胸腔镜下纵隔病损切除术 | E96: =[2]胸外科!$I$7 -> 食管全切除术，经颈+胸腔镜+腹腔镜 | F96: =[2]胸外科!$C$7 -> 食管全切除术，经颈+胸腔镜+腹腔镜
A97: 第四顺位手术编码 | C97: 信息科 | D97: =[2]胸外科!$N$7 -> 34.3x | E97: =[2]胸外科!$H$7 -> 42.42 | F97: =[2]胸外科!$B$7 -> 42.42
A98: 第四顺位手术占比 | B98: % | C98: 信息科 | D98: =[2]胸外科!$Q$7 -> 5.6840077 | E98: =[2]胸外科!$K$7 -> 4.7803618 | F98: =[2]胸外科!$E$7 -> 5.047749
A99: 第五顺位手术名称 | C99: 信息科 | D99: =[2]胸外科!$O$8 -> 颈胸腹三切口食管部分切除术 | E99: =[2]胸外科!$I$8 -> 胸交感神经切断术，经胸腔镜 | F99: =[2]胸外科!$C$8 -> 胸膜剥脱术，经胸腔镜
A100: 第五顺位手术编码 | C100: 信息科 | D100: =[2]胸外科!$N$8 -> 42.41 | E100: =[2]胸外科!$H$8 -> 05.0 | F100: =[2]胸外科!$B$8 -> 34.51
...

Sheet 神经外科
A1: 数据名 | B1: 计量单位 | C1: 填报部门 | D1: Y2021 | E1: Y2020 | F1: Y2019 | G1: 指标说明 | H1: 计算公式
A2: 出院患者手术占比 | B2: % | C2: 统计室 | D2: 29.261273 | E2: 31.041322 | F2: 32.273919 | G2: 详见三级公立、二级公立国考手册。举例：30%请填写30（不带百分号），而非写成30%，或0.3。下同 | H2: 出院患者手术台次数/同期出院患者总人次数*100
A3: 出院患者微创手术占比 | B3: % | C3: 统计室 | D3: 11.147541 | E3: 3.9403621 | F3: 2.8426396 | G3: 详见三级公立、二级公立国考手册 | H3: 出院患者微创手术台次数/同期出院患者手术台次数*100
A4: 出院患者四级手术比例 | B4: % | C4: 统计室 | D4: 41.639344 | E4: 41.746539 | F4: 41.218274 | G4: 详见三级公立国考手册 | H4: 出院患者四级手术台次数/同期出院患者手术台次数*100
A5: 出院患者疑难危重病例比例 | B5: % | C5: 统计室 | D5: 92.375 | E5: 92.535 | F5: 92.1675 | G5: 即CD型病例占比 | H5: (疑难病例数+危重病例数)/出院人数*100
A6: 手术患者并发症发生率 | B6: % | C6: 质控科 | D6: 0 | E6: 0 | F6: 0 | G6: 详见国考手册 | H6: 手术患者并发症发生例数/同期出院的手术患者人数*100
A7: I类切口手术部位感染率 | B7: % | C7: 质控科 | D7: 0.06 | E7: 0.05 | F7: 0 | G7: 详见三级中医、三级公立国考手册 | H7: I类切口手术部位感染人次数/同期I类切口手术台次数*100
A8: 大型医用设备检查阳性率 | B8: % | C8: 医务科 | G8: 详见三级中医、三级公立国考手册 | H8: 大型医用设备检查阳性数/同期大型医用设备检查人次数*100
A9: 低风险组病例死亡率 | B9: % | C9: 质控科 | D9: 0 | E9: 0 | F9: 0 | G9: 详见三级公立、二级公立国考手册 | H9: 低风险组死亡例数/低风险组病例数*100
A10: 医院感染发生率 | B10: % | C10: 院感科 | D10: 3.76 | E10: 4.39 | F10: 5.24 | G10: 等级评审标准细则
A11: 抗菌药物使用强度DDDs | B11: DDD | C11: 药学部 | D11: 50.06 | E11: 54.42 | F11: 196.02 | G11: 详见国考手册 | H11: 住院患者抗菌药物消耗量（累计DDD数）/同期收治患者人天数*100
A12: 门诊患者基本药物处方占比 | B12: % | C12: 药学部 | D12: 82.38 | E12: 67.66 | F12: 61.56 | G12: 详见三级中医、三级公立国考手册 | H12: 门诊使用基本药物人次数/同期门诊诊疗总人次数*100
A13: 住院患者基本药物使用率 | B13: % | C13: 药学部 | D13: 97.92 | E13: 98.08 | F13: 94.31 | G13: 详见三级中医、三级公立国考手册 | H13: 出院患者使用基本药物总人次数/同期出院总人次数*100
A14: 重点监控高值医用耗材收入占比 | B14: % | C14: 设备科 | D14: =(2502461+416598)/41054915*100 -> 7.1101329 | E14: =3662543/39973299*100 -> 9.1624737 | F14: =1716817.5/59549948*100 -> 2.8829874 | G14: 详见国考手册 | H14: 重点监控高值医用耗材收入/同期卫生材料收入*100
A15: 平均住院日 | B15: 天 | C15: 统计室 | D15: 15.64 | E15: 16.535 | F15: 13.5125 | G15: 详见二级公立国考手册 | H15: 出院患者占用总床日数/同期出院患者人数
A16: CMI值 | C16: 质控科 | D16: 2.865 | E16: 3 | F16: 2.705 | G16: 病例组合指数
A17: DRGs组数 | B17: 组 | C17: 质控科 | D17: 124 | E17: 131 | F17: 90 | G17: 诊断相关分组组数
A18: 核定床位数 | B18: 张 | C18: 统计室 | D18: 130 | E18: 130 | F18: 130 | G18: 等级评审标准细则
A19: 实际开放床位数 | B19: 张 | C19: 统计室 | D19: 140 | E19: 130 | F19: 120 | G19: 等级评审标准细则
A20: 开放床位使用率 | B20: % | C20: 统计室 | D20: 104.045 | E20: 118.75 | F20: 102.6025 | G20: 等级评审标准细则 | H20: 实际占用的总床日数/同期实际开放的总床日数*100
A21: 医师人数与开放床位数比 | C21: 人事科 | D21: =D43/D19 -> 0.15714286 | E21: =E43/E19 -> 0.14615385 | F21: =F43/F19 -> 0.15 | G21: 等级评审标准细则，原计量单位为比值（1:X），现改为小数 | H21: 医院执业（助理）医师总数/同期全院实际开放床位数
A22: 护士人数与开放床位数比 | C22: 人事科 | D22: =D44/D19 -> 0.59285714 | E22: =E44/E19 -> 0.63846154 | F22: =F44/F19 -> 0.675 | G22: 等级评审标准细则，原计量单位为比值（1:X），现改为小数 | H22: 医院注册护士总数/同期全院实际开放床位数
A23: 人均医疗服务收入 | B23: 万元 | C23: 财务科 | D23: 27.339768 | E23: 28.829451 | F23: 21.136676 | G23: 按科室人员数人均医疗服务收入
A24: 人均有效收入 | B24: 万元 | C24: 财务科 | D24: 38.372209 | E24: 40.583123 | F24: 30.443729 | G24: 按科室人员数人均有效收入
A25: 床均医疗服务收入 | B25: 万元 | C25: 财务科 | D25: 22.798139 | E25: 25.537443 | F25: 29.632091 | G25: 按开放床位数床均医疗服务收入
A26: 床均有效收入 | B26: 万元 | C26: 财务科 | D26: 31.997892 | E26: 35.948973 | F26: 42.679905 | G26: 按开放床位数床均有效收入
A27: 每名执业医师日均住院工作负担 | B27: 床日 | C27: 财务科 | D27: 5.9803238 | E27: 7.0126893 | F27: 7.6447489 | G27: 详见三级中医、三级公立国考手册 | H27: 全年实际占用总床日数/医院平均执业(助理)医师人数/365
A28: 医疗服务收入占医疗收入比例 | B28: % | C28: 财务科 | D28: 41.554585 | E28: 42.566344 | F28: 40.497632 | G28: 参考国考手册，原指标名为：医疗服务收入（不含药品、耗材、检查检验收入）占医疗收入比例 | H28: 医疗服务收入/医疗收入*100
A29: 医疗收入 | B29: 万元 | C29: 财务科 | D29: 7500.3363 | E29: 7450.1105 | F29: 5845.5461 | H29: 门诊收入+住院收入
A30: 医疗服务收入 | B30: 万元 | C30: 财务科 | D30: 3116.7336 | E30: 3171.2396 | F30: 2367.3077
A31: 有效收入 | B31: 万元 | C31: 财务科 | D31: 4374.4319 | E31: 4464.1435 | F31: 3409.6976 | H31: 医疗服务收入+检查检验收入
A32: 医疗直接成本 | B32: 万元 | D32: 5923.74 | E32: 5242.98 | F32: 5355.62
A33: 收支结余率 | B33: % | D33: -27.08 | E33: -5.5 | F33: -14.65
A34: 万元收入能耗占比 | B34: 吨标煤/万元 | C34: 后勤管理科 | G34: 详见国考手册 | H34: 年总能耗/年总收入*10000
A35: 门诊收入占医疗收入比例 | B35: % | C35: 财务科 | D35: 3.6803863 | E35: 3.0495555 | F35: 3.9241613 | G35: 详见三级公立国考手册 | H35: 门诊收入/医疗收入*100
A36: 住院收入占医疗收入比例 | B36: % | C36: 财务科 | D36: 96.319614 | E36: 96.950445 | F36: 96.075839 | G36: 详见三级公立国考手册 | H36: 住院收入/医疗收入*100
A37: 医疗收入增幅 | B37: % | C37: 财务科 | D37: 0.67416206 | E37: 27.449349 | F37: -6.4083309 | G37: 详见国考手册 | H37: （本年度医疗收入－上一年度医疗收入）/上一年度医疗收入*100
A38: 门诊次均费用增幅 | B38: % | C38: 财务科 | D38: -7.5371278 | E38: -0.20096038 | F38: 5.2005415 | G38: 详见国考手册 | H38: （本年度门诊患者次均医药费用－上一年度门诊患者次均医药费用）/上一年度门诊患者次均医药费用*100
A39: 住院次均费用增幅 | B39: % | C39: 财务科 | D39: -4.6742756 | E39: -11.820326 | F39: 26.670215 | G39: 详见国考手册 | H39: （本年度出院患者次均医药费用－上一年度出院患者次均医药费用）/上一年度出院患者次均医药费用*100
A40: 门诊次均药品费用增幅 | B40: % | C40: 财务科 | D40: -10.213564 | E40: -3.0401897 | F40: -7.2909429 | G40: 详见国考手册 | H40: （本年度门诊患者次均药品费用－上一年度门诊患者次均药品费用）/上一年度门诊患者次均药品费用*100
A41: 住院次均药品费用增幅 | B41: % | C41: 财务科 | D41: 3.7022471 | E41: -19.237253 | F41: 13.352443 | G41: 详见国考手册 | H41: （本年度出院患者次均药品费用－上一年度出院患者次均药品费用）/上一年度出院患者次均药品费用*100
A42: 医护比 | C42: 人事科 | D42: 0.27 | E42: 0.23 | F42: 0.22 | G42: 参考国考手册，原计量单位为比值（1:X），现改为小数 | H42: 医院注册医师总数/全院同期注册护士总数
A43: 医师人数 | B43: 人 | C43: 人事科 | D43: 22 | E43: 19 | F43: 18 | G43: 详见国考手册中，医护比定义
A44: 护士人数 | B44: 人 | C44: 人事科 | D44: 83 | E44: 83 | F44: 81 | G44: 详见国考手册中，医护比定义
A45: 医师高级职称占比 | B45: % | C45: 人事科 | D45: 45.45 | E45: 47.37 | F45: 44.44 | H45: (正高职称医师人数+副高职称医师人数)/医师人数*100
A46: 医师博士占比 | B46: % | C46: 人事科 | D46: 9.09 | E46: 5.26 | F46: 5.56 | H46: 博士医师人数/医师人数*100
A47: 医师硕士占比 | B47: % | C47: 人事科 | D47: 68.18 | E47: 68.42 | F47: 66.67 | H47: 硕士医师人数/医师人数*100
A48: 发表教学文章数与卫生技术人员数之比 | C48: 科教科 | D48: 0.01 | E48: 0.01 | F48: 0 | G48: 参考三级中医、三级公立国考手册，医院承担培养医学人才的工作成效的构成元素。原计量单位为比值（1:X），现改为小数 | H48: 本年度发表的教学文章数/同期卫生技术人员总数
A49: 省部级及以上教育教学课题数与卫生技术人员数之比 | C49: 科教科 | D49: 0 | E49: 0 | F49: 0 | G49: 参考三级中医、三级公立国考手册，医院承担培养医学人才的工作成效的构成元素。本指标为延伸指标。原计量单位为比值（1:X），现改为小数 | H49: 本年度获得的省部级及以上教育教学课题数/同期卫生技术人员总数
A50: 国家级继续医学教育项目数与卫生技术人员数之比 | C50: 科教科 | D50: 0 | E50: 0 | F50: 0 | G50: 参考三级中医、三级公立国考手册，医院承担培养医学人才的工作成效的构成元素。本指标为延伸指标。原计量单位为比值（1:X），现改为小数 | H50: 本年度举办的国家级继续医学教育项目数/同期卫生技术人员总数
A51: 每百名卫生技术人员科研项目经费 | B51: 元 | C51: 科教科 | D51: 0 | E51: 0 | F51: 0 | G51: 详见三级中医、三级公立国考手册 | H51: 本年度科研项目立项经费总金额/同期卫生技术人员总数*100
A52: 每百名卫生技术人员科研成果转化金额 | B52: 元 | C52: 科教科 | D52: 0 | E52: 0 | F52: 0 | G52: 详见三级公立国考手册 | H52: 本年度科技成果转化总金额/同期医院卫生技术人员总数*100
A53: 医师人均国家自然科学基金项目数量 | B53: 项 | C53: 科教科 | D53: 0 | E53: 0 | F53: 0 | G53: 说明：本年度成功立项的项目数量。要求本科室为主研单位
A54: 医师人均SCI文章数量 | B54: 篇 | C54: 科教科 | D54: 0 | E54: 0 | F54: 0 | G54: 说明：本年度成功发表的论文，要求第一作者或通讯作者为本院员工
A55: SCI平均影响因子 | B55: 分 | C55: 科教科 | D55: 0 | E55: 0 | F55: 0 | G55: 说明：本年度成功发表的论文，要求第一作者或通讯作者为本院员工
A56: 博士研究生导师占比 | B56: % | C56: 科教科 | D56: 0 | E56: 0 | F56: 0 | H56: 博士研究生导师人数/同期医师总数*100
A57: 硕士研究生导师占比 | B57: % | C57: 科教科 | D57: 4.55 | E57: 5.26 | F57: 0 | H57: 硕士研究生导师人数/同期医师总数*100
A58: 外省住院患者占比 | B58: % | C58: 统计室 | D58: =AVERAGE(D59:D60) -> 1.0873041 | E58: =AVERAGE(E59:E60) -> 6.5950413 | F58: 9.13 | H58: 外省住院患者人数/同期出院患者人次数*100
A59: 非医嘱离院率 | B59: % | C59: 统计室 | D59: 2.1746083 | E59: 13.190083 | F59: 13.499345 | H59: 非医嘱离院人次/同期出院患者总人次*100
A60: 是否为教育部或科技部重点学科或重点实验室 | B60: 分 | C60: 科教科 | D60: 0 | E60: 0 | F60: 0 | G60: 是填1,否填0
A61: 是否为国家卫健委临床重点专科 | B61: 分 | C61: 科教科 | D61: 0 | E61: 0 | F61: 0 | G61: 是填1,否填0
A62: 是否为国家中医药局重点专科 | B62: 分 | C62: 科教科 | D62: 0 | E62: 0 | F62: 0 | G62: 是填1,否填0
A63: 是否为省教育厅或科技厅重点学科或重点实验室 | B63: 分 | C63: 科教科 | D63: 0 | E63: 0 | F63: 0 | G63: 是填1,否填0
A64: 是否为省卫健委重点专科 | B64: 分 | C64: 科教科 | D64: 1 | E64: 1 | F64: 1 | G64: 是填1,否填0
A65: 是否为省中医药局重点专科 | B65: 分 | C65: 科教科 | D65: 0 | E65: 0 | F65: 0 | G65: 是填1,否填0
A66: 是否为地市级教育局或科技局重点学科或重点实验室 | B66: 分 | C66: 科教科 | D66: 0 | E66: 0 | F66: 0 | G66: 是填1,否填0
A67: 是否为地市级卫健委重点专科 | B67: 分 | C67: 科教科 | D67: 1 | E67: 1 | F67: 1 | G67: 是填1,否填0
A68: 是否为地市级中医药局重点专科 | B68: 分 | C68: 科教科 | D68: 0 | E68: 0 | F68: 0 | G68: 是填1,否填0
A69: 是否为县级教育局或科技局重点学科或重点实验室 | B69: 分 | C69: 科教科 | D69: 0 | E69: 0 | F69: 0 | G69: 是填1,否填0
A70: 是否为县级卫健委重点专科 | B70: 分 | C70: 科教科 | D70: 0 | E70: 0 | F70: 0 | G70: 是填1,否填0
A71: 是否为县级中医药局重点专科 | B71: 分 | C71: 科教科 | D71: 0 | E71: 0 | F71: 0 | G71: 是填1,否填0
A72: 第一顺位疾病名称 | C72: 信息科 | D72: =[1]神经外科!$O$4 -> 创伤性颅内损伤 | E72: =[1]神经外科!$I$4 -> 创伤性颅内损伤 | F72: =[1]神经外科!$C$4 -> 创伤性颅内损伤
A73: 第一顺位疾病编码 | C73: 信息科 | D73: =[1]神经外科!$N$4 -> S06 | E73: =[1]神经外科!$H$4 -> S06 | F73: =[1]神经外科!$B$4 -> S06
A74: 第一顺位疾病占比 | B74: % | C74: 信息科 | D74: =[1]神经外科!$Q$4 -> 23.504957 | E74: =[1]神经外科!$K$4 -> 21.983471 | F74: =[1]神经外科!$E$4 -> 22.57536
A75: 第二顺位疾病名称 | C75: 信息科 | D75: =[1]神经外科!$O$5 -> 脑内出血 | E75: =[1]神经外科!$I$5 -> 脑内出血 | F75: =[1]神经外科!$C$5 -> 脑内出血
A76: 第二顺位疾病编码 | C76: 信息科 | D76: =[1]神经外科!$N$5 -> I61 | E76: =[1]神经外科!$H$5 -> I61 | F76: =[1]神经外科!$B$5 -> I61
A77: 第二顺位疾病占比 | B77: % | C77: 信息科 | D77: =[1]神经外科!$Q$5 -> 11.928366 | E77: =[1]神经外科!$K$5 -> 14.049587 | F77: =[1]神经外科!$E$5 -> 13.695937
A78: 第三顺位疾病名称 | C78: 信息科 | D78: =[1]神经外科!$O$6 -> 毒蛇咬伤 | E78: =[1]神经外科!$I$6 -> 毒蛇咬伤 | F78: =[1]神经外科!$C$6 -> 毒蛇咬伤
A79: 第三顺位疾病编码 | C79: 信息科 | D79: =[1]神经外科!$N$6 -> T63.0 | E79: =[1]神经外科!$H$6 -> T63.0 | F79: =[1]神经外科!$B$6 -> T63
A80: 第三顺位疾病占比 | B80: % | C80: 信息科 | D80: =[1]神经外科!$Q$6 -> 9.178126 | E80: =[1]神经外科!$K$6 -> 10.247934 | F80: =[1]神经外科!$E$6 -> 11.107471
A81: 第四顺位疾病名称 | C81: 信息科 | D81: =[1]神经外科!$O$7 -> 脑脊膜良性肿瘤 | E81: =[1]神经外科!$I$7 -> 颅内动脉瘤破裂伴蛛网膜下腔出血 | F81: =[1]神经外科!$C$7 -> 颅内动脉瘤破裂伴蛛网膜下腔出血
A82: 第四顺位疾病编码 | C82: 信息科 | D82: =[1]神经外科!$N$7 -> D32 | E82: =[1]神经外科!$H$7 -> I60.0-I60.7 | F82: =[1]神经外科!$B$7 -> I60.0-I60.7
A83: 第四顺位疾病占比 | B83: % | C83: 信息科 | D83: =[1]神经外科!$Q$7 -> 3.5817077 | E83: =[1]神经外科!$K$7 -> 7.1404959 | F83: =[1]神经外科!$E$7 -> 6.6186107
A84: 第五顺位疾病名称 | C84: 信息科 | D84: =[1]神经外科!$O$8 -> 脑梗死 | E84: =[1]神经外科!$I$8 -> 脑脊膜良性肿瘤 | F84: =[1]神经外科!$C$8 -> 全身多处严重复合伤
A85: 第五顺位疾病编码 | C85: 信息科 | D85: =[1]神经外科!$N$8 -> I63 | E85: =[1]神经外科!$H$8 -> D32 | F85: =[1]神经外科!$B$8 -> T06
A86: 第五顺位疾病占比 | B86: % | C86: 信息科 | D86: =[1]神经外科!$Q$8 -> 3.357851 | E86: =[1]神经外科!$K$8 -> 3.107438 | F86: =[1]神经外科!$E$8 -> 4.91481
A87: 第一顺位手术名称 | C87: 信息科 | D87: =[2]神经外科!$O$4 -> 脑内血肿清除术 | E87: =[2]神经外科!$I$4 -> 头颈部血管腔内裸弹簧圈栓塞术 | F87: =[2]神经外科!$C$4 -> 头颈部血管腔内裸弹簧圈栓塞术
A88: 第一顺位手术编码 | C88: 信息科 | D88: =[2]神经外科!$N$4 -> 01.39 | E88: =[2]神经外科!$H$4 -> 39.75 | F88: =[2]神经外科!$B$4 -> 39.75
A89: 第一顺位手术占比 | B89: % | C89: 信息科 | D89: =[2]神经外科!$Q$4 -> 12.677596 | E89: =[2]神经外科!$K$4 -> 14.483493 | F89: =[2]神经外科!$E$4 -> 12.588832
A90: 第二顺位手术名称 | C90: 信息科 | D90: =[2]神经外科!$O$5 -> 脑膜切开伴硬脑膜下腔血肿清除术 | E90: =[2]神经外科!$I$5 -> 脑血肿清除术 | F90: =[2]神经外科!$C$5 -> 脑血肿清除术
A91: 第二顺位手术编码 | C91: 信息科 | D91: =[2]神经外科!$N$5 -> 01.31 | E91: =[2]神经外科!$H$5 -> 01.39 | F91: =[2]神经外科!$B$5 -> 01.39
A92: 第二顺位手术占比 | B92: % | C92: 信息科 | D92: =[2]神经外科!$Q$5 -> 9.726776 | E92: =[2]神经外科!$K$5 -> 12.247071 | F92: =[2]神经外科!$E$5 -> 11.675127
A93: 第三顺位手术名称 | C93: 信息科 | D93: =[2]神经外科!$O$6 -> 头皮缝合术 | E93: =[2]神经外科!$I$6 -> 皮肤裂伤清创缝合术(除外胸壁、腹壁） | F93: =[2]神经外科!$C$6 -> 硬脑膜下血肿清除术
A94: 第三顺位手术编码 | C94: 信息科 | D94: =[2]神经外科!$N$6 -> 86.59 | E94: =[2]神经外科!$H$6 -> 86.59 | F94: =[2]神经外科!$B$6 -> 01.31
A95: 第三顺位手术占比 | B95: % | C95: 信息科 | D95: =[2]神经外科!$Q$6 -> 9.3989071 | E95: =[2]神经外科!$K$6 -> 11.182109 | F95: =[2]神经外科!$E$6 -> 10.964467
A96: 第四顺位手术名称 | C96: 信息科 | D96: =[2]神经外科!$O$7 -> 脑病损切除术 | E96: =[2]神经外科!$I$7 -> 脑病损切除术 | F96: =[2]神经外科!$C$7 -> 皮肤裂伤清创缝合术(除外胸壁、腹壁）
A97: 第四顺位手术编码 | C97: 信息科 | D97: =[2]神经外科!$N$7 -> 01.59 | E97: =[2]神经外科!$H$7 -> 01.59 | F97: =[2]神经外科!$B$7 -> 86.59
A98: 第四顺位手术占比 | B98: % | C98: 信息科 | D98: =[2]神经外科!$Q$7 -> 8.4153005 | E98: =[2]神经外科!$K$7 -> 7.3482428 | F98: =[2]神经外科!$E$7 -> 9.5431472
A99: 第五顺位手术名称 | C99: 信息科 | D99: =[2]神经外科!$O$8 -> 经导管颅内动脉瘤弹簧圈栓塞术 | E99: =[2]神经外科!$I$8 -> 头皮病损切除术(伴松解） | F99: =[2]神经外科!$C$8 -> 脑病损切除术
A100: 第五顺位手术编码 | C100: 信息科 | D100: =[2]神经外科!$N$8 -> 39.72 | E100: =[2]神经外科!$H$8 -> 86.30 | F100: =[2]神经外科!$B$8 -> 01.59
...

Sheet 肝胆外科
A1: 数据名 | B1: 计量单位 | C1: 填报部门 | D1: Y2021 | E1: Y2020 | F1: Y2019 | G1: 指标说明 | H1: 计算公式
A2: 出院患者手术占比 | B2: % | C2: 统计室 | D2: 48.231863 | E2: 50.881226 | F2: 49.551857 | G2: 详见三级公立、二级公立国考手册。举例：30%请填写30（不带百分号），而非写成30%，或0.3。下同 | H2: 出院患者手术台次数/同期出院患者总人次数*100
A3: 出院患者微创手术占比 | B3: % | C3: 统计室 | D3: 61.602419 | E3: 57.153614 | F3: 54.349699 | G3: 详见三级公立、二级公立国考手册 | H3: 出院患者微创手术台次数/同期出院患者手术台次数*100
A4: 出院患者四级手术比例 | B4: % | C4: 统计室 | D4: 29.780801 | E4: 26.28012 | F4: 26.442722 | G4: 详见三级公立国考手册 | H4: 出院患者四级手术台次数/同期出院患者手术台次数*100
A5: 出院患者疑难危重病例比例 | B5: % | C5: 统计室 | D5: 99.585 | E5: 99.425 | F5: 97.683333 | G5: 即CD型病例占比 | H5: (疑难病例数+危重病例数)/出院人数*100
A6: 手术患者并发症发生率 | B6: % | C6: 质控科 | D6: 0 | E6: 0 | F6: 0 | G6: 详见国考手册 | H6: 手术患者并发症发生例数/同期出院的手术患者人数*100
A7: I类切口手术部位感染率 | B7: % | C7: 质控科 | D7: 0 | E7: 0.26 | F7: 0 | G7: 详见三级中医、三级公立国考手册 | H7: I类切口手术部位感染人次数/同期I类切口手术台次数*100
A8: 大型医用设备检查阳性率 | B8: % | C8: 医务科 | G8: 详见三级中医、三级公立国考手册 | H8: 大型医用设备检查阳性数/同期大型医用设备检查人次数*100
A9: 低风险组病例死亡率 | B9: % | C9: 质控科 | D9: 0 | E9: 0 | F9: 0 | G9: 详见三级公立、二级公立国考手册 | H9: 低风险组死亡例数/低风险组病例数*100
A10: 医院感染发生率 | B10: % | C10: 院感科 | D10: 1.31 | E10: 1.45 | F10: 1.54 | G10: 等级评审标准细则
A11: 抗菌药物使用强度DDDs | B11: DDD | C11: 药学部 | D11: 61.19 | E11: 62.34 | F11: 171.48 | G11: 详见国考手册 | H11: 住院患者抗菌药物消耗量（累计DDD数）/同期收治患者人天数*100
A12: 门诊患者基本药物处方占比 | B12: % | C12: 药学部 | D12: 69.01 | E12: 41.78 | F12: 45.91 | G12: 详见三级中医、三级公立国考手册 | H12: 门诊使用基本药物人次数/同期门诊诊疗总人次数*100
A13: 住院患者基本药物使用率 | B13: % | C13: 药学部 | D13: 95.61 | E13: 93.62 | F13: 90.38 | G13: 详见三级中医、三级公立国考手册 | H13: 出院患者使用基本药物总人次数/同期出院总人次数*100
A14: 重点监控高值医用耗材收入占比 | B14: % | C14: 设备科 | D14: =(113400+44100)/22637541*100 -> 0.69574695 | E14: =251401/21519099*100 -> 1.1682692 | G14: 详见国考手册 | H14: 重点监控高值医用耗材收入/同期卫生材料收入*100
A15: 平均住院日 | B15: 天 | C15: 统计室 | D15: 9.595 | E15: 10.14 | F15: 10.723333 | G15: 详见二级公立国考手册 | H15: 出院患者占用总床日数/同期出院患者人数
A16: CMI值 | C16: 质控科 | D16: 2.105 | E16: 2.08 | F16: 2.08 | G16: 病例组合指数
A17: DRGs组数 | B17: 组 | C17: 质控科 | D17: 102 | E17: 106 | F17: 65 | G17: 诊断相关分组组数
A18: 核定床位数 | B18: 张 | C18: 统计室 | D18: 65 | E18: 65 | F18: 65 | G18: 等级评审标准细则
A19: 实际开放床位数 | B19: 张 | C19: 统计室 | D19: 73 | E19: 65 | F19: 60 | G19: 等级评审标准细则
A20: 开放床位使用率 | B20: % | C20: 统计室 | D20: 99.32 | E20: 112.28 | F20: 113.07667 | G20: 等级评审标准细则 | H20: 实际占用的总床日数/同期实际开放的总床日数*100
A21: 医师人数与开放床位数比 | C21: 人事科 | D21: =D43/D19 -> 0.20547945 | E21: =E43/E19 -> 0.21538462 | F21: =F43/F19 -> 0.21666667 | G21: 等级评审标准细则，原计量单位为比值（1:X），现改为小数 | H21: 医院执业（助理）医师总数/同期全院实际开放床位数
A22: 护士人数与开放床位数比 | C22: 人事科 | D22: =D44/D19 -> 0.64383562 | E22: =E44/E19 -> 0.56923077 | F22: =F44/F19 -> 0.55 | G22: 等级评审标准细则，原计量单位为比值（1:X），现改为小数 | H22: 医院注册护士总数/同期全院实际开放床位数
A23: 人均医疗服务收入 | B23: 万元 | C23: 财务科 | D23: 27.210687 | E23: 27.232991 | F23: 24.865102 | G23: 按科室人员数人均医疗服务收入
A24: 人均有效收入 | B24: 万元 | C24: 财务科 | D24: 45.988641 | E24: 45.121927 | F24: 41.751459 | G24: 按科室人员数人均有效收入
A25: 床均医疗服务收入 | B25: 万元 | C25: 财务科 | D25: 21.654092 | E25: 24.123281 | F25: 32.987494 | G25: 按开放床位数床均医疗服务收入
A26: 床均有效收入 | B26: 万元 | C26: 财务科 | D26: 36.597469 | E26: 39.969496 | F26: 55.389921 | G26: 按开放床位数床均有效收入
A27: 每名执业医师日均住院工作负担 | B27: 床日 | C27: 财务科 | D27: 4.6518721 | E27: 4.9908023 | F27: 5.2155954 | G27: 详见三级中医、三级公立国考手册 | H27: 全年实际占用总床日数/医院平均执业(助理)医师人数/365
A28: 医疗服务收入占医疗收入比例 | B28: % | C28: 财务科 | D28: 35.029646 | E28: 35.190442 | F28: 33.780934 | G28: 参考国考手册，原指标名为：医疗服务收入（不含药品、耗材、检查检验收入）占医疗收入比例 | H28: 医疗服务收入/医疗收入*100
A29: 医疗收入 | B29: 万元 | C29: 财务科 | D29: 4350.0254 | E29: 4256.3106 | F29: 3901.1663 | H29: 门诊收入+住院收入
A30: 医疗服务收入 | B30: 万元 | C30: 财务科 | D30: 1523.7985 | E30: 1497.8145 | F30: 1317.8504
A31: 有效收入 | B31: 万元 | C31: 财务科 | D31: 2575.3639 | E31: 2481.706 | F31: 2212.8273 | H31: 医疗服务收入+检查检验收入
A32: 医疗直接成本 | B32: 万元 | D32: 2982.02 | E32: 2447.02 | F32: 2111.28
A33: 收支结余率 | B33: % | D33: 20.24 | E33: 10.85 | F33: -0.24
A34: 万元收入能耗占比 | B34: 吨标煤/万元 | C34: 后勤管理科 | G34: 详见国考手册 | H34: 年总能耗/年总收入*10000
A35: 门诊收入占医疗收入比例 | B35: % | C35: 财务科 | D35: 6.8663849 | E35: 5.6825098 | F35: 5.2620872 | G35: 详见三级公立国考手册 | H35: 门诊收入/医疗收入*100
A36: 住院收入占医疗收入比例 | B36: % | C36: 财务科 | D36: 93.133615 | E36: 94.31749 | F36: 94.737913 | G36: 详见三级公立国考手册 | H36: 住院收入/医疗收入*100
A37: 医疗收入增幅 | B37: % | C37: 财务科 | D37: 2.2017829 | E37: 9.1035435 | F37: 22.140851 | G37: 详见国考手册 | H37: （本年度医疗收入－上一年度医疗收入）/上一年度医疗收入*100
A38: 门诊次均费用增幅 | B38: % | C38: 财务科 | D38: 0.99817345 | E38: 1.673963 | F38: 3.0881782 | G38: 详见国考手册 | H38: （本年度门诊患者次均医药费用－上一年度门诊患者次均医药费用）/上一年度门诊患者次均医药费用*100
A39: 住院次均费用增幅 | B39: % | C39: 财务科 | D39: -4.518548 | E39: -35.240968 | F39: 62.502239 | G39: 详见国考手册 | H39: （本年度出院患者次均医药费用－上一年度出院患者次均医药费用）/上一年度出院患者次均医药费用*100
A40: 门诊次均药品费用增幅 | B40: % | C40: 财务科 | D40: 10.112721 | E40: 9.343416 | F40: 10.360037 | G40: 详见国考手册 | H40: （本年度门诊患者次均药品费用－上一年度门诊患者次均药品费用）/上一年度门诊患者次均药品费用*100
A41: 住院次均药品费用增幅 | B41: % | C41: 财务科 | D41: -6.3254158 | E41: -42.357882 | F41: 62.717843 | G41: 详见国考手册 | H41: （本年度出院患者次均药品费用－上一年度出院患者次均药品费用）/上一年度出院患者次均药品费用*100
A42: 医护比 | C42: 人事科 | D42: 0.32 | E42: 0.38 | F42: 0.39 | G42: 参考国考手册，原计量单位为比值（1:X），现改为小数 | H42: 医院注册医师总数/全院同期注册护士总数
A43: 医师人数 | B43: 人 | C43: 人事科 | D43: 15 | E43: 14 | F43: 13 | G43: 详见国考手册中，医护比定义
A44: 护士人数 | B44: 人 | C44: 人事科 | D44: 47 | E44: 37 | F44: 33 | G44: 详见国考手册中，医护比定义
A45: 医师高级职称占比 | B45: % | C45: 人事科 | D45: 46.67 | E45: 50 | F45: 38.46 | H45: (正高职称医师人数+副高职称医师人数)/医师人数*100
A46: 医师博士占比 | B46: % | C46: 人事科 | D46: 20 | E46: 21.43 | F46: 23.08 | H46: 博士医师人数/医师人数*100
A47: 医师硕士占比 | B47: % | C47: 人事科 | D47: 66.67 | E47: 64.29 | F47: 61.54 | H47: 硕士医师人数/医师人数*100
A48: 发表教学文章数与卫生技术人员数之比 | C48: 科教科 | D48: 0 | E48: 0 | F48: 0 | G48: 参考三级中医、三级公立国考手册，医院承担培养医学人才的工作成效的构成元素。原计量单位为比值（1:X），现改为小数 | H48: 本年度发表的教学文章数/同期卫生技术人员总数
A49: 省部级及以上教育教学课题数与卫生技术人员数之比 | C49: 科教科 | D49: 0 | E49: 0 | F49: 0 | G49: 参考三级中医、三级公立国考手册，医院承担培养医学人才的工作成效的构成元素。本指标为延伸指标。原计量单位为比值（1:X），现改为小数 | H49: 本年度获得的省部级及以上教育教学课题数/同期卫生技术人员总数
A50: 国家级继续医学教育项目数与卫生技术人员数之比 | C50: 科教科 | D50: 0 | E50: 0 | F50: 0 | G50: 参考三级中医、三级公立国考手册，医院承担培养医学人才的工作成效的构成元素。本指标为延伸指标。原计量单位为比值（1:X），现改为小数 | H50: 本年度举办的国家级继续医学教育项目数/同期卫生技术人员总数
A51: 每百名卫生技术人员科研项目经费 | B51: 元 | C51: 科教科 | D51: 32258.065 | E51: 0 | F51: 21739.13 | G51: 详见三级中医、三级公立国考手册 | H51: 本年度科研项目立项经费总金额/同期卫生技术人员总数*100
A52: 每百名卫生技术人员科研成果转化金额 | B52: 元 | C52: 科教科 | D52: 0 | E52: 0 | F52: 0 | G52: 详见三级公立国考手册 | H52: 本年度科技成果转化总金额/同期医院卫生技术人员总数*100
A53: 医师人均国家自然科学基金项目数量 | B53: 项 | C53: 科教科 | D53: 0 | E53: 0 | F53: 0 | G53: 说明：本年度成功立项的项目数量。要求本科室为主研单位
A54: 医师人均SCI文章数量 | B54: 篇 | C54: 科教科 | D54: 0 | E54: 0 | F54: 0 | G54: 说明：本年度成功发表的论文，要求第一作者或通讯作者为本院员工
A55: SCI平均影响因子 | B55: 分 | C55: 科教科 | D55: 0 | E55: 0 | F55: 0 | G55: 说明：本年度成功发表的论文，要求第一作者或通讯作者为本院员工
A56: 博士研究生导师占比 | B56: % | C56: 科教科 | D56: 0 | E56: 0 | F56: 0 | H56: 博士研究生导师人数/同期医师总数*100
A57: 硕士研究生导师占比 | B57: % | C57: 科教科 | D57: 20 | E57: 21.42 | F57: 0 | H57: 硕士研究生导师人数/同期医师总数*100
A58: 外省住院患者占比 | B58: % | C58: 统计室 | D58: =AVERAGE(D59:D60) -> 0.76558513 | E58: =AVERAGE(E59:E60) -> 1.7049808 | F58: 5.570118 | H58: 外省住院患者人数/同期出院患者人次数*100
A59: 非医嘱离院率 | B59: % | C59: 统计室 | D59: 1.5311703 | E59: 3.4099617 | F59: 2.7742211 | H59: 非医嘱离院人次/同期出院患者总人次*100
A60: 是否为教育部或科技部重点学科或重点实验室 | B60: 分 | C60: 科教科 | D60: 0 | E60: 0 | F60: 0 | G60: 是填1,否填0
A61: 是否为国家卫健委临床重点专科 | B61: 分 | C61: 科教科 | D61: 0 | E61: 0 | F61: 0 | G61: 是填1,否填0
A62: 是否为国家中医药局重点专科 | B62: 分 | C62: 科教科 | D62: 0 | E62: 0 | F62: 0 | G62: 是填1,否填0
A63: 是否为省教育厅或科技厅重点学科或重点实验室 | B63: 分 | C63: 科教科 | D63: 0 | E63: 0 | F63: 0 | G63: 是填1,否填0
A64: 是否为省卫健委重点专科 | B64: 分 | C64: 科教科 | D64: 1 | E64: 1 | F64: 1 | G64: 是填1,否填0
A65: 是否为省中医药局重点专科 | B65: 分 | C65: 科教科 | D65: 0 | E65: 0 | F65: 0 | G65: 是填1,否填0
A66: 是否为地市级教育局或科技局重点学科或重点实验室 | B66: 分 | C66: 科教科 | D66: 0 | E66: 0 | F66: 0 | G66: 是填1,否填0
A67: 是否为地市级卫健委重点专科 | B67: 分 | C67: 科教科 | D67: 1 | E67: 1 | F67: 1 | G67: 是填1,否填0
A68: 是否为地市级中医药局重点专科 | B68: 分 | C68: 科教科 | D68: 0 | E68: 0 | F68: 0 | G68: 是填1,否填0
A69: 是否为县级教育局或科技局重点学科或重点实验室 | B69: 分 | C69: 科教科 | D69: 0 | E69: 0 | F69: 0 | G69: 是填1,否填0
A70: 是否为县级卫健委重点专科 | B70: 分 | C70: 科教科 | D70: 0 | E70: 0 | F70: 0 | G70: 是填1,否填0
A71: 是否为县级中医药局重点专科 | B71: 分 | C71: 科教科 | D71: 0 | E71: 0 | F71: 0 | G71: 是填1,否填0
A72: 第一顺位疾病名称 | C72: 信息科 | D72: =[1]肝胆外科!$O$4 -> 胆石症（胆囊结石、胆管结石） | E72: =[1]肝胆外科!$I$4 -> 胆石症（胆囊结石、胆管结石） | F72: =[1]肝胆外科!$C$4 -> 胆石症（胆囊结石、胆管结石）
A73: 第一顺位疾病编码 | C73: 信息科 | D73: =[1]肝胆外科!$N$4 -> K80 | E73: =[1]肝胆外科!$H$4 -> K80 | F73: =[1]肝胆外科!$B$4 -> K80
A74: 第一顺位疾病占比 | B74: % | C74: 信息科 | D74: =[1]肝胆外科!$Q$4 -> 30.404666 | E74: =[1]肝胆外科!$K$4 -> 32.796935 | F74: =[1]肝胆外科!$E$4 -> 31.199317
A75: 第二顺位疾病名称 | C75: 信息科 | D75: =[1]肝胆外科!$O$5 -> 肝和肝内胆管恶性肿瘤 | E75: =[1]肝胆外科!$I$5 -> 肝和肝内胆管恶性肿瘤 | F75: =[1]肝胆外科!$C$5 -> 肝和肝内胆管恶性肿瘤
A76: 第二顺位疾病编码 | C76: 信息科 | D76: =[1]肝胆外科!$N$5 -> C22 | E76: =[1]肝胆外科!$H$5 -> C22 | F76: =[1]肝胆外科!$B$5 -> C22
A77: 第二顺位疾病占比 | B77: % | C77: 信息科 | D77: =[1]肝胆外科!$Q$5 -> 23.076923 | E77: =[1]肝胆外科!$K$5 -> 22.375479 | F77: =[1]肝胆外科!$E$5 -> 23.132736
A78: 第三顺位疾病名称 | C78: 信息科 | D78: =[1]肝胆外科!$O$6 -> 为肿瘤化学治疗疗程 | E78: =[1]肝胆外科!$I$6 -> 为肿瘤化学治疗疗程 | F78: =[1]肝胆外科!$C$6 -> 为肿瘤化学治疗疗程
A79: 第三顺位疾病编码 | C79: 信息科 | D79: =[1]肝胆外科!$N$6 -> Z51.1 | E79: =[1]肝胆外科!$H$6 -> Z51.1 | F79: =[1]肝胆外科!$B$6 -> Z51.1
A80: 第三顺位疾病占比 | B80: % | C80: 信息科 | D80: =[1]肝胆外科!$Q$6 -> 8.6766314 | E80: =[1]肝胆外科!$K$6 -> 6.2452107 | F80: =[1]肝胆外科!$E$6 -> 4.9509176
A81: 第四顺位疾病名称 | C81: 信息科 | D81: =[1]肝胆外科!$O$7 -> 急性胰腺炎 | E81: =[1]肝胆外科!$I$7 -> 胆道疾病 | F81: =[1]肝胆外科!$C$7 -> 急性胰腺炎
A82: 第四顺位疾病编码 | C82: 信息科 | D82: =[1]肝胆外科!$N$7 -> K85 | E82: =[1]肝胆外科!$H$7 -> K83 | F82: =[1]肝胆外科!$B$7 -> K85
A83: 第四顺位疾病占比 | B83: % | C83: 信息科 | D83: =[1]肝胆外科!$Q$7 -> 3.5727306 | E83: =[1]肝胆外科!$K$7 -> 2.4521073 | F83: =[1]肝胆外科!$E$7 -> 3.9692702
A84: 第五顺位疾病名称 | C84: 信息科 | D84: =[1]肝胆外科!$O$8 -> 胰恶性肿瘤 | E84: =[1]肝胆外科!$I$8 -> 胰恶性肿瘤 | F84: =[1]肝胆外科!$C$8 -> 肝脓肿
A85: 第五顺位疾病编码 | C85: 信息科 | D85: =[1]肝胆外科!$N$8 -> C25 | E85: =[1]肝胆外科!$H$8 -> C25 | F85: =[1]肝胆外科!$B$8 -> K75.0
A86: 第五顺位疾病占比 | B86: % | C86: 信息科 | D86: =[1]肝胆外科!$Q$8 -> 2.7342326 | E86: =[1]肝胆外科!$K$8 -> 2.2988506 | F86: =[1]肝胆外科!$E$8 -> 1.9206146
A87: 第一顺位手术名称 | C87: 信息科 | D87: =[2]肝胆外科!$O$4 -> 腹腔镜下胆囊切除术 | E87: =[2]肝胆外科!$I$4 -> 胆囊切除术，经腹腔镜 | F87: =[2]肝胆外科!$C$4 -> 胆囊切除术，经腹腔镜
A88: 第一顺位手术编码 | C88: 信息科 | D88: =[2]肝胆外科!$N$4 -> 51.23 | E88: =[2]肝胆外科!$H$4 -> 51.23 | F88: =[2]肝胆外科!$B$4 -> 51.23
A89: 第一顺位手术占比 | B89: % | C89: 信息科 | D89: =[2]肝胆外科!$Q$4 -> 30.083144 | E89: =[2]肝胆外科!$K$4 -> 28.463855 | F89: =[2]肝胆外科!$E$4 -> 31.438415
A90: 第二顺位手术名称 | C90: 信息科 | D90: =[2]肝胆外科!$O$5 -> 经导管肝动脉栓塞术 | E90: =[2]肝胆外科!$I$5 -> 肝动脉腔内栓塞术 | F90: =[2]肝胆外科!$C$5 -> 肝动脉腔内栓塞术
A91: 第二顺位手术编码 | C91: 信息科 | D91: =[2]肝胆外科!$N$5 -> 39.79 | E91: =[2]肝胆外科!$H$5 -> 39.79 | F91: =[2]肝胆外科!$B$5 -> 39.79
A92: 第二顺位手术占比 | B92: % | C92: 信息科 | D92: =[2]肝胆外科!$Q$5 -> 22.071051 | E92: =[2]肝胆外科!$K$5 -> 22.891566 | F92: =[2]肝胆外科!$E$5 -> 21.016365
A93: 第三顺位手术名称 | C93: 信息科 | D93: =[2]肝胆外科!$O$6 -> 腹腔镜下肝叶切除术 | E93: =[2]肝胆外科!$I$6 -> 胆总管切开取石伴T管引流术，经腹腔镜 | F93: =[2]肝胆外科!$C$6 -> 肝叶切除术（肝段切除术）
A94: 第三顺位手术编码 | C94: 信息科 | D94: =[2]肝胆外科!$N$6 -> 50.3x | E94: =[2]肝胆外科!$H$6 -> 51.88 | F94: =[2]肝胆外科!$B$6 -> 50.30
A95: 第三顺位手术占比 | B95: % | C95: 信息科 | D95: =[2]肝胆外科!$Q$6 -> 11.942555 | E95: =[2]肝胆外科!$K$6 -> 14.006024 | F95: =[2]肝胆外科!$E$6 -> 13.178295
A96: 第四顺位手术名称 | C96: 信息科 | D96: =[2]肝胆外科!$O$7 -> 腹腔镜下胆总管切开取石术 | E96: =[2]肝胆外科!$I$7 -> 肝叶切除术（肝段切除术） | F96: =[2]肝胆外科!$C$7 -> 胆总管切开取石伴T管引流术，经腹腔镜
A97: 第四顺位手术编码 | C97: 信息科 | D97: =[2]肝胆外科!$N$7 -> 51.88 | E97: =[2]肝胆外科!$H$7 -> 50.30 | F97: =[2]肝胆外科!$B$7 -> 51.88
A98: 第四顺位手术占比 | B98: % | C98: 信息科 | D98: =[2]肝胆外科!$Q$7 -> 11.48904 | E98: =[2]肝胆外科!$K$7 -> 11.972892 | F98: =[2]肝胆外科!$E$7 -> 10.077519
A99: 第五顺位手术名称 | C99: 信息科 | D99: =[2]肝胆外科!$O$8 -> 腹腔镜下肝部分切除术 | E99: =[2]肝胆外科!$I$8 -> 胆总管切开取石T管引流术 | F99: =[2]肝胆外科!$C$8 -> 胆总管切开取石T管引流术
A100: 第五顺位手术编码 | C100: 信息科 | D100: =[2]肝胆外科!$N$8 -> 50.22 | E100: =[2]肝胆外科!$H$8 -> 51.41 | F100: =[2]肝胆外科!$B$8 -> 51.41
...

Sheet 泌尿外科
A1: 数据名 | B1: 计量单位 | C1: 填报部门 | D1: Y2021 | E1: Y2020 | F1: Y2019 | G1: 指标说明 | H1: 计算公式
A2: 出院患者手术占比 | B2: % | C2: 统计室 | D2: 72.116955 | E2: 66.586405 | F2: 58.817685 | G2: 详见三级公立、二级公立国考手册。举例：30%请填写30（不带百分号），而非写成30%，或0.3。下同 | H2: 出院患者手术台次数/同期出院患者总人次数*100
A3: 出院患者微创手术占比 | B3: % | C3: 统计室 | D3: 38.437146 | E3: 45.785814 | F3: 48.902027 | G3: 详见三级公立、二级公立国考手册 | H3: 出院患者微创手术台次数/同期出院患者手术台次数*100
A4: 出院患者四级手术比例 | B4: % | C4: 统计室 | D4: 10.486976 | E4: 7.6216968 | F4: 6.5596847 | G4: 详见三级公立国考手册 | H4: 出院患者四级手术台次数/同期出院患者手术台次数*100
A5: 出院患者疑难危重病例比例 | B5: % | C5: 统计室 | D5: 91.13 | E5: 93.71 | F5: 91.525 | G5: 即CD型病例占比 | H5: (疑难病例数+危重病例数)/出院人数*100
A6: 手术患者并发症发生率 | B6: % | C6: 质控科 | D6: 0 | E6: 0 | F6: 0 | G6: 详见国考手册 | H6: 手术患者并发症发生例数/同期出院的手术患者人数*100
A7: I类切口手术部位感染率 | B7: % | C7: 质控科 | D7: 0 | E7: 0 | F7: 0 | G7: 详见三级中医、三级公立国考手册 | H7: I类切口手术部位感染人次数/同期I类切口手术台次数*100
A8: 大型医用设备检查阳性率 | B8: % | C8: 医务科 | G8: 详见三级中医、三级公立国考手册 | H8: 大型医用设备检查阳性数/同期大型医用设备检查人次数*100
A9: 低风险组病例死亡率 | B9: % | C9: 质控科 | D9: 0 | E9: 0 | F9: 0 | G9: 详见三级公立、二级公立国考手册 | H9: 低风险组死亡例数/低风险组病例数*100
A10: 医院感染发生率 | B10: % | C10: 院感科 | D10: 0.34 | E10: 0.28 | F10: 0.37 | G10: 等级评审标准细则
A11: 抗菌药物使用强度DDDs | B11: DDD | C11: 药学部 | D11: 90.28 | E11: 84.94 | F11: 79.91 | G11: 详见国考手册 | H11: 住院患者抗菌药物消耗量（累计DDD数）/同期收治患者人天数*100
A12: 门诊患者基本药物处方占比 | B12: % | C12: 药学部 | D12: 69.11 | E12: 37.96 | F12: 48.28 | G12: 详见三级中医、三级公立国考手册 | H12: 门诊使用基本药物人次数/同期门诊诊疗总人次数*100
A13: 住院患者基本药物使用率 | B13: % | C13: 药学部 | D13: 97.13 | E13: 93.91 | F13: 86.08 | G13: 详见三级中医、三级公立国考手册 | H13: 出院患者使用基本药物总人次数/同期出院总人次数*100
A14: 重点监控高值医用耗材收入占比 | B14: % | C14: 设备科 | D14: =(145720+7500)/31522709*100 -> 0.48606229 | E14: 0 | F14: 0 | G14: 详见国考手册 | H14: 重点监控高值医用耗材收入/同期卫生材料收入*100
A15: 平均住院日 | B15: 天 | C15: 统计室 | D15: 6.085 | E15: 7.27 | F15: 7.895 | G15: 详见二级公立国考手册 | H15: 出院患者占用总床日数/同期出院患者人数
A16: CMI值 | C16: 质控科 | D16: 1.275 | E16: 1.33 | F16: 1.315 | G16: 病例组合指数
A17: DRGs组数 | B17: 组 | C17: 质控科 | D17: 104 | E17: 95 | F17: 93 | G17: 诊断相关分组组数
A18: 核定床位数 | B18: 张 | C18: 统计室 | D18: 112 | E18: 112 | F18: 112 | G18: 等级评审标准细则
A19: 实际开放床位数 | B19: 张 | C19: 统计室 | D19: 117 | E19: 112 | F19: 120 | G19: 等级评审标准细则
A20: 开放床位使用率 | B20: % | C20: 统计室 | D20: 91.13 | E20: 89.815 | F20: 108.125 | G20: 等级评审标准细则 | H20: 实际占用的总床日数/同期实际开放的总床日数*100
A21: 医师人数与开放床位数比 | C21: 人事科 | D21: =D43/D19 -> 0.16239316 | E21: =E43/E19 -> 0.16964286 | F21: =F43/F19 -> 0.16666667 | G21: 等级评审标准细则，原计量单位为比值（1:X），现改为小数 | H21: 医院执业（助理）医师总数/同期全院实际开放床位数
A22: 护士人数与开放床位数比 | C22: 人事科 | D22: =D44/D19 -> 0.46153846 | E22: =E44/E19 -> 0.5 | F22: =F44/F19 -> 0.475 | G22: 等级评审标准细则，原计量单位为比值（1:X），现改为小数 | H22: 医院注册护士总数/同期全院实际开放床位数
A23: 人均医疗服务收入 | B23: 万元 | C23: 财务科 | D23: 46.982937 | E23: 43.47441 | F23: 43.694543 | G23: 按科室人员数人均医疗服务收入
A24: 人均有效收入 | B24: 万元 | C24: 财务科 | D24: 74.069871 | E24: 65.985213 | F24: 67.417405 | G24: 按科室人员数人均有效收入
A25: 床均医疗服务收入 | B25: 万元 | C25: 财务科 | D25: 30.952698 | E25: 28.69475 | F25: 28.401453 | G25: 按开放床位数床均医疗服务收入
A26: 床均有效收入 | B26: 万元 | C26: 财务科 | D26: 48.797766 | E26: 43.552729 | F26: 43.821313 | G26: 按开放床位数床均有效收入
A27: 每名执业医师日均住院工作负担 | B27: 床日 | C27: 财务科 | D27: 5.1346792 | E27: 5.5299207 | F27: 6.4873973 | G27: 详见三级中医、三级公立国考手册 | H27: 全年实际占用总床日数/医院平均执业(助理)医师人数/365
A28: 医疗服务收入占医疗收入比例 | B28: % | C28: 财务科 | D28: 46.670287 | E28: 47.589538 | F28: 44.241647 | G28: 参考国考手册，原指标名为：医疗服务收入（不含药品、耗材、检查检验收入）占医疗收入比例 | H28: 医疗服务收入/医疗收入*100
A29: 医疗收入 | B29: 万元 | C29: 财务科 | D29: 7650.9135 | E29: 7034.1712 | F29: 7703.5432 | H29: 门诊收入+住院收入
A30: 医疗服务收入 | B30: 万元 | C30: 财务科 | D30: 3570.7032 | E30: 3347.5296 | F30: 3408.1744
A31: 有效收入 | B31: 万元 | C31: 财务科 | D31: 5629.3102 | E31: 5080.8614 | F31: 5258.5576 | H31: 医疗服务收入+检查检验收入
A32: 医疗直接成本 | B32: 万元 | D32: 4393.21 | E32: 3725.83 | F32: 4112.7
A33: 收支结余率 | B33: % | D33: 18.17 | E33: 14.16 | F33: 17.67
A34: 万元收入能耗占比 | B34: 吨标煤/万元 | C34: 后勤管理科 | G34: 详见国考手册 | H34: 年总能耗/年总收入*10000
A35: 门诊收入占医疗收入比例 | B35: % | C35: 财务科 | D35: 18.195411 | E35: 15.307517 | F35: 10.253409 | G35: 详见三级公立国考手册 | H35: 门诊收入/医疗收入*100
A36: 住院收入占医疗收入比例 | B36: % | C36: 财务科 | D36: 81.804589 | E36: 84.692483 | F36: 89.746591 | G36: 详见三级公立国考手册 | H36: 住院收入/医疗收入*100
A37: 医疗收入增幅 | B37: % | C37: 财务科 | D37: 8.767803 | E37: -8.6891451 | F37: 5.7525215 | G37: 详见国考手册 | H37: （本年度医疗收入－上一年度医疗收入）/上一年度医疗收入*100
A38: 门诊次均费用增幅 | B38: % | C38: 财务科 | D38: 13.298318 | E38: 36.411286 | F38: -2.2918744 | G38: 详见国考手册 | H38: （本年度门诊患者次均医药费用－上一年度门诊患者次均医药费用）/上一年度门诊患者次均医药费用*100
A39: 住院次均费用增幅 | B39: % | C39: 财务科 | D39: 17.45137 | E39: -23.054087 | F39: -0.042197081 | G39: 详见国考手册 | H39: （本年度出院患者次均医药费用－上一年度出院患者次均医药费用）/上一年度出院患者次均医药费用*100
A40: 门诊次均药品费用增幅 | B40: % | C40: 财务科 | D40: 24.098983 | E40: 117.85483 | F40: -8.8789392 | G40: 详见国考手册 | H40: （本年度门诊患者次均药品费用－上一年度门诊患者次均药品费用）/上一年度门诊患者次均药品费用*100
A41: 住院次均药品费用增幅 | B41: % | C41: 财务科 | D41: -2.5053487 | E41: -43.133091 | F41: -3.7831585 | G41: 详见国考手册 | H41: （本年度出院患者次均药品费用－上一年度出院患者次均药品费用）/上一年度出院患者次均药品费用*100
A42: 医护比 | C42: 人事科 | D42: 0.35 | E42: 0.34 | F42: 0.35 | G42: 参考国考手册，原计量单位为比值（1:X），现改为小数 | H42: 医院注册医师总数/全院同期注册护士总数
A43: 医师人数 | B43: 人 | C43: 人事科 | D43: 19 | E43: 19 | F43: 20 | G43: 详见国考手册中，医护比定义
A44: 护士人数 | B44: 人 | C44: 人事科 | D44: 54 | E44: 56 | F44: 57 | G44: 详见国考手册中，医护比定义
A45: 医师高级职称占比 | B45: % | C45: 人事科 | D45: 47.37 | E45: 47.37 | F45: 40 | H45: (正高职称医师人数+副高职称医师人数)/医师人数*100
A46: 医师博士占比 | B46: % | C46: 人事科 | D46: 5.26 | E46: 10.53 | F46: 10 | H46: 博士医师人数/医师人数*100
A47: 医师硕士占比 | B47: % | C47: 人事科 | D47: 73.68 | E47: 68.42 | F47: 65 | H47: 硕士医师人数/医师人数*100
A48: 发表教学文章数与卫生技术人员数之比 | C48: 科教科 | D48: 0 | E48: 0 | F48: 0 | G48: 参考三级中医、三级公立国考手册，医院承担培养医学人才的工作成效的构成元素。原计量单位为比值（1:X），现改为小数 | H48: 本年度发表的教学文章数/同期卫生技术人员总数
A49: 省部级及以上教育教学课题数与卫生技术人员数之比 | C49: 科教科 | D49: 0 | E49: 0 | F49: 0 | G49: 参考三级中医、三级公立国考手册，医院承担培养医学人才的工作成效的构成元素。本指标为延伸指标。原计量单位为比值（1:X），现改为小数 | H49: 本年度获得的省部级及以上教育教学课题数/同期卫生技术人员总数
A50: 国家级继续医学教育项目数与卫生技术人员数之比 | C50: 科教科 | D50: 0.013699 | E50: 0 | F50: 0.012987 | G50: 参考三级中医、三级公立国考手册，医院承担培养医学人才的工作成效的构成元素。本指标为延伸指标。原计量单位为比值（1:X），现改为小数 | H50: 本年度举办的国家级继续医学教育项目数/同期卫生技术人员总数
A51: 每百名卫生技术人员科研项目经费 | B51: 元 | C51: 科教科 | D51: 41095.89 | E51: 0 | F51: 12987.013 | G51: 详见三级中医、三级公立国考手册 | H51: 本年度科研项目立项经费总金额/同期卫生技术人员总数*100
A52: 每百名卫生技术人员科研成果转化金额 | B52: 元 | C52: 科教科 | D52: 0 | E52: 0 | F52: 0 | G52: 详见三级公立国考手册 | H52: 本年度科技成果转化总金额/同期医院卫生技术人员总数*100
A53: 医师人均国家自然科学基金项目数量 | B53: 项 | C53: 科教科 | D53: 0 | E53: 0 | F53: 0 | G53: 说明：本年度成功立项的项目数量。要求本科室为主研单位
A54: 医师人均SCI文章数量 | B54: 篇 | C54: 科教科 | D54: 0.053 | E54: 0 | F54: 0 | G54: 说明：本年度成功发表的论文，要求第一作者或通讯作者为本院员工
A55: SCI平均影响因子 | B55: 分 | C55: 科教科 | D55: 0.172 | E55: 0 | F55: 0 | G55: 说明：本年度成功发表的论文，要求第一作者或通讯作者为本院员工
A56: 博士研究生导师占比 | B56: % | C56: 科教科 | D56: 0 | E56: 0 | F56: 0 | H56: 博士研究生导师人数/同期医师总数*100
A57: 硕士研究生导师占比 | B57: % | C57: 科教科 | D57: 5.26 | E57: 5.26 | F57: 5 | H57: 硕士研究生导师人数/同期医师总数*100
A58: 外省住院患者占比 | B58: % | C58: 统计室 | D58: 3.3563076 | E58: 3.4077203 | F58: 3.4761727 | H58: 外省住院患者人数/同期出院患者人次数*100
A59: 非医嘱离院率 | B59: % | C59: 统计室 | D59: 1.04541 | E59: 1.7040193 | F59: 1.8214936 | H59: 非医嘱离院人次/同期出院患者总人次*100
A60: 是否为教育部或科技部重点学科或重点实验室 | B60: 分 | C60: 科教科 | D60: 0 | E60: 0 | F60: 0 | G60: 是填1,否填0
A61: 是否为国家卫健委临床重点专科 | B61: 分 | C61: 科教科 | D61: 0 | E61: 0 | F61: 0 | G61: 是填1,否填0
A62: 是否为国家中医药局重点专科 | B62: 分 | C62: 科教科 | D62: 0 | E62: 0 | F62: 0 | G62: 是填1,否填0
A63: 是否为省教育厅或科技厅重点学科或重点实验室 | B63: 分 | C63: 科教科 | D63: 0 | E63: 0 | F63: 0 | G63: 是填1,否填0
A64: 是否为省卫健委重点专科 | B64: 分 | C64: 科教科 | D64: 0 | E64: 0 | F64: 0 | G64: 是填1,否填0
A65: 是否为省中医药局重点专科 | B65: 分 | C65: 科教科 | D65: 0 | E65: 0 | F65: 0 | G65: 是填1,否填0
A66: 是否为地市级教育局或科技局重点学科或重点实验室 | B66: 分 | C66: 科教科 | D66: 0 | E66: 0 | F66: 0 | G66: 是填1,否填0
A67: 是否为地市级卫健委重点专科 | B67: 分 | C67: 科教科 | D67: 1 | E67: 1 | F67: 1 | G67: 是填1,否填0
A68: 是否为地市级中医药局重点专科 | B68: 分 | C68: 科教科 | D68: 0 | E68: 0 | F68: 0 | G68: 是填1,否填0
A69: 是否为县级教育局或科技局重点学科或重点实验室 | B69: 分 | C69: 科教科 | D69: 0 | E69: 0 | F69: 0 | G69: 是填1,否填0
A70: 是否为县级卫健委重点专科 | B70: 分 | C70: 科教科 | D70: 0 | E70: 0 | F70: 0 | G70: 是填1,否填0
A71: 是否为县级中医药局重点专科 | B71: 分 | C71: 科教科 | D71: 0 | E71: 0 | F71: 0 | G71: 是填1,否填0
A72: 第一顺位疾病名称 | C72: 信息科 | D72: =[1]泌尿外科!$O$4 -> 肾结石伴有积水和感染 | E72: =[1]泌尿外科!$I$4 -> 肾结石伴有积水和感染 | F72: =[1]泌尿外科!$C$4 -> 肾结石伴有积水和感染
A73: 第一顺位疾病编码 | C73: 信息科 | D73: =[1]泌尿外科!$N$4 -> N13.2/N13.6 | E73: =[1]泌尿外科!$H$4 -> N13.2/N13.6 | F73: =[1]泌尿外科!$B$4 -> N13.2/N13.6
A74: 第一顺位疾病占比 | B74: % | C74: 信息科 | D74: =[1]泌尿外科!$Q$4 -> 22.623326 | E74: =[1]泌尿外科!$K$4 -> 25.652899 | F74: =[1]泌尿外科!$E$4 -> 32.124524
A75: 第二顺位疾病名称 | C75: 信息科 | D75: =[1]泌尿外科!$O$5 -> 前列腺增生 | E75: =[1]泌尿外科!$I$5 -> 前列腺增生 | F75: =[1]泌尿外科!$C$5 -> 前列腺癌内分泌治疗
A76: 第二顺位疾病编码 | C76: 信息科 | D76: =[1]泌尿外科!$N$5 -> N40.x | E76: =[1]泌尿外科!$H$5 -> N40.x | F76: =[1]泌尿外科!$B$5 -> Z51.8
A77: 第二顺位疾病占比 | B77: % | C77: 信息科 | D77: =[1]泌尿外科!$Q$5 -> 8.8696504 | E77: =[1]泌尿外科!$K$5 -> 8.0570476 | F77: =[1]泌尿外科!$E$5 -> 9.0743501
A78: 第三顺位疾病名称 | C78: 信息科 | D78: =[1]泌尿外科!$O$6 -> 前列腺恶性肿瘤 | E78: =[1]泌尿外科!$I$6 -> 前列腺癌内分泌治疗 | F78: =[1]泌尿外科!$C$6 -> 前列腺增生
A79: 第三顺位疾病编码 | C79: 信息科 | D79: =[1]泌尿外科!$N$6 -> C61.x | E79: =[1]泌尿外科!$H$6 -> Z51.8 | F79: =[1]泌尿外科!$B$6 -> N40.x
A80: 第三顺位疾病占比 | B80: % | C80: 信息科 | D80: =[1]泌尿外科!$Q$6 -> 3.5772623 | E80: =[1]泌尿外科!$K$6 -> 4.0748287 | F80: =[1]泌尿外科!$E$6 -> 8.3623116
A81: 第四顺位疾病名称 | C81: 信息科 | D81: =[1]泌尿外科!$O$7 -> 膀胱结石 | E81: =[1]泌尿外科!$I$7 -> 前列腺恶性肿瘤 | F81: =[1]泌尿外科!$C$7 -> 膀胱结石
A82: 第四顺位疾病编码 | C82: 信息科 | D82: =[1]泌尿外科!$N$7 -> N21.0 | E82: =[1]泌尿外科!$H$7 -> C61.x | F82: =[1]泌尿外科!$B$7 -> N21.0
A83: 第四顺位疾病占比 | B83: % | C83: 信息科 | D83: =[1]泌尿外科!$Q$7 -> 3.1198955 | E83: =[1]泌尿外科!$K$7 -> 3.0005557 | F83: =[1]泌尿外科!$E$7 -> 2.997185
A84: 第五顺位疾病名称 | C84: 信息科 | D84: =[1]泌尿外科!$O$8 -> 肾结石 | E84: =[1]泌尿外科!$I$8 -> 膀胱结石 | F84: =[1]泌尿外科!$C$8 -> 前列腺恶性肿瘤
A85: 第五顺位疾病编码 | C85: 信息科 | D85: =[1]泌尿外科!$N$8 -> N20.0 | E85: =[1]泌尿外科!$H$8 -> N21.0 | F85: =[1]泌尿外科!$B$8 -> C61.x
A86: 第五顺位疾病占比 | B86: % | C86: 信息科 | D86: =[1]泌尿外科!$Q$8 -> 1.8621366 | E86: =[1]泌尿外科!$K$8 -> 2.7782923 | F86: =[1]泌尿外科!$E$8 -> 2.4010598
A87: 第一顺位手术名称 | C87: 信息科 | D87: =[2]泌尿外科!$O$4 -> 经皮肾镜气压弹道碎石术 | E87: =[2]泌尿外科!$I$4 -> 肾造口结石去除术，伴碎石，经肾镜(PCNL) | F87: =[2]泌尿外科!$C$4 -> 肾造口结石去除术，伴碎石，经肾镜(PCNL)
A88: 第一顺位手术编码 | C88: 信息科 | D88: =[2]泌尿外科!$N$4 -> 55.04 | E88: =[2]泌尿外科!$H$4 -> 55.04 | F88: =[2]泌尿外科!$B$4 -> 55.04
A89: 第一顺位手术占比 | B89: % | C89: 信息科 | D89: =[2]泌尿外科!$Q$4 -> 29.784824 | E89: =[2]泌尿外科!$K$4 -> 36.801113 | F89: =[2]泌尿外科!$E$4 -> 40.962838
A90: 第二顺位手术名称 | C90: 信息科 | D90: =[2]泌尿外科!$O$5 -> 经尿道输尿管镜输尿管气压弹道碎石取石术 | E90: =[2]泌尿外科!$I$5 -> 输尿管结石去除术，经输尿管镜 | F90: =[2]泌尿外科!$C$5 -> 输尿管结石去除术，经输尿管镜
A91: 第二顺位手术编码 | C91: 信息科 | D91: =[2]泌尿外科!$N$5 -> 56.0x | E91: =[2]泌尿外科!$H$5 -> 56.00 | F91: =[2]泌尿外科!$B$5 -> 56.00
A92: 第二顺位手术占比 | B92: % | C92: 信息科 | D92: =[2]泌尿外科!$Q$5 -> 27.361268 | E92: =[2]泌尿外科!$K$5 -> 22.86509 | F92: =[2]泌尿外科!$E$5 -> 20.27027
A93: 第三顺位手术名称 | C93: 信息科 | D93: =[2]泌尿外科!$O$6 -> 经尿道前列腺等离子电切术 | E93: =[2]泌尿外科!$I$6 -> 前列腺（电）切除术，经尿道(TURP) | F93: =[2]泌尿外科!$C$6 -> 前列腺（电）切除术，经尿道(TURP)
A94: 第三顺位手术编码 | C94: 信息科 | D94: =[2]泌尿外科!$N$6 -> 60.29 | E94: =[2]泌尿外科!$H$6 -> 60.29 | F94: =[2]泌尿外科!$B$6 -> 60.29
A95: 第三顺位手术占比 | B95: % | C95: 信息科 | D95: =[2]泌尿外科!$Q$6 -> 6.8629672 | E95: =[2]泌尿外科!$K$6 -> 8.4283727 | F95: =[2]泌尿外科!$E$6 -> 8.7556306
A96: 第四顺位手术名称 | C96: 信息科 | D96: =[2]泌尿外科!$O$7 -> 经皮肾造口术 | E96: =[2]泌尿外科!$I$7 -> 肾造瘘术，经肾镜 | F96: =[2]泌尿外科!$C$7 -> 膀胱取石术，经膀胱镜
A97: 第四顺位手术编码 | C97: 信息科 | D97: =[2]泌尿外科!$N$7 -> 55.03 | E97: =[2]泌尿外科!$H$7 -> 55.02 | F97: =[2]泌尿外科!$B$7 -> 57.00
A98: 第四顺位手术占比 | B98: % | C98: 信息科 | D98: =[2]泌尿外科!$Q$7 -> 4.4847112 | E98: =[2]泌尿外科!$K$7 -> 3.4214186 | F98: =[2]泌尿外科!$E$7 -> 4.3355856
A99: 第五顺位手术名称 | C99: 信息科 | D99: =[2]泌尿外科!$O$8 -> 经尿道膀胱气压弹道碎石术 | E99: =[2]泌尿外科!$I$8 -> 膀胱病损电切术，经尿道(TURBT) | F99: =[2]泌尿外科!$C$8 -> 膀胱病损电切术，经尿道(TURBT)
A100: 第五顺位手术编码 | C100: 信息科 | D100: =[2]泌尿外科!$N$8 -> 57.0x | E100: =[2]泌尿外科!$H$8 -> 57.49 | F100: =[2]泌尿外科!$B$8 -> 57.49
...

Sheet 麻醉科
A1: 数据名 | B1: 计量单位 | C1: 填报部门 | D1: Y2021 | E1: Y2020 | F1: Y2019 | G1: 指标说明 | H1: 计算公式
A2: 出院患者手术占比 | B2: % | C2: 统计室 | G2: 详见三级公立、二级公立国考手册。举例：30%请填写30（不带百分号），而非写成30%，或0.3。下同 | H2: 出院患者手术台次数/同期出院患者总人次数*100
A3: 出院患者微创手术占比 | B3: % | C3: 统计室 | G3: 详见三级公立、二级公立国考手册 | H3: 出院患者微创手术台次数/同期出院患者手术台次数*100
A4: 出院患者四级手术比例 | B4: % | C4: 统计室 | G4: 详见三级公立国考手册 | H4: 出院患者四级手术台次数/同期出院患者手术台次数*100
A5: 出院患者疑难危重病例比例 | B5: % | C5: 统计室 | G5: 即CD型病例占比 | H5: (疑难病例数+危重病例数)/出院人数*100
A6: 手术患者并发症发生率 | B6: % | C6: 质控科 | G6: 详见国考手册 | H6: 手术患者并发症发生例数/同期出院的手术患者人数*100
A7: I类切口手术部位感染率 | B7: % | C7: 质控科 | G7: 详见三级中医、三级公立国考手册 | H7: I类切口手术部位感染人次数/同期I类切口手术台次数*100
A8: 大型医用设备检查阳性率 | B8: % | C8: 医务科 | G8: 详见三级中医、三级公立国考手册 | H8: 大型医用设备检查阳性数/同期大型医用设备检查人次数*100
A9: 低风险组病例死亡率 | B9: % | C9: 质控科 | G9: 详见三级公立、二级公立国考手册 | H9: 低风险组死亡例数/低风险组病例数*100
A10: 医院感染发生率 | B10: % | C10: 院感科 | G10: 等级评审标准细则
A11: 抗菌药物使用强度DDDs | B11: DDD | C11: 药学部 | G11: 详见国考手册 | H11: 住院患者抗菌药物消耗量（累计DDD数）/同期收治患者人天数*100
A12: 门诊患者基本药物处方占比 | B12: % | C12: 药学部 | D12: 99.82 | E12: 69.69 | F12: 77.39 | G12: 详见三级中医、三级公立国考手册 | H12: 门诊使用基本药物人次数/同期门诊诊疗总人次数*100
A13: 住院患者基本药物使用率 | B13: % | C13: 药学部 | G13: 详见三级中医、三级公立国考手册 | H13: 出院患者使用基本药物总人次数/同期出院总人次数*100
A14: 重点监控高值医用耗材收入占比 | B14: % | C14: 设备科 | G14: 详见国考手册 | H14: 重点监控高值医用耗材收入/同期卫生材料收入*100
A15: 平均住院日 | B15: 天 | C15: 统计室 | G15: 详见二级公立国考手册 | H15: 出院患者占用总床日数/同期出院患者人数
A16: CMI值 | C16: 质控科 | G16: 病例组合指数
A17: DRGs组数 | B17: 组 | C17: 质控科 | G17: 诊断相关分组组数
A18: 核定床位数 | B18: 张 | C18: 统计室 | G18: 等级评审标准细则
A19: 实际开放床位数 | B19: 张 | C19: 统计室 | G19: 等级评审标准细则
A20: 开放床位使用率 | B20: % | C20: 统计室 | G20: 等级评审标准细则 | H20: 实际占用的总床日数/同期实际开放的总床日数*100
A21: 医师人数与开放床位数比 | C21: 人事科 | G21: 等级评审标准细则，原计量单位为比值（1:X），现改为小数 | H21: 医院执业（助理）医师总数/同期全院实际开放床位数
A22: 护士人数与开放床位数比 | C22: 人事科 | G22: 等级评审标准细则，原计量单位为比值（1:X），现改为小数 | H22: 医院注册护士总数/同期全院实际开放床位数
A23: 人均医疗服务收入 | B23: 万元 | C23: 财务科 | G23: 按科室人员数人均医疗服务收入
A24: 人均有效收入 | B24: 万元 | C24: 财务科 | G24: 按科室人员数人均有效收入
A25: 床均医疗服务收入 | B25: 万元 | C25: 财务科 | G25: 按开放床位数床均医疗服务收入
A26: 床均有效收入 | B26: 万元 | C26: 财务科 | G26: 按开放床位数床均有效收入
A27: 每名执业医师日均住院工作负担 | B27: 床日 | C27: 财务科 | G27: 详见三级中医、三级公立国考手册 | H27: 全年实际占用总床日数/医院平均执业(助理)医师人数/365
A28: 医疗服务收入占医疗收入比例 | B28: % | C28: 财务科 | G28: 参考国考手册，原指标名为：医疗服务收入（不含药品、耗材、检查检验收入）占医疗收入比例 | H28: 医疗服务收入/医疗收入*100
A29: 医疗收入 | B29: 万元 | C29: 财务科 | D29: 17101.076 | E29: 15064.595 | F29: 15262.824 | H29: 门诊收入+住院收入
A30: 医疗服务收入 | B30: 万元 | C30: 财务科
A31: 有效收入 | B31: 万元 | C31: 财务科 | H31: 医疗服务收入+检查检验收入
A32: 医疗直接成本 | B32: 万元 | D32: 8058.06 | E32: 209.51 | F32: 7746.34
A33: 收支结余率 | B33: %
A34: 万元收入能耗占比 | B34: 吨标煤/万元 | C34: 后勤管理科 | G34: 详见国考手册 | H34: 年总能耗/年总收入*10000
A35: 门诊收入占医疗收入比例 | B35: % | C35: 财务科 | D35: 8.6633498 | E35: 6.1973322 | F35: 6.7568379 | G35: 详见三级公立国考手册 | H35: 门诊收入/医疗收入*100
A36: 住院收入占医疗收入比例 | B36: % | C36: 财务科 | D36: 91.33665 | E36: 93.802668 | F36: 93.243162 | G36: 详见三级公立国考手册 | H36: 住院收入/医疗收入*100
A37: 医疗收入增幅 | B37: % | C37: 财务科 | D37: 13.51832 | E37: -1.2987664 | F37: 0 | G37: 详见国考手册 | H37: （本年度医疗收入－上一年度医疗收入）/上一年度医疗收入*100
A38: 门诊次均费用增幅 | B38: % | C38: 财务科 | G38: 详见国考手册 | H38: （本年度门诊患者次均医药费用－上一年度门诊患者次均医药费用）/上一年度门诊患者次均医药费用*100
A39: 住院次均费用增幅 | B39: % | C39: 财务科 | G39: 详见国考手册 | H39: （本年度出院患者次均医药费用－上一年度出院患者次均医药费用）/上一年度出院患者次均医药费用*100
A40: 门诊次均药品费用增幅 | B40: % | C40: 财务科 | G40: 详见国考手册 | H40: （本年度门诊患者次均药品费用－上一年度门诊患者次均药品费用）/上一年度门诊患者次均药品费用*100
A41: 住院次均药品费用增幅 | B41: % | C41: 财务科 | G41: 详见国考手册 | H41: （本年度出院患者次均药品费用－上一年度出院患者次均药品费用）/上一年度出院患者次均药品费用*100
A42: 医护比 | C42: 人事科 | D42: 0.45 | E42: 0.42 | F42: 0.4 | G42: 参考国考手册，原计量单位为比值（1:X），现改为小数 | H42: 医院注册医师总数/全院同期注册护士总数
A43: 医师人数 | B43: 人 | C43: 人事科 | D43: 41 | E43: 38 | F43: 36 | G43: 详见国考手册中，医护比定义
A44: 护士人数 | B44: 人 | C44: 人事科 | D44: 91 | E44: 91 | F44: 90 | G44: 详见国考手册中，医护比定义
A45: 医师高级职称占比 | B45: % | C45: 人事科 | D45: 34.15 | E45: 34.21 | F45: 36.11 | H45: (正高职称医师人数+副高职称医师人数)/医师人数*100
A46: 医师博士占比 | B46: % | C46: 人事科 | D46: 2.44 | E46: 2.63 | F46: 2.78 | H46: 博士医师人数/医师人数*100
A47: 医师硕士占比 | B47: % | C47: 人事科 | D47: 51.22 | E47: 55.26 | F47: 50 | H47: 硕士医师人数/医师人数*100
A48: 发表教学文章数与卫生技术人员数之比 | C48: 科教科 | D48: 0.008 | E48: 0 | F48: 0 | G48: 参考三级中医、三级公立国考手册，医院承担培养医学人才的工作成效的构成元素。原计量单位为比值（1:X），现改为小数 | H48: 本年度发表的教学文章数/同期卫生技术人员总数
A49: 省部级及以上教育教学课题数与卫生技术人员数之比 | C49: 科教科 | D49: 0 | E49: 0 | F49: 0 | G49: 参考三级中医、三级公立国考手册，医院承担培养医学人才的工作成效的构成元素。本指标为延伸指标。原计量单位为比值（1:X），现改为小数 | H49: 本年度获得的省部级及以上教育教学课题数/同期卫生技术人员总数
A50: 国家级继续医学教育项目数与卫生技术人员数之比 | C50: 科教科 | D50: 0 | E50: 0 | F50: 0 | G50: 参考三级中医、三级公立国考手册，医院承担培养医学人才的工作成效的构成元素。本指标为延伸指标。原计量单位为比值（1:X），现改为小数 | H50: 本年度举办的国家级继续医学教育项目数/同期卫生技术人员总数
A51: 每百名卫生技术人员科研项目经费 | B51: 元 | C51: 科教科 | D51: 0 | E51: 0 | F51: 0 | G51: 详见三级中医、三级公立国考手册 | H51: 本年度科研项目立项经费总金额/同期卫生技术人员总数*100
A52: 每百名卫生技术人员科研成果转化金额 | B52: 元 | C52: 科教科 | D52: 0 | E52: 0 | F52: 0 | G52: 详见三级公立国考手册 | H52: 本年度科技成果转化总金额/同期医院卫生技术人员总数*100
A53: 医师人均国家自然科学基金项目数量 | B53: 项 | C53: 科教科 | D53: 0 | E53: 0 | F53: 0 | G53: 说明：本年度成功立项的项目数量。要求本科室为主研单位
A54: 医师人均SCI文章数量 | B54: 篇 | C54: 科教科 | D54: 0.024 | E54: 0 | F54: 0 | G54: 说明：本年度成功发表的论文，要求第一作者或通讯作者为本院员工
A55: SCI平均影响因子 | B55: 分 | C55: 科教科 | D55: 0.064 | E55: 0 | F55: 0 | G55: 说明：本年度成功发表的论文，要求第一作者或通讯作者为本院员工
A56: 博士研究生导师占比 | B56: % | C56: 科教科 | D56: 0 | E56: 0 | F56: 0 | H56: 博士研究生导师人数/同期医师总数*100
A57: 硕士研究生导师占比 | B57: % | C57: 科教科 | D57: 0 | E57: 0 | F57: 0 | H57: 硕士研究生导师人数/同期医师总数*100
A58: 外省住院患者占比 | B58: % | C58: 统计室 | H58: 外省住院患者人数/同期出院患者人次数*100
A59: 非医嘱离院率 | B59: % | C59: 统计室 | H59: 非医嘱离院人次/同期出院患者总人次*100
A60: 是否为教育部或科技部重点学科或重点实验室 | B60: 分 | C60: 科教科 | D60: 0 | E60: 0 | F60: 0 | G60: 是填1,否填0
A61: 是否为国家卫健委临床重点专科 | B61: 分 | C61: 科教科 | D61: 0 | E61: 0 | F61: 0 | G61: 是填1,否填0
A62: 是否为国家中医药局重点专科 | B62: 分 | C62: 科教科 | D62: 0 | E62: 0 | F62: 0 | G62: 是填1,否填0
A63: 是否为省教育厅或科技厅重点学科或重点实验室 | B63: 分 | C63: 科教科 | D63: 0 | E63: 0 | F63: 0 | G63: 是填1,否填0
A64: 是否为省卫健委重点专科 | B64: 分 | C64: 科教科 | D64: 0 | E64: 0 | F64: 0 | G64: 是填1,否填0
A65: 是否为省中医药局重点专科 | B65: 分 | C65: 科教科 | D65: 0 | E65: 0 | F65: 0 | G65: 是填1,否填0
A66: 是否为地市级教育局或科技局重点学科或重点实验室 | B66: 分 | C66: 科教科 | D66: 0 | E66: 0 | F66: 0 | G66: 是填1,否填0
A67: 是否为地市级卫健委重点专科 | B67: 分 | C67: 科教科 | D67: 0 | E67: 0 | F67: 0 | G67: 是填1,否填0
A68: 是否为地市级中医药局重点专科 | B68: 分 | C68: 科教科 | D68: 0 | E68: 0 | F68: 0 | G68: 是填1,否填0
A69: 是否为县级教育局或科技局重点学科或重点实验室 | B69: 分 | C69: 科教科 | D69: 0 | E69: 0 | F69: 0 | G69: 是填1,否填0
A70: 是否为县级卫健委重点专科 | B70: 分 | C70: 科教科 | D70: 0 | E70: 0 | F70: 0 | G70: 是填1,否填0
A71: 是否为县级中医药局重点专科 | B71: 分 | C71: 科教科 | D71: 0 | E71: 0 | F71: 0 | G71: 是填1,否填0
A72: 第一顺位疾病名称 | C72: 信息科
A73: 第一顺位疾病编码 | C73: 信息科
A74: 第一顺位疾病占比 | B74: % | C74: 信息科
A75: 第二顺位疾病名称 | C75: 信息科
A76: 第二顺位疾病编码 | C76: 信息科
A77: 第二顺位疾病占比 | B77: % | C77: 信息科
A78: 第三顺位疾病名称 | C78: 信息科
A79: 第三顺位疾病编码 | C79: 信息科
A80: 第三顺位疾病占比 | B80: % | C80: 信息科
A81: 第四顺位疾病名称 | C81: 信息科
A82: 第四顺位疾病编码 | C82: 信息科
A83: 第四顺位疾病占比 | B83: % | C83: 信息科
A84: 第五顺位疾病名称 | C84: 信息科
A85: 第五顺位疾病编码 | C85: 信息科
A86: 第五顺位疾病占比 | B86: % | C86: 信息科
A87: 第一顺位手术名称 | C87: 信息科
A88: 第一顺位手术编码 | C88: 信息科
A89: 第一顺位手术占比 | B89: % | C89: 信息科
A90: 第二顺位手术名称 | C90: 信息科
A91: 第二顺位手术编码 | C91: 信息科
A92: 第二顺位手术占比 | B92: % | C92: 信息科
A93: 第三顺位手术名称 | C93: 信息科
A94: 第三顺位手术编码 | C94: 信息科
A95: 第三顺位手术占比 | B95: % | C95: 信息科
A96: 第四顺位手术名称 | C96: 信息科
A97: 第四顺位手术编码 | C97: 信息科
A98: 第四顺位手术占比 | B98: % | C98: 信息科
A99: 第五顺位手术名称 | C99: 信息科
A100: 第五顺位手术编码 | C100: 信息科
...

Sheet 呼吸内科
A1: 数据名 | B1: 计量单位 | C1: 填报部门 | D1: Y2021 | E1: Y2020 | F1: Y2019 | G1: 指标说明 | H1: 计算公式
A2: 出院患者手术占比 | B2: % | C2: 统计室 | D2: 1.1812627 | E2: 1.1482469 | F2: 0.75054316 | G2: 详见三级公立、二级公立国考手册。举例：30%请填写30（不带百分号），而非写成30%，或0.3。下同 | H2: 出院患者手术台次数/同期出院患者总人次数*100
A3: 出院患者微创手术占比 | B3: % | C3: 统计室 | D3: 17.241379 | E3: 10.714286 | F3: 0 | G3: 详见三级公立、二级公立国考手册 | H3: 出院患者微创手术台次数/同期出院患者手术台次数*100
A4: 出院患者四级手术比例 | B4: % | C4: 统计室 | D4: 5.1724138 | E4: 7.1428571 | F4: 2.6315789 | G4: 详见三级公立国考手册 | H4: 出院患者四级手术台次数/同期出院患者手术台次数*100
A5: 出院患者疑难危重病例比例 | B5: % | C5: 统计室 | D5: 99.25 | E5: 98.69 | F5: 95.95 | G5: 即CD型病例占比 | H5: (疑难病例数+危重病例数)/出院人数*100
A6: 手术患者并发症发生率 | B6: % | C6: 质控科 | D6: 0 | E6: 0 | F6: 0 | G6: 详见国考手册 | H6: 手术患者并发症发生例数/同期出院的手术患者人数*100
A7: I类切口手术部位感染率 | B7: % | C7: 质控科 | D7: 0 | E7: 0 | F7: 0 | G7: 详见三级中医、三级公立国考手册 | H7: I类切口手术部位感染人次数/同期I类切口手术台次数*100
A8: 大型医用设备检查阳性率 | B8: % | C8: 医务科 | G8: 详见三级中医、三级公立国考手册 | H8: 大型医用设备检查阳性数/同期大型医用设备检查人次数*100
A9: 低风险组病例死亡率 | B9: % | C9: 质控科 | D9: 0 | E9: 0 | F9: 0 | G9: 详见三级公立、二级公立国考手册 | H9: 低风险组死亡例数/低风险组病例数*100
A10: 医院感染发生率 | B10: % | C10: 院感科 | D10: 0.2 | E10: 0.27 | F10: 0.1 | G10: 等级评审标准细则
A11: 抗菌药物使用强度DDDs | B11: DDD | C11: 药学部 | D11: 104.02516 | E11: 110.63852 | F11: 104.98734 | G11: 详见国考手册 | H11: 住院患者抗菌药物消耗量（累计DDD数）/同期收治患者人天数*100
A12: 门诊患者基本药物处方占比 | B12: % | C12: 药学部 | D12: 83.01 | E12: 69.42 | F12: 76.34 | G12: 详见三级中医、三级公立国考手册 | H12: 门诊使用基本药物人次数/同期门诊诊疗总人次数*100
A13: 住院患者基本药物使用率 | B13: % | C13: 药学部 | D13: 98.42 | E13: 98.52 | F13: 96.56 | G13: 详见三级中医、三级公立国考手册 | H13: 出院患者使用基本药物总人次数/同期出院总人次数*100
A14: 重点监控高值医用耗材收入占比 | B14: % | C14: 设备科 | E14: =2402/44846550*100 -> 0.0053560419 | G14: 详见国考手册 | H14: 重点监控高值医用耗材收入/同期卫生材料收入*100
A15: 平均住院日 | B15: 天 | C15: 统计室 | D15: 9.03 | E15: 9.38 | F15: 9.72 | G15: 详见二级公立国考手册 | H15: 出院患者占用总床日数/同期出院患者人数
A16: CMI值 | C16: 质控科 | D16: 1.32 | E16: 1.25 | F16: 1.24 | G16: 病例组合指数
A17: DRGs组数 | B17: 组 | C17: 质控科 | D17: 155 | E17: 153 | F17: 142 | G17: 诊断相关分组组数
A18: 核定床位数 | B18: 张 | C18: 统计室 | D18: 110 | E18: 110 | F18: 110 | G18: 等级评审标准细则
A19: 实际开放床位数 | B19: 张 | C19: 统计室 | D19: 126 | E19: 120 | F19: 130 | G19: 等级评审标准细则
A20: 开放床位使用率 | B20: % | C20: 统计室 | D20: 95.88 | E20: 98.25 | F20: 101.86 | G20: 等级评审标准细则 | H20: 实际占用的总床日数/同期实际开放的总床日数*100
A21: 医师人数与开放床位数比 | C21: 人事科 | D21: =D43/D19 -> 0.15079365 | E21: =E43/E19 -> 0.15 | F21: =F43/F19 -> 0.13076923 | G21: 等级评审标准细则，原计量单位为比值（1:X），现改为小数 | H21: 医院执业（助理）医师总数/同期全院实际开放床位数
A22: 护士人数与开放床位数比 | C22: 人事科 | D22: =D44/D19 -> 0.45238095 | E22: =E44/E19 -> 0.46666667 | F22: =F44/F19 -> 0.47692308 | G22: 等级评审标准细则，原计量单位为比值（1:X），现改为小数 | H22: 医院注册护士总数/同期全院实际开放床位数
A23: 人均医疗服务收入 | B23: 万元 | C23: 财务科 | D23: 17.831436 | E23: 18.118104 | F23: 18.036814 | G23: 按科室人员数人均医疗服务收入
A24: 人均有效收入 | B24: 万元 | C24: 财务科 | D24: 38.942476 | E24: 37.482985 | F24: 35.560684 | G24: 按科室人员数人均有效收入
A25: 床均医疗服务收入 | B25: 万元 | C25: 财务科 | D25: 11.213836 | E25: 10.944014 | F25: 10.683344 | G25: 按开放床位数床均医疗服务收入
A26: 床均有效收入 | B26: 万元 | C26: 财务科 | D26: 24.490148 | E26: 22.641129 | F26: 21.062867 | G26: 按开放床位数床均有效收入
A27: 每名执业医师日均住院工作负担 | B27: 床日 | C27: 财务科 | D27: 6.2589762 | E27: 6.8861492 | F27: 7.7893634 | G27: 详见三级中医、三级公立国考手册 | H27: 全年实际占用总床日数/医院平均执业(助理)医师人数/365
A28: 医疗服务收入占医疗收入比例 | B28: % | C28: 财务科 | D28: 29.114892 | E28: 30.684325 | F28: 30.862635 | G28: 参考国考手册，原指标名为：医疗服务收入（不含药品、耗材、检查检验收入）占医疗收入比例 | H28: 医疗服务收入/医疗收入*100
A29: 医疗收入 | B29: 万元 | C29: 财务科 | D29: 4777.1155 | E29: 4487.5548 | F29: 4500.0521 | H29: 门诊收入+住院收入
A30: 医疗服务收入 | B30: 万元 | C30: 财务科 | D30: 1390.852 | E30: 1376.9759 | F30: 1388.8347
A31: 有效收入 | B31: 万元 | C31: 财务科 | D31: 3037.5131 | E31: 2848.7069 | F31: 2738.1727 | H31: 医疗服务收入+检查检验收入
A32: 医疗直接成本 | B32: 万元 | D32: 3921.4 | E32: 3437.35 | F32: 3518.51
A33: 收支结余率 | B33: % | D33: -27.35 | E33: -25.43 | F33: -27.91
A34: 万元收入能耗占比 | B34: 吨标煤/万元 | C34: 后勤管理科 | G34: 详见国考手册 | H34: 年总能耗/年总收入*10000
A35: 门诊收入占医疗收入比例 | B35: % | C35: 财务科 | D35: 18.887576 | E35: 13.366378 | F35: 11.936526 | G35: 详见三级公立国考手册 | H35: 门诊收入/医疗收入*100
A36: 住院收入占医疗收入比例 | B36: % | C36: 财务科 | D36: 81.112424 | E36: 86.633622 | F36: 88.063474 | G36: 详见三级公立国考手册 | H36: 住院收入/医疗收入*100
A37: 医疗收入增幅 | B37: % | C37: 财务科 | D37: 6.4525282 | E37: -0.27771612 | F37: 3.1257637 | G37: 详见国考手册 | H37: （本年度医疗收入－上一年度医疗收入）/上一年度医疗收入*100
A38: 门诊次均费用增幅 | B38: % | C38: 财务科 | D38: 15.044826 | E38: 55.566411 | F38: 15.244797 | G38: 详见国考手册 | H38: （本年度门诊患者次均医药费用－上一年度门诊患者次均医药费用）/上一年度门诊患者次均医药费用*100
A39: 住院次均费用增幅 | B39: % | C39: 财务科 | D39: 0.014421704 | E39: 1.1371187 | F39: -0.5284291 | G39: 详见国考手册 | H39: （本年度出院患者次均医药费用－上一年度出院患者次均医药费用）/上一年度出院患者次均医药费用*100
A40: 门诊次均药品费用增幅 | B40: % | C40: 财务科 | D40: 37.69733 | E40: 73.98056 | F40: 5.6282418 | G40: 详见国考手册 | H40: （本年度门诊患者次均药品费用－上一年度门诊患者次均药品费用）/上一年度门诊患者次均药品费用*100
A41: 住院次均药品费用增幅 | B41: % | C41: 财务科 | D41: -8.3621087 | E41: -9.5081943 | F41: -4.0649343 | G41: 详见国考手册 | H41: （本年度出院患者次均药品费用－上一年度出院患者次均药品费用）/上一年度出院患者次均药品费用*100
A42: 医护比 | C42: 人事科 | D42: 0.33 | E42: 0.32 | F42: 0.27 | G42: 参考国考手册，原计量单位为比值（1:X），现改为小数 | H42: 医院注册医师总数/全院同期注册护士总数
A43: 医师人数 | B43: 人 | C43: 人事科 | D43: 19 | E43: 18 | F43: 17 | G43: 详见国考手册中，医护比定义
A44: 护士人数 | B44: 人 | C44: 人事科 | D44: 57 | E44: 56 | F44: 62 | G44: 详见国考手册中，医护比定义
A45: 医师高级职称占比 | B45: % | C45: 人事科 | D45: 57.89 | E45: 61.11 | F45: 52.94 | H45: (正高职称医师人数+副高职称医师人数)/医师人数*100
A46: 医师博士占比 | B46: % | C46: 人事科 | D46: 10.53 | E46: 5.56 | F46: 5.88 | H46: 博士医师人数/医师人数*100
A47: 医师硕士占比 | B47: % | C47: 人事科 | D47: 78.95 | E47: 83.33 | F47: 82.35 | H47: 硕士医师人数/医师人数*100
A48: 发表教学文章数与卫生技术人员数之比 | C48: 科教科 | D48: 0.013 | E48: 0 | F48: 0 | G48: 参考三级中医、三级公立国考手册，医院承担培养医学人才的工作成效的构成元素。原计量单位为比值（1:X），现改为小数 | H48: 本年度发表的教学文章数/同期卫生技术人员总数
A49: 省部级及以上教育教学课题数与卫生技术人员数之比 | C49: 科教科 | D49: 0 | E49: 0 | F49: 0 | G49: 参考三级中医、三级公立国考手册，医院承担培养医学人才的工作成效的构成元素。本指标为延伸指标。原计量单位为比值（1:X），现改为小数 | H49: 本年度获得的省部级及以上教育教学课题数/同期卫生技术人员总数
A50: 国家级继续医学教育项目数与卫生技术人员数之比 | C50: 科教科 | D50: 0 | E50: 0 | F50: 0 | G50: 参考三级中医、三级公立国考手册，医院承担培养医学人才的工作成效的构成元素。本指标为延伸指标。原计量单位为比值（1:X），现改为小数 | H50: 本年度举办的国家级继续医学教育项目数/同期卫生技术人员总数
A51: 每百名卫生技术人员科研项目经费 | B51: 元 | C51: 科教科 | D51: 26315.789 | E51: 504991.46 | F51: 0 | G51: 详见三级中医、三级公立国考手册 | H51: 本年度科研项目立项经费总金额/同期卫生技术人员总数*100
A52: 每百名卫生技术人员科研成果转化金额 | B52: 元 | C52: 科教科 | D52: 0 | E52: 0 | F52: 0 | G52: 详见三级公立国考手册 | H52: 本年度科技成果转化总金额/同期医院卫生技术人员总数*100
A53: 医师人均国家自然科学基金项目数量 | B53: 项 | C53: 科教科 | D53: 0 | E53: 0 | F53: 0 | G53: 说明：本年度成功立项的项目数量。要求本科室为主研单位
A54: 医师人均SCI文章数量 | B54: 篇 | C54: 科教科 | D54: 0 | E54: 0 | F54: 0 | G54: 说明：本年度成功发表的论文，要求第一作者或通讯作者为本院员工
A55: SCI平均影响因子 | B55: 分 | C55: 科教科 | D55: 0 | E55: 0 | F55: 0 | G55: 说明：本年度成功发表的论文，要求第一作者或通讯作者为本院员工
A56: 博士研究生导师占比 | B56: % | C56: 科教科 | D56: 0 | E56: 0 | F56: 0 | H56: 博士研究生导师人数/同期医师总数*100
A57: 硕士研究生导师占比 | B57: % | C57: 科教科 | D57: 15.79 | E57: 16.67 | F57: 0 | H57: 硕士研究生导师人数/同期医师总数*100
A58: 外省住院患者占比 | B58: % | C58: 统计室 | D58: 3.0142566 | E58: 3.2191921 | F58: 3.5552044 | H58: 外省住院患者人数/同期出院患者人次数*100
A59: 非医嘱离院率 | B59: % | C59: 统计室 | D59: 2.0570265 | E59: 4.818536 | F59: 3.4169465 | H59: 非医嘱离院人次/同期出院患者总人次*100
A60: 是否为教育部或科技部重点学科或重点实验室 | B60: 分 | C60: 科教科 | D60: 0 | E60: 0 | F60: 0 | G60: 是填1,否填0
A61: 是否为国家卫健委临床重点专科 | B61: 分 | C61: 科教科 | D61: 0 | E61: 0 | F61: 0 | G61: 是填1,否填0
A62: 是否为国家中医药局重点专科 | B62: 分 | C62: 科教科 | D62: 0 | E62: 0 | F62: 0 | G62: 是填1,否填0
A63: 是否为省教育厅或科技厅重点学科或重点实验室 | B63: 分 | C63: 科教科 | D63: 0 | E63: 0 | F63: 0 | G63: 是填1,否填0
A64: 是否为省卫健委重点专科 | B64: 分 | C64: 科教科 | D64: 0 | E64: 0 | F64: 0 | G64: 是填1,否填0
A65: 是否为省中医药局重点专科 | B65: 分 | C65: 科教科 | D65: 0 | E65: 0 | F65: 0 | G65: 是填1,否填0
A66: 是否为地市级教育局或科技局重点学科或重点实验室 | B66: 分 | C66: 科教科 | D66: 0 | E66: 0 | F66: 0 | G66: 是填1,否填0
A67: 是否为地市级卫健委重点专科 | B67: 分 | C67: 科教科 | D67: 1 | E67: 1 | F67: 1 | G67: 是填1,否填0
A68: 是否为地市级中医药局重点专科 | B68: 分 | C68: 科教科 | D68: 0 | E68: 0 | F68: 0 | G68: 是填1,否填0
A69: 是否为县级教育局或科技局重点学科或重点实验室 | B69: 分 | C69: 科教科 | D69: 0 | E69: 0 | F69: 0 | G69: 是填1,否填0
A70: 是否为县级卫健委重点专科 | B70: 分 | C70: 科教科 | D70: 0 | E70: 0 | F70: 0 | G70: 是填1,否填0
A71: 是否为县级中医药局重点专科 | B71: 分 | C71: 科教科 | D71: 0 | E71: 0 | F71: 0 | G71: 是填1,否填0
A72: 第一顺位疾病名称 | C72: 信息科 | D72: =[1]呼吸内科!$O$4 -> 慢性阻塞性肺病 | E72: =[1]呼吸内科!$I$4 -> 细菌性肺炎 | F72: =[1]呼吸内科!$C$4 -> 慢性阻塞性肺病
A73: 第一顺位疾病编码 | C73: 信息科 | D73: =[1]呼吸内科!$N$4 -> J44 | E73: =[1]呼吸内科!$H$4 -> J13-J18 | F73: =[1]呼吸内科!$B$4 -> J44
A74: 第一顺位疾病占比 | B74: % | C74: 信息科 | D74: =[1]呼吸内科!$Q$4 -> 25.661914 | E74: =[1]呼吸内科!$K$4 -> 27.496412 | F74: =[1]呼吸内科!$E$4 -> 32.53012
A75: 第二顺位疾病名称 | C75: 信息科 | D75: =[1]呼吸内科!$O$5 -> 细菌性肺炎 | E75: =[1]呼吸内科!$I$5 -> 慢性阻塞性肺病 | F75: =[1]呼吸内科!$C$5 -> 细菌性肺炎
A76: 第二顺位疾病编码 | C76: 信息科 | D76: =[1]呼吸内科!$N$5 -> J13-J18 | E76: =[1]呼吸内科!$H$5 -> J44 | F76: =[1]呼吸内科!$B$5 -> J13-J18
A77: 第二顺位疾病占比 | B77: % | C77: 信息科 | D77: =[1]呼吸内科!$Q$5 -> 24.480652 | E77: =[1]呼吸内科!$K$5 -> 26.204634 | F77: =[1]呼吸内科!$E$5 -> 27.849101
A78: 第三顺位疾病名称 | C78: 信息科 | D78: =[1]呼吸内科!$O$6 -> 肺恶性肿瘤 | E78: =[1]呼吸内科!$I$6 -> 肺恶性肿瘤 | F78: =[1]呼吸内科!$C$6 -> 支气管扩张(症)
A79: 第三顺位疾病编码 | C79: 信息科 | D79: =[1]呼吸内科!$N$6 -> C34 | E79: =[1]呼吸内科!$H$6 -> C34 | F79: =[1]呼吸内科!$B$6 -> J47.x
A80: 第三顺位疾病占比 | B80: % | C80: 信息科 | D80: =[1]呼吸内科!$Q$6 -> 7.7596741 | E80: =[1]呼吸内科!$K$6 -> 6.6639327 | F80: =[1]呼吸内科!$E$6 -> 6.3401146
A81: 第四顺位疾病名称 | C81: 信息科 | D81: =[1]呼吸内科!$O$7 -> 为肿瘤化学治疗疗程 | E81: =[1]呼吸内科!$I$7 -> 支气管扩张(症) | F81: =[1]呼吸内科!$C$7 -> 肺恶性肿瘤
A82: 第四顺位疾病编码 | C82: 信息科 | D82: =[1]呼吸内科!$N$7 -> Z51.1 | E82: =[1]呼吸内科!$H$7 -> J47.x | F82: =[1]呼吸内科!$B$7 -> C34
A83: 第四顺位疾病占比 | B83: % | C83: 信息科 | D83: =[1]呼吸内科!$Q$7 -> 7.107943 | E83: =[1]呼吸内科!$K$7 -> 6.1308181 | F83: =[1]呼吸内科!$E$7 -> 5.6883271
A84: 第五顺位疾病名称 | C84: 信息科 | D84: =[1]呼吸内科!$O$8 -> 支气管扩张(症) | E84: =[1]呼吸内科!$I$8 -> 为肿瘤化学治疗疗程 | F84: =[1]呼吸内科!$C$8 -> 为肿瘤化学治疗疗程
A85: 第五顺位疾病编码 | C85: 信息科 | D85: =[1]呼吸内科!$N$8 -> J47.x | E85: =[1]呼吸内科!$H$8 -> Z51.1 | F85: =[1]呼吸内科!$B$8 -> Z51.1
A86: 第五顺位疾病占比 | B86: % | C86: 信息科 | D86: =[1]呼吸内科!$Q$8 -> 6.598778 | E86: =[1]呼吸内科!$K$8 -> 5.7617388 | F86: =[1]呼吸内科!$E$8 -> 3.8909737
A87: 第一顺位手术名称 | C87: 信息科
A88: 第一顺位手术编码 | C88: 信息科
A89: 第一顺位手术占比 | B89: % | C89: 信息科
A90: 第二顺位手术名称 | C90: 信息科
A91: 第二顺位手术编码 | C91: 信息科
A92: 第二顺位手术占比 | B92: % | C92: 信息科
A93: 第三顺位手术名称 | C93: 信息科
A94: 第三顺位手术编码 | C94: 信息科
A95: 第三顺位手术占比 | B95: % | C95: 信息科
A96: 第四顺位手术名称 | C96: 信息科
A97: 第四顺位手术编码 | C97: 信息科
A98: 第四顺位手术占比 | B98: % | C98: 信息科
A99: 第五顺位手术名称 | C99: 信息科
A100: 第五顺位手术编码 | C100: 信息科
...

Sheet 消化内科
A1: 数据名 | B1: 计量单位 | C1: 填报部门 | D1: Y2021 | E1: Y2020 | F1: Y2019 | G1: 指标说明 | H1: 计算公式
A2: 出院患者手术占比 | B2: % | C2: 统计室 | D2: 2.5155532 | E2: 1.5527023 | F2: 1.7918471 | G2: 详见三级公立、二级公立国考手册。举例：30%请填写30（不带百分号），而非写成30%，或0.3。下同 | H2: 出院患者手术台次数/同期出院患者总人次数*100
A3: 出院患者微创手术占比 | B3: % | C3: 统计室 | D3: 0.53763441 | E3: 0 | F3: 0 | G3: 详见三级公立、二级公立国考手册 | H3: 出院患者微创手术台次数/同期出院患者手术台次数*100
A4: 出院患者四级手术比例 | B4: % | C4: 统计室 | D4: 2.688172 | E4: 1.9230769 | F4: 1.6666667 | G4: 详见三级公立国考手册 | H4: 出院患者四级手术台次数/同期出院患者手术台次数*100
A5: 出院患者疑难危重病例比例 | B5: % | C5: 统计室 | D5: 98.43 | E5: 96.72 | F5: 91.55 | G5: 即CD型病例占比 | H5: (疑难病例数+危重病例数)/出院人数*100
A6: 手术患者并发症发生率 | B6: % | C6: 质控科 | D6: 0 | E6: 0 | F6: 0 | G6: 详见国考手册 | H6: 手术患者并发症发生例数/同期出院的手术患者人数*100
A7: I类切口手术部位感染率 | B7: % | C7: 质控科 | D7: 0.37 | E7: 0 | F7: 0.47 | G7: 详见三级中医、三级公立国考手册 | H7: I类切口手术部位感染人次数/同期I类切口手术台次数*100
A8: 大型医用设备检查阳性率 | B8: % | C8: 医务科 | G8: 详见三级中医、三级公立国考手册 | H8: 大型医用设备检查阳性数/同期大型医用设备检查人次数*100
A9: 低风险组病例死亡率 | B9: % | C9: 质控科 | D9: 0 | E9: 0 | F9: 0 | G9: 详见三级公立、二级公立国考手册 | H9: 低风险组死亡例数/低风险组病例数*100
A10: 医院感染发生率 | B10: % | C10: 院感科 | D10: 0.38 | E10: 0.49 | F10: 0.86 | G10: 等级评审标准细则
A11: 抗菌药物使用强度DDDs | B11: DDD | C11: 药学部 | D11: 27.065801 | E11: 29.411059 | F11: 27.065801 | G11: 详见国考手册 | H11: 住院患者抗菌药物消耗量（累计DDD数）/同期收治患者人天数*100
A12: 门诊患者基本药物处方占比 | B12: % | C12: 药学部 | D12: 82.74 | E12: 77.53 | F12: 67.97 | G12: 详见三级中医、三级公立国考手册 | H12: 门诊使用基本药物人次数/同期门诊诊疗总人次数*100
A13: 住院患者基本药物使用率 | B13: % | C13: 药学部 | D13: 97.81 | E13: 97.11 | F13: 92.52 | G13: 详见三级中医、三级公立国考手册 | H13: 出院患者使用基本药物总人次数/同期出院总人次数*100
A14: 重点监控高值医用耗材收入占比 | B14: % | C14: 设备科 | D14: =(164200+6600)/80256193*100 -> 0.21281847 | E14: =505843/73459844*100 -> 0.68859798 | F14: =276311/74944117*100 -> 0.36868938 | G14: 详见国考手册 | H14: 重点监控高值医用耗材收入/同期卫生材料收入*100
A15: 平均住院日 | B15: 天 | C15: 统计室 | D15: 6.09 | E15: 6.33 | F15: 6.58 | G15: 详见二级公立国考手册 | H15: 出院患者占用总床日数/同期出院患者人数
A16: CMI值 | C16: 质控科 | D16: 0.99 | E16: 0.89 | F16: 0.93 | G16: 病例组合指数
A17: DRGs组数 | B17: 组 | C17: 质控科 | D17: 215 | E17: 219 | F17: 219 | G17: 诊断相关分组组数
A18: 核定床位数 | B18: 张 | C18: 统计室 | D18: 100 | E18: 100 | F18: 100 | G18: 等级评审标准细则
A19: 实际开放床位数 | B19: 张 | C19: 统计室 | D19: 113 | E19: 110 | F19: 110 | G19: 等级评审标准细则
A20: 开放床位使用率 | B20: % | C20: 统计室 | D20: 112.68 | E20: 108.23 | F20: 113.21 | G20: 等级评审标准细则 | H20: 实际占用的总床日数/同期实际开放的总床日数*100
A21: 医师人数与开放床位数比 | C21: 人事科 | D21: =D43/D19 -> 0.2300885 | E21: =E43/E19 -> 0.22727273 | F21: =F43/F19 -> 0.21818182 | G21: 等级评审标准细则，原计量单位为比值（1:X），现改为小数 | H21: 医院执业（助理）医师总数/同期全院实际开放床位数
A22: 护士人数与开放床位数比 | C22: 人事科 | D22: =D44/D19 -> 0.48672566 | E22: =E44/E19 -> 0.51818182 | F22: =F44/F19 -> 0.49090909 | G22: 等级评审标准细则，原计量单位为比值（1:X），现改为小数 | H22: 医院注册护士总数/同期全院实际开放床位数
A23: 人均医疗服务收入 | B23: 万元 | C23: 财务科 | D23: 20.387885 | E23: 25.007659 | F23: 20.647379 | G23: 按科室人员数人均医疗服务收入
A24: 人均有效收入 | B24: 万元 | C24: 财务科 | D24: 52.832932 | E24: 55.708035 | F24: 47.594564 | G24: 按科室人员数人均有效收入
A25: 床均医疗服务收入 | B25: 万元 | C25: 财务科 | D25: 17.655788 | E25: 17.505362 | F25: 16.705606 | G25: 按开放床位数床均医疗服务收入
A26: 床均有效收入 | B26: 万元 | C26: 财务科 | D26: 45.753008 | E26: 38.995625 | F26: 38.508329 | G26: 按开放床位数床均有效收入
A27: 每名执业医师日均住院工作负担 | B27: 床日 | C27: 财务科 | D27: 4.8546891 | E27: 4.7752329 | F27: 5.1888128 | G27: 详见三级中医、三级公立国考手册 | H27: 全年实际占用总床日数/医院平均执业(助理)医师人数/365
A28: 医疗服务收入占医疗收入比例 | B28: % | C28: 财务科 | D28: 24.518508 | E28: 28.671499 | F28: 26.920702 | G28: 参考国考手册，原指标名为：医疗服务收入（不含药品、耗材、检查检验收入）占医疗收入比例 | H28: 医疗服务收入/医疗收入*100
A29: 医疗收入 | B29: 万元 | C29: 财务科 | D29: 8065.8449 | E29: 6716.0414 | F29: 6826.0357 | H29: 门诊收入+住院收入
A30: 医疗服务收入 | B30: 万元 | C30: 财务科 | D30: 1977.6248 | E30: 1925.5898 | F30: 1837.6167
A31: 有效收入 | B31: 万元 | C31: 财务科 | D31: 5124.7944 | E31: 4289.5187 | F31: 4235.9162 | H31: 医疗服务收入+检查检验收入
A32: 医疗直接成本 | B32: 万元 | D32: 6117.75 | E32: 5490.13 | F32: 5742.05
A33: 收支结余率 | B33: % | D33: -16.84 | E33: -13.68 | F33: -6.27
A34: 万元收入能耗占比 | B34: 吨标煤/万元 | C34: 后勤管理科 | G34: 详见国考手册 | H34: 年总能耗/年总收入*10000
A35: 门诊收入占医疗收入比例 | B35: % | C35: 财务科 | D35: 38.597 | E35: 32.952442 | F35: 33.335067 | G35: 详见三级公立国考手册 | H35: 门诊收入/医疗收入*100
A36: 住院收入占医疗收入比例 | B36: % | C36: 财务科 | D36: 61.403 | E36: 67.047558 | F36: 66.664933 | G36: 详见三级公立国考手册 | H36: 住院收入/医疗收入*100
A37: 医疗收入增幅 | B37: % | C37: 财务科 | D37: 20.098202 | E37: -1.6113935 | F37: 10.078079 | G37: 详见国考手册 | H37: （本年度医疗收入－上一年度医疗收入）/上一年度医疗收入*100
A38: 门诊次均费用增幅 | B38: % | C38: 财务科 | D38: -1.3261204 | E38: 4.607492 | F38: 5.9287112 | G38: 详见国考手册 | H38: （本年度门诊患者次均医药费用－上一年度门诊患者次均医药费用）/上一年度门诊患者次均医药费用*100
A39: 住院次均费用增幅 | B39: % | C39: 财务科 | D39: 0.02929466 | E39: -0.64018328 | F39: -6.6195429 | G39: 详见国考手册 | H39: （本年度出院患者次均医药费用－上一年度出院患者次均医药费用）/上一年度出院患者次均医药费用*100
A40: 门诊次均药品费用增幅 | B40: % | C40: 财务科 | D40: 10.870816 | E40: 3.2399732 | F40: 8.2486745 | G40: 详见国考手册 | H40: （本年度门诊患者次均药品费用－上一年度门诊患者次均药品费用）/上一年度门诊患者次均药品费用*100
A41: 住院次均药品费用增幅 | B41: % | C41: 财务科 | D41: -1.8145609 | E41: -9.7512622 | F41: -10.252017 | G41: 详见国考手册 | H41: （本年度出院患者次均药品费用－上一年度出院患者次均药品费用）/上一年度出院患者次均药品费用*100
A42: 医护比 | C42: 人事科 | D42: 0.47 | E42: 0.44 | F42: 0.44 | G42: 参考国考手册，原计量单位为比值（1:X），现改为小数 | H42: 医院注册医师总数/全院同期注册护士总数
A43: 医师人数 | B43: 人 | C43: 人事科 | D43: 26 | E43: 25 | F43: 24 | G43: 详见国考手册中，医护比定义
A44: 护士人数 | B44: 人 | C44: 人事科 | D44: 55 | E44: 57 | F44: 54 | G44: 详见国考手册中，医护比定义
A45: 医师高级职称占比 | B45: % | C45: 人事科 | D45: 46.15 | E45: 48 | F45: 50 | H45: (正高职称医师人数+副高职称医师人数)/医师人数*100
A46: 医师博士占比 | B46: % | C46: 人事科 | D46: 7.69 | E46: 4 | F46: 4.17 | H46: 博士医师人数/医师人数*100
A47: 医师硕士占比 | B47: % | C47: 人事科 | D47: 57.69 | E47: 60 | F47: 58.33 | H47: 硕士医师人数/医师人数*100
A48: 发表教学文章数与卫生技术人员数之比 | C48: 科教科 | D48: 0 | E48: 0 | F48: 0 | G48: 参考三级中医、三级公立国考手册，医院承担培养医学人才的工作成效的构成元素。原计量单位为比值（1:X），现改为小数 | H48: 本年度发表的教学文章数/同期卫生技术人员总数
A49: 省部级及以上教育教学课题数与卫生技术人员数之比 | C49: 科教科 | D49: 0 | E49: 0 | F49: 0 | G49: 参考三级中医、三级公立国考手册，医院承担培养医学人才的工作成效的构成元素。本指标为延伸指标。原计量单位为比值（1:X），现改为小数 | H49: 本年度获得的省部级及以上教育教学课题数/同期卫生技术人员总数
A50: 国家级继续医学教育项目数与卫生技术人员数之比 | C50: 科教科 | D50: 0 | E50: 0 | F50: 0 | G50: 参考三级中医、三级公立国考手册，医院承担培养医学人才的工作成效的构成元素。本指标为延伸指标。原计量单位为比值（1:X），现改为小数 | H50: 本年度举办的国家级继续医学教育项目数/同期卫生技术人员总数
A51: 每百名卫生技术人员科研项目经费 | B51: 元 | C51: 科教科 | D51: 501307.64 | E51: 707048.29 | F51: 12820.513 | G51: 详见三级中医、三级公立国考手册 | H51: 本年度科研项目立项经费总金额/同期卫生技术人员总数*100
A52: 每百名卫生技术人员科研成果转化金额 | B52: 元 | C52: 科教科 | D52: 0 | E52: 0 | F52: 0 | G52: 详见三级公立国考手册 | H52: 本年度科技成果转化总金额/同期医院卫生技术人员总数*100
A53: 医师人均国家自然科学基金项目数量 | B53: 项 | C53: 科教科 | D53: 0 | E53: 0 | F53: 0 | G53: 说明：本年度成功立项的项目数量。要求本科室为主研单位
A54: 医师人均SCI文章数量 | B54: 篇 | C54: 科教科 | D54: 0 | E54: 0 | F54: 0 | G54: 说明：本年度成功发表的论文，要求第一作者或通讯作者为本院员工
A55: SCI平均影响因子 | B55: 分 | C55: 科教科 | D55: 0 | E55: 0 | F55: 0 | G55: 说明：本年度成功发表的论文，要求第一作者或通讯作者为本院员工
A56: 博士研究生导师占比 | B56: % | C56: 科教科 | D56: 0 | E56: 0 | F56: 0 | H56: 博士研究生导师人数/同期医师总数*100
A57: 硕士研究生导师占比 | B57: % | C57: 科教科 | D57: 0 | E57: 0 | F57: 0 | H57: 硕士研究生导师人数/同期医师总数*100
A58: 外省住院患者占比 | B58: % | C58: 统计室 | D58: 3.6651339 | E58: 4.5535981 | F58: 4.9425116 | H58: 外省住院患者人数/同期出院患者人次数*100
A59: 非医嘱离院率 | B59: % | C59: 统计室 | D59: 0.63565053 | E59: 1.3884742 | F59: 3.1208004 | H59: 非医嘱离院人次/同期出院患者总人次*100
A60: 是否为教育部或科技部重点学科或重点实验室 | B60: 分 | C60: 科教科 | D60: 0 | E60: 0 | F60: 0 | G60: 是填1,否填0
A61: 是否为国家卫健委临床重点专科 | B61: 分 | C61: 科教科 | D61: 0 | E61: 0 | F61: 0 | G61: 是填1,否填0
A62: 是否为国家中医药局重点专科 | B62: 分 | C62: 科教科 | D62: 0 | E62: 0 | F62: 0 | G62: 是填1,否填0
A63: 是否为省教育厅或科技厅重点学科或重点实验室 | B63: 分 | C63: 科教科 | D63: 0 | E63: 0 | F63: 0 | G63: 是填1,否填0
A64: 是否为省卫健委重点专科 | B64: 分 | C64: 科教科 | D64: 1 | E64: 1 | F64: 1 | G64: 是填1,否填0
A65: 是否为省中医药局重点专科 | B65: 分 | C65: 科教科 | D65: 0 | E65: 0 | F65: 0 | G65: 是填1,否填0
A66: 是否为地市级教育局或科技局重点学科或重点实验室 | B66: 分 | C66: 科教科 | D66: 0 | E66: 0 | F66: 0 | G66: 是填1,否填0
A67: 是否为地市级卫健委重点专科 | B67: 分 | C67: 科教科 | D67: 1 | E67: 1 | F67: 1 | G67: 是填1,否填0
A68: 是否为地市级中医药局重点专科 | B68: 分 | C68: 科教科 | D68: 0 | E68: 0 | F68: 0 | G68: 是填1,否填0
A69: 是否为县级教育局或科技局重点学科或重点实验室 | B69: 分 | C69: 科教科 | D69: 0 | E69: 0 | F69: 0 | G69: 是填1,否填0
A70: 是否为县级卫健委重点专科 | B70: 分 | C70: 科教科 | D70: 0 | E70: 0 | F70: 0 | G70: 是填1,否填0
A71: 是否为县级中医药局重点专科 | B71: 分 | C71: 科教科 | D71: 0 | E71: 0 | F71: 0 | G71: 是填1,否填0
A72: 第一顺位疾病名称 | C72: 信息科 | D72: =[1]消化内科!$O$4 -> 肝硬化 | E72: =[1]消化内科!$I$4 -> 肝硬化 | F72: =[1]消化内科!$C$4 -> 肝硬化
A73: 第一顺位疾病编码 | C73: 信息科 | D73: =[1]消化内科!$N$4 -> K70.2-K70.3/K74 | E73: =[1]消化内科!$H$4 -> K70.2-K70.3/K74 | F73: =[1]消化内科!$B$4 -> K70.2-K70.3/K74
A74: 第一顺位疾病占比 | B74: % | C74: 信息科 | D74: =[1]消化内科!$Q$4 -> 15.796592 | E74: =[1]消化内科!$K$4 -> 15.153777 | F74: =[1]消化内科!$E$4 -> 13.842019
A75: 第二顺位疾病名称 | C75: 信息科 | D75: =[1]消化内科!$O$5 -> 结肠良性肿瘤 | E75: =[1]消化内科!$I$5 -> 结肠良性肿瘤 | F75: =[1]消化内科!$C$5 -> 结肠良性肿瘤
A76: 第二顺位疾病编码 | C76: 信息科 | D76: =[1]消化内科!$N$5 -> D12.0-D12.7 | E76: =[1]消化内科!$H$5 -> D12.0-D12.7 | F76: =[1]消化内科!$B$5 -> D12.0-D12.7
A77: 第二顺位疾病占比 | B77: % | C77: 信息科 | D77: =[1]消化内科!$Q$5 -> 13.727346 | E77: =[1]消化内科!$K$5 -> 10.465811 | F77: =[1]消化内科!$E$5 -> 9.3026728
A78: 第三顺位疾病名称 | C78: 信息科 | D78: =[1]消化内科!$O$6 -> 胃和十二指肠息肉 | E78: =[1]消化内科!$I$6 -> 十二指肠溃疡及并发症 | F78: =[1]消化内科!$C$6 -> 胃炎
